Workbook
Name Base_int_rate: Parameters!$B$19
Name Claims_data: Rawdata!$A$4:$L$85
Name Dep_term: Parameters!$B$7
Name Dep_term_alt: Parameters!$B$39
Name Deposit_mon: Parameters!$B$5
Name Deposit_mon_alt: Parameters!$B$37
Name Fixed_freq: Parameters!$B$13
Name Fixed_int: Parameters!$B$11
Name House_price: Parameters!$B$3
Name Int_check_tolerance: Parameters!$B$32
Name Int_rate_movements: Parameters!$B$25:$C$29
Name Mort_term: Parameters!$B$1
Name Product_term: Parameters!$B$15
Name Product_term_alt: Parameters!$B$41
Name Var_freq: Parameters!$B$21

Sheet Rawdata
A1: Rawdata and checks
A3: -0.92172448 | B3: 0.32750996 | C3: -1.3244954 | D3: -1.9981274 | E3: 0.59329849 | F3: 0.55677076 | G3: -0.17643932 | H3: 1.1308616 | I3: -0.26877028 | J3: 0.11361492 | K3: -1.1705027 | L3: -0.55666961 | M3: -0.29364409 | N3: 0.4625711 | O3: 0.089100725 | P3: 0.99981378 | Q3: -0.14966168 | R3: 0.52797863 | S3: 0.11506667 | T3: -0.5184396 | U3: 1.0409057 | V3: -1.481207 | W3: -1.1185463 | X3: 0.67663554 | Z3: Count | AC3: Expected | AE3: Check
A4: -1.4058169 | B4: -0.93267724 | C4: 0.12684171 | D4: -0.036890547 | E4: 0.46815803 | F4: 0.26356884 | G4: -1.786932 | H4: 0.11208809 | I4: -1.8453835 | J4: 0.33464744 | K4: -1.7934745 | L4: 0.51226808 | M4: -0.61662905 | N4: 1.016938 | O4: -0.02710161 | P4: 0.71736013 | Q4: 0.61304696 | R4: -0.67584412 | S4: -0.39346176 | T4: -0.50163836 | U4: 0.58001463 | V4: -0.25511878 | W4: 0.85955655 | X4: 1.2809476 | Z4: Total | AA4: =COUNT(A3:X202) -> 4800 | AC4: 4800 | AE4: =IF(AA4=AC4,"OK","CHECKDATA") -> OK
A5: 1.2579029 | B5: -0.50074129 | C5: -0.37879919 | D5: 0.62485291 | E5: 0.60425439 | F5: -0.66320047 | G5: 0.36349057 | H5: 0.053056984 | I5: 0.26056496 | J5: 0.12280153 | K5: -0.28400233 | L5: -1.4224254 | M5: -1.9392792 | N5: 1.8778183 | O5: -0.96808353 | P5: 1.2326872 | Q5: -2.0617263 | R5: 0.8535878 | S5: 0.95717132 | T5: -0.37226513 | U5: -0.76641897 | V5: 1.2759865 | W5: -0.90415049 | X5: -1.3331658 | Z5: <0 | AA5: =COUNTIF(A3:X202,"<0") -> 2431 | AC5: =AC4/2 -> 2400 | AE5: =IF(ABS(AA5/AC5-1)<2%,"OK","CHECKDATA") -> OK
A6: -1.2930748 | B6: -1.4015525 | C6: -0.57922257 | D6: -1.0144911 | E6: 0.023442313 | F6: 0.87732029 | G6: -0.61337153 | H6: 2.0609019 | I6: 1.840303 | J6: 0.029457489 | K6: 1.313214 | L6: -0.82139679 | M6: -0.08516264 | N6: 0.40688615 | O6: 1.2226787 | P6: 1.4116945 | Q6: -1.8497058 | R6: -0.5836251 | S6: 0.14973599 | T6: -2.2772537 | U6: 1.2328949 | V6: 0.47288466 | W6: 1.0319211 | X6: -2.4647719 | Z6: >0 | AA6: =COUNTIF(A3:X202,">0") -> 2369 | AC6: =AC4/2 -> 2400 | AE6: =IF(ABS(AA6/AC6-1)<2%,"OK","CHECKDATA") -> OK
A7: 0.97645433 | B7: -1.0185433 | C7: -1.6425807 | D7: -0.17814921 | E7: -0.15292036 | F7: 0.88263481 | G7: 1.1508422 | H7: 0.48022094 | I7: 1.486055 | J7: -0.010283795 | K7: 0.25446361 | L7: -2.3512973 | M7: -0.52950226 | N7: 0.90016167 | O7: 0.68200178 | P7: 0.57076691 | Q7: 0.51778464 | R7: -0.69469038 | S7: 1.0487796 | T7: 0.57999913 | U7: -1.8627087 | V7: 0.73296116 | W7: -0.17657887 | X7: 0.7363381 | AC7: Expected | AD7: Tolerance | AE7: Check
A8: -0.89793305 | B8: 0.57866967 | C8: 0.44446828 | D8: -0.079801854 | E8: 1.1959355 | F8: -0.17686668 | G8: -0.21831739 | H8: 0.48039795 | I8: 0.62761288 | J8: -1.5816897 | K8: -0.40265934 | L8: 0.66805509 | M8: -0.45937814 | N8: 0.23799758 | O8: -0.69853613 | P8: -0.39542171 | Q8: -0.28027179 | R8: -0.24458638 | S8: 1.6673754 | T8: 0.93199237 | U8: 0.25480723 | V8: -1.2585138 | W8: 0.87496672 | X8: 0.50649196 | Z8: Mean | AA8: =AVERAGE(A3:X202) -> -0.0021149778 | AC8: 0 | AD8: 0.01 | AE8: =IF(ABS(AA8-AC8)<AD8,"OK","CHECKDATA") -> OK
A9: -0.28262547 | B9: 0.092131873 | C9: 1.4346317 | D9: 0.28768373 | E9: -0.44805699 | F9: 0.33504424 | G9: 1.1038574 | H9: 1.641755 | I9: -1.0560149 | J9: 1.2528972 | K9: 1.1673231 | L9: -0.42298839 | M9: -0.42381573 | N9: -0.30959528 | O9: 0.23475941 | P9: 0.17326858 | Q9: 0.94135992 | R9: 0.51714367 | S9: 1.0231535 | T9: -0.45127996 | U9: 1.2453767 | V9: -0.45441396 | W9: 0.59183306 | X9: -0.68961071 | Z9: St Dev | AA9: =STDEVA(A3:X202) -> 0.99322894 | AC9: 1 | AD9: 0.01 | AE9: =IF(ABS(AA9-AC9)<AD9,"OK","CHECKDATA") -> OK
A10: 0.90337071 | B10: 0.20097557 | C10: -0.17961626 | D10: 0.0045265381 | E10: -0.5156771 | F10: -0.1146855 | G10: 0.15290375 | H10: 0.29527162 | I10: 0.66278178 | J10: -0.2700742 | K10: 1.2567103 | L10: 1.0045954 | M10: 0.57127317 | N10: 1.689452 | O10: -0.76394124 | P10: -0.428957 | Q10: 0.11828814 | R10: -0.036902563 | S10: -1.2478017 | T10: 1.392183 | U10: 0.82882088 | V10: -1.1175509 | W10: -0.99459728 | X10: 1.4793026
A11: 1.1144525 | B11: 0.63320791 | C11: -0.33650724 | D11: 0.93129751 | E11: -1.5634076 | F11: -1.8792415 | G11: -0.68946732 | H11: -1.3919243 | I11: 0.79634023 | J11: 2.040625 | K11: -0.04825759 | L11: 0.29400641 | M11: 0.2903614 | N11: 1.1216287 | O11: 0.91389305 | P11: -0.56443755 | Q11: 0.97659422 | R11: 1.3319002 | S11: -0.33520942 | T11: 2.1087631 | U11: -0.89867309 | V11: 0.68305667 | W11: -1.0570373 | X11: -0.48237981 | AF11: Chi squared test
A12: -1.0388333 | B12: -1.0343195 | C12: 0.18127506 | D12: -0.56337446 | E12: -1.539804 | F12: 0.49717132 | G12: -0.024042095 | H12: 0.42455778 | I12: -0.93023363 | J12: -0.40444205 | K12: -1.4412951 | L12: 0.52855254 | M12: -0.49289391 | N12: -0.14667295 | O12: -0.86809933 | P12: 1.1966965 | Q12: -0.18942311 | R12: -0.083567678 | S12: 2.1344693 | T12: -0.6274444 | U12: -1.1937021 | V12: 2.4328129 | W12: 0.31838041 | X12: 0.40142765 | Z12: Cumulative frequency | AF12: Observed | AG12: Expected
A13: -0.51425268 | B13: -1.7896973 | C13: -0.082282113 | D13: 0.42921776 | E13: 0.92688709 | F13: -1.3398257 | G13: 1.8196508 | H13: 1.4371506 | I13: -2.4504708 | J13: 0.20057385 | K13: 0.75251932 | L13: -0.34702932 | M13: 0.0027284143 | N13: 0.81591701 | O13: 0.92390942 | P13: 0.69013291 | Q13: 1.2270554 | R13: 0.67557972 | S13: -0.33896996 | T13: -1.0822111 | U13: -0.19721318 | V13: -0.15486837 | W13: 0.89451648 | X13: 0.14417841 | Z13: Less than | AC13: Frequency | AF13: Frequency | AG13: Cumulative | AH13: Frequency | AI13: (O-E)^2/E
A14: 0.69298321 | B14: 2.3164552 | C14: -0.3815292 | D14: -0.73239989 | E14: 2.6704296 | F14: -0.17996439 | G14: -0.48227998 | H14: 0.68429159 | I14: -0.048781595 | J14: 0.30143617 | K14: -0.79492688 | L14: 0.5317517 | M14: -0.78131751 | N14: -0.14256959 | O14: -0.69972298 | P14: 2.2871523 | Q14: 0.60536539 | R14: 1.9944174 | S14: -1.0690809 | T14: -0.54274653 | U14: -1.6847495 | V14: 1.6567354 | W14: -1.2776804 | X14: 0.28709107 | Z14: -3.5 | AA14: =COUNTIF($A$3:$X$202,"<"&Z14) -> 0 | AC14: =AA14 -> 0 | AF14: =AC14 -> 0 | AG14: =_xlfn.NORM.DIST(Z14,$AC$8,$AC$9,TRUE)*$AC$4 -> 1.1166196 | AH14: =AG14 -> 1.1166196 | AI14: =IF(AH14=0,0,((AF14-AH14)^2)/AH14) -> 1.1166196
A15: 1.2161366 | B15: -1.3828136 | C15: -0.93431672 | D15: 0.32365383 | E15: 0.84582575 | F15: 0.33073895 | G15: -0.43162982 | H15: 0.44581214 | I15: 0.89458483 | J15: 0.84549195 | K15: 0.9811145 | L15: -0.58523934 | M15: -0.095366828 | N15: 0.69082485 | O15: 0.5744406 | P15: -0.098536065 | Q15: 1.3315907 | R15: 1.7801374 | S15: -0.25204468 | T15: -0.74581943 | U15: -1.8849188 | V15: 0.8372638 | W15: 0.72954101 | X15: -0.83145346 | Z15: =Z14+0.5 -> -3 | AA15: =COUNTIF($A$3:$X$202,"<"&Z15) -> 6 | AC15: =AA15-AA14 -> 6 | AF15: =AC15 -> 6 | AG15: =_xlfn.NORM.DIST(Z15,$AC$8,$AC$9,TRUE)*$AC$4 -> 6.4795106 | AH15: =AG15-AG14 -> 5.362891 | AI15: =IF(AH15=0,0,((AF15-AH15)^2)/AH15) -> 0.075688265
A16: 0.75236481 | B16: 0.080884748 | C16: -1.4232576 | D16: 0.76359051 | E16: 0.92085098 | F16: -1.3999599 | G16: -0.54455169 | H16: 0.058251538 | I16: 0.14944889 | J16: 0.49583876 | K16: 0.8557322 | L16: 0.40764744 | M16: -0.73386808 | N16: 1.1258467 | O16: -0.33105202 | P16: -0.69591805 | Q16: -0.0067873776 | R16: 0.93388983 | S16: -1.0883986 | T16: 0.36422622 | U16: -0.58400455 | V16: 1.7972833 | W16: -1.4103036 | X16: 0.064535533 | Z16: =Z15+0.5 -> -2.5 | AA16: =COUNTIF($A$3:$X$202,"<"&Z16) -> 25 | AC16: =AA16-AA15 -> 19 | AF16: =AC16 -> 19 | AG16: =_xlfn.NORM.DIST(Z16,$AC$8,$AC$9,TRUE)*$AC$4 -> 29.806394 | AH16: =AG16-AG15 -> 23.326883 | AI16: =IF(AH16=0,0,((AF16-AH16)^2)/AH16) -> 0.80258972
A17: 0.83641238 | B17: 0.20698769 | C17: -0.45687292 | D17: 0.39690874 | E17: -0.44398274 | F17: -0.87970068 | G17: -0.29678258 | H17: -1.8867864 | I17: 2.1313089 | J17: -0.63910491 | K17: 1.1087503 | L17: 0.51551824 | M17: -0.70849688 | N17: 0.11832167 | O17: 0.54805635 | P17: -0.92992907 | Q17: -1.0871728 | R17: 1.2389688 | S17: -0.054527571 | T17: 2.2377699 | U17: -0.24237181 | V17: 1.375237 | W17: -0.70587402 | X17: 0.15247909 | Z17: =Z16+0.5 -> -2 | AA17: =COUNTIF($A$3:$X$202,"<"&Z17) -> 99 | AC17: =AA17-AA16 -> 74 | AF17: =AC17 -> 74 | AG17: =_xlfn.NORM.DIST(Z17,$AC$8,$AC$9,TRUE)*$AC$4 -> 109.20063 | AH17: =AG17-AG16 -> 79.39424 | AI17: =IF(AH17=0,0,((AF17-AH17)^2)/AH17) -> 0.36649791
A18: 1.8493337 | B18: 1.587434 | C18: -0.85836188 | D18: -0.19801793 | E18: 0.067847972 | F18: -1.3071658 | G18: -0.0067500606 | H18: 0.61840986 | I18: 0.29899986 | J18: -0.92612887 | K18: -0.038211928 | L18: -2.600958 | M18: 0.16327293 | N18: 0.91317616 | O18: -1.9666593 | P18: 0.025279147 | Q18: -0.10402992 | R18: 2.1230427 | S18: 0.66208941 | T18: -0.50497021 | U18: 0.71106753 | V18: -1.0466232 | W18: -0.51374437 | X18: -0.50878319 | Z18: =Z17+0.5 -> -1.5 | AA18: =COUNTIF($A$3:$X$202,"<"&Z18) -> 308 | AC18: =AA18-AA17 -> 209 | AF18: =AC18 -> 209 | AG18: =_xlfn.NORM.DIST(Z18,$AC$8,$AC$9,TRUE)*$AC$4 -> 320.67457 | AH18: =AG18-AG17 -> 211.47393 | AI18: =IF(AH18=0,0,((AF18-AH18)^2)/AH18) -> 0.02894136
A19: -0.50421011 | B19: 0.7485653 | C19: -1.2621451 | D19: -0.90801786 | E19: -0.84747089 | F19: -0.33410796 | G19: -1.3556098 | H19: 0.98648164 | I19: -0.9058722 | J19: 0.48853468 | K19: -1.7415017 | L19: 0.3074255 | M19: -1.3852498 | N19: -2.2866829 | O19: 0.097081482 | P19: -1.3408218 | Q19: -1.0285668 | R19: 1.6007877 | S19: -0.64466582 | T19: 0.86520557 | U19: -0.45623713 | V19: 0.46938802 | W19: 0.6380247 | X19: 1.4141735 | Z19: =Z18+0.5 -> -1 | AA19: =COUNTIF($A$3:$X$202,"<"&Z19) -> 756 | AC19: =AA19-AA18 -> 448 | AF19: =AC19 -> 448 | AG19: =_xlfn.NORM.DIST(Z19,$AC$8,$AC$9,TRUE)*$AC$4 -> 761.54522 | AH19: =AG19-AG18 -> 440.87065 | AI19: =IF(AH19=0,0,((AF19-AH19)^2)/AH19) -> 0.11528912
A20: 0.026831162 | B20: 0.094072323 | C20: 0.26176874 | D20: -1.1461351 | E20: -1.2507429 | F20: -0.81350573 | G20: 0.21217187 | H20: 0.66627967 | I20: 0.66078202 | J20: -0.27620688 | K20: 0.57478277 | L20: 1.9315833 | M20: 0.26073809 | N20: -0.57776599 | O20: 0.6327144 | P20: 0.4488114 | Q20: 0.98131873 | R20: 0.11570795 | S20: 0.34187796 | T20: -0.56117809 | U20: -0.83248349 | V20: 0.45060032 | W20: 1.2856427 | X20: 0.42780211 | Z20: =Z19+0.5 -> -0.5 | AA20: =COUNTIF($A$3:$X$202,"<"&Z20) -> 1515 | AC20: =AA20-AA19 -> 759 | AF20: =AC20 -> 759 | AG20: =_xlfn.NORM.DIST(Z20,$AC$8,$AC$9,TRUE)*$AC$4 -> 1480.9802 | AH20: =AG20-AG19 -> 719.43497 | AI20: =IF(AH20=0,0,((AF20-AH20)^2)/AH20) -> 2.1758629
A21: -0.47908031 | B21: -0.20984074 | C21: 3.5326788 | D21: 0.32705945 | E21: -0.48729843 | F21: 2.5198122 | G21: 1.5079537 | H21: -0.8342939 | I21: 0.33539125 | J21: 1.4820509 | K21: -0.37965249 | L21: -0.11797461 | M21: 0.32605594 | N21: -0.77666858 | O21: 1.4225897 | P21: 1.1096281 | Q21: 0.4464303 | R21: 0.11689596 | S21: 0.58727187 | T21: -0.12299907 | U21: -0.29758587 | V21: -1.1772214 | W21: -0.36569911 | X21: -0.61653357 | Z21: =Z20+0.5 -> 0 | AA21: =COUNTIF($A$3:$X$202,"<"&Z21) -> 2431 | AC21: =AA21-AA20 -> 916 | AF21: =AC21 -> 916 | AG21: =_xlfn.NORM.DIST(Z21,$AC$8,$AC$9,TRUE)*$AC$4 -> 2400 | AH21: =AG21-AG20 -> 919.01981 | AI21: =IF(AH21=0,0,((AF21-AH21)^2)/AH21) -> 0.0099228299
A22: 0.50371427 | B22: -0.99231714 | C22: -0.29094974 | D22: 1.0536583 | E22: -0.77454801 | F22: 0.12979083 | G22: -0.76158118 | H22: -0.94449558 | I22: 0.4544607 | J22: 0.97057723 | K22: 1.3040868 | L22: 2.0048174 | M22: -0.032978061 | N22: 0.13306548 | O22: 0.083695107 | P22: -1.5692632 | Q22: -0.070445403 | R22: -1.217408 | S22: -0.23584082 | T22: -1.3055378 | U22: -0.005225342 | V22: 0.075130955 | W22: -0.34259802 | X22: -0.92772454 | Z22: =Z21+0.5 -> 0.5 | AA22: =COUNTIF($A$3:$X$202,"<"&Z22) -> 3306 | AC22: =AA22-AA21 -> 875 | AF22: =AC22 -> 875 | AG22: =_xlfn.NORM.DIST(Z22,$AC$8,$AC$9,TRUE)*$AC$4 -> 3319.0198 | AH22: =AG22-AG21 -> 919.01981 | AI22: =IF(AH22=0,0,((AF22-AH22)^2)/AH22) -> 2.1084899
A23: 0.35576582 | B23: 0.96115003 | C23: 0.55115594 | D23: 1.2247622 | E23: 1.2354768 | F23: 2.6294129 | G23: 0.36432212 | H23: 1.5755909 | I23: 0.60010049 | J23: 0.83518245 | K23: -0.72844906 | L23: -0.88990185 | M23: 0.29865665 | N23: 1.0393409 | O23: 0.59124429 | P23: 0.008194518 | Q23: -0.85626386 | R23: 0.62373566 | S23: 0.31963095 | T23: 0.26924288 | U23: 0.88520749 | V23: 0.48660523 | W23: -0.068339417 | X23: -0.061251136 | Z23: =Z22+0.5 -> 1 | AA23: =COUNTIF($A$3:$X$202,"<"&Z23) -> 4030 | AC23: =AA23-AA22 -> 724 | AF23: =AC23 -> 724 | AG23: =_xlfn.NORM.DIST(Z23,$AC$8,$AC$9,TRUE)*$AC$4 -> 4038.4548 | AH23: =AG23-AG22 -> 719.43497 | AI23: =IF(AH23=0,0,((AF23-AH23)^2)/AH23) -> 0.028966518
A24: 0.093213964 | B24: 0.60535639 | C24: -1.4001201 | D24: 1.0113555 | E24: 1.1990871 | F24: 0.77996102 | G24: -0.59270283 | H24: -1.0152444 | I24: -0.20751415 | J24: -0.18589044 | K24: -0.53230913 | L24: -0.5564443 | M24: -0.43595857 | N24: 0.65868892 | O24: 0.49112837 | P24: 0.16558835 | Q24: 0.13820024 | R24: 0.53871373 | S24: -0.10339617 | T24: -0.5249774 | U24: -0.12594535 | V24: -0.61277812 | W24: 0.76560224 | X24: 0.68891088 | Z24: =Z23+0.5 -> 1.5 | AA24: =COUNTIF($A$3:$X$202,"<"&Z24) -> 4482 | AC24: =AA24-AA23 -> 452 | AF24: =AC24 -> 452 | AG24: =_xlfn.NORM.DIST(Z24,$AC$8,$AC$9,TRUE)*$AC$4 -> 4479.3254 | AH24: =AG24-AG23 -> 440.87065 | AI24: =IF(AH24=0,0,((AF24-AH24)^2)/AH24) -> 0.28094945
A25: -0.18876042 | B25: 0.011038919 | C25: -0.71879608 | D25: 0.24455367 | E25: 0.48973834 | F25: 0.36144805 | G25: -1.7919001 | H25: 0.82168526 | I25: 0.21083671 | J25: 0.15881338 | K25: 0.32201163 | L25: 0.030606567 | M25: -1.7241888 | N25: -0.72068297 | O25: 0.40042844 | P25: 0.9102522 | Q25: 1.7372556 | R25: -0.25917283 | S25: 0.12436436 | T25: -0.95152844 | U25: 1.0887335 | V25: -1.8218776 | W25: 0.62284552 | X25: -0.033702851 | Z25: =Z24+0.5 -> 2 | AA25: =COUNTIF($A$3:$X$202,"<"&Z25) -> 4697 | AC25: =AA25-AA24 -> 215 | AF25: =AC25 -> 215 | AG25: =_xlfn.NORM.DIST(Z25,$AC$8,$AC$9,TRUE)*$AC$4 -> 4690.7994 | AH25: =AG25-AG24 -> 211.47393 | AI25: =IF(AH25=0,0,((AF25-AH25)^2)/AH25) -> 0.058792827
A26: 1.120455 | B26: -0.23273267 | C26: -0.48985249 | D26: -1.5463445 | E26: -0.40701286 | F26: 1.8743616 | G26: 0.3360675 | H26: 1.6115294 | I26: 1.3876082 | J26: -1.1189132 | K26: 1.302495 | L26: -0.60691409 | M26: 0.82913869 | N26: -0.20855015 | O26: -1.4296083 | P26: 0.0041970175 | Q26: -1.1994723 | R26: 0.83211127 | S26: -1.7882665 | T26: -1.2114134 | U26: -0.20372206 | V26: 2.0986665 | W26: -1.1018403 | X26: 1.5519444 | Z26: =Z25+0.5 -> 2.5 | AA26: =COUNTIF($A$3:$X$202,"<"&Z26) -> 4768 | AC26: =AA26-AA25 -> 71 | AF26: =AC26 -> 71 | AG26: =_xlfn.NORM.DIST(Z26,$AC$8,$AC$9,TRUE)*$AC$4 -> 4770.1936 | AH26: =AG26-AG25 -> 79.39424 | AI26: =IF(AH26=0,0,((AF26-AH26)^2)/AH26) -> 0.88751101
... A28: 0.59436605 | B28: 0.97332291 | C28: -0.19254159 | D28: 0.34444304 | E28: 0.23290895 | F28: -0.65640995 | G28: 0.33035284 | H28: 0.26850251 | I28: 0.8523767 | J28: -0.40077819 | K28: -0.33718509 | L28: -1.6099334 | M28: -1.5964488 | N28: 1.6099292 | O28: 0.0098813419 | P28: 0.90410234 | Q28: -0.23086087 | R28: 0.44735595 | S28: 0.9491471 | T28: 0.36412889 | U28: -0.28101921 | V28: -0.15576053 | W28: 0.011442133 | X28: 0.48538863 | Z28: =Z27+0.5 -> 3.5 | AA28: =COUNTIF($A$3:$X$202,"<"&Z28) -> 4798 | AC28: =AA28-AA27 -> 5 | AF28: =AC28 -> 5 | AG28: =_xlfn.NORM.DIST(Z28,$AC$8,$AC$9,TRUE)*$AC$4 -> 4798.8834 | AH28: =AG28-AG27 -> 5.362891 | AI28: =IF(AH28=0,0,((AF28-AH28)^2)/AH28) -> 0.024555759
A29: 1.0784272 | B29: -0.092208202 | C29: 0.1751745 | D29: -1.8658773 | E29: 0.78240722 | F29: -0.70762296 | G29: -1.8297238 | H29: 0.51158256 | I29: -0.33668991 | J29: -0.89997898 | K29: -0.22143301 | L29: -0.9874783 | M29: 0.17559429 | N29: 0.21563051 | O29: -0.7468317 | P29: -1.1534674 | Q29: -1.4022242 | R29: -0.51756686 | S29: 0.52519658 | T29: -0.22104584 | U29: -0.22619865 | V29: -0.10463054 | W29: -0.61452358 | X29: 0.26184273 | Y29: Greater than | Z29: 3.5 | AA29: =AA4 -> 4800 | AC29: =AA29-AA28 -> 2 | AF29: =AC29 -> 2 | AG29: =AC4 -> 4800 | AH29: =AG29-AG28 -> 1.1166196 | AI29: =IF(AH29=0,0,((AF29-AH29)^2)/AH29) -> 0.69886019
A30: -1.1333851 | B30: -0.44304625 | C30: 1.1668325 | D30: -0.99970368 | E30: -0.92196426 | F30: -1.8399916 | G30: -0.46958363 | H30: -1.3509215 | I30: -0.40269321 | J30: 0.82484534 | K30: 0.36496222 | L30: -0.027741843 | M30: 0.90899555 | N30: -0.38012911 | O30: -1.0083168 | P30: 2.0635238 | Q30: -2.2049343 | R30: -0.73026681 | S30: -1.0672472 | T30: 0.27790117 | U30: -0.82859196 | V30: -0.67339837 | W30: -0.18967077 | X30: 0.073221937 | AC30: =SUM(AC14:AC29) -> 4800 | AD30: =IF(AA29=AC30,"OK","Check frequencies") -> OK | AF30: Total | AI30: =SUM(AI14:AI29) -> 8.8995414
A31: -1.334601 | B31: 0.35838842 | C31: -0.30475605 | D31: 3.6562013 | E31: -0.52235416 | F31: -1.7855205 | G31: -0.41381909 | H31: -1.0986998 | I31: -0.32538824 | J31: -1.5476362 | K31: -0.78169223 | L31: 1.1692844 | M31: -0.41386425 | N31: 0.27247018 | O31: 0.60273429 | P31: 1.932645 | Q31: -0.72394635 | R31: 0.67150868 | S31: 1.0997312 | T31: 2.1057818 | U31: -1.7343362 | V31: 1.764252 | W31: 0.42391697 | X31: -3.13275 | AH31: Degrees of freedom | AI31: =COUNT(Z14:Z29)-1 -> 15
A32: 1.5347621 | B32: -2.6646504 | C32: -1.8206573 | D32: -0.82012156 | E32: -0.83979579 | F32: -0.9216245 | G32: 0.72721278 | H32: 0.94963448 | I32: -2.0702039 | J32: 1.1848321 | K32: -0.93005224 | L32: 1.0376494 | M32: -1.12137 | N32: 1.7034729 | O32: 1.1046464 | P32: -0.36884797 | Q32: -0.43262844 | R32: 0.38880102 | S32: 0.72190334 | T32: -0.66995149 | U32: -0.93118052 | V32: -0.49815578 | W32: -1.5711579 | X32: -0.023274946
A33: 1.6123527 | B33: 0.48680411 | C33: -0.91517094 | D33: -1.0382023 | E33: -0.27523826 | F33: -1.1581128 | G33: 0.064994811 | H33: -1.6225365 | I33: -1.6429458 | J33: -0.57021798 | K33: -0.52746345 | L33: 1.3745647 | M33: 0.56434418 | N33: -0.51903864 | O33: -0.75046447 | P33: 0.86588124 | Q33: -0.55623017 | R33: 0.1116461 | S33: 0.47430942 | T33: -0.96434764 | U33: -0.10988615 | V33: -0.78713789 | W33: -0.57971717 | X33: -1.7786931 | AH33: Test Statistic (85% confidence) | AI33: =CHIINV(85%,AI31) -> 9.4992816
A34: 0.94736079 | B34: -0.51632123 | C34: -0.18834587 | D34: 1.8417488 | E34: -0.18224578 | F34: 0.15201406 | G34: 0.27629419 | H34: 1.3736237 | I34: -0.33745027 | J34: -3.1058177 | K34: 1.7863364 | L34: -0.83233112 | M34: -0.17010867 | N34: -1.1419059 | O34: -0.56158464 | P34: -0.46675584 | Q34: 0.10612564 | R34: -1.5378739 | S34: -0.53377145 | T34: 0.19214951 | U34: 1.6367637 | V34: -1.4001157 | W34: 0.80184421 | X34: -0.11549875
A35: -0.36970787 | B35: -0.027897289 | C35: -0.48474717 | D35: -0.78331261 | E35: 1.0350076 | F35: 0.48860186 | G35: -0.82168782 | H35: -0.75222778 | I35: -0.17490694 | J35: -2.1692993 | K35: -0.052874059 | L35: 0.91388771 | M35: 0.62904693 | N35: 0.93591205 | O35: -0.49423596 | P35: 1.2814736 | Q35: 0.54793547 | R35: 0.015856527 | S35: -2.924716 | T35: 0.4195013 | U35: 0.40584677 | V35: -0.87376323 | W35: 1.378394 | X35: 1.7215833 | AH35: Result of Chi-squared test | AI35: =IF(AI33>AI30,"Accept Hypothesis", "Reject Hypothesis") -> Accept Hypothesis
A36: 1.2080412 | B36: 0.0077260303 | C36: -0.39157903 | D36: 0.194809 | E36: 2.0360602 | F36: 0.4121811 | G36: 0.91631982 | H36: 0.18179786 | I36: 0.63343193 | J36: 1.0082218 | K36: 0.89010299 | L36: 1.9982864 | M36: 0.1562516 | N36: 0.51374072 | O36: -0.10322577 | P36: -0.45319956 | Q36: 2.2882493 | R36: -0.63155019 | S36: 0.23676281 | T36: 0.73840676 | U36: 1.6782176 | V36: -0.73727932 | W36: -0.16436652 | X36: 1.0985271
A37: -0.23102431 | B37: -0.93078006 | C37: -0.16046686 | D37: -1.4816431 | E37: -1.1990797 | F37: -0.52605465 | G37: 0.65318148 | H37: 0.73762309 | I37: 0.12026044 | J37: -0.5764139 | K37: 0.39554023 | L37: -1.6733726 | M37: -0.89288296 | N37: 0.40870711 | O37: 1.6432465 | P37: 1.166852 | Q37: -1.7311158 | R37: -0.36214287 | S37: 0.23430698 | T37: 0.23036617 | U37: 1.7535142 | V37: 0.21297669 | W37: 0.66233061 | X37: 0.98329528
A38: 1.171946 | B38: 0.26642403 | C38: -0.45181825 | D38: -0.029530694 | E38: -0.45574619 | F38: 0.55411881 | G38: -1.1877385 | H38: 0.079891615 | I38: 1.0021609 | J38: -0.85970691 | K38: -2.3407317 | L38: -0.50482653 | M38: 1.1882356 | N38: -1.1083553 | O38: 0.84702546 | P38: -0.46273534 | Q38: 1.3518906 | R38: -0.041885585 | S38: -1.2256424 | T38: 1.1218256 | U38: -0.29244098 | V38: -0.60885198 | W38: -0.083088099 | X38: -0.010502245
A39: -1.4718158 | B39: -0.17414591 | C39: -0.11506885 | D39: -1.3746392 | E39: -1.2022078 | F39: -0.51645241 | G39: -0.6553581 | H39: 0.46036908 | I39: -1.8412926 | J39: 0.46169839 | K39: 0.42148892 | L39: -1.4557863 | M39: -0.96371867 | N39: -0.41658814 | O39: -0.10244953 | P39: 0.041082565 | Q39: -0.50654452 | R39: 0.99600721 | S39: 0.98637553 | T39: -0.26083372 | U39: -0.36744006 | V39: 0.326808 | W39: -1.2812904 | X39: -0.70943076
A40: -1.3131976 | B40: 3.0824735 | C40: 0.77726622 | D40: -0.22808361 | E40: 1.5735455 | F40: -0.65934216 | G40: 0.96625716 | H40: -0.13577945 | I40: 2.6414689 | J40: -0.7018091 | K40: -0.44319227 | L40: -0.90319682 | M40: 0.12491883 | N40: -1.0325723 | O40: -0.48597281 | P40: 0.38209795 | Q40: -0.70408117 | R40: -0.67213233 | S40: -0.87207085 | T40: -0.029731386 | U40: 1.5456126 | V40: 0.29195231 | W40: 1.3215612 | X40: -0.1784399
A41: -1.2926706 | B41: -0.4352653 | C41: -1.7578548 | D41: -0.66988133 | E41: -0.91528405 | F41: -1.1157637 | G41: -0.28325205 | H41: -0.92768269 | I41: -0.24244994 | J41: -0.73191076 | K41: -1.0763893 | L41: 0.20150693 | M41: -0.84594037 | N41: -0.97624131 | O41: -1.6560209 | P41: 0.7175584 | Q41: 0.13957442 | R41: 0.36379973 | S41: -0.0915272 | T41: 1.91236 | U41: -1.2824826 | V41: -0.41548186 | W41: 0.83297024 | X41: 0.83954313
A42: -0.2218566 | B42: 0.52744218 | C42: -0.1886978 | D42: -1.4983137 | E42: 0.14973062 | F42: -0.3464965 | G42: 0.27741927 | H42: -1.8159724 | I42: 0.76509596 | J42: 0.021057503 | K42: -0.60744025 | L42: -1.0148628 | M42: 1.1309534 | N42: 0.036650445 | O42: -0.73699902 | P42: 0.15880395 | Q42: -1.2340053 | R42: 0.54083301 | S42: -0.14585809 | T42: 1.3618533 | U42: 1.2727094 | V42: 0.33290601 | W42: 0.19477092 | X42: 0.063836822
A43: 0.30463678 | B43: 1.5865851 | C43: -0.23887888 | D43: 0.5530484 | E43: 0.057167995 | F43: 1.1717614 | G43: -0.48697055 | H43: -1.1968364 | I43: 0.55788098 | J43: -1.6351276 | K43: -1.3520555 | L43: -1.3392234 | M43: -0.59822535 | N43: -0.32424367 | O43: 0.13623858 | P43: -0.11627217 | Q43: 0.99201629 | R43: -0.016260663 | S43: -1.637957 | T43: -0.72331554 | U43: -1.300267 | V43: -1.5410615 | W43: 0.85151464 | X43: -1.5645496
A44: -0.28600425 | B44: 0.0086453434 | C44: -0.74223503 | D44: 1.3221615 | E44: 0.19436971 | F44: 0.70402014 | G44: -0.030251963 | H44: -0.03875293 | I44: 1.0241238 | J44: 0.14018486 | K44: 0.2763479 | L44: -0.15488666 | M44: -0.52272284 | N44: 0.23772643 | O44: -0.0076181796 | P44: -0.82134884 | Q44: 0.42144583 | R44: 1.468385 | S44: -0.013336301 | T44: 1.2147433 | U44: 0.74340434 | V44: -1.3504776 | W44: 0.33981743 | X44: 0.9955029
A45: -1.5804897 | B45: -0.58398015 | C45: -0.69279339 | D45: 0.45484886 | E45: 0.84197765 | F45: -0.8422194 | G45: 1.1297326 | H45: 2.4324062 | I45: -0.73504101 | J45: -0.56572887 | K45: -0.26619828 | L45: -0.57718684 | M45: -0.69909689 | N45: 0.42771985 | O45: -0.079260703 | P45: 0.3467579 | Q45: -0.11180237 | R45: -0.70840658 | S45: -0.76647937 | T45: -1.2577463 | U45: -0.34167921 | V45: -0.072737836 | W45: -1.3310152 | X45: 1.1752537
A46: -1.7146014 | B46: 0.61265296 | C46: 1.0057741 | D46: 0.91946237 | E46: 1.8535673 | F46: -1.1003162 | G46: 1.0403808 | H46: 0.80264266 | I46: -0.88202058 | J46: 0.33697692 | K46: -0.57897418 | L46: -0.42411841 | M46: 1.5138019 | N46: -0.018007487 | O46: -1.2832524 | P46: 1.4143175 | Q46: 0.62726674 | R46: -0.9225435 | S46: -1.006537 | T46: -0.056114089 | U46: -0.27099613 | V46: -0.048765834 | W46: 0.25606704 | X46: 0.28402289
A47: -0.71078331 | B47: -0.60287416 | C47: 1.015963 | D47: -1.5049066 | E47: -0.75166076 | F47: -1.20322 | G47: 0.13649328 | H47: -1.1951042 | I47: 0.88019565 | J47: 0.95226715 | K47: 0.63055325 | L47: -1.6869833 | M47: -0.27099242 | N47: 2.1255432 | O47: 0.81913395 | P47: -1.5276665 | Q47: 0.91649257 | R47: -1.3772965 | S47: 0.59386136 | T47: 1.2285224 | U47: 0.37777254 | V47: 0.38026343 | W47: 0.85695568 | X47: -0.23512632
... A202: -0.25658939 | B202: -0.9417663 | C202: 0.4828304 | D202: 1.0275812 | E202: 0.58672894 | F202: -0.85655301 | G202: 0.5568549 | H202: -2.1275822 | I202: -0.28762155 | J202: 1.0358353 | K202: 1.5316532 | L202: -0.41555853 | M202: 0.49672297 | N202: 0.34087845 | O202: 0.68420876 | P202: 0.54293877 | Q202: 2.0395807 | R202: -0.18211208 | S202: -3.0926302 | T202: 0.08355831 | U202: -0.53997734 | V202: 0.6434959 | W202: -0.75029362 | X202: -0.19931849

Sheet Parameters
A1: Mortgage Term | B1: 25 | C1: years | E1: Mort_term
A3: House price | B3: 200000 | C3: $ | E3: House_price
A5: Monthly Deposit Saving | B5: 1000 | C5: $ | E5: Deposit_mon
A7: Deposit investment term | B7: 2 | C7: years | E7: Dep_term
A9: Fixed projection
A11: Fixed interest rate | B11: 0.05 | E11: Fixed_int
A13: Period of payments | B13: 12 | C13: months | E13: Fixed_freq
A15: Fixed term for mortgage | B15: 25 | C15: years | E15: Product_term
A17: Simulations
A19: Base interest rate | B19: 0.045 | E19: Base_int_rate
A21: Period of payments | B21: 12 | C21: months | E21: Var_freq
A23: Interest rate movements
A25: <-2.0 | B25: -1000000 | C25: -0.005
A26: -2.0 to -1.5 | B26: -2 | C26: -0.0025
A27: -1.5 to 1.5 | B27: -1.5 | C27: 0
A28: 1.5 to 2.0 | B28: 1.5 | C28: 0.0025
A29: >=2.0 | B29: 2 | C29: 0.005 | E29: Int_rate_movements
A32: Average interest tolerance | B32: 0.001 | E32: Int_check_tolerance
A35: Alternative scenario
A37: Monthly Deposit Saving | B37: 2000 | C37: $ | E37: Deposit_mon_alt
A39: Deposit investment term | B39: 1 | C39: year | E39: Dep_term_alt
A41: Fixed term for mortgage | B41: 5 | C41: years | E41: Product_term_alt

Sheet Fixed rate projection
A1: Fixed rate projection
A3: Rate of interest | B3: i | C3: =Fixed_int -> 0.05 | Z3: Expected accumulation | AA3: =Deposit_mon*Fixed_freq*Dep_term*(1+'Fixed rate projection'!C3)^(Dep_term/2) -> 25200 | AD3: Total monthly repayments | AE3: =AE10*Product_term*Fixed_freq -> 303069
A4: Rate of interest convertible monthly | B4: i(12) | C4: =Fixed_freq*((1+C3)^(1/Fixed_freq)-1) -> 0.048889485 | Z4: Check on accumulation | AA4: =IF((AA10/AA3)-1<1%,"OK","CHECK ACCUMULATION") -> OK
A5: Annuity rate | C5: =(1-(1+C3)^-Mort_term)/C4 -> 14.414086
A7: Projection
A9: Month | B9: Start | C9: 1 | D9: =IF(C9+1>Dep_term*12,"Mortgage starts",C9+1) -> 2 | E9: =IF(D9+1>Dep_term*12,"Mortgage starts",D9+1) -> 3 | F9: =IF(E9+1>Dep_term*12,"Mortgage starts",E9+1) -> 4 | G9: =IF(F9+1>Dep_term*12,"Mortgage starts",F9+1) -> 5 | H9: =IF(G9+1>Dep_term*12,"Mortgage starts",G9+1) -> 6 | I9: =IF(H9+1>Dep_term*12,"Mortgage starts",H9+1) -> 7 | J9: =IF(I9+1>Dep_term*12,"Mortgage starts",I9+1) -> 8 | K9: =IF(J9+1>Dep_term*12,"Mortgage starts",J9+1) -> 9 | ... AA9: =IF(Z9+1>Dep_term*12,"Mortgage starts",Z9+1) -> Mortgage starts | AC9: Mortgage required | AE9: Monthly repayment
A10: Deposit accumulation ($) | C10: =Deposit_mon -> 1000 | D10: =ROUND(C10*(1+$C$4/Fixed_freq)+IF(D$9="Mortgage Starts",0,Deposit_mon),2) -> 2004.07 | E10: =ROUND(D10*(1+$C$4/Fixed_freq)+IF(E$9="Mortgage Starts",0,Deposit_mon),2) -> 3012.23 | F10: =ROUND(E10*(1+$C$4/Fixed_freq)+IF(F$9="Mortgage Starts",0,Deposit_mon),2) -> 4024.5 | G10: =ROUND(F10*(1+$C$4/Fixed_freq)+IF(G$9="Mortgage Starts",0,Deposit_mon),2) -> 5040.9 | H10: =ROUND(G10*(1+$C$4/Fixed_freq)+IF(H$9="Mortgage Starts",0,Deposit_mon),2) -> 6061.44 | I10: =ROUND(H10*(1+$C$4/Fixed_freq)+IF(I$9="Mortgage Starts",0,Deposit_mon),2) -> 7086.14 | J10: =ROUND(I10*(1+$C$4/Fixed_freq)+IF(J$9="Mortgage Starts",0,Deposit_mon),2) -> 8115.01 | K10: =ROUND(J10*(1+$C$4/Fixed_freq)+IF(K$9="Mortgage Starts",0,Deposit_mon),2) -> 9148.07 | ... AA10: =ROUND(Z10*(1+$C$4/Fixed_freq)+IF(AA$9="Mortgage Starts",0,Deposit_mon),2) -> 25261.28 | AC10: =House_price-AA10 -> 174738.72 | AE10: =ROUND(AC10/C5/Fixed_freq,2) -> 1010.23

Sheet Interest rate projection
A1: Projection of variable interest rate | AB1: Variable interest rate convertible monthly
B3: Average | C3: =AVERAGE(C8:C207) -> 0.0450625 | D3: =AVERAGE(D8:D207) -> 0.0451375 | E3: =AVERAGE(E8:E207) -> 0.0451625 | F3: =AVERAGE(F8:F207) -> 0.0451625 | G3: =AVERAGE(G8:G207) -> 0.0451625 | H3: =AVERAGE(H8:H207) -> 0.04515 | I3: =AVERAGE(I8:I207) -> 0.0451625 | J3: =AVERAGE(J8:J207) -> 0.04525 | ... Z3: =AVERAGE(Z8:Z207) -> 0.045175 | AB3: =AVERAGE(AB8:AB207) -> 0.044097713 | AC3: =AVERAGE(AC8:AC207) -> 0.04415728 | AD3: =AVERAGE(AD8:AD207) -> 0.044228183 | AE3: =AVERAGE(AE8:AE207) -> 0.044251302 | AF3: =AVERAGE(AF8:AF207) -> 0.044250828 | AG3: =AVERAGE(AG8:AG207) -> 0.044250196 | AH3: =AVERAGE(AH8:AH207) -> 0.044237046 | AI3: =AVERAGE(AI8:AI207) -> 0.044247855 | ... AZ3: =AVERAGE(AZ8:AZ207) -> 0.044249557
A4: Check average close to starting position | C4: =IF(ABS(C3-Base_int_rate)<Int_check_tolerance,"OK","CHECK") -> OK | D4: =IF(ABS(D3-Base_int_rate)<Int_check_tolerance,"OK","CHECK") -> OK | E4: =IF(ABS(E3-Base_int_rate)<Int_check_tolerance,"OK","CHECK") -> OK | F4: =IF(ABS(F3-Base_int_rate)<Int_check_tolerance,"OK","CHECK") -> OK | G4: =IF(ABS(G3-Base_int_rate)<Int_check_tolerance,"OK","CHECK") -> OK | H4: =IF(ABS(H3-Base_int_rate)<Int_check_tolerance,"OK","CHECK") -> OK | I4: =IF(ABS(I3-Base_int_rate)<Int_check_tolerance,"OK","CHECK") -> OK | J4: =IF(ABS(J3-Base_int_rate)<Int_check_tolerance,"OK","CHECK") -> OK | ... Z4: =IF(ABS(Z3-Base_int_rate)<Int_check_tolerance,"OK","CHECK") -> OK | AB4: =IF(ABS(AB3-(Var_freq*((1+Base_int_rate)^(1/Var_freq)-1)))<Int_check_tolerance,"OK","CHECK") -> OK | AC4: =IF(ABS(AC3-(Var_freq*((1+Base_int_rate)^(1/Var_freq)-1)))<Int_check_tolerance,"OK","CHECK") -> OK | AD4: =IF(ABS(AD3-(Var_freq*((1+Base_int_rate)^(1/Var_freq)-1)))<Int_check_tolerance,"OK","CHECK") -> OK | AE4: =IF(ABS(AE3-(Var_freq*((1+Base_int_rate)^(1/Var_freq)-1)))<Int_check_tolerance,"OK","CHECK") -> OK | AF4: =IF(ABS(AF3-(Var_freq*((1+Base_int_rate)^(1/Var_freq)-1)))<Int_check_tolerance,"OK","CHECK") -> OK | AG4: =IF(ABS(AG3-(Var_freq*((1+Base_int_rate)^(1/Var_freq)-1)))<Int_check_tolerance,"OK","CHECK") -> OK | AH4: =IF(ABS(AH3-(Var_freq*((1+Base_int_rate)^(1/Var_freq)-1)))<Int_check_tolerance,"OK","CHECK") -> OK | AI4: =IF(ABS(AI3-(Var_freq*((1+Base_int_rate)^(1/Var_freq)-1)))<Int_check_tolerance,"OK","CHECK") -> OK | ... AZ4: =IF(ABS(AZ3-(Var_freq*((1+Base_int_rate)^(1/Var_freq)-1)))<Int_check_tolerance,"OK","CHECK") -> OK
B6: Month - start of
A7: Simulation | B7: 1 | C7: 2 | D7: 3 | E7: 4 | F7: 5 | G7: 6 | H7: 7 | I7: 8 | J7: 9 | K7: 10 | L7: 11 | M7: 12 | N7: 13 | O7: 14 | P7: 15 | Q7: 16 | R7: 17 | S7: 18 | T7: 19 | U7: 20 | V7: 21 | W7: 22 | X7: 23 | Y7: 24 | Z7: 25 | AB7: =B7 -> 1 | AC7: =C7 -> 2 | AD7: =D7 -> 3 | AE7: =E7 -> 4 | AF7: =F7 -> 5 | AG7: =G7 -> 6 | AH7: =H7 -> 7 | AI7: =I7 -> 8 | ... AZ7: =Z7 -> 25
A8: 1 | B8: =Base_int_rate -> 0.045 | C8: =B8+VLOOKUP(Rawdata!A3,Int_rate_movements,2,TRUE) -> 0.045 | D8: =C8+VLOOKUP(Rawdata!B3,Int_rate_movements,2,TRUE) -> 0.045 | E8: =D8+VLOOKUP(Rawdata!C3,Int_rate_movements,2,TRUE) -> 0.045 | F8: =E8+VLOOKUP(Rawdata!D3,Int_rate_movements,2,TRUE) -> 0.0425 | G8: =F8+VLOOKUP(Rawdata!E3,Int_rate_movements,2,TRUE) -> 0.0425 | H8: =G8+VLOOKUP(Rawdata!F3,Int_rate_movements,2,TRUE) -> 0.0425 | I8: =H8+VLOOKUP(Rawdata!G3,Int_rate_movements,2,TRUE) -> 0.0425 | J8: =I8+VLOOKUP(Rawdata!H3,Int_rate_movements,2,TRUE) -> 0.0425 | ... Z8: =Y8+VLOOKUP(Rawdata!X3,Int_rate_movements,2,TRUE) -> 0.0425 | AB8: =Var_freq*((1+B8)^(1/Var_freq)-1) -> 0.044097713 | AC8: =Var_freq*((1+C8)^(1/Var_freq)-1) -> 0.044097713 | AD8: =Var_freq*((1+D8)^(1/Var_freq)-1) -> 0.044097713 | AE8: =Var_freq*((1+E8)^(1/Var_freq)-1) -> 0.044097713 | AF8: =Var_freq*((1+F8)^(1/Var_freq)-1) -> 0.04169394 | AG8: =Var_freq*((1+G8)^(1/Var_freq)-1) -> 0.04169394 | AH8: =Var_freq*((1+H8)^(1/Var_freq)-1) -> 0.04169394 | AI8: =Var_freq*((1+I8)^(1/Var_freq)-1) -> 0.04169394 | ... AZ8: =Var_freq*((1+Z8)^(1/Var_freq)-1) -> 0.04169394
A9: 2 | B9: =Base_int_rate -> 0.045 | C9: =B9+VLOOKUP(Rawdata!A4,Int_rate_movements,2,TRUE) -> 0.045 | D9: =C9+VLOOKUP(Rawdata!B4,Int_rate_movements,2,TRUE) -> 0.045 | E9: =D9+VLOOKUP(Rawdata!C4,Int_rate_movements,2,TRUE) -> 0.045 | F9: =E9+VLOOKUP(Rawdata!D4,Int_rate_movements,2,TRUE) -> 0.045 | G9: =F9+VLOOKUP(Rawdata!E4,Int_rate_movements,2,TRUE) -> 0.045 | H9: =G9+VLOOKUP(Rawdata!F4,Int_rate_movements,2,TRUE) -> 0.045 | I9: =H9+VLOOKUP(Rawdata!G4,Int_rate_movements,2,TRUE) -> 0.0425 | J9: =I9+VLOOKUP(Rawdata!H4,Int_rate_movements,2,TRUE) -> 0.0425 | ... Z9: =Y9+VLOOKUP(Rawdata!X4,Int_rate_movements,2,TRUE) -> 0.0375 | AB9: =Var_freq*((1+B9)^(1/Var_freq)-1) -> 0.044097713 | AC9: =Var_freq*((1+C9)^(1/Var_freq)-1) -> 0.044097713 | AD9: =Var_freq*((1+D9)^(1/Var_freq)-1) -> 0.044097713 | AE9: =Var_freq*((1+E9)^(1/Var_freq)-1) -> 0.044097713 | AF9: =Var_freq*((1+F9)^(1/Var_freq)-1) -> 0.044097713 | AG9: =Var_freq*((1+G9)^(1/Var_freq)-1) -> 0.044097713 | AH9: =Var_freq*((1+H9)^(1/Var_freq)-1) -> 0.044097713 | AI9: =Var_freq*((1+I9)^(1/Var_freq)-1) -> 0.04169394 | ... AZ9: =Var_freq*((1+Z9)^(1/Var_freq)-1) -> 0.0368705
A10: 3 | B10: =Base_int_rate -> 0.045 | C10: =B10+VLOOKUP(Rawdata!A5,Int_rate_movements,2,TRUE) -> 0.045 | D10: =C10+VLOOKUP(Rawdata!B5,Int_rate_movements,2,TRUE) -> 0.045 | E10: =D10+VLOOKUP(Rawdata!C5,Int_rate_movements,2,TRUE) -> 0.045 | F10: =E10+VLOOKUP(Rawdata!D5,Int_rate_movements,2,TRUE) -> 0.045 | G10: =F10+VLOOKUP(Rawdata!E5,Int_rate_movements,2,TRUE) -> 0.045 | H10: =G10+VLOOKUP(Rawdata!F5,Int_rate_movements,2,TRUE) -> 0.045 | I10: =H10+VLOOKUP(Rawdata!G5,Int_rate_movements,2,TRUE) -> 0.045 | J10: =I10+VLOOKUP(Rawdata!H5,Int_rate_movements,2,TRUE) -> 0.045 | ... Z10: =Y10+VLOOKUP(Rawdata!X5,Int_rate_movements,2,TRUE) -> 0.04 | AB10: =Var_freq*((1+B10)^(1/Var_freq)-1) -> 0.044097713 | AC10: =Var_freq*((1+C10)^(1/Var_freq)-1) -> 0.044097713 | AD10: =Var_freq*((1+D10)^(1/Var_freq)-1) -> 0.044097713 | AE10: =Var_freq*((1+E10)^(1/Var_freq)-1) -> 0.044097713 | AF10: =Var_freq*((1+F10)^(1/Var_freq)-1) -> 0.044097713 | AG10: =Var_freq*((1+G10)^(1/Var_freq)-1) -> 0.044097713 | AH10: =Var_freq*((1+H10)^(1/Var_freq)-1) -> 0.044097713 | AI10: =Var_freq*((1+I10)^(1/Var_freq)-1) -> 0.044097713 | ... AZ10: =Var_freq*((1+Z10)^(1/Var_freq)-1) -> 0.039284877
A11: 4 | B11: =Base_int_rate -> 0.045 | C11: =B11+VLOOKUP(Rawdata!A6,Int_rate_movements,2,TRUE) -> 0.045 | D11: =C11+VLOOKUP(Rawdata!B6,Int_rate_movements,2,TRUE) -> 0.045 | E11: =D11+VLOOKUP(Rawdata!C6,Int_rate_movements,2,TRUE) -> 0.045 | F11: =E11+VLOOKUP(Rawdata!D6,Int_rate_movements,2,TRUE) -> 0.045 | G11: =F11+VLOOKUP(Rawdata!E6,Int_rate_movements,2,TRUE) -> 0.045 | H11: =G11+VLOOKUP(Rawdata!F6,Int_rate_movements,2,TRUE) -> 0.045 | I11: =H11+VLOOKUP(Rawdata!G6,Int_rate_movements,2,TRUE) -> 0.045 | J11: =I11+VLOOKUP(Rawdata!H6,Int_rate_movements,2,TRUE) -> 0.05 | ... Z11: =Y11+VLOOKUP(Rawdata!X6,Int_rate_movements,2,TRUE) -> 0.04 | AB11: =Var_freq*((1+B11)^(1/Var_freq)-1) -> 0.044097713 | AC11: =Var_freq*((1+C11)^(1/Var_freq)-1) -> 0.044097713 | AD11: =Var_freq*((1+D11)^(1/Var_freq)-1) -> 0.044097713 | AE11: =Var_freq*((1+E11)^(1/Var_freq)-1) -> 0.044097713 | AF11: =Var_freq*((1+F11)^(1/Var_freq)-1) -> 0.044097713 | AG11: =Var_freq*((1+G11)^(1/Var_freq)-1) -> 0.044097713 | AH11: =Var_freq*((1+H11)^(1/Var_freq)-1) -> 0.044097713 | AI11: =Var_freq*((1+I11)^(1/Var_freq)-1) -> 0.044097713 | ... AZ11: =Var_freq*((1+Z11)^(1/Var_freq)-1) -> 0.039284877
A12: 5 | B12: =Base_int_rate -> 0.045 | C12: =B12+VLOOKUP(Rawdata!A7,Int_rate_movements,2,TRUE) -> 0.045 | D12: =C12+VLOOKUP(Rawdata!B7,Int_rate_movements,2,TRUE) -> 0.045 | E12: =D12+VLOOKUP(Rawdata!C7,Int_rate_movements,2,TRUE) -> 0.0425 | F12: =E12+VLOOKUP(Rawdata!D7,Int_rate_movements,2,TRUE) -> 0.0425 | G12: =F12+VLOOKUP(Rawdata!E7,Int_rate_movements,2,TRUE) -> 0.0425 | H12: =G12+VLOOKUP(Rawdata!F7,Int_rate_movements,2,TRUE) -> 0.0425 | I12: =H12+VLOOKUP(Rawdata!G7,Int_rate_movements,2,TRUE) -> 0.0425 | J12: =I12+VLOOKUP(Rawdata!H7,Int_rate_movements,2,TRUE) -> 0.0425 | ... Z12: =Y12+VLOOKUP(Rawdata!X7,Int_rate_movements,2,TRUE) -> 0.035 | AB12: =Var_freq*((1+B12)^(1/Var_freq)-1) -> 0.044097713 | AC12: =Var_freq*((1+C12)^(1/Var_freq)-1) -> 0.044097713 | AD12: =Var_freq*((1+D12)^(1/Var_freq)-1) -> 0.044097713 | AE12: =Var_freq*((1+E12)^(1/Var_freq)-1) -> 0.04169394 | AF12: =Var_freq*((1+F12)^(1/Var_freq)-1) -> 0.04169394 | AG12: =Var_freq*((1+G12)^(1/Var_freq)-1) -> 0.04169394 | AH12: =Var_freq*((1+H12)^(1/Var_freq)-1) -> 0.04169394 | AI12: =Var_freq*((1+I12)^(1/Var_freq)-1) -> 0.04169394 | ... AZ12: =Var_freq*((1+Z12)^(1/Var_freq)-1) -> 0.034450785
A13: 6 | B13: =Base_int_rate -> 0.045 | C13: =B13+VLOOKUP(Rawdata!A8,Int_rate_movements,2,TRUE) -> 0.045 | D13: =C13+VLOOKUP(Rawdata!B8,Int_rate_movements,2,TRUE) -> 0.045 | E13: =D13+VLOOKUP(Rawdata!C8,Int_rate_movements,2,TRUE) -> 0.045 | F13: =E13+VLOOKUP(Rawdata!D8,Int_rate_movements,2,TRUE) -> 0.045 | G13: =F13+VLOOKUP(Rawdata!E8,Int_rate_movements,2,TRUE) -> 0.045 | H13: =G13+VLOOKUP(Rawdata!F8,Int_rate_movements,2,TRUE) -> 0.045 | I13: =H13+VLOOKUP(Rawdata!G8,Int_rate_movements,2,TRUE) -> 0.045 | J13: =I13+VLOOKUP(Rawdata!H8,Int_rate_movements,2,TRUE) -> 0.045 | ... Z13: =Y13+VLOOKUP(Rawdata!X8,Int_rate_movements,2,TRUE) -> 0.045 | AB13: =Var_freq*((1+B13)^(1/Var_freq)-1) -> 0.044097713 | AC13: =Var_freq*((1+C13)^(1/Var_freq)-1) -> 0.044097713 | AD13: =Var_freq*((1+D13)^(1/Var_freq)-1) -> 0.044097713 | AE13: =Var_freq*((1+E13)^(1/Var_freq)-1) -> 0.044097713 | AF13: =Var_freq*((1+F13)^(1/Var_freq)-1) -> 0.044097713 | AG13: =Var_freq*((1+G13)^(1/Var_freq)-1) -> 0.044097713 | AH13: =Var_freq*((1+H13)^(1/Var_freq)-1) -> 0.044097713 | AI13: =Var_freq*((1+I13)^(1/Var_freq)-1) -> 0.044097713 | ... AZ13: =Var_freq*((1+Z13)^(1/Var_freq)-1) -> 0.044097713
A14: 7 | B14: =Base_int_rate -> 0.045 | C14: =B14+VLOOKUP(Rawdata!A9,Int_rate_movements,2,TRUE) -> 0.045 | D14: =C14+VLOOKUP(Rawdata!B9,Int_rate_movements,2,TRUE) -> 0.045 | E14: =D14+VLOOKUP(Rawdata!C9,Int_rate_movements,2,TRUE) -> 0.045 | F14: =E14+VLOOKUP(Rawdata!D9,Int_rate_movements,2,TRUE) -> 0.045 | G14: =F14+VLOOKUP(Rawdata!E9,Int_rate_movements,2,TRUE) -> 0.045 | H14: =G14+VLOOKUP(Rawdata!F9,Int_rate_movements,2,TRUE) -> 0.045 | I14: =H14+VLOOKUP(Rawdata!G9,Int_rate_movements,2,TRUE) -> 0.045 | J14: =I14+VLOOKUP(Rawdata!H9,Int_rate_movements,2,TRUE) -> 0.0475 | ... Z14: =Y14+VLOOKUP(Rawdata!X9,Int_rate_movements,2,TRUE) -> 0.0475 | AB14: =Var_freq*((1+B14)^(1/Var_freq)-1) -> 0.044097713 | AC14: =Var_freq*((1+C14)^(1/Var_freq)-1) -> 0.044097713 | AD14: =Var_freq*((1+D14)^(1/Var_freq)-1) -> 0.044097713 | AE14: =Var_freq*((1+E14)^(1/Var_freq)-1) -> 0.044097713 | AF14: =Var_freq*((1+F14)^(1/Var_freq)-1) -> 0.044097713 | AG14: =Var_freq*((1+G14)^(1/Var_freq)-1) -> 0.044097713 | AH14: =Var_freq*((1+H14)^(1/Var_freq)-1) -> 0.044097713 | AI14: =Var_freq*((1+I14)^(1/Var_freq)-1) -> 0.044097713 | ... AZ14: =Var_freq*((1+Z14)^(1/Var_freq)-1) -> 0.04649622
A15: 8 | B15: =Base_int_rate -> 0.045 | C15: =B15+VLOOKUP(Rawdata!A10,Int_rate_movements,2,TRUE) -> 0.045 | D15: =C15+VLOOKUP(Rawdata!B10,Int_rate_movements,2,TRUE) -> 0.045 | E15: =D15+VLOOKUP(Rawdata!C10,Int_rate_movements,2,TRUE) -> 0.045 | F15: =E15+VLOOKUP(Rawdata!D10,Int_rate_movements,2,TRUE) -> 0.045 | G15: =F15+VLOOKUP(Rawdata!E10,Int_rate_movements,2,TRUE) -> 0.045 | H15: =G15+VLOOKUP(Rawdata!F10,Int_rate_movements,2,TRUE) -> 0.045 | I15: =H15+VLOOKUP(Rawdata!G10,Int_rate_movements,2,TRUE) -> 0.045 | J15: =I15+VLOOKUP(Rawdata!H10,Int_rate_movements,2,TRUE) -> 0.045 | ... Z15: =Y15+VLOOKUP(Rawdata!X10,Int_rate_movements,2,TRUE) -> 0.0475 | AB15: =Var_freq*((1+B15)^(1/Var_freq)-1) -> 0.044097713 | AC15: =Var_freq*((1+C15)^(1/Var_freq)-1) -> 0.044097713 | AD15: =Var_freq*((1+D15)^(1/Var_freq)-1) -> 0.044097713 | AE15: =Var_freq*((1+E15)^(1/Var_freq)-1) -> 0.044097713 | AF15: =Var_freq*((1+F15)^(1/Var_freq)-1) -> 0.044097713 | AG15: =Var_freq*((1+G15)^(1/Var_freq)-1) -> 0.044097713 | AH15: =Var_freq*((1+H15)^(1/Var_freq)-1) -> 0.044097713 | AI15: =Var_freq*((1+I15)^(1/Var_freq)-1) -> 0.044097713 | ... AZ15: =Var_freq*((1+Z15)^(1/Var_freq)-1) -> 0.04649622
A16: 9 | B16: =Base_int_rate -> 0.045 | C16: =B16+VLOOKUP(Rawdata!A11,Int_rate_movements,2,TRUE) -> 0.045 | D16: =C16+VLOOKUP(Rawdata!B11,Int_rate_movements,2,TRUE) -> 0.045 | E16: =D16+VLOOKUP(Rawdata!C11,Int_rate_movements,2,TRUE) -> 0.045 | F16: =E16+VLOOKUP(Rawdata!D11,Int_rate_movements,2,TRUE) -> 0.045 | G16: =F16+VLOOKUP(Rawdata!E11,Int_rate_movements,2,TRUE) -> 0.0425 | H16: =G16+VLOOKUP(Rawdata!F11,Int_rate_movements,2,TRUE) -> 0.04 | I16: =H16+VLOOKUP(Rawdata!G11,Int_rate_movements,2,TRUE) -> 0.04 | J16: =I16+VLOOKUP(Rawdata!H11,Int_rate_movements,2,TRUE) -> 0.04 | ... Z16: =Y16+VLOOKUP(Rawdata!X11,Int_rate_movements,2,TRUE) -> 0.05 | AB16: =Var_freq*((1+B16)^(1/Var_freq)-1) -> 0.044097713 | AC16: =Var_freq*((1+C16)^(1/Var_freq)-1) -> 0.044097713 | AD16: =Var_freq*((1+D16)^(1/Var_freq)-1) -> 0.044097713 | AE16: =Var_freq*((1+E16)^(1/Var_freq)-1) -> 0.044097713 | AF16: =Var_freq*((1+F16)^(1/Var_freq)-1) -> 0.044097713 | AG16: =Var_freq*((1+G16)^(1/Var_freq)-1) -> 0.04169394 | AH16: =Var_freq*((1+H16)^(1/Var_freq)-1) -> 0.039284877 | AI16: =Var_freq*((1+I16)^(1/Var_freq)-1) -> 0.039284877 | ... AZ16: =Var_freq*((1+Z16)^(1/Var_freq)-1) -> 0.048889485
A17: 10 | B17: =Base_int_rate -> 0.045 | C17: =B17+VLOOKUP(Rawdata!A12,Int_rate_movements,2,TRUE) -> 0.045 | D17: =C17+VLOOKUP(Rawdata!B12,Int_rate_movements,2,TRUE) -> 0.045 | E17: =D17+VLOOKUP(Rawdata!C12,Int_rate_movements,2,TRUE) -> 0.045 | F17: =E17+VLOOKUP(Rawdata!D12,Int_rate_movements,2,TRUE) -> 0.045 | G17: =F17+VLOOKUP(Rawdata!E12,Int_rate_movements,2,TRUE) -> 0.0425 | H17: =G17+VLOOKUP(Rawdata!F12,Int_rate_movements,2,TRUE) -> 0.0425 | I17: =H17+VLOOKUP(Rawdata!G12,Int_rate_movements,2,TRUE) -> 0.0425 | J17: =I17+VLOOKUP(Rawdata!H12,Int_rate_movements,2,TRUE) -> 0.0425 | ... Z17: =Y17+VLOOKUP(Rawdata!X12,Int_rate_movements,2,TRUE) -> 0.0525 | AB17: =Var_freq*((1+B17)^(1/Var_freq)-1) -> 0.044097713 | AC17: =Var_freq*((1+C17)^(1/Var_freq)-1) -> 0.044097713 | AD17: =Var_freq*((1+D17)^(1/Var_freq)-1) -> 0.044097713 | AE17: =Var_freq*((1+E17)^(1/Var_freq)-1) -> 0.044097713 | AF17: =Var_freq*((1+F17)^(1/Var_freq)-1) -> 0.044097713 | AG17: =Var_freq*((1+G17)^(1/Var_freq)-1) -> 0.04169394 | AH17: =Var_freq*((1+H17)^(1/Var_freq)-1) -> 0.04169394 | AI17: =Var_freq*((1+I17)^(1/Var_freq)-1) -> 0.04169394 | ... AZ17: =Var_freq*((1+Z17)^(1/Var_freq)-1) -> 0.051277533
A18: 11 | B18: =Base_int_rate -> 0.045 | C18: =B18+VLOOKUP(Rawdata!A13,Int_rate_movements,2,TRUE) -> 0.045 | D18: =C18+VLOOKUP(Rawdata!B13,Int_rate_movements,2,TRUE) -> 0.0425 | E18: =D18+VLOOKUP(Rawdata!C13,Int_rate_movements,2,TRUE) -> 0.0425 | F18: =E18+VLOOKUP(Rawdata!D13,Int_rate_movements,2,TRUE) -> 0.0425 | G18: =F18+VLOOKUP(Rawdata!E13,Int_rate_movements,2,TRUE) -> 0.0425 | H18: =G18+VLOOKUP(Rawdata!F13,Int_rate_movements,2,TRUE) -> 0.0425 | I18: =H18+VLOOKUP(Rawdata!G13,Int_rate_movements,2,TRUE) -> 0.045 | J18: =I18+VLOOKUP(Rawdata!H13,Int_rate_movements,2,TRUE) -> 0.045 | ... Z18: =Y18+VLOOKUP(Rawdata!X13,Int_rate_movements,2,TRUE) -> 0.04 | AB18: =Var_freq*((1+B18)^(1/Var_freq)-1) -> 0.044097713 | AC18: =Var_freq*((1+C18)^(1/Var_freq)-1) -> 0.044097713 | AD18: =Var_freq*((1+D18)^(1/Var_freq)-1) -> 0.04169394 | AE18: =Var_freq*((1+E18)^(1/Var_freq)-1) -> 0.04169394 | AF18: =Var_freq*((1+F18)^(1/Var_freq)-1) -> 0.04169394 | AG18: =Var_freq*((1+G18)^(1/Var_freq)-1) -> 0.04169394 | AH18: =Var_freq*((1+H18)^(1/Var_freq)-1) -> 0.04169394 | AI18: =Var_freq*((1+I18)^(1/Var_freq)-1) -> 0.044097713 | ... AZ18: =Var_freq*((1+Z18)^(1/Var_freq)-1) -> 0.039284877
A19: 12 | B19: =Base_int_rate -> 0.045 | C19: =B19+VLOOKUP(Rawdata!A14,Int_rate_movements,2,TRUE) -> 0.045 | D19: =C19+VLOOKUP(Rawdata!B14,Int_rate_movements,2,TRUE) -> 0.05 | E19: =D19+VLOOKUP(Rawdata!C14,Int_rate_movements,2,TRUE) -> 0.05 | F19: =E19+VLOOKUP(Rawdata!D14,Int_rate_movements,2,TRUE) -> 0.05 | G19: =F19+VLOOKUP(Rawdata!E14,Int_rate_movements,2,TRUE) -> 0.055 | H19: =G19+VLOOKUP(Rawdata!F14,Int_rate_movements,2,TRUE) -> 0.055 | I19: =H19+VLOOKUP(Rawdata!G14,Int_rate_movements,2,TRUE) -> 0.055 | J19: =I19+VLOOKUP(Rawdata!H14,Int_rate_movements,2,TRUE) -> 0.055 | ... Z19: =Y19+VLOOKUP(Rawdata!X14,Int_rate_movements,2,TRUE) -> 0.0625 | AB19: =Var_freq*((1+B19)^(1/Var_freq)-1) -> 0.044097713 | AC19: =Var_freq*((1+C19)^(1/Var_freq)-1) -> 0.044097713 | AD19: =Var_freq*((1+D19)^(1/Var_freq)-1) -> 0.048889485 | AE19: =Var_freq*((1+E19)^(1/Var_freq)-1) -> 0.048889485 | AF19: =Var_freq*((1+F19)^(1/Var_freq)-1) -> 0.048889485 | AG19: =Var_freq*((1+G19)^(1/Var_freq)-1) -> 0.053660387 | AH19: =Var_freq*((1+H19)^(1/Var_freq)-1) -> 0.053660387 | AI19: =Var_freq*((1+I19)^(1/Var_freq)-1) -> 0.053660387 | ... AZ19: =Var_freq*((1+Z19)^(1/Var_freq)-1) -> 0.060778019
... A207: 200 | B207: =Base_int_rate -> 0.045 | C207: =B207+VLOOKUP(Rawdata!A202,Int_rate_movements,2,TRUE) -> 0.045 | D207: =C207+VLOOKUP(Rawdata!B202,Int_rate_movements,2,TRUE) -> 0.045 | E207: =D207+VLOOKUP(Rawdata!C202,Int_rate_movements,2,TRUE) -> 0.045 | F207: =E207+VLOOKUP(Rawdata!D202,Int_rate_movements,2,TRUE) -> 0.045 | G207: =F207+VLOOKUP(Rawdata!E202,Int_rate_movements,2,TRUE) -> 0.045 | H207: =G207+VLOOKUP(Rawdata!F202,Int_rate_movements,2,TRUE) -> 0.045 | I207: =H207+VLOOKUP(Rawdata!G202,Int_rate_movements,2,TRUE) -> 0.045 | J207: =I207+VLOOKUP(Rawdata!H202,Int_rate_movements,2,TRUE) -> 0.04 | ... Z207: =Y207+VLOOKUP(Rawdata!X202,Int_rate_movements,2,TRUE) -> 0.0425 | AB207: =Var_freq*((1+B207)^(1/Var_freq)-1) -> 0.044097713 | AC207: =Var_freq*((1+C207)^(1/Var_freq)-1) -> 0.044097713 | AD207: =Var_freq*((1+D207)^(1/Var_freq)-1) -> 0.044097713 | AE207: =Var_freq*((1+E207)^(1/Var_freq)-1) -> 0.044097713 | AF207: =Var_freq*((1+F207)^(1/Var_freq)-1) -> 0.044097713 | AG207: =Var_freq*((1+G207)^(1/Var_freq)-1) -> 0.044097713 | AH207: =Var_freq*((1+H207)^(1/Var_freq)-1) -> 0.044097713 | AI207: =Var_freq*((1+I207)^(1/Var_freq)-1) -> 0.044097713 | ... AZ207: =Var_freq*((1+Z207)^(1/Var_freq)-1) -> 0.04169394

Sheet Variable rate projection
A1: Cashflow projection and mortgage calculation using projection of variable interest rates | AC1: Count of Errors | AD1: =COUNTIF(AD6:AD205,"ERROR") -> 0 | AH1: Average | AI1: =AVERAGE(AI6:AI205) -> 965.41005
AH2: Min | AI2: =MIN(AI6:AI205) -> 761.71
B3: All amounts in $ | AH3: Max | AI3: =MAX(AI6:AI205) -> 1132.8
B4: Month - start of | AB4: Mortgage annuity | AG4: Financial projection
A5: Simulation | B5: 1 | C5: =IF(B5+1>Dep_term*12,"Mortgage starts",B5+1) -> 2 | D5: =IF(C5+1>Dep_term*12,"Mortgage starts",C5+1) -> 3 | E5: =IF(D5+1>Dep_term*12,"Mortgage starts",D5+1) -> 4 | F5: =IF(E5+1>Dep_term*12,"Mortgage starts",E5+1) -> 5 | G5: =IF(F5+1>Dep_term*12,"Mortgage starts",F5+1) -> 6 | H5: =IF(G5+1>Dep_term*12,"Mortgage starts",G5+1) -> 7 | I5: =IF(H5+1>Dep_term*12,"Mortgage starts",H5+1) -> 8 | J5: =IF(I5+1>Dep_term*12,"Mortgage starts",I5+1) -> 9 | ... Z5: =IF(Y5+1>Dep_term*12,"Mortgage starts",Y5+1) -> Mortgage starts | AB5: Annual int rate | AC5: Interest rate convertible monthly | AD5: Check annual equiv to monthly | AE5: Annuity rate | AG5: Deposit with interest | AH5: Mortgage amount | AI5: Monthly repayment | AK5: Total repayments under fixed option less total repayments under variable option | AM5: Analysis of difference in total mortgage repayments between fixed rate option and variable rate option
A6: 1 | B6: =Deposit_mon -> 1000 | C6: =ROUND(B6*(1+'Interest rate projection'!AB8/Var_freq)+IF(C$5="Mortgage Starts",0,Deposit_mon),2) -> 2003.67 | D6: =ROUND(C6*(1+'Interest rate projection'!AC8/Var_freq)+IF(D$5="Mortgage Starts",0,Deposit_mon),2) -> 3011.03 | E6: =ROUND(D6*(1+'Interest rate projection'!AD8/Var_freq)+IF(E$5="Mortgage Starts",0,Deposit_mon),2) -> 4022.09 | F6: =ROUND(E6*(1+'Interest rate projection'!AE8/Var_freq)+IF(F$5="Mortgage Starts",0,Deposit_mon),2) -> 5036.87 | G6: =ROUND(F6*(1+'Interest rate projection'!AF8/Var_freq)+IF(G$5="Mortgage Starts",0,Deposit_mon),2) -> 6054.37 | H6: =ROUND(G6*(1+'Interest rate projection'!AG8/Var_freq)+IF(H$5="Mortgage Starts",0,Deposit_mon),2) -> 7075.41 | I6: =ROUND(H6*(1+'Interest rate projection'!AH8/Var_freq)+IF(I$5="Mortgage Starts",0,Deposit_mon),2) -> 8099.99 | J6: =ROUND(I6*(1+'Interest rate projection'!AI8/Var_freq)+IF(J$5="Mortgage Starts",0,Deposit_mon),2) -> 9128.13 | ... Z6: =ROUND(Y6*(1+'Interest rate projection'!AY8/Var_freq)+IF(Z$5="Mortgage Starts",0,Deposit_mon),2) -> 25072.79 | AB6: ='Interest rate projection'!Z8 -> 0.0425 | AC6: ='Interest rate projection'!AZ8 -> 0.04169394 | AD6: =IF(ROUND(AB6,6)=ROUND((1+AC6/Var_freq)^Var_freq-1,6),"OK","ERROR") -> OK | AE6: =(1-(1+AB6)^-Mort_term)/AC6 -> 15.51153 | AG6: =Z6 -> 25072.79 | AH6: =House_price-AG6 -> 174927.21 | AI6: =ROUND(AH6/AE6/Var_freq,2) -> 939.77 | AK6: ='Fixed rate projection'!$AE$3-('Variable rate projection'!AI6*Product_term*Var_freq) -> 21138
A7: 2 | B7: =Deposit_mon -> 1000 | C7: =ROUND(B7*(1+'Interest rate projection'!AB9/Var_freq)+IF(C$5="Mortgage Starts",0,Deposit_mon),2) -> 2003.67 | D7: =ROUND(C7*(1+'Interest rate projection'!AC9/Var_freq)+IF(D$5="Mortgage Starts",0,Deposit_mon),2) -> 3011.03 | E7: =ROUND(D7*(1+'Interest rate projection'!AD9/Var_freq)+IF(E$5="Mortgage Starts",0,Deposit_mon),2) -> 4022.09 | F7: =ROUND(E7*(1+'Interest rate projection'!AE9/Var_freq)+IF(F$5="Mortgage Starts",0,Deposit_mon),2) -> 5036.87 | G7: =ROUND(F7*(1+'Interest rate projection'!AF9/Var_freq)+IF(G$5="Mortgage Starts",0,Deposit_mon),2) -> 6055.38 | H7: =ROUND(G7*(1+'Interest rate projection'!AG9/Var_freq)+IF(H$5="Mortgage Starts",0,Deposit_mon),2) -> 7077.63 | I7: =ROUND(H7*(1+'Interest rate projection'!AH9/Var_freq)+IF(I$5="Mortgage Starts",0,Deposit_mon),2) -> 8103.64 | J7: =ROUND(I7*(1+'Interest rate projection'!AI9/Var_freq)+IF(J$5="Mortgage Starts",0,Deposit_mon),2) -> 9131.8 | ... Z7: =ROUND(Y7*(1+'Interest rate projection'!AY9/Var_freq)+IF(Z$5="Mortgage Starts",0,Deposit_mon),2) -> 24973.6 | AB7: ='Interest rate projection'!Z9 -> 0.0375 | AC7: ='Interest rate projection'!AZ9 -> 0.0368705 | AD7: =IF(ROUND(AB7,6)=ROUND((1+AC7/Var_freq)^Var_freq-1,6),"OK","ERROR") -> OK | AE7: =(1-(1+AB7)^-Mort_term)/AC7 -> 16.317114 | AG7: =Z7 -> 24973.6 | AH7: =House_price-AG7 -> 175026.4 | AI7: =ROUND(AH7/AE7/Var_freq,2) -> 893.88 | AK7: ='Fixed rate projection'!$AE$3-('Variable rate projection'!AI7*Product_term*Var_freq) -> 34905 | AM7: Minimum | AN7: =MIN(AK6:AK205) -> -36771
A8: 3 | B8: =Deposit_mon -> 1000 | C8: =ROUND(B8*(1+'Interest rate projection'!AB10/Var_freq)+IF(C$5="Mortgage Starts",0,Deposit_mon),2) -> 2003.67 | D8: =ROUND(C8*(1+'Interest rate projection'!AC10/Var_freq)+IF(D$5="Mortgage Starts",0,Deposit_mon),2) -> 3011.03 | E8: =ROUND(D8*(1+'Interest rate projection'!AD10/Var_freq)+IF(E$5="Mortgage Starts",0,Deposit_mon),2) -> 4022.09 | F8: =ROUND(E8*(1+'Interest rate projection'!AE10/Var_freq)+IF(F$5="Mortgage Starts",0,Deposit_mon),2) -> 5036.87 | G8: =ROUND(F8*(1+'Interest rate projection'!AF10/Var_freq)+IF(G$5="Mortgage Starts",0,Deposit_mon),2) -> 6055.38 | H8: =ROUND(G8*(1+'Interest rate projection'!AG10/Var_freq)+IF(H$5="Mortgage Starts",0,Deposit_mon),2) -> 7077.63 | I8: =ROUND(H8*(1+'Interest rate projection'!AH10/Var_freq)+IF(I$5="Mortgage Starts",0,Deposit_mon),2) -> 8103.64 | J8: =ROUND(I8*(1+'Interest rate projection'!AI10/Var_freq)+IF(J$5="Mortgage Starts",0,Deposit_mon),2) -> 9133.42 | ... Z8: =ROUND(Y8*(1+'Interest rate projection'!AY10/Var_freq)+IF(Z$5="Mortgage Starts",0,Deposit_mon),2) -> 25069.36 | AB8: ='Interest rate projection'!Z10 -> 0.04 | AC8: ='Interest rate projection'!AZ10 -> 0.039284877 | AD8: =IF(ROUND(AB8,6)=ROUND((1+AC8/Var_freq)^Var_freq-1,6),"OK","ERROR") -> OK | AE8: =(1-(1+AB8)^-Mort_term)/AC8 -> 15.906457 | AG8: =Z8 -> 25069.36 | AH8: =House_price-AG8 -> 174930.64 | AI8: =ROUND(AH8/AE8/Var_freq,2) -> 916.46 | AK8: ='Fixed rate projection'!$AE$3-('Variable rate projection'!AI8*Product_term*Var_freq) -> 28131 | AM8: Maximum | AN8: =MAX(AK6:AK205) -> 74556
A9: 4 | B9: =Deposit_mon -> 1000 | C9: =ROUND(B9*(1+'Interest rate projection'!AB11/Var_freq)+IF(C$5="Mortgage Starts",0,Deposit_mon),2) -> 2003.67 | D9: =ROUND(C9*(1+'Interest rate projection'!AC11/Var_freq)+IF(D$5="Mortgage Starts",0,Deposit_mon),2) -> 3011.03 | E9: =ROUND(D9*(1+'Interest rate projection'!AD11/Var_freq)+IF(E$5="Mortgage Starts",0,Deposit_mon),2) -> 4022.09 | F9: =ROUND(E9*(1+'Interest rate projection'!AE11/Var_freq)+IF(F$5="Mortgage Starts",0,Deposit_mon),2) -> 5036.87 | G9: =ROUND(F9*(1+'Interest rate projection'!AF11/Var_freq)+IF(G$5="Mortgage Starts",0,Deposit_mon),2) -> 6055.38 | H9: =ROUND(G9*(1+'Interest rate projection'!AG11/Var_freq)+IF(H$5="Mortgage Starts",0,Deposit_mon),2) -> 7077.63 | I9: =ROUND(H9*(1+'Interest rate projection'!AH11/Var_freq)+IF(I$5="Mortgage Starts",0,Deposit_mon),2) -> 8103.64 | J9: =ROUND(I9*(1+'Interest rate projection'!AI11/Var_freq)+IF(J$5="Mortgage Starts",0,Deposit_mon),2) -> 9133.42 | ... Z9: =ROUND(Y9*(1+'Interest rate projection'!AY11/Var_freq)+IF(Z$5="Mortgage Starts",0,Deposit_mon),2) -> 25230.85 | AB9: ='Interest rate projection'!Z11 -> 0.04 | AC9: ='Interest rate projection'!AZ11 -> 0.039284877 | AD9: =IF(ROUND(AB9,6)=ROUND((1+AC9/Var_freq)^Var_freq-1,6),"OK","ERROR") -> OK | AE9: =(1-(1+AB9)^-Mort_term)/AC9 -> 15.906457 | AG9: =Z9 -> 25230.85 | AH9: =House_price-AG9 -> 174769.15 | AI9: =ROUND(AH9/AE9/Var_freq,2) -> 915.61 | AK9: ='Fixed rate projection'!$AE$3-('Variable rate projection'!AI9*Product_term*Var_freq) -> 28386 | AM9: Average | AN9: =AVERAGE(AK6:AK205) -> 13445.985
A10: 5 | B10: =Deposit_mon -> 1000 | C10: =ROUND(B10*(1+'Interest rate projection'!AB12/Var_freq)+IF(C$5="Mortgage Starts",0,Deposit_mon),2) -> 2003.67 | D10: =ROUND(C10*(1+'Interest rate projection'!AC12/Var_freq)+IF(D$5="Mortgage Starts",0,Deposit_mon),2) -> 3011.03 | E10: =ROUND(D10*(1+'Interest rate projection'!AD12/Var_freq)+IF(E$5="Mortgage Starts",0,Deposit_mon),2) -> 4022.09 | F10: =ROUND(E10*(1+'Interest rate projection'!AE12/Var_freq)+IF(F$5="Mortgage Starts",0,Deposit_mon),2) -> 5036.06 | G10: =ROUND(F10*(1+'Interest rate projection'!AF12/Var_freq)+IF(G$5="Mortgage Starts",0,Deposit_mon),2) -> 6053.56 | H10: =ROUND(G10*(1+'Interest rate projection'!AG12/Var_freq)+IF(H$5="Mortgage Starts",0,Deposit_mon),2) -> 7074.59 | I10: =ROUND(H10*(1+'Interest rate projection'!AH12/Var_freq)+IF(I$5="Mortgage Starts",0,Deposit_mon),2) -> 8099.17 | J10: =ROUND(I10*(1+'Interest rate projection'!AI12/Var_freq)+IF(J$5="Mortgage Starts",0,Deposit_mon),2) -> 9127.31 | ... Z10: =ROUND(Y10*(1+'Interest rate projection'!AY12/Var_freq)+IF(Z$5="Mortgage Starts",0,Deposit_mon),2) -> 24963.98 | AB10: ='Interest rate projection'!Z12 -> 0.035 | AC10: ='Interest rate projection'!AZ12 -> 0.034450785 | AD10: =IF(ROUND(AB10,6)=ROUND((1+AC10/Var_freq)^Var_freq-1,6),"OK","ERROR") -> OK | AE10: =(1-(1+AB10)^-Mort_term)/AC10 -> 16.744263 | AG10: =Z10 -> 24963.98 | AH10: =House_price-AG10 -> 175036.02 | AI10: =ROUND(AH10/AE10/Var_freq,2) -> 871.12 | AK10: ='Fixed rate projection'!$AE$3-('Variable rate projection'!AI10*Product_term*Var_freq) -> 41733
A11: 6 | B11: =Deposit_mon -> 1000 | C11: =ROUND(B11*(1+'Interest rate projection'!AB13/Var_freq)+IF(C$5="Mortgage Starts",0,Deposit_mon),2) -> 2003.67 | D11: =ROUND(C11*(1+'Interest rate projection'!AC13/Var_freq)+IF(D$5="Mortgage Starts",0,Deposit_mon),2) -> 3011.03 | E11: =ROUND(D11*(1+'Interest rate projection'!AD13/Var_freq)+IF(E$5="Mortgage Starts",0,Deposit_mon),2) -> 4022.09 | F11: =ROUND(E11*(1+'Interest rate projection'!AE13/Var_freq)+IF(F$5="Mortgage Starts",0,Deposit_mon),2) -> 5036.87 | G11: =ROUND(F11*(1+'Interest rate projection'!AF13/Var_freq)+IF(G$5="Mortgage Starts",0,Deposit_mon),2) -> 6055.38 | H11: =ROUND(G11*(1+'Interest rate projection'!AG13/Var_freq)+IF(H$5="Mortgage Starts",0,Deposit_mon),2) -> 7077.63 | I11: =ROUND(H11*(1+'Interest rate projection'!AH13/Var_freq)+IF(I$5="Mortgage Starts",0,Deposit_mon),2) -> 8103.64 | J11: =ROUND(I11*(1+'Interest rate projection'!AI13/Var_freq)+IF(J$5="Mortgage Starts",0,Deposit_mon),2) -> 9133.42 | ... Z11: =ROUND(Y11*(1+'Interest rate projection'!AY13/Var_freq)+IF(Z$5="Mortgage Starts",0,Deposit_mon),2) -> 25105.48 | AB11: ='Interest rate projection'!Z13 -> 0.045 | AC11: ='Interest rate projection'!AZ13 -> 0.044097713 | AD11: =IF(ROUND(AB11,6)=ROUND((1+AC11/Var_freq)^Var_freq-1,6),"OK","ERROR") -> OK | AE11: =(1-(1+AB11)^-Mort_term)/AC11 -> 15.13161 | AG11: =Z11 -> 25105.48 | AH11: =House_price-AG11 -> 174894.52 | AI11: =ROUND(AH11/AE11/Var_freq,2) -> 963.19 | AK11: ='Fixed rate projection'!$AE$3-('Variable rate projection'!AI11*Product_term*Var_freq) -> 14112 | AM11: Probability Fixed < Variable | AN11: =COUNTIF(AK6:AK205,"<0")/COUNT(AK6:AK205) -> 0.255
A12: 7 | B12: =Deposit_mon -> 1000 | C12: =ROUND(B12*(1+'Interest rate projection'!AB14/Var_freq)+IF(C$5="Mortgage Starts",0,Deposit_mon),2) -> 2003.67 | D12: =ROUND(C12*(1+'Interest rate projection'!AC14/Var_freq)+IF(D$5="Mortgage Starts",0,Deposit_mon),2) -> 3011.03 | E12: =ROUND(D12*(1+'Interest rate projection'!AD14/Var_freq)+IF(E$5="Mortgage Starts",0,Deposit_mon),2) -> 4022.09 | F12: =ROUND(E12*(1+'Interest rate projection'!AE14/Var_freq)+IF(F$5="Mortgage Starts",0,Deposit_mon),2) -> 5036.87 | G12: =ROUND(F12*(1+'Interest rate projection'!AF14/Var_freq)+IF(G$5="Mortgage Starts",0,Deposit_mon),2) -> 6055.38 | H12: =ROUND(G12*(1+'Interest rate projection'!AG14/Var_freq)+IF(H$5="Mortgage Starts",0,Deposit_mon),2) -> 7077.63 | I12: =ROUND(H12*(1+'Interest rate projection'!AH14/Var_freq)+IF(I$5="Mortgage Starts",0,Deposit_mon),2) -> 8103.64 | J12: =ROUND(I12*(1+'Interest rate projection'!AI14/Var_freq)+IF(J$5="Mortgage Starts",0,Deposit_mon),2) -> 9133.42 | ... Z12: =ROUND(Y12*(1+'Interest rate projection'!AY14/Var_freq)+IF(Z$5="Mortgage Starts",0,Deposit_mon),2) -> 25189.86 | AB12: ='Interest rate projection'!Z14 -> 0.0475 | AC12: ='Interest rate projection'!AZ14 -> 0.04649622 | AD12: =IF(ROUND(AB12,6)=ROUND((1+AC12/Var_freq)^Var_freq-1,6),"OK","ERROR") -> OK | AE12: =(1-(1+AB12)^-Mort_term)/AC12 -> 14.766012 | AG12: =Z12 -> 25189.86 | AH12: =House_price-AG12 -> 174810.14 | AI12: =ROUND(AH12/AE12/Var_freq,2) -> 986.56 | AK12: ='Fixed rate projection'!$AE$3-('Variable rate projection'!AI12*Product_term*Var_freq) -> 7101
A13: 8 | B13: =Deposit_mon -> 1000 | C13: =ROUND(B13*(1+'Interest rate projection'!AB15/Var_freq)+IF(C$5="Mortgage Starts",0,Deposit_mon),2) -> 2003.67 | D13: =ROUND(C13*(1+'Interest rate projection'!AC15/Var_freq)+IF(D$5="Mortgage Starts",0,Deposit_mon),2) -> 3011.03 | E13: =ROUND(D13*(1+'Interest rate projection'!AD15/Var_freq)+IF(E$5="Mortgage Starts",0,Deposit_mon),2) -> 4022.09 | F13: =ROUND(E13*(1+'Interest rate projection'!AE15/Var_freq)+IF(F$5="Mortgage Starts",0,Deposit_mon),2) -> 5036.87 | G13: =ROUND(F13*(1+'Interest rate projection'!AF15/Var_freq)+IF(G$5="Mortgage Starts",0,Deposit_mon),2) -> 6055.38 | H13: =ROUND(G13*(1+'Interest rate projection'!AG15/Var_freq)+IF(H$5="Mortgage Starts",0,Deposit_mon),2) -> 7077.63 | I13: =ROUND(H13*(1+'Interest rate projection'!AH15/Var_freq)+IF(I$5="Mortgage Starts",0,Deposit_mon),2) -> 8103.64 | J13: =ROUND(I13*(1+'Interest rate projection'!AI15/Var_freq)+IF(J$5="Mortgage Starts",0,Deposit_mon),2) -> 9133.42 | ... Z13: =ROUND(Y13*(1+'Interest rate projection'!AY15/Var_freq)+IF(Z$5="Mortgage Starts",0,Deposit_mon),2) -> 25175.12 | AB13: ='Interest rate projection'!Z15 -> 0.0475 | AC13: ='Interest rate projection'!AZ15 -> 0.04649622 | AD13: =IF(ROUND(AB13,6)=ROUND((1+AC13/Var_freq)^Var_freq-1,6),"OK","ERROR") -> OK | AE13: =(1-(1+AB13)^-Mort_term)/AC13 -> 14.766012 | AG13: =Z13 -> 25175.12 | AH13: =House_price-AG13 -> 174824.88 | AI13: =ROUND(AH13/AE13/Var_freq,2) -> 986.64 | AK13: ='Fixed rate projection'!$AE$3-('Variable rate projection'!AI13*Product_term*Var_freq) -> 7077
A14: 9 | B14: =Deposit_mon -> 1000 | C14: =ROUND(B14*(1+'Interest rate projection'!AB16/Var_freq)+IF(C$5="Mortgage Starts",0,Deposit_mon),2) -> 2003.67 | D14: =ROUND(C14*(1+'Interest rate projection'!AC16/Var_freq)+IF(D$5="Mortgage Starts",0,Deposit_mon),2) -> 3011.03 | E14: =ROUND(D14*(1+'Interest rate projection'!AD16/Var_freq)+IF(E$5="Mortgage Starts",0,Deposit_mon),2) -> 4022.09 | F14: =ROUND(E14*(1+'Interest rate projection'!AE16/Var_freq)+IF(F$5="Mortgage Starts",0,Deposit_mon),2) -> 5036.87 | G14: =ROUND(F14*(1+'Interest rate projection'!AF16/Var_freq)+IF(G$5="Mortgage Starts",0,Deposit_mon),2) -> 6055.38 | H14: =ROUND(G14*(1+'Interest rate projection'!AG16/Var_freq)+IF(H$5="Mortgage Starts",0,Deposit_mon),2) -> 7076.42 | I14: =ROUND(H14*(1+'Interest rate projection'!AH16/Var_freq)+IF(I$5="Mortgage Starts",0,Deposit_mon),2) -> 8099.59 | J14: =ROUND(I14*(1+'Interest rate projection'!AI16/Var_freq)+IF(J$5="Mortgage Starts",0,Deposit_mon),2) -> 9126.11 | ... Z14: =ROUND(Y14*(1+'Interest rate projection'!AY16/Var_freq)+IF(Z$5="Mortgage Starts",0,Deposit_mon),2) -> 25155.82 | AB14: ='Interest rate projection'!Z16 -> 0.05 | AC14: ='Interest rate projection'!AZ16 -> 0.048889485 | AD14: =IF(ROUND(AB14,6)=ROUND((1+AC14/Var_freq)^Var_freq-1,6),"OK","ERROR") -> OK | AE14: =(1-(1+AB14)^-Mort_term)/AC14 -> 14.414086 | AG14: =Z14 -> 25155.82 | AH14: =House_price-AG14 -> 174844.18 | AI14: =ROUND(AH14/AE14/Var_freq,2) -> 1010.84 | AK14: ='Fixed rate projection'!$AE$3-('Variable rate projection'!AI14*Product_term*Var_freq) -> -183
A15: 10 | B15: =Deposit_mon -> 1000 | C15: =ROUND(B15*(1+'Interest rate projection'!AB17/Var_freq)+IF(C$5="Mortgage Starts",0,Deposit_mon),2) -> 2003.67 | D15: =ROUND(C15*(1+'Interest rate projection'!AC17/Var_freq)+IF(D$5="Mortgage Starts",0,Deposit_mon),2) -> 3011.03 | E15: =ROUND(D15*(1+'Interest rate projection'!AD17/Var_freq)+IF(E$5="Mortgage Starts",0,Deposit_mon),2) -> 4022.09 | F15: =ROUND(E15*(1+'Interest rate projection'!AE17/Var_freq)+IF(F$5="Mortgage Starts",0,Deposit_mon),2) -> 5036.87 | G15: =ROUND(F15*(1+'Interest rate projection'!AF17/Var_freq)+IF(G$5="Mortgage Starts",0,Deposit_mon),2) -> 6055.38 | H15: =ROUND(G15*(1+'Interest rate projection'!AG17/Var_freq)+IF(H$5="Mortgage Starts",0,Deposit_mon),2) -> 7076.42 | I15: =ROUND(H15*(1+'Interest rate projection'!AH17/Var_freq)+IF(I$5="Mortgage Starts",0,Deposit_mon),2) -> 8101.01 | J15: =ROUND(I15*(1+'Interest rate projection'!AI17/Var_freq)+IF(J$5="Mortgage Starts",0,Deposit_mon),2) -> 9129.16 | ... Z15: =ROUND(Y15*(1+'Interest rate projection'!AY17/Var_freq)+IF(Z$5="Mortgage Starts",0,Deposit_mon),2) -> 25139.45 | AB15: ='Interest rate projection'!Z17 -> 0.0525 | AC15: ='Interest rate projection'!AZ17 -> 0.051277533 | AD15: =IF(ROUND(AB15,6)=ROUND((1+AC15/Var_freq)^Var_freq-1,6),"OK","ERROR") -> OK | AE15: =(1-(1+AB15)^-Mort_term)/AC15 -> 14.075212 | AG15: =Z15 -> 25139.45 | AH15: =House_price-AG15 -> 174860.55 | AI15: =ROUND(AH15/AE15/Var_freq,2) -> 1035.27 | AK15: ='Fixed rate projection'!$AE$3-('Variable rate projection'!AI15*Product_term*Var_freq) -> -7512
A16: 11 | B16: =Deposit_mon -> 1000 | C16: =ROUND(B16*(1+'Interest rate projection'!AB18/Var_freq)+IF(C$5="Mortgage Starts",0,Deposit_mon),2) -> 2003.67 | D16: =ROUND(C16*(1+'Interest rate projection'!AC18/Var_freq)+IF(D$5="Mortgage Starts",0,Deposit_mon),2) -> 3011.03 | E16: =ROUND(D16*(1+'Interest rate projection'!AD18/Var_freq)+IF(E$5="Mortgage Starts",0,Deposit_mon),2) -> 4021.49 | F16: =ROUND(E16*(1+'Interest rate projection'!AE18/Var_freq)+IF(F$5="Mortgage Starts",0,Deposit_mon),2) -> 5035.46 | G16: =ROUND(F16*(1+'Interest rate projection'!AF18/Var_freq)+IF(G$5="Mortgage Starts",0,Deposit_mon),2) -> 6052.96 | H16: =ROUND(G16*(1+'Interest rate projection'!AG18/Var_freq)+IF(H$5="Mortgage Starts",0,Deposit_mon),2) -> 7073.99 | I16: =ROUND(H16*(1+'Interest rate projection'!AH18/Var_freq)+IF(I$5="Mortgage Starts",0,Deposit_mon),2) -> 8098.57 | J16: =ROUND(I16*(1+'Interest rate projection'!AI18/Var_freq)+IF(J$5="Mortgage Starts",0,Deposit_mon),2) -> 9128.33 | ... Z16: =ROUND(Y16*(1+'Interest rate projection'!AY18/Var_freq)+IF(Z$5="Mortgage Starts",0,Deposit_mon),2) -> 25021.15 | AB16: ='Interest rate projection'!Z18 -> 0.04 | AC16: ='Interest rate projection'!AZ18 -> 0.039284877 | AD16: =IF(ROUND(AB16,6)=ROUND((1+AC16/Var_freq)^Var_freq-1,6),"OK","ERROR") -> OK | AE16: =(1-(1+AB16)^-Mort_term)/AC16 -> 15.906457 | AG16: =Z16 -> 25021.15 | AH16: =House_price-AG16 -> 174978.85 | AI16: =ROUND(AH16/AE16/Var_freq,2) -> 916.71 | AK16: ='Fixed rate projection'!$AE$3-('Variable rate projection'!AI16*Product_term*Var_freq) -> 28056
A17: 12 | B17: =Deposit_mon -> 1000 | C17: =ROUND(B17*(1+'Interest rate projection'!AB19/Var_freq)+IF(C$5="Mortgage Starts",0,Deposit_mon),2) -> 2003.67 | D17: =ROUND(C17*(1+'Interest rate projection'!AC19/Var_freq)+IF(D$5="Mortgage Starts",0,Deposit_mon),2) -> 3011.03 | E17: =ROUND(D17*(1+'Interest rate projection'!AD19/Var_freq)+IF(E$5="Mortgage Starts",0,Deposit_mon),2) -> 4023.3 | F17: =ROUND(E17*(1+'Interest rate projection'!AE19/Var_freq)+IF(F$5="Mortgage Starts",0,Deposit_mon),2) -> 5039.69 | G17: =ROUND(F17*(1+'Interest rate projection'!AF19/Var_freq)+IF(G$5="Mortgage Starts",0,Deposit_mon),2) -> 6060.22 | H17: =ROUND(G17*(1+'Interest rate projection'!AG19/Var_freq)+IF(H$5="Mortgage Starts",0,Deposit_mon),2) -> 7087.32 | I17: =ROUND(H17*(1+'Interest rate projection'!AH19/Var_freq)+IF(I$5="Mortgage Starts",0,Deposit_mon),2) -> 8119.01 | J17: =ROUND(I17*(1+'Interest rate projection'!AI19/Var_freq)+IF(J$5="Mortgage Starts",0,Deposit_mon),2) -> 9155.32 | ... Z17: =ROUND(Y17*(1+'Interest rate projection'!AY19/Var_freq)+IF(Z$5="Mortgage Starts",0,Deposit_mon),2) -> 25472.07 | AB17: ='Interest rate projection'!Z19 -> 0.0625 | AC17: ='Interest rate projection'!AZ19 -> 0.060778019 | AD17: =IF(ROUND(AB17,6)=ROUND((1+AC17/Var_freq)^Var_freq-1,6),"OK","ERROR") -> OK | AE17: =(1-(1+AB17)^-Mort_term)/AC17 -> 12.838968 | AG17: =Z17 -> 25472.07 | AH17: =House_price-AG17 -> 174527.93 | AI17: =ROUND(AH17/AE17/Var_freq,2) -> 1132.8 | AK17: ='Fixed rate projection'!$AE$3-('Variable rate projection'!AI17*Product_term*Var_freq) -> -36771
A18: 13 | B18: =Deposit_mon -> 1000 | C18: =ROUND(B18*(1+'Interest rate projection'!AB20/Var_freq)+IF(C$5="Mortgage Starts",0,Deposit_mon),2) -> 2003.67 | D18: =ROUND(C18*(1+'Interest rate projection'!AC20/Var_freq)+IF(D$5="Mortgage Starts",0,Deposit_mon),2) -> 3011.03 | E18: =ROUND(D18*(1+'Interest rate projection'!AD20/Var_freq)+IF(E$5="Mortgage Starts",0,Deposit_mon),2) -> 4022.09 | F18: =ROUND(E18*(1+'Interest rate projection'!AE20/Var_freq)+IF(F$5="Mortgage Starts",0,Deposit_mon),2) -> 5036.87 | G18: =ROUND(F18*(1+'Interest rate projection'!AF20/Var_freq)+IF(G$5="Mortgage Starts",0,Deposit_mon),2) -> 6055.38 | H18: =ROUND(G18*(1+'Interest rate projection'!AG20/Var_freq)+IF(H$5="Mortgage Starts",0,Deposit_mon),2) -> 7077.63 | I18: =ROUND(H18*(1+'Interest rate projection'!AH20/Var_freq)+IF(I$5="Mortgage Starts",0,Deposit_mon),2) -> 8103.64 | J18: =ROUND(I18*(1+'Interest rate projection'!AI20/Var_freq)+IF(J$5="Mortgage Starts",0,Deposit_mon),2) -> 9133.42 | ... Z18: =ROUND(Y18*(1+'Interest rate projection'!AY20/Var_freq)+IF(Z$5="Mortgage Starts",0,Deposit_mon),2) -> 25146.71 | AB18: ='Interest rate projection'!Z20 -> 0.045 | AC18: ='Interest rate projection'!AZ20 -> 0.044097713 | AD18: =IF(ROUND(AB18,6)=ROUND((1+AC18/Var_freq)^Var_freq-1,6),"OK","ERROR") -> OK | AE18: =(1-(1+AB18)^-Mort_term)/AC18 -> 15.13161 | AG18: =Z18 -> 25146.71 | AH18: =House_price-AG18 -> 174853.29 | AI18: =ROUND(AH18/AE18/Var_freq,2) -> 962.96 | AK18: ='Fixed rate projection'!$AE$3-('Variable rate projection'!AI18*Product_term*Var_freq) -> 14181
A19: 14 | B19: =Deposit_mon -> 1000 | C19: =ROUND(B19*(1+'Interest rate projection'!AB21/Var_freq)+IF(C$5="Mortgage Starts",0,Deposit_mon),2) -> 2003.67 | D19: =ROUND(C19*(1+'Interest rate projection'!AC21/Var_freq)+IF(D$5="Mortgage Starts",0,Deposit_mon),2) -> 3011.03 | E19: =ROUND(D19*(1+'Interest rate projection'!AD21/Var_freq)+IF(E$5="Mortgage Starts",0,Deposit_mon),2) -> 4022.09 | F19: =ROUND(E19*(1+'Interest rate projection'!AE21/Var_freq)+IF(F$5="Mortgage Starts",0,Deposit_mon),2) -> 5036.87 | G19: =ROUND(F19*(1+'Interest rate projection'!AF21/Var_freq)+IF(G$5="Mortgage Starts",0,Deposit_mon),2) -> 6055.38 | H19: =ROUND(G19*(1+'Interest rate projection'!AG21/Var_freq)+IF(H$5="Mortgage Starts",0,Deposit_mon),2) -> 7077.63 | I19: =ROUND(H19*(1+'Interest rate projection'!AH21/Var_freq)+IF(I$5="Mortgage Starts",0,Deposit_mon),2) -> 8103.64 | J19: =ROUND(I19*(1+'Interest rate projection'!AI21/Var_freq)+IF(J$5="Mortgage Starts",0,Deposit_mon),2) -> 9133.42 | ... Z19: =ROUND(Y19*(1+'Interest rate projection'!AY21/Var_freq)+IF(Z$5="Mortgage Starts",0,Deposit_mon),2) -> 25143.91 | AB19: ='Interest rate projection'!Z21 -> 0.0475 | AC19: ='Interest rate projection'!AZ21 -> 0.04649622 | AD19: =IF(ROUND(AB19,6)=ROUND((1+AC19/Var_freq)^Var_freq-1,6),"OK","ERROR") -> OK | AE19: =(1-(1+AB19)^-Mort_term)/AC19 -> 14.766012 | AG19: =Z19 -> 25143.91 | AH19: =House_price-AG19 -> 174856.09 | AI19: =ROUND(AH19/AE19/Var_freq,2) -> 986.82 | AK19: ='Fixed rate projection'!$AE$3-('Variable rate projection'!AI19*Product_term*Var_freq) -> 7023
A20: 15 | B20: =Deposit_mon -> 1000 | C20: =ROUND(B20*(1+'Interest rate projection'!AB22/Var_freq)+IF(C$5="Mortgage Starts",0,Deposit_mon),2) -> 2003.67 | D20: =ROUND(C20*(1+'Interest rate projection'!AC22/Var_freq)+IF(D$5="Mortgage Starts",0,Deposit_mon),2) -> 3011.03 | E20: =ROUND(D20*(1+'Interest rate projection'!AD22/Var_freq)+IF(E$5="Mortgage Starts",0,Deposit_mon),2) -> 4022.09 | F20: =ROUND(E20*(1+'Interest rate projection'!AE22/Var_freq)+IF(F$5="Mortgage Starts",0,Deposit_mon),2) -> 5036.87 | G20: =ROUND(F20*(1+'Interest rate projection'!AF22/Var_freq)+IF(G$5="Mortgage Starts",0,Deposit_mon),2) -> 6055.38 | H20: =ROUND(G20*(1+'Interest rate projection'!AG22/Var_freq)+IF(H$5="Mortgage Starts",0,Deposit_mon),2) -> 7077.63 | I20: =ROUND(H20*(1+'Interest rate projection'!AH22/Var_freq)+IF(I$5="Mortgage Starts",0,Deposit_mon),2) -> 8103.64 | J20: =ROUND(I20*(1+'Interest rate projection'!AI22/Var_freq)+IF(J$5="Mortgage Starts",0,Deposit_mon),2) -> 9133.42 | ... Z20: =ROUND(Y20*(1+'Interest rate projection'!AY22/Var_freq)+IF(Z$5="Mortgage Starts",0,Deposit_mon),2) -> 25223.63 | AB20: ='Interest rate projection'!Z22 -> 0.0525 | AC20: ='Interest rate projection'!AZ22 -> 0.051277533 | AD20: =IF(ROUND(AB20,6)=ROUND((1+AC20/Var_freq)^Var_freq-1,6),"OK","ERROR") -> OK | AE20: =(1-(1+AB20)^-Mort_term)/AC20 -> 14.075212 | AG20: =Z20 -> 25223.63 | AH20: =House_price-AG20 -> 174776.37 | AI20: =ROUND(AH20/AE20/Var_freq,2) -> 1034.78 | AK20: ='Fixed rate projection'!$AE$3-('Variable rate projection'!AI20*Product_term*Var_freq) -> -7365
A21: 16 | B21: =Deposit_mon -> 1000 | C21: =ROUND(B21*(1+'Interest rate projection'!AB23/Var_freq)+IF(C$5="Mortgage Starts",0,Deposit_mon),2) -> 2003.67 | D21: =ROUND(C21*(1+'Interest rate projection'!AC23/Var_freq)+IF(D$5="Mortgage Starts",0,Deposit_mon),2) -> 3011.43 | E21: =ROUND(D21*(1+'Interest rate projection'!AD23/Var_freq)+IF(E$5="Mortgage Starts",0,Deposit_mon),2) -> 4023.7 | F21: =ROUND(E21*(1+'Interest rate projection'!AE23/Var_freq)+IF(F$5="Mortgage Starts",0,Deposit_mon),2) -> 5040.09 | G21: =ROUND(F21*(1+'Interest rate projection'!AF23/Var_freq)+IF(G$5="Mortgage Starts",0,Deposit_mon),2) -> 6060.62 | H21: =ROUND(G21*(1+'Interest rate projection'!AG23/Var_freq)+IF(H$5="Mortgage Starts",0,Deposit_mon),2) -> 7085.31 | I21: =ROUND(H21*(1+'Interest rate projection'!AH23/Var_freq)+IF(I$5="Mortgage Starts",0,Deposit_mon),2) -> 8114.18 | J21: =ROUND(I21*(1+'Interest rate projection'!AI23/Var_freq)+IF(J$5="Mortgage Starts",0,Deposit_mon),2) -> 9147.24 | ... Z21: =ROUND(Y21*(1+'Interest rate projection'!AY23/Var_freq)+IF(Z$5="Mortgage Starts",0,Deposit_mon),2) -> 25182.99 | AB21: ='Interest rate projection'!Z23 -> 0.0475 | AC21: ='Interest rate projection'!AZ23 -> 0.04649622 | AD21: =IF(ROUND(AB21,6)=ROUND((1+AC21/Var_freq)^Var_freq-1,6),"OK","ERROR") -> OK | AE21: =(1-(1+AB21)^-Mort_term)/AC21 -> 14.766012 | AG21: =Z21 -> 25182.99 | AH21: =House_price-AG21 -> 174817.01 | AI21: =ROUND(AH21/AE21/Var_freq,2) -> 986.6 | AK21: ='Fixed rate projection'!$AE$3-('Variable rate projection'!AI21*Product_term*Var_freq) -> 7089
A22: 17 | B22: =Deposit_mon -> 1000 | C22: =ROUND(B22*(1+'Interest rate projection'!AB24/Var_freq)+IF(C$5="Mortgage Starts",0,Deposit_mon),2) -> 2003.67 | D22: =ROUND(C22*(1+'Interest rate projection'!AC24/Var_freq)+IF(D$5="Mortgage Starts",0,Deposit_mon),2) -> 3011.03 | E22: =ROUND(D22*(1+'Interest rate projection'!AD24/Var_freq)+IF(E$5="Mortgage Starts",0,Deposit_mon),2) -> 4022.09 | F22: =ROUND(E22*(1+'Interest rate projection'!AE24/Var_freq)+IF(F$5="Mortgage Starts",0,Deposit_mon),2) -> 5036.87 | G22: =ROUND(F22*(1+'Interest rate projection'!AF24/Var_freq)+IF(G$5="Mortgage Starts",0,Deposit_mon),2) -> 6055.38 | H22: =ROUND(G22*(1+'Interest rate projection'!AG24/Var_freq)+IF(H$5="Mortgage Starts",0,Deposit_mon),2) -> 7077.63 | I22: =ROUND(H22*(1+'Interest rate projection'!AH24/Var_freq)+IF(I$5="Mortgage Starts",0,Deposit_mon),2) -> 8103.64 | J22: =ROUND(I22*(1+'Interest rate projection'!AI24/Var_freq)+IF(J$5="Mortgage Starts",0,Deposit_mon),2) -> 9133.42 | ... Z22: =ROUND(Y22*(1+'Interest rate projection'!AY24/Var_freq)+IF(Z$5="Mortgage Starts",0,Deposit_mon),2) -> 25029.77 | AB22: ='Interest rate projection'!Z24 -> 0.04 | AC22: ='Interest rate projection'!AZ24 -> 0.039284877 | AD22: =IF(ROUND(AB22,6)=ROUND((1+AC22/Var_freq)^Var_freq-1,6),"OK","ERROR") -> OK | AE22: =(1-(1+AB22)^-Mort_term)/AC22 -> 15.906457 | AG22: =Z22 -> 25029.77 | AH22: =House_price-AG22 -> 174970.23 | AI22: =ROUND(AH22/AE22/Var_freq,2) -> 916.66 | AK22: ='Fixed rate projection'!$AE$3-('Variable rate projection'!AI22*Product_term*Var_freq) -> 28071
A23: 18 | B23: =Deposit_mon -> 1000 | C23: =ROUND(B23*(1+'Interest rate projection'!AB25/Var_freq)+IF(C$5="Mortgage Starts",0,Deposit_mon),2) -> 2003.67 | D23: =ROUND(C23*(1+'Interest rate projection'!AC25/Var_freq)+IF(D$5="Mortgage Starts",0,Deposit_mon),2) -> 3011.03 | E23: =ROUND(D23*(1+'Interest rate projection'!AD25/Var_freq)+IF(E$5="Mortgage Starts",0,Deposit_mon),2) -> 4022.09 | F23: =ROUND(E23*(1+'Interest rate projection'!AE25/Var_freq)+IF(F$5="Mortgage Starts",0,Deposit_mon),2) -> 5036.87 | G23: =ROUND(F23*(1+'Interest rate projection'!AF25/Var_freq)+IF(G$5="Mortgage Starts",0,Deposit_mon),2) -> 6055.38 | H23: =ROUND(G23*(1+'Interest rate projection'!AG25/Var_freq)+IF(H$5="Mortgage Starts",0,Deposit_mon),2) -> 7077.63 | I23: =ROUND(H23*(1+'Interest rate projection'!AH25/Var_freq)+IF(I$5="Mortgage Starts",0,Deposit_mon),2) -> 8103.64 | J23: =ROUND(I23*(1+'Interest rate projection'!AI25/Var_freq)+IF(J$5="Mortgage Starts",0,Deposit_mon),2) -> 9133.42 | ... Z23: =ROUND(Y23*(1+'Interest rate projection'!AY25/Var_freq)+IF(Z$5="Mortgage Starts",0,Deposit_mon),2) -> 25180.89 | AB23: ='Interest rate projection'!Z25 -> 0.0475 | AC23: ='Interest rate projection'!AZ25 -> 0.04649622 | AD23: =IF(ROUND(AB23,6)=ROUND((1+AC23/Var_freq)^Var_freq-1,6),"OK","ERROR") -> OK | AE23: =(1-(1+AB23)^-Mort_term)/AC23 -> 14.766012 | AG23: =Z23 -> 25180.89 | AH23: =House_price-AG23 -> 174819.11 | AI23: =ROUND(AH23/AE23/Var_freq,2) -> 986.61 | AK23: ='Fixed rate projection'!$AE$3-('Variable rate projection'!AI23*Product_term*Var_freq) -> 7086
... A205: 200 | B205: =Deposit_mon -> 1000 | C205: =ROUND(B205*(1+'Interest rate projection'!AB207/Var_freq)+IF(C$5="Mortgage Starts",0,Deposit_mon),2) -> 2003.67 | D205: =ROUND(C205*(1+'Interest rate projection'!AC207/Var_freq)+IF(D$5="Mortgage Starts",0,Deposit_mon),2) -> 3011.03 | E205: =ROUND(D205*(1+'Interest rate projection'!AD207/Var_freq)+IF(E$5="Mortgage Starts",0,Deposit_mon),2) -> 4022.09 | F205: =ROUND(E205*(1+'Interest rate projection'!AE207/Var_freq)+IF(F$5="Mortgage Starts",0,Deposit_mon),2) -> 5036.87 | G205: =ROUND(F205*(1+'Interest rate projection'!AF207/Var_freq)+IF(G$5="Mortgage Starts",0,Deposit_mon),2) -> 6055.38 | H205: =ROUND(G205*(1+'Interest rate projection'!AG207/Var_freq)+IF(H$5="Mortgage Starts",0,Deposit_mon),2) -> 7077.63 | I205: =ROUND(H205*(1+'Interest rate projection'!AH207/Var_freq)+IF(I$5="Mortgage Starts",0,Deposit_mon),2) -> 8103.64 | J205: =ROUND(I205*(1+'Interest rate projection'!AI207/Var_freq)+IF(J$5="Mortgage Starts",0,Deposit_mon),2) -> 9133.42 | ... Z205: =ROUND(Y205*(1+'Interest rate projection'!AY207/Var_freq)+IF(Z$5="Mortgage Starts",0,Deposit_mon),2) -> 25087.51 | AB205: ='Interest rate projection'!Z207 -> 0.0425 | AC205: ='Interest rate projection'!AZ207 -> 0.04169394 | AD205: =IF(ROUND(AB205,6)=ROUND((1+AC205/Var_freq)^Var_freq-1,6),"OK","ERROR") -> OK | AE205: =(1-(1+AB205)^-Mort_term)/AC205 -> 15.51153 | AG205: =Z205 -> 25087.51 | AH205: =House_price-AG205 -> 174912.49 | AI205: =ROUND(AH205/AE205/Var_freq,2) -> 939.69 | AK205: ='Fixed rate projection'!$AE$3-('Variable rate projection'!AI205*Product_term*Var_freq) -> 21162

Sheet Fixed rate projection Alt
A1: Scenario 2 - Alternative product
A3: Rate of interest | B3: i | C3: =Fixed_int -> 0.05 | S3: Total monthly repayments | T3: =T10*Product_term_alt*Fixed_freq -> 60827.4
A4: Rate of interest convertible monthly | B4: i(12) | C4: =Fixed_freq*((1+C3)^(1/Fixed_freq)-1) -> 0.048889485
A5: Annuity rate | C5: =(1-(1+C3)^-Mort_term)/C4 -> 14.414086
A7: Projection
A9: Month | B9: Start | C9: 1 | D9: =IF(C9+1>Dep_term_alt*12,"Mortgage starts",C9+1) -> 2 | E9: =IF(D9+1>Dep_term_alt*12,"Mortgage starts",D9+1) -> 3 | F9: =IF(E9+1>Dep_term_alt*12,"Mortgage starts",E9+1) -> 4 | G9: =IF(F9+1>Dep_term_alt*12,"Mortgage starts",F9+1) -> 5 | H9: =IF(G9+1>Dep_term_alt*12,"Mortgage starts",G9+1) -> 6 | I9: =IF(H9+1>Dep_term_alt*12,"Mortgage starts",H9+1) -> 7 | J9: =IF(I9+1>Dep_term_alt*12,"Mortgage starts",I9+1) -> 8 | K9: =IF(J9+1>Dep_term_alt*12,"Mortgage starts",J9+1) -> 9 | ... O9: =IF(N9+1>Dep_term_alt*12,"Mortgage starts",N9+1) -> Mortgage starts | R9: Mortgage required | T9: Monthly repayment
A10: Deposit accumulation ($) | C10: =Deposit_mon_alt -> 2000 | D10: =ROUND(C10*(1+$C$4/Fixed_freq)+IF(D$9="Mortgage Starts",0,Deposit_mon_alt),2) -> 4008.15 | E10: =ROUND(D10*(1+$C$4/Fixed_freq)+IF(E$9="Mortgage Starts",0,Deposit_mon_alt),2) -> 6024.48 | F10: =ROUND(E10*(1+$C$4/Fixed_freq)+IF(F$9="Mortgage Starts",0,Deposit_mon_alt),2) -> 8049.02 | G10: =ROUND(F10*(1+$C$4/Fixed_freq)+IF(G$9="Mortgage Starts",0,Deposit_mon_alt),2) -> 10081.81 | H10: =ROUND(G10*(1+$C$4/Fixed_freq)+IF(H$9="Mortgage Starts",0,Deposit_mon_alt),2) -> 12122.88 | I10: =ROUND(H10*(1+$C$4/Fixed_freq)+IF(I$9="Mortgage Starts",0,Deposit_mon_alt),2) -> 14172.27 | J10: =ROUND(I10*(1+$C$4/Fixed_freq)+IF(J$9="Mortgage Starts",0,Deposit_mon_alt),2) -> 16230.01 | K10: =ROUND(J10*(1+$C$4/Fixed_freq)+IF(K$9="Mortgage Starts",0,Deposit_mon_alt),2) -> 18296.13 | ... O10: =ROUND(N10*(1+$C$4/Fixed_freq)+IF(O$9="Mortgage Starts",0,Deposit_mon_alt),2) -> 24645.14 | R10: =House_price-O10 -> 175354.86 | T10: =ROUND(R10/C5/Fixed_freq,2) -> 1013.79

Sheet Variable rate projection Alt
A1: Scenario 2 - Alternative product - Cashflow projection and mortgage calculation using projection of variable interest rates | Q1: Count of Errors | R1: =COUNTIF(R6:R205,"ERROR") -> 0
B3: All amounts in $
B4: Month - start of | P4: Mortgage annuity | U4: Financial projection
A5: Simulation | B5: 1 | C5: =IF(B5+1>Dep_term_alt*12,"Mortgage starts",B5+1) -> 2 | D5: =IF(C5+1>Dep_term_alt*12,"Mortgage starts",C5+1) -> 3 | E5: =IF(D5+1>Dep_term_alt*12,"Mortgage starts",D5+1) -> 4 | F5: =IF(E5+1>Dep_term_alt*12,"Mortgage starts",E5+1) -> 5 | G5: =IF(F5+1>Dep_term_alt*12,"Mortgage starts",F5+1) -> 6 | H5: =IF(G5+1>Dep_term_alt*12,"Mortgage starts",G5+1) -> 7 | I5: =IF(H5+1>Dep_term_alt*12,"Mortgage starts",H5+1) -> 8 | J5: =IF(I5+1>Dep_term_alt*12,"Mortgage starts",I5+1) -> 9 | ... N5: =IF(M5+1>Dep_term_alt*12,"Mortgage starts",M5+1) -> Mortgage starts | P5: Annual int rate | Q5: Interest rate convertible monthly | R5: Check annual equiv to monthly | S5: Annuity rate | U5: Deposit with interest | V5: Mortgage amount | W5: Monthly repayment | Y5: Total repayments under fixed option less total repayments under variable option | AA5: Analysis of difference in total mortgage repayments between fixed rate option and variable rate option
A6: 1 | B6: =Deposit_mon_alt -> 2000 | C6: =ROUND(B6*(1+'Interest rate projection'!AB8/Var_freq)+IF(C$5="Mortgage Starts",0,Deposit_mon_alt),2) -> 4007.35 | D6: =ROUND(C6*(1+'Interest rate projection'!AC8/Var_freq)+IF(D$5="Mortgage Starts",0,Deposit_mon_alt),2) -> 6022.08 | E6: =ROUND(D6*(1+'Interest rate projection'!AD8/Var_freq)+IF(E$5="Mortgage Starts",0,Deposit_mon_alt),2) -> 8044.21 | F6: =ROUND(E6*(1+'Interest rate projection'!AE8/Var_freq)+IF(F$5="Mortgage Starts",0,Deposit_mon_alt),2) -> 10073.77 | G6: =ROUND(F6*(1+'Interest rate projection'!AF8/Var_freq)+IF(G$5="Mortgage Starts",0,Deposit_mon_alt),2) -> 12108.77 | H6: =ROUND(G6*(1+'Interest rate projection'!AG8/Var_freq)+IF(H$5="Mortgage Starts",0,Deposit_mon_alt),2) -> 14150.84 | I6: =ROUND(H6*(1+'Interest rate projection'!AH8/Var_freq)+IF(I$5="Mortgage Starts",0,Deposit_mon_alt),2) -> 16200.01 | J6: =ROUND(I6*(1+'Interest rate projection'!AI8/Var_freq)+IF(J$5="Mortgage Starts",0,Deposit_mon_alt),2) -> 18256.3 | ... N6: =ROUND(M6*(1+'Interest rate projection'!AM8/Var_freq)+IF(N$5="Mortgage Starts",0,Deposit_mon_alt),2) -> 24553.14 | P6: ='Interest rate projection'!N8 -> 0.0425 | Q6: ='Interest rate projection'!AN8 -> 0.04169394 | R6: =IF(ROUND(P6,6)=ROUND((1+Q6/Var_freq)^Var_freq-1,6),"OK","ERROR") -> OK | S6: =(1-(1+P6)^-Mort_term)/Q6 -> 15.51153 | U6: =N6 -> 24553.14 | V6: =House_price-U6 -> 175446.86 | W6: =ROUND(V6/S6/Var_freq,2) -> 942.56 | Y6: ='Fixed rate projection Alt'!$T$3-('Variable rate projection Alt'!W6*Product_term_alt*Var_freq) -> 4273.8
A7: 2 | B7: =Deposit_mon_alt -> 2000 | C7: =ROUND(B7*(1+'Interest rate projection'!AB9/Var_freq)+IF(C$5="Mortgage Starts",0,Deposit_mon_alt),2) -> 4007.35 | D7: =ROUND(C7*(1+'Interest rate projection'!AC9/Var_freq)+IF(D$5="Mortgage Starts",0,Deposit_mon_alt),2) -> 6022.08 | E7: =ROUND(D7*(1+'Interest rate projection'!AD9/Var_freq)+IF(E$5="Mortgage Starts",0,Deposit_mon_alt),2) -> 8044.21 | F7: =ROUND(E7*(1+'Interest rate projection'!AE9/Var_freq)+IF(F$5="Mortgage Starts",0,Deposit_mon_alt),2) -> 10073.77 | G7: =ROUND(F7*(1+'Interest rate projection'!AF9/Var_freq)+IF(G$5="Mortgage Starts",0,Deposit_mon_alt),2) -> 12110.79 | H7: =ROUND(G7*(1+'Interest rate projection'!AG9/Var_freq)+IF(H$5="Mortgage Starts",0,Deposit_mon_alt),2) -> 14155.29 | I7: =ROUND(H7*(1+'Interest rate projection'!AH9/Var_freq)+IF(I$5="Mortgage Starts",0,Deposit_mon_alt),2) -> 16207.31 | J7: =ROUND(I7*(1+'Interest rate projection'!AI9/Var_freq)+IF(J$5="Mortgage Starts",0,Deposit_mon_alt),2) -> 18263.62 | ... N7: =ROUND(M7*(1+'Interest rate projection'!AM9/Var_freq)+IF(N$5="Mortgage Starts",0,Deposit_mon_alt),2) -> 24542.12 | P7: ='Interest rate projection'!N9 -> 0.0375 | Q7: ='Interest rate projection'!AN9 -> 0.0368705 | R7: =IF(ROUND(P7,6)=ROUND((1+Q7/Var_freq)^Var_freq-1,6),"OK","ERROR") -> OK | S7: =(1-(1+P7)^-Mort_term)/Q7 -> 16.317114 | U7: =N7 -> 24542.12 | V7: =House_price-U7 -> 175457.88 | W7: =ROUND(V7/S7/Var_freq,2) -> 896.08 | Y7: ='Fixed rate projection Alt'!$T$3-('Variable rate projection Alt'!W7*Product_term_alt*Var_freq) -> 7062.6 | AA7: Minimum | AB7: =MIN(Y6:Y205) -> -4419.6
A8: 3 | B8: =Deposit_mon_alt -> 2000 | C8: =ROUND(B8*(1+'Interest rate projection'!AB10/Var_freq)+IF(C$5="Mortgage Starts",0,Deposit_mon_alt),2) -> 4007.35 | D8: =ROUND(C8*(1+'Interest rate projection'!AC10/Var_freq)+IF(D$5="Mortgage Starts",0,Deposit_mon_alt),2) -> 6022.08 | E8: =ROUND(D8*(1+'Interest rate projection'!AD10/Var_freq)+IF(E$5="Mortgage Starts",0,Deposit_mon_alt),2) -> 8044.21 | F8: =ROUND(E8*(1+'Interest rate projection'!AE10/Var_freq)+IF(F$5="Mortgage Starts",0,Deposit_mon_alt),2) -> 10073.77 | G8: =ROUND(F8*(1+'Interest rate projection'!AF10/Var_freq)+IF(G$5="Mortgage Starts",0,Deposit_mon_alt),2) -> 12110.79 | H8: =ROUND(G8*(1+'Interest rate projection'!AG10/Var_freq)+IF(H$5="Mortgage Starts",0,Deposit_mon_alt),2) -> 14155.29 | I8: =ROUND(H8*(1+'Interest rate projection'!AH10/Var_freq)+IF(I$5="Mortgage Starts",0,Deposit_mon_alt),2) -> 16207.31 | J8: =ROUND(I8*(1+'Interest rate projection'!AI10/Var_freq)+IF(J$5="Mortgage Starts",0,Deposit_mon_alt),2) -> 18266.87 | ... N8: =ROUND(M8*(1+'Interest rate projection'!AM10/Var_freq)+IF(N$5="Mortgage Starts",0,Deposit_mon_alt),2) -> 24581.07 | P8: ='Interest rate projection'!N10 -> 0.045 | Q8: ='Interest rate projection'!AN10 -> 0.044097713 | R8: =IF(ROUND(P8,6)=ROUND((1+Q8/Var_freq)^Var_freq-1,6),"OK","ERROR") -> OK | S8: =(1-(1+P8)^-Mort_term)/Q8 -> 15.13161 | U8: =N8 -> 24581.07 | V8: =House_price-U8 -> 175418.93 | W8: =ROUND(V8/S8/Var_freq,2) -> 966.07 | Y8: ='Fixed rate projection Alt'!$T$3-('Variable rate projection Alt'!W8*Product_term_alt*Var_freq) -> 2863.2 | AA8: Maximum | AB8: =MAX(Y6:Y205) -> 9766.8
A9: 4 | B9: =Deposit_mon_alt -> 2000 | C9: =ROUND(B9*(1+'Interest rate projection'!AB11/Var_freq)+IF(C$5="Mortgage Starts",0,Deposit_mon_alt),2) -> 4007.35 | D9: =ROUND(C9*(1+'Interest rate projection'!AC11/Var_freq)+IF(D$5="Mortgage Starts",0,Deposit_mon_alt),2) -> 6022.08 | E9: =ROUND(D9*(1+'Interest rate projection'!AD11/Var_freq)+IF(E$5="Mortgage Starts",0,Deposit_mon_alt),2) -> 8044.21 | F9: =ROUND(E9*(1+'Interest rate projection'!AE11/Var_freq)+IF(F$5="Mortgage Starts",0,Deposit_mon_alt),2) -> 10073.77 | G9: =ROUND(F9*(1+'Interest rate projection'!AF11/Var_freq)+IF(G$5="Mortgage Starts",0,Deposit_mon_alt),2) -> 12110.79 | H9: =ROUND(G9*(1+'Interest rate projection'!AG11/Var_freq)+IF(H$5="Mortgage Starts",0,Deposit_mon_alt),2) -> 14155.29 | I9: =ROUND(H9*(1+'Interest rate projection'!AH11/Var_freq)+IF(I$5="Mortgage Starts",0,Deposit_mon_alt),2) -> 16207.31 | J9: =ROUND(I9*(1+'Interest rate projection'!AI11/Var_freq)+IF(J$5="Mortgage Starts",0,Deposit_mon_alt),2) -> 18266.87 | ... N9: =ROUND(M9*(1+'Interest rate projection'!AM11/Var_freq)+IF(N$5="Mortgage Starts",0,Deposit_mon_alt),2) -> 24628.84 | P9: ='Interest rate projection'!N11 -> 0.0525 | Q9: ='Interest rate projection'!AN11 -> 0.051277533 | R9: =IF(ROUND(P9,6)=ROUND((1+Q9/Var_freq)^Var_freq-1,6),"OK","ERROR") -> OK | S9: =(1-(1+P9)^-Mort_term)/Q9 -> 14.075212 | U9: =N9 -> 24628.84 | V9: =House_price-U9 -> 175371.16 | W9: =ROUND(V9/S9/Var_freq,2) -> 1038.3 | Y9: ='Fixed rate projection Alt'!$T$3-('Variable rate projection Alt'!W9*Product_term_alt*Var_freq) -> -1470.6 | AA9: Average | AB9: =AVERAGE(Y6:Y205) -> 2695.488
A10: 5 | B10: =Deposit_mon_alt -> 2000 | C10: =ROUND(B10*(1+'Interest rate projection'!AB12/Var_freq)+IF(C$5="Mortgage Starts",0,Deposit_mon_alt),2) -> 4007.35 | D10: =ROUND(C10*(1+'Interest rate projection'!AC12/Var_freq)+IF(D$5="Mortgage Starts",0,Deposit_mon_alt),2) -> 6022.08 | E10: =ROUND(D10*(1+'Interest rate projection'!AD12/Var_freq)+IF(E$5="Mortgage Starts",0,Deposit_mon_alt),2) -> 8044.21 | F10: =ROUND(E10*(1+'Interest rate projection'!AE12/Var_freq)+IF(F$5="Mortgage Starts",0,Deposit_mon_alt),2) -> 10072.16 | G10: =ROUND(F10*(1+'Interest rate projection'!AF12/Var_freq)+IF(G$5="Mortgage Starts",0,Deposit_mon_alt),2) -> 12107.16 | H10: =ROUND(G10*(1+'Interest rate projection'!AG12/Var_freq)+IF(H$5="Mortgage Starts",0,Deposit_mon_alt),2) -> 14149.23 | I10: =ROUND(H10*(1+'Interest rate projection'!AH12/Var_freq)+IF(I$5="Mortgage Starts",0,Deposit_mon_alt),2) -> 16198.39 | J10: =ROUND(I10*(1+'Interest rate projection'!AI12/Var_freq)+IF(J$5="Mortgage Starts",0,Deposit_mon_alt),2) -> 18254.67 | ... N10: =ROUND(M10*(1+'Interest rate projection'!AM12/Var_freq)+IF(N$5="Mortgage Starts",0,Deposit_mon_alt),2) -> 24551.5 | P10: ='Interest rate projection'!N12 -> 0.0375 | Q10: ='Interest rate projection'!AN12 -> 0.0368705 | R10: =IF(ROUND(P10,6)=ROUND((1+Q10/Var_freq)^Var_freq-1,6),"OK","ERROR") -> OK | S10: =(1-(1+P10)^-Mort_term)/Q10 -> 16.317114 | U10: =N10 -> 24551.5 | V10: =House_price-U10 -> 175448.5 | W10: =ROUND(V10/S10/Var_freq,2) -> 896.04 | Y10: ='Fixed rate projection Alt'!$T$3-('Variable rate projection Alt'!W10*Product_term_alt*Var_freq) -> 7065
A11: 6 | B11: =Deposit_mon_alt -> 2000 | C11: =ROUND(B11*(1+'Interest rate projection'!AB13/Var_freq)+IF(C$5="Mortgage Starts",0,Deposit_mon_alt),2) -> 4007.35 | D11: =ROUND(C11*(1+'Interest rate projection'!AC13/Var_freq)+IF(D$5="Mortgage Starts",0,Deposit_mon_alt),2) -> 6022.08 | E11: =ROUND(D11*(1+'Interest rate projection'!AD13/Var_freq)+IF(E$5="Mortgage Starts",0,Deposit_mon_alt),2) -> 8044.21 | F11: =ROUND(E11*(1+'Interest rate projection'!AE13/Var_freq)+IF(F$5="Mortgage Starts",0,Deposit_mon_alt),2) -> 10073.77 | G11: =ROUND(F11*(1+'Interest rate projection'!AF13/Var_freq)+IF(G$5="Mortgage Starts",0,Deposit_mon_alt),2) -> 12110.79 | H11: =ROUND(G11*(1+'Interest rate projection'!AG13/Var_freq)+IF(H$5="Mortgage Starts",0,Deposit_mon_alt),2) -> 14155.29 | I11: =ROUND(H11*(1+'Interest rate projection'!AH13/Var_freq)+IF(I$5="Mortgage Starts",0,Deposit_mon_alt),2) -> 16207.31 | J11: =ROUND(I11*(1+'Interest rate projection'!AI13/Var_freq)+IF(J$5="Mortgage Starts",0,Deposit_mon_alt),2) -> 18266.87 | ... N11: =ROUND(M11*(1+'Interest rate projection'!AM13/Var_freq)+IF(N$5="Mortgage Starts",0,Deposit_mon_alt),2) -> 24571.66 | P11: ='Interest rate projection'!N13 -> 0.0425 | Q11: ='Interest rate projection'!AN13 -> 0.04169394 | R11: =IF(ROUND(P11,6)=ROUND((1+Q11/Var_freq)^Var_freq-1,6),"OK","ERROR") -> OK | S11: =(1-(1+P11)^-Mort_term)/Q11 -> 15.51153 | U11: =N11 -> 24571.66 | V11: =House_price-U11 -> 175428.34 | W11: =ROUND(V11/S11/Var_freq,2) -> 942.46 | Y11: ='Fixed rate projection Alt'!$T$3-('Variable rate projection Alt'!W11*Product_term_alt*Var_freq) -> 4279.8 | AA11: Probability Fixed < Variable | AB11: =COUNTIF(Y6:Y205,"<0")/COUNT(Y6:Y205) -> 0.16
A12: 7 | B12: =Deposit_mon_alt -> 2000 | C12: =ROUND(B12*(1+'Interest rate projection'!AB14/Var_freq)+IF(C$5="Mortgage Starts",0,Deposit_mon_alt),2) -> 4007.35 | D12: =ROUND(C12*(1+'Interest rate projection'!AC14/Var_freq)+IF(D$5="Mortgage Starts",0,Deposit_mon_alt),2) -> 6022.08 | E12: =ROUND(D12*(1+'Interest rate projection'!AD14/Var_freq)+IF(E$5="Mortgage Starts",0,Deposit_mon_alt),2) -> 8044.21 | F12: =ROUND(E12*(1+'Interest rate projection'!AE14/Var_freq)+IF(F$5="Mortgage Starts",0,Deposit_mon_alt),2) -> 10073.77 | G12: =ROUND(F12*(1+'Interest rate projection'!AF14/Var_freq)+IF(G$5="Mortgage Starts",0,Deposit_mon_alt),2) -> 12110.79 | H12: =ROUND(G12*(1+'Interest rate projection'!AG14/Var_freq)+IF(H$5="Mortgage Starts",0,Deposit_mon_alt),2) -> 14155.29 | I12: =ROUND(H12*(1+'Interest rate projection'!AH14/Var_freq)+IF(I$5="Mortgage Starts",0,Deposit_mon_alt),2) -> 16207.31 | J12: =ROUND(I12*(1+'Interest rate projection'!AI14/Var_freq)+IF(J$5="Mortgage Starts",0,Deposit_mon_alt),2) -> 18266.87 | ... N12: =ROUND(M12*(1+'Interest rate projection'!AM14/Var_freq)+IF(N$5="Mortgage Starts",0,Deposit_mon_alt),2) -> 24598.25 | P12: ='Interest rate projection'!N14 -> 0.0475 | Q12: ='Interest rate projection'!AN14 -> 0.04649622 | R12: =IF(ROUND(P12,6)=ROUND((1+Q12/Var_freq)^Var_freq-1,6),"OK","ERROR") -> OK | S12: =(1-(1+P12)^-Mort_term)/Q12 -> 14.766012 | U12: =N12 -> 24598.25 | V12: =House_price-U12 -> 175401.75 | W12: =ROUND(V12/S12/Var_freq,2) -> 989.9 | Y12: ='Fixed rate projection Alt'!$T$3-('Variable rate projection Alt'!W12*Product_term_alt*Var_freq) -> 1433.4
A13: 8 | B13: =Deposit_mon_alt -> 2000 | C13: =ROUND(B13*(1+'Interest rate projection'!AB15/Var_freq)+IF(C$5="Mortgage Starts",0,Deposit_mon_alt),2) -> 4007.35 | D13: =ROUND(C13*(1+'Interest rate projection'!AC15/Var_freq)+IF(D$5="Mortgage Starts",0,Deposit_mon_alt),2) -> 6022.08 | E13: =ROUND(D13*(1+'Interest rate projection'!AD15/Var_freq)+IF(E$5="Mortgage Starts",0,Deposit_mon_alt),2) -> 8044.21 | F13: =ROUND(E13*(1+'Interest rate projection'!AE15/Var_freq)+IF(F$5="Mortgage Starts",0,Deposit_mon_alt),2) -> 10073.77 | G13: =ROUND(F13*(1+'Interest rate projection'!AF15/Var_freq)+IF(G$5="Mortgage Starts",0,Deposit_mon_alt),2) -> 12110.79 | H13: =ROUND(G13*(1+'Interest rate projection'!AG15/Var_freq)+IF(H$5="Mortgage Starts",0,Deposit_mon_alt),2) -> 14155.29 | I13: =ROUND(H13*(1+'Interest rate projection'!AH15/Var_freq)+IF(I$5="Mortgage Starts",0,Deposit_mon_alt),2) -> 16207.31 | J13: =ROUND(I13*(1+'Interest rate projection'!AI15/Var_freq)+IF(J$5="Mortgage Starts",0,Deposit_mon_alt),2) -> 18266.87 | ... N13: =ROUND(M13*(1+'Interest rate projection'!AM15/Var_freq)+IF(N$5="Mortgage Starts",0,Deposit_mon_alt),2) -> 24581.07 | P13: ='Interest rate projection'!N15 -> 0.045 | Q13: ='Interest rate projection'!AN15 -> 0.044097713 | R13: =IF(ROUND(P13,6)=ROUND((1+Q13/Var_freq)^Var_freq-1,6),"OK","ERROR") -> OK | S13: =(1-(1+P13)^-Mort_term)/Q13 -> 15.13161 | U13: =N13 -> 24581.07 | V13: =House_price-U13 -> 175418.93 | W13: =ROUND(V13/S13/Var_freq,2) -> 966.07 | Y13: ='Fixed rate projection Alt'!$T$3-('Variable rate projection Alt'!W13*Product_term_alt*Var_freq) -> 2863.2
A14: 9 | B14: =Deposit_mon_alt -> 2000 | C14: =ROUND(B14*(1+'Interest rate projection'!AB16/Var_freq)+IF(C$5="Mortgage Starts",0,Deposit_mon_alt),2) -> 4007.35 | D14: =ROUND(C14*(1+'Interest rate projection'!AC16/Var_freq)+IF(D$5="Mortgage Starts",0,Deposit_mon_alt),2) -> 6022.08 | E14: =ROUND(D14*(1+'Interest rate projection'!AD16/Var_freq)+IF(E$5="Mortgage Starts",0,Deposit_mon_alt),2) -> 8044.21 | F14: =ROUND(E14*(1+'Interest rate projection'!AE16/Var_freq)+IF(F$5="Mortgage Starts",0,Deposit_mon_alt),2) -> 10073.77 | G14: =ROUND(F14*(1+'Interest rate projection'!AF16/Var_freq)+IF(G$5="Mortgage Starts",0,Deposit_mon_alt),2) -> 12110.79 | H14: =ROUND(G14*(1+'Interest rate projection'!AG16/Var_freq)+IF(H$5="Mortgage Starts",0,Deposit_mon_alt),2) -> 14152.87 | I14: =ROUND(H14*(1+'Interest rate projection'!AH16/Var_freq)+IF(I$5="Mortgage Starts",0,Deposit_mon_alt),2) -> 16199.2 | J14: =ROUND(I14*(1+'Interest rate projection'!AI16/Var_freq)+IF(J$5="Mortgage Starts",0,Deposit_mon_alt),2) -> 18252.23 | ... N14: =ROUND(M14*(1+'Interest rate projection'!AM16/Var_freq)+IF(N$5="Mortgage Starts",0,Deposit_mon_alt),2) -> 24550.61 | P14: ='Interest rate projection'!N16 -> 0.045 | Q14: ='Interest rate projection'!AN16 -> 0.044097713 | R14: =IF(ROUND(P14,6)=ROUND((1+Q14/Var_freq)^Var_freq-1,6),"OK","ERROR") -> OK | S14: =(1-(1+P14)^-Mort_term)/Q14 -> 15.13161 | U14: =N14 -> 24550.61 | V14: =House_price-U14 -> 175449.39 | W14: =ROUND(V14/S14/Var_freq,2) -> 966.24 | Y14: ='Fixed rate projection Alt'!$T$3-('Variable rate projection Alt'!W14*Product_term_alt*Var_freq) -> 2853
A15: 10 | B15: =Deposit_mon_alt -> 2000 | C15: =ROUND(B15*(1+'Interest rate projection'!AB17/Var_freq)+IF(C$5="Mortgage Starts",0,Deposit_mon_alt),2) -> 4007.35 | D15: =ROUND(C15*(1+'Interest rate projection'!AC17/Var_freq)+IF(D$5="Mortgage Starts",0,Deposit_mon_alt),2) -> 6022.08 | E15: =ROUND(D15*(1+'Interest rate projection'!AD17/Var_freq)+IF(E$5="Mortgage Starts",0,Deposit_mon_alt),2) -> 8044.21 | F15: =ROUND(E15*(1+'Interest rate projection'!AE17/Var_freq)+IF(F$5="Mortgage Starts",0,Deposit_mon_alt),2) -> 10073.77 | G15: =ROUND(F15*(1+'Interest rate projection'!AF17/Var_freq)+IF(G$5="Mortgage Starts",0,Deposit_mon_alt),2) -> 12110.79 | H15: =ROUND(G15*(1+'Interest rate projection'!AG17/Var_freq)+IF(H$5="Mortgage Starts",0,Deposit_mon_alt),2) -> 14152.87 | I15: =ROUND(H15*(1+'Interest rate projection'!AH17/Var_freq)+IF(I$5="Mortgage Starts",0,Deposit_mon_alt),2) -> 16202.04 | J15: =ROUND(I15*(1+'Interest rate projection'!AI17/Var_freq)+IF(J$5="Mortgage Starts",0,Deposit_mon_alt),2) -> 18258.33 | ... N15: =ROUND(M15*(1+'Interest rate projection'!AM17/Var_freq)+IF(N$5="Mortgage Starts",0,Deposit_mon_alt),2) -> 24555.2 | P15: ='Interest rate projection'!N17 -> 0.0425 | Q15: ='Interest rate projection'!AN17 -> 0.04169394 | R15: =IF(ROUND(P15,6)=ROUND((1+Q15/Var_freq)^Var_freq-1,6),"OK","ERROR") -> OK | S15: =(1-(1+P15)^-Mort_term)/Q15 -> 15.51153 | U15: =N15 -> 24555.2 | V15: =House_price-U15 -> 175444.8 | W15: =ROUND(V15/S15/Var_freq,2) -> 942.55 | Y15: ='Fixed rate projection Alt'!$T$3-('Variable rate projection Alt'!W15*Product_term_alt*Var_freq) -> 4274.4
A16: 11 | B16: =Deposit_mon_alt -> 2000 | C16: =ROUND(B16*(1+'Interest rate projection'!AB18/Var_freq)+IF(C$5="Mortgage Starts",0,Deposit_mon_alt),2) -> 4007.35 | D16: =ROUND(C16*(1+'Interest rate projection'!AC18/Var_freq)+IF(D$5="Mortgage Starts",0,Deposit_mon_alt),2) -> 6022.08 | E16: =ROUND(D16*(1+'Interest rate projection'!AD18/Var_freq)+IF(E$5="Mortgage Starts",0,Deposit_mon_alt),2) -> 8043 | F16: =ROUND(E16*(1+'Interest rate projection'!AE18/Var_freq)+IF(F$5="Mortgage Starts",0,Deposit_mon_alt),2) -> 10070.95 | G16: =ROUND(F16*(1+'Interest rate projection'!AF18/Var_freq)+IF(G$5="Mortgage Starts",0,Deposit_mon_alt),2) -> 12105.94 | H16: =ROUND(G16*(1+'Interest rate projection'!AG18/Var_freq)+IF(H$5="Mortgage Starts",0,Deposit_mon_alt),2) -> 14148 | I16: =ROUND(H16*(1+'Interest rate projection'!AH18/Var_freq)+IF(I$5="Mortgage Starts",0,Deposit_mon_alt),2) -> 16197.16 | J16: =ROUND(I16*(1+'Interest rate projection'!AI18/Var_freq)+IF(J$5="Mortgage Starts",0,Deposit_mon_alt),2) -> 18256.68 | ... N16: =ROUND(M16*(1+'Interest rate projection'!AM18/Var_freq)+IF(N$5="Mortgage Starts",0,Deposit_mon_alt),2) -> 24543.69 | P16: ='Interest rate projection'!N18 -> 0.04 | Q16: ='Interest rate projection'!AN18 -> 0.039284877 | R16: =IF(ROUND(P16,6)=ROUND((1+Q16/Var_freq)^Var_freq-1,6),"OK","ERROR") -> OK | S16: =(1-(1+P16)^-Mort_term)/Q16 -> 15.906457 | U16: =N16 -> 24543.69 | V16: =House_price-U16 -> 175456.31 | W16: =ROUND(V16/S16/Var_freq,2) -> 919.21 | Y16: ='Fixed rate projection Alt'!$T$3-('Variable rate projection Alt'!W16*Product_term_alt*Var_freq) -> 5674.8
A17: 12 | B17: =Deposit_mon_alt -> 2000 | C17: =ROUND(B17*(1+'Interest rate projection'!AB19/Var_freq)+IF(C$5="Mortgage Starts",0,Deposit_mon_alt),2) -> 4007.35 | D17: =ROUND(C17*(1+'Interest rate projection'!AC19/Var_freq)+IF(D$5="Mortgage Starts",0,Deposit_mon_alt),2) -> 6022.08 | E17: =ROUND(D17*(1+'Interest rate projection'!AD19/Var_freq)+IF(E$5="Mortgage Starts",0,Deposit_mon_alt),2) -> 8046.61 | F17: =ROUND(E17*(1+'Interest rate projection'!AE19/Var_freq)+IF(F$5="Mortgage Starts",0,Deposit_mon_alt),2) -> 10079.39 | G17: =ROUND(F17*(1+'Interest rate projection'!AF19/Var_freq)+IF(G$5="Mortgage Starts",0,Deposit_mon_alt),2) -> 12120.45 | H17: =ROUND(G17*(1+'Interest rate projection'!AG19/Var_freq)+IF(H$5="Mortgage Starts",0,Deposit_mon_alt),2) -> 14174.65 | I17: =ROUND(H17*(1+'Interest rate projection'!AH19/Var_freq)+IF(I$5="Mortgage Starts",0,Deposit_mon_alt),2) -> 16238.03 | J17: =ROUND(I17*(1+'Interest rate projection'!AI19/Var_freq)+IF(J$5="Mortgage Starts",0,Deposit_mon_alt),2) -> 18310.64 | ... N17: =ROUND(M17*(1+'Interest rate projection'!AM19/Var_freq)+IF(N$5="Mortgage Starts",0,Deposit_mon_alt),2) -> 24694.18 | P17: ='Interest rate projection'!N19 -> 0.055 | Q17: ='Interest rate projection'!AN19 -> 0.053660387 | R17: =IF(ROUND(P17,6)=ROUND((1+Q17/Var_freq)^Var_freq-1,6),"OK","ERROR") -> OK | S17: =(1-(1+P17)^-Mort_term)/Q17 -> 13.748807 | U17: =N17 -> 24694.18 | V17: =House_price-U17 -> 175305.82 | W17: =ROUND(V17/S17/Var_freq,2) -> 1062.55 | Y17: ='Fixed rate projection Alt'!$T$3-('Variable rate projection Alt'!W17*Product_term_alt*Var_freq) -> -2925.6
A18: 13 | B18: =Deposit_mon_alt -> 2000 | C18: =ROUND(B18*(1+'Interest rate projection'!AB20/Var_freq)+IF(C$5="Mortgage Starts",0,Deposit_mon_alt),2) -> 4007.35 | D18: =ROUND(C18*(1+'Interest rate projection'!AC20/Var_freq)+IF(D$5="Mortgage Starts",0,Deposit_mon_alt),2) -> 6022.08 | E18: =ROUND(D18*(1+'Interest rate projection'!AD20/Var_freq)+IF(E$5="Mortgage Starts",0,Deposit_mon_alt),2) -> 8044.21 | F18: =ROUND(E18*(1+'Interest rate projection'!AE20/Var_freq)+IF(F$5="Mortgage Starts",0,Deposit_mon_alt),2) -> 10073.77 | G18: =ROUND(F18*(1+'Interest rate projection'!AF20/Var_freq)+IF(G$5="Mortgage Starts",0,Deposit_mon_alt),2) -> 12110.79 | H18: =ROUND(G18*(1+'Interest rate projection'!AG20/Var_freq)+IF(H$5="Mortgage Starts",0,Deposit_mon_alt),2) -> 14155.29 | I18: =ROUND(H18*(1+'Interest rate projection'!AH20/Var_freq)+IF(I$5="Mortgage Starts",0,Deposit_mon_alt),2) -> 16207.31 | J18: =ROUND(I18*(1+'Interest rate projection'!AI20/Var_freq)+IF(J$5="Mortgage Starts",0,Deposit_mon_alt),2) -> 18266.87 | ... N18: =ROUND(M18*(1+'Interest rate projection'!AM20/Var_freq)+IF(N$5="Mortgage Starts",0,Deposit_mon_alt),2) -> 24581.07 | P18: ='Interest rate projection'!N20 -> 0.045 | Q18: ='Interest rate projection'!AN20 -> 0.044097713 | R18: =IF(ROUND(P18,6)=ROUND((1+Q18/Var_freq)^Var_freq-1,6),"OK","ERROR") -> OK | S18: =(1-(1+P18)^-Mort_term)/Q18 -> 15.13161 | U18: =N18 -> 24581.07 | V18: =House_price-U18 -> 175418.93 | W18: =ROUND(V18/S18/Var_freq,2) -> 966.07 | Y18: ='Fixed rate projection Alt'!$T$3-('Variable rate projection Alt'!W18*Product_term_alt*Var_freq) -> 2863.2
A19: 14 | B19: =Deposit_mon_alt -> 2000 | C19: =ROUND(B19*(1+'Interest rate projection'!AB21/Var_freq)+IF(C$5="Mortgage Starts",0,Deposit_mon_alt),2) -> 4007.35 | D19: =ROUND(C19*(1+'Interest rate projection'!AC21/Var_freq)+IF(D$5="Mortgage Starts",0,Deposit_mon_alt),2) -> 6022.08 | E19: =ROUND(D19*(1+'Interest rate projection'!AD21/Var_freq)+IF(E$5="Mortgage Starts",0,Deposit_mon_alt),2) -> 8044.21 | F19: =ROUND(E19*(1+'Interest rate projection'!AE21/Var_freq)+IF(F$5="Mortgage Starts",0,Deposit_mon_alt),2) -> 10073.77 | G19: =ROUND(F19*(1+'Interest rate projection'!AF21/Var_freq)+IF(G$5="Mortgage Starts",0,Deposit_mon_alt),2) -> 12110.79 | H19: =ROUND(G19*(1+'Interest rate projection'!AG21/Var_freq)+IF(H$5="Mortgage Starts",0,Deposit_mon_alt),2) -> 14155.29 | I19: =ROUND(H19*(1+'Interest rate projection'!AH21/Var_freq)+IF(I$5="Mortgage Starts",0,Deposit_mon_alt),2) -> 16207.31 | J19: =ROUND(I19*(1+'Interest rate projection'!AI21/Var_freq)+IF(J$5="Mortgage Starts",0,Deposit_mon_alt),2) -> 18266.87 | ... N19: =ROUND(M19*(1+'Interest rate projection'!AM21/Var_freq)+IF(N$5="Mortgage Starts",0,Deposit_mon_alt),2) -> 24581.07 | P19: ='Interest rate projection'!N21 -> 0.045 | Q19: ='Interest rate projection'!AN21 -> 0.044097713 | R19: =IF(ROUND(P19,6)=ROUND((1+Q19/Var_freq)^Var_freq-1,6),"OK","ERROR") -> OK | S19: =(1-(1+P19)^-Mort_term)/Q19 -> 15.13161 | U19: =N19 -> 24581.07 | V19: =House_price-U19 -> 175418.93 | W19: =ROUND(V19/S19/Var_freq,2) -> 966.07 | Y19: ='Fixed rate projection Alt'!$T$3-('Variable rate projection Alt'!W19*Product_term_alt*Var_freq) -> 2863.2
A20: 15 | B20: =Deposit_mon_alt -> 2000 | C20: =ROUND(B20*(1+'Interest rate projection'!AB22/Var_freq)+IF(C$5="Mortgage Starts",0,Deposit_mon_alt),2) -> 4007.35 | D20: =ROUND(C20*(1+'Interest rate projection'!AC22/Var_freq)+IF(D$5="Mortgage Starts",0,Deposit_mon_alt),2) -> 6022.08 | E20: =ROUND(D20*(1+'Interest rate projection'!AD22/Var_freq)+IF(E$5="Mortgage Starts",0,Deposit_mon_alt),2) -> 8044.21 | F20: =ROUND(E20*(1+'Interest rate projection'!AE22/Var_freq)+IF(F$5="Mortgage Starts",0,Deposit_mon_alt),2) -> 10073.77 | G20: =ROUND(F20*(1+'Interest rate projection'!AF22/Var_freq)+IF(G$5="Mortgage Starts",0,Deposit_mon_alt),2) -> 12110.79 | H20: =ROUND(G20*(1+'Interest rate projection'!AG22/Var_freq)+IF(H$5="Mortgage Starts",0,Deposit_mon_alt),2) -> 14155.29 | I20: =ROUND(H20*(1+'Interest rate projection'!AH22/Var_freq)+IF(I$5="Mortgage Starts",0,Deposit_mon_alt),2) -> 16207.31 | J20: =ROUND(I20*(1+'Interest rate projection'!AI22/Var_freq)+IF(J$5="Mortgage Starts",0,Deposit_mon_alt),2) -> 18266.87 | ... N20: =ROUND(M20*(1+'Interest rate projection'!AM22/Var_freq)+IF(N$5="Mortgage Starts",0,Deposit_mon_alt),2) -> 24590.85 | P20: ='Interest rate projection'!N22 -> 0.0475 | Q20: ='Interest rate projection'!AN22 -> 0.04649622 | R20: =IF(ROUND(P20,6)=ROUND((1+Q20/Var_freq)^Var_freq-1,6),"OK","ERROR") -> OK | S20: =(1-(1+P20)^-Mort_term)/Q20 -> 14.766012 | U20: =N20 -> 24590.85 | V20: =House_price-U20 -> 175409.15 | W20: =ROUND(V20/S20/Var_freq,2) -> 989.94 | Y20: ='Fixed rate projection Alt'!$T$3-('Variable rate projection Alt'!W20*Product_term_alt*Var_freq) -> 1431
A21: 16 | B21: =Deposit_mon_alt -> 2000 | C21: =ROUND(B21*(1+'Interest rate projection'!AB23/Var_freq)+IF(C$5="Mortgage Starts",0,Deposit_mon_alt),2) -> 4007.35 | D21: =ROUND(C21*(1+'Interest rate projection'!AC23/Var_freq)+IF(D$5="Mortgage Starts",0,Deposit_mon_alt),2) -> 6022.88 | E21: =ROUND(D21*(1+'Interest rate projection'!AD23/Var_freq)+IF(E$5="Mortgage Starts",0,Deposit_mon_alt),2) -> 8047.42 | F21: =ROUND(E21*(1+'Interest rate projection'!AE23/Var_freq)+IF(F$5="Mortgage Starts",0,Deposit_mon_alt),2) -> 10080.21 | G21: =ROUND(F21*(1+'Interest rate projection'!AF23/Var_freq)+IF(G$5="Mortgage Starts",0,Deposit_mon_alt),2) -> 12121.28 | H21: =ROUND(G21*(1+'Interest rate projection'!AG23/Var_freq)+IF(H$5="Mortgage Starts",0,Deposit_mon_alt),2) -> 14170.66 | I21: =ROUND(H21*(1+'Interest rate projection'!AH23/Var_freq)+IF(I$5="Mortgage Starts",0,Deposit_mon_alt),2) -> 16228.39 | J21: =ROUND(I21*(1+'Interest rate projection'!AI23/Var_freq)+IF(J$5="Mortgage Starts",0,Deposit_mon_alt),2) -> 18294.51 | ... N21: =ROUND(M21*(1+'Interest rate projection'!AM23/Var_freq)+IF(N$5="Mortgage Starts",0,Deposit_mon_alt),2) -> 24643.49 | P21: ='Interest rate projection'!N23 -> 0.045 | Q21: ='Interest rate projection'!AN23 -> 0.044097713 | R21: =IF(ROUND(P21,6)=ROUND((1+Q21/Var_freq)^Var_freq-1,6),"OK","ERROR") -> OK | S21: =(1-(1+P21)^-Mort_term)/Q21 -> 15.13161 | U21: =N21 -> 24643.49 | V21: =House_price-U21 -> 175356.51 | W21: =ROUND(V21/S21/Var_freq,2) -> 965.73 | Y21: ='Fixed rate projection Alt'!$T$3-('Variable rate projection Alt'!W21*Product_term_alt*Var_freq) -> 2883.6
A22: 17 | B22: =Deposit_mon_alt -> 2000 | C22: =ROUND(B22*(1+'Interest rate projection'!AB24/Var_freq)+IF(C$5="Mortgage Starts",0,Deposit_mon_alt),2) -> 4007.35 | D22: =ROUND(C22*(1+'Interest rate projection'!AC24/Var_freq)+IF(D$5="Mortgage Starts",0,Deposit_mon_alt),2) -> 6022.08 | E22: =ROUND(D22*(1+'Interest rate projection'!AD24/Var_freq)+IF(E$5="Mortgage Starts",0,Deposit_mon_alt),2) -> 8044.21 | F22: =ROUND(E22*(1+'Interest rate projection'!AE24/Var_freq)+IF(F$5="Mortgage Starts",0,Deposit_mon_alt),2) -> 10073.77 | G22: =ROUND(F22*(1+'Interest rate projection'!AF24/Var_freq)+IF(G$5="Mortgage Starts",0,Deposit_mon_alt),2) -> 12110.79 | H22: =ROUND(G22*(1+'Interest rate projection'!AG24/Var_freq)+IF(H$5="Mortgage Starts",0,Deposit_mon_alt),2) -> 14155.29 | I22: =ROUND(H22*(1+'Interest rate projection'!AH24/Var_freq)+IF(I$5="Mortgage Starts",0,Deposit_mon_alt),2) -> 16207.31 | J22: =ROUND(I22*(1+'Interest rate projection'!AI24/Var_freq)+IF(J$5="Mortgage Starts",0,Deposit_mon_alt),2) -> 18266.87 | ... N22: =ROUND(M22*(1+'Interest rate projection'!AM24/Var_freq)+IF(N$5="Mortgage Starts",0,Deposit_mon_alt),2) -> 24576.16 | P22: ='Interest rate projection'!N24 -> 0.0425 | Q22: ='Interest rate projection'!AN24 -> 0.04169394 | R22: =IF(ROUND(P22,6)=ROUND((1+Q22/Var_freq)^Var_freq-1,6),"OK","ERROR") -> OK | S22: =(1-(1+P22)^-Mort_term)/Q22 -> 15.51153 | U22: =N22 -> 24576.16 | V22: =House_price-U22 -> 175423.84 | W22: =ROUND(V22/S22/Var_freq,2) -> 942.44 | Y22: ='Fixed rate projection Alt'!$T$3-('Variable rate projection Alt'!W22*Product_term_alt*Var_freq) -> 4281
A23: 18 | B23: =Deposit_mon_alt -> 2000 | C23: =ROUND(B23*(1+'Interest rate projection'!AB25/Var_freq)+IF(C$5="Mortgage Starts",0,Deposit_mon_alt),2) -> 4007.35 | D23: =ROUND(C23*(1+'Interest rate projection'!AC25/Var_freq)+IF(D$5="Mortgage Starts",0,Deposit_mon_alt),2) -> 6022.08 | E23: =ROUND(D23*(1+'Interest rate projection'!AD25/Var_freq)+IF(E$5="Mortgage Starts",0,Deposit_mon_alt),2) -> 8044.21 | F23: =ROUND(E23*(1+'Interest rate projection'!AE25/Var_freq)+IF(F$5="Mortgage Starts",0,Deposit_mon_alt),2) -> 10073.77 | G23: =ROUND(F23*(1+'Interest rate projection'!AF25/Var_freq)+IF(G$5="Mortgage Starts",0,Deposit_mon_alt),2) -> 12110.79 | H23: =ROUND(G23*(1+'Interest rate projection'!AG25/Var_freq)+IF(H$5="Mortgage Starts",0,Deposit_mon_alt),2) -> 14155.29 | I23: =ROUND(H23*(1+'Interest rate projection'!AH25/Var_freq)+IF(I$5="Mortgage Starts",0,Deposit_mon_alt),2) -> 16207.31 | J23: =ROUND(I23*(1+'Interest rate projection'!AI25/Var_freq)+IF(J$5="Mortgage Starts",0,Deposit_mon_alt),2) -> 18266.87 | ... N23: =ROUND(M23*(1+'Interest rate projection'!AM25/Var_freq)+IF(N$5="Mortgage Starts",0,Deposit_mon_alt),2) -> 24581.07 | P23: ='Interest rate projection'!N25 -> 0.0475 | Q23: ='Interest rate projection'!AN25 -> 0.04649622 | R23: =IF(ROUND(P23,6)=ROUND((1+Q23/Var_freq)^Var_freq-1,6),"OK","ERROR") -> OK | S23: =(1-(1+P23)^-Mort_term)/Q23 -> 14.766012 | U23: =N23 -> 24581.07 | V23: =House_price-U23 -> 175418.93 | W23: =ROUND(V23/S23/Var_freq,2) -> 989.99 | Y23: ='Fixed rate projection Alt'!$T$3-('Variable rate projection Alt'!W23*Product_term_alt*Var_freq) -> 1428
... A205: 200 | B205: =Deposit_mon_alt -> 2000 | C205: =ROUND(B205*(1+'Interest rate projection'!AB207/Var_freq)+IF(C$5="Mortgage Starts",0,Deposit_mon_alt),2) -> 4007.35 | D205: =ROUND(C205*(1+'Interest rate projection'!AC207/Var_freq)+IF(D$5="Mortgage Starts",0,Deposit_mon_alt),2) -> 6022.08 | E205: =ROUND(D205*(1+'Interest rate projection'!AD207/Var_freq)+IF(E$5="Mortgage Starts",0,Deposit_mon_alt),2) -> 8044.21 | F205: =ROUND(E205*(1+'Interest rate projection'!AE207/Var_freq)+IF(F$5="Mortgage Starts",0,Deposit_mon_alt),2) -> 10073.77 | G205: =ROUND(F205*(1+'Interest rate projection'!AF207/Var_freq)+IF(G$5="Mortgage Starts",0,Deposit_mon_alt),2) -> 12110.79 | H205: =ROUND(G205*(1+'Interest rate projection'!AG207/Var_freq)+IF(H$5="Mortgage Starts",0,Deposit_mon_alt),2) -> 14155.29 | I205: =ROUND(H205*(1+'Interest rate projection'!AH207/Var_freq)+IF(I$5="Mortgage Starts",0,Deposit_mon_alt),2) -> 16207.31 | J205: =ROUND(I205*(1+'Interest rate projection'!AI207/Var_freq)+IF(J$5="Mortgage Starts",0,Deposit_mon_alt),2) -> 18266.87 | ... N205: =ROUND(M205*(1+'Interest rate projection'!AM207/Var_freq)+IF(N$5="Mortgage Starts",0,Deposit_mon_alt),2) -> 24551.53 | P205: ='Interest rate projection'!N207 -> 0.0425 | Q205: ='Interest rate projection'!AN207 -> 0.04169394 | R205: =IF(ROUND(P205,6)=ROUND((1+Q205/Var_freq)^Var_freq-1,6),"OK","ERROR") -> OK | S205: =(1-(1+P205)^-Mort_term)/Q205 -> 15.51153 | U205: =N205 -> 24551.53 | V205: =House_price-U205 -> 175448.47 | W205: =ROUND(V205/S205/Var_freq,2) -> 942.57 | Y205: ='Fixed rate projection Alt'!$T$3-('Variable rate projection Alt'!W205*Product_term_alt*Var_freq) -> 4273.2
