Workbook
Name CarData: Parameters!$A$13:$I$20
Name Header: Parameters!$A$13:$I$13
Name HeaderCol: Parameters!$A$13:$A$20
Name TaxCO2: Parameters!$A$3:$D$8
Name TaxWeight: Parameters!$F$3:$H$8

Sheet Parameters
A1: Parameters
F2: Alternative
A3: Tax - CO2 (g/km) | C3: Year of purchase ($) | D3: Year 2-5 ($) | F3: Tax - Weight (kg) | H3: Amount ($)
A4: from | B4: to | F4: from | G4: to
A5: 0 | B5: 50 | C5: 0 | D5: 0 | F5: 0 | G5: 1500 | H5: 150
A6: 50 | B6: 150 | C6: =2*D6 -> 300 | D6: 150 | F6: 1500 | G6: 2500 | H6: =H5*2 -> 300
A7: 150 | B7: 200 | C7: =2*D7 -> 400 | D7: 200 | F7: 2500 | G7: 3500 | H7: =H6*2 -> 600
A8: 200 | C8: =2*D8 -> 600 | D8: 300 | F8: 3500 | H8: =H7*2 -> 1200
A10: Kilometers per year | B10: 15000
A12: Car Specifications
B13: CO2 | C13: Fuel | D13: Battery capacity | E13: Range | F13: Weight | G13: Price | H13: Profit margin | I13: Annual service cost
B14: emitted per km (g) | C14: Consumption (litres per 100km) | D14: (kWh) | E14: * (km) | F14: (kg) | G14: ($) | I14: ($)
A15: Small Petrol | B15: 125 | C15: 6.4 | F15: 1900 | G15: 28450 | H15: 0.05 | I15: 250
A16: Medium Petrol | B16: 186 | C16: 7.7 | F16: 2070 | G16: 36866 | H16: 0.07 | I16: 300
A17: Large Petrol | B17: 215 | C17: 8.2 | F17: 2850 | G17: 65585 | H17: 0.11 | I17: 350
A18: Small Electric | B18: 0 | D18: 62 | E18: 264 | F18: 2270 | G18: 39465 | H18: 0.11 | I18: 100
A19: Medium Electric | B19: 0 | D19: 82 | E19: 315 | F19: 2540 | G19: 47825 | H19: 0.14 | I19: 150
A20: Large Electric | B20: 0 | D20: 96 | E20: 309 | F20: 3730 | G20: 68834 | H20: 0.18 | I20: 180
E21: * Distance travelled on full battery
B22: Base | C22: Alt
A23: Electricity cost per kWh ($) | B23: 0.28 | C23: =B23-0.05 -> 0.23
A24: Fuel cost per litre ($) | B24: 1.5
A26: Discount rate | B26: 0.04
A27: Service cost from year | B27: 4

Sheet Data
A1: Vehicle Sales for the last year - number of cars sold each month
A3: Model | B3: Jan | C3: Feb | D3: Mar | E3: Apr | F3: May | G3: Jun | H3: Jul | I3: Aug | J3: Sep | K3: Oct | L3: Nov | M3: Dec | N3: Total
A4: Small Petrol | B4: 1296 | C4: 1111 | D4: 3190 | E4: 2198 | F4: 2335 | G4: 2804 | H4: 2076 | I4: 1947 | J4: 2423 | K4: 2228 | L4: 2380 | M4: 1579 | N4: =SUM(B4:M4) -> 25567
A5: Medium Petrol | B5: 154 | C5: 63 | D5: 333 | E5: 163 | F5: 122 | G5: 204 | H5: 156 | I5: 46 | J5: 197 | K5: 102 | L5: 217 | M5: 136 | N5: =SUM(B5:M5) -> 1893
A6: Large Petrol | B6: 163 | C6: 145 | D6: 621 | E6: 225 | F6: 177 | G6: 72 | H6: 53 | I6: 68 | J6: 162 | K6: 47 | L6: 31 | M6: 72 | N6: =SUM(B6:M6) -> 1836
A7: Small Electric | B7: 719 | C7: 632 | D7: 1234 | E7: 890 | F7: 791 | G7: 733 | H7: 752 | I7: 636 | J7: 880 | K7: 1109 | L7: 1338 | M7: 1432 | N7: =SUM(B7:M7) -> 11146
A8: Medium Electric | B8: 379 | C8: 252 | D8: 706 | E8: 618 | F8: 821 | G8: 261 | H8: 205 | I8: 254 | J8: 637 | K8: 749 | L8: 622 | M8: 787 | N8: =SUM(B8:M8) -> 6291
A9: Large Electric | B9: 215 | C9: 82 | D9: 355 | E9: 178 | F9: 203 | G9: 149 | H9: 74 | I9: 139 | J9: 479 | K9: 510 | L9: 355 | M9: 1109 | N9: =SUM(B9:M9) -> 3848
A10: Total | B10: =SUM(B4:B9) -> 2926 | C10: =SUM(C4:C9) -> 2285 | D10: =SUM(D4:D9) -> 6439 | E10: =SUM(E4:E9) -> 4272 | F10: =SUM(F4:F9) -> 4449 | G10: =SUM(G4:G9) -> 4223 | H10: =SUM(H4:H9) -> 3316 | I10: =SUM(I4:I9) -> 3090 | ... N10: =SUM(N4:N9) -> 50581

Sheet Calculations-Base
A1: Base Scenario
A2: Calculates the total cost of ownership for all cars in the current range under the old tax regime.
B5: Small Petrol | H5: Medium Petrol | N5: Large Petrol
A6: Year | B6: Price | C6: Tax | D6: Annual service cost | E6: Fuel | F6: PV start | G6: PV mid | H6: Price | I6: Tax | J6: Annual service cost | K6: Fuel | L6: PV start | M6: PV mid | N6: Price | O6: Tax | P6: Annual service cost | Q6: Fuel | R6: PV start | S6: PV mid
A7: 1 | B7: =INDEX(CarData,MATCH($B$5,HeaderCol,0),MATCH(B$6,Header,0)) -> 28450 | C7: =VLOOKUP(INDEX(CarData,MATCH($B$5,HeaderCol,0),MATCH("CO2",Header,0)),TaxCO2,MIN($A7,2)+2,TRUE) -> 300 | D7: =IF($A7>=Parameters!$B$27,INDEX(CarData,MATCH($B$5,HeaderCol,0),MATCH(D$6,Header,0)),0) -> 0 | E7: =Parameters!$B$10*INDEX(CarData,MATCH($B$5,HeaderCol,0),MATCH("Fuel",Header,0))/100*Parameters!$B$24 -> 1440 | F7: =(B7+C7)*(1+Parameters!$B$26)^-($A7-1) -> 28750 | G7: =(D7+E7)*(1+Parameters!$B$26)^-($A7-0.5) -> 1412.0362 | H7: =INDEX(CarData,MATCH($H$5,HeaderCol,0),MATCH(H$6,Header,0)) -> 36866 | I7: =VLOOKUP(INDEX(CarData,MATCH($H$5,HeaderCol,0),MATCH("CO2",Header,0)),TaxCO2,MIN($A7,2)+2,TRUE) -> 400 | J7: =IF($A7>=Parameters!$B$27,INDEX(CarData,MATCH($H$5,HeaderCol,0),MATCH(J$6,Header,0)),0) -> 0 | K7: =Parameters!$B$10*INDEX(CarData,MATCH($H$5,HeaderCol,0),MATCH("Fuel",Header,0))/100*Parameters!$B$24 -> 1732.5 | L7: =(H7+I7)*(1+Parameters!$B$26)^-($A7-1) -> 37266 | M7: =(J7+K7)*(1+Parameters!$B$26)^-($A7-0.5) -> 1698.856 | N7: =INDEX(CarData,MATCH($N$5,HeaderCol,0),MATCH(N$6,Header,0)) -> 65585 | O7: =VLOOKUP(INDEX(CarData,MATCH($N$5,HeaderCol,0),MATCH("CO2",Header,0)),TaxCO2,MIN($A7,2)+2,TRUE) -> 600 | P7: =IF($A7>=Parameters!$B$27,INDEX(CarData,MATCH($N$5,HeaderCol,0),MATCH(P$6,Header,0)),0) -> 0 | Q7: =Parameters!$B$10*INDEX(CarData,MATCH($N$5,HeaderCol,0),MATCH("Fuel",Header,0))/100*Parameters!$B$24 -> 1845 | R7: =(N7+O7)*(1+Parameters!$B$26)^-($A7-1) -> 66185 | S7: =(P7+Q7)*(1+Parameters!$B$26)^-($A7-0.5) -> 1809.1713
A8: 2 | C8: =VLOOKUP(INDEX(CarData,MATCH($B$5,HeaderCol,0),MATCH("CO2",Header,0)),TaxCO2,MIN($A8,2)+2,TRUE) -> 150 | D8: =IF($A8>=Parameters!$B$27,INDEX(CarData,MATCH($B$5,HeaderCol,0),MATCH(D$6,Header,0)),0) -> 0 | E8: =Parameters!$B$10*INDEX(CarData,MATCH($B$5,HeaderCol,0),MATCH("Fuel",Header,0))/100*Parameters!$B$24 -> 1440 | F8: =(B8+C8)*(1+Parameters!$B$26)^-($A8-1) -> 144.23077 | G8: =(D8+E8)*(1+Parameters!$B$26)^-($A8-0.5) -> 1357.7271 | I8: =VLOOKUP(INDEX(CarData,MATCH($H$5,HeaderCol,0),MATCH("CO2",Header,0)),TaxCO2,MIN($A8,2)+2,TRUE) -> 200 | J8: =IF($A8>=Parameters!$B$27,INDEX(CarData,MATCH($H$5,HeaderCol,0),MATCH(J$6,Header,0)),0) -> 0 | K8: =Parameters!$B$10*INDEX(CarData,MATCH($H$5,HeaderCol,0),MATCH("Fuel",Header,0))/100*Parameters!$B$24 -> 1732.5 | L8: =(H8+I8)*(1+Parameters!$B$26)^-($A8-1) -> 192.30769 | M8: =(J8+K8)*(1+Parameters!$B$26)^-($A8-0.5) -> 1633.5154 | O8: =VLOOKUP(INDEX(CarData,MATCH($N$5,HeaderCol,0),MATCH("CO2",Header,0)),TaxCO2,MIN($A8,2)+2,TRUE) -> 300 | P8: =IF($A8>=Parameters!$B$27,INDEX(CarData,MATCH($N$5,HeaderCol,0),MATCH(P$6,Header,0)),0) -> 0 | Q8: =Parameters!$B$10*INDEX(CarData,MATCH($N$5,HeaderCol,0),MATCH("Fuel",Header,0))/100*Parameters!$B$24 -> 1845 | R8: =(N8+O8)*(1+Parameters!$B$26)^-($A8-1) -> 288.46154 | S8: =(P8+Q8)*(1+Parameters!$B$26)^-($A8-0.5) -> 1739.5878
A9: 3 | C9: =VLOOKUP(INDEX(CarData,MATCH($B$5,HeaderCol,0),MATCH("CO2",Header,0)),TaxCO2,MIN($A9,2)+2,TRUE) -> 150 | D9: =IF($A9>=Parameters!$B$27,INDEX(CarData,MATCH($B$5,HeaderCol,0),MATCH(D$6,Header,0)),0) -> 0 | E9: =Parameters!$B$10*INDEX(CarData,MATCH($B$5,HeaderCol,0),MATCH("Fuel",Header,0))/100*Parameters!$B$24 -> 1440 | F9: =(B9+C9)*(1+Parameters!$B$26)^-($A9-1) -> 138.68343 | G9: =(D9+E9)*(1+Parameters!$B$26)^-($A9-0.5) -> 1305.5068 | I9: =VLOOKUP(INDEX(CarData,MATCH($H$5,HeaderCol,0),MATCH("CO2",Header,0)),TaxCO2,MIN($A9,2)+2,TRUE) -> 200 | J9: =IF($A9>=Parameters!$B$27,INDEX(CarData,MATCH($H$5,HeaderCol,0),MATCH(J$6,Header,0)),0) -> 0 | K9: =Parameters!$B$10*INDEX(CarData,MATCH($H$5,HeaderCol,0),MATCH("Fuel",Header,0))/100*Parameters!$B$24 -> 1732.5 | L9: =(H9+I9)*(1+Parameters!$B$26)^-($A9-1) -> 184.91124 | M9: =(J9+K9)*(1+Parameters!$B$26)^-($A9-0.5) -> 1570.6879 | O9: =VLOOKUP(INDEX(CarData,MATCH($N$5,HeaderCol,0),MATCH("CO2",Header,0)),TaxCO2,MIN($A9,2)+2,TRUE) -> 300 | P9: =IF($A9>=Parameters!$B$27,INDEX(CarData,MATCH($N$5,HeaderCol,0),MATCH(P$6,Header,0)),0) -> 0 | Q9: =Parameters!$B$10*INDEX(CarData,MATCH($N$5,HeaderCol,0),MATCH("Fuel",Header,0))/100*Parameters!$B$24 -> 1845 | R9: =(N9+O9)*(1+Parameters!$B$26)^-($A9-1) -> 277.36686 | S9: =(P9+Q9)*(1+Parameters!$B$26)^-($A9-0.5) -> 1672.6806
A10: 4 | C10: =VLOOKUP(INDEX(CarData,MATCH($B$5,HeaderCol,0),MATCH("CO2",Header,0)),TaxCO2,MIN($A10,2)+2,TRUE) -> 150 | D10: =IF($A10>=Parameters!$B$27,INDEX(CarData,MATCH($B$5,HeaderCol,0),MATCH(D$6,Header,0)),0) -> 250 | E10: =Parameters!$B$10*INDEX(CarData,MATCH($B$5,HeaderCol,0),MATCH("Fuel",Header,0))/100*Parameters!$B$24 -> 1440 | F10: =(B10+C10)*(1+Parameters!$B$26)^-($A10-1) -> 133.34945 | G10: =(D10+E10)*(1+Parameters!$B$26)^-($A10-0.5) -> 1473.2282 | I10: =VLOOKUP(INDEX(CarData,MATCH($H$5,HeaderCol,0),MATCH("CO2",Header,0)),TaxCO2,MIN($A10,2)+2,TRUE) -> 200 | J10: =IF($A10>=Parameters!$B$27,INDEX(CarData,MATCH($H$5,HeaderCol,0),MATCH(J$6,Header,0)),0) -> 300 | K10: =Parameters!$B$10*INDEX(CarData,MATCH($H$5,HeaderCol,0),MATCH("Fuel",Header,0))/100*Parameters!$B$24 -> 1732.5 | L10: =(H10+I10)*(1+Parameters!$B$26)^-($A10-1) -> 177.79927 | M10: =(J10+K10)*(1+Parameters!$B$26)^-($A10-0.5) -> 1771.7966 | O10: =VLOOKUP(INDEX(CarData,MATCH($N$5,HeaderCol,0),MATCH("CO2",Header,0)),TaxCO2,MIN($A10,2)+2,TRUE) -> 300 | P10: =IF($A10>=Parameters!$B$27,INDEX(CarData,MATCH($N$5,HeaderCol,0),MATCH(P$6,Header,0)),0) -> 350 | Q10: =Parameters!$B$10*INDEX(CarData,MATCH($N$5,HeaderCol,0),MATCH("Fuel",Header,0))/100*Parameters!$B$24 -> 1845 | R10: =(N10+O10)*(1+Parameters!$B$26)^-($A10-1) -> 266.69891 | S10: =(P10+Q10)*(1+Parameters!$B$26)^-($A10-0.5) -> 1913.4532
A11: 5 | C11: =VLOOKUP(INDEX(CarData,MATCH($B$5,HeaderCol,0),MATCH("CO2",Header,0)),TaxCO2,MIN($A11,2)+2,TRUE) -> 150 | D11: =IF($A11>=Parameters!$B$27,INDEX(CarData,MATCH($B$5,HeaderCol,0),MATCH(D$6,Header,0)),0) -> 250 | E11: =Parameters!$B$10*INDEX(CarData,MATCH($B$5,HeaderCol,0),MATCH("Fuel",Header,0))/100*Parameters!$B$24 -> 1440 | F11: =(B11+C11)*(1+Parameters!$B$26)^-($A11-1) -> 128.22063 | G11: =(D11+E11)*(1+Parameters!$B$26)^-($A11-0.5) -> 1416.5656 | I11: =VLOOKUP(INDEX(CarData,MATCH($H$5,HeaderCol,0),MATCH("CO2",Header,0)),TaxCO2,MIN($A11,2)+2,TRUE) -> 200 | J11: =IF($A11>=Parameters!$B$27,INDEX(CarData,MATCH($H$5,HeaderCol,0),MATCH(J$6,Header,0)),0) -> 300 | K11: =Parameters!$B$10*INDEX(CarData,MATCH($H$5,HeaderCol,0),MATCH("Fuel",Header,0))/100*Parameters!$B$24 -> 1732.5 | L11: =(H11+I11)*(1+Parameters!$B$26)^-($A11-1) -> 170.96084 | M11: =(J11+K11)*(1+Parameters!$B$26)^-($A11-0.5) -> 1703.6506 | O11: =VLOOKUP(INDEX(CarData,MATCH($N$5,HeaderCol,0),MATCH("CO2",Header,0)),TaxCO2,MIN($A11,2)+2,TRUE) -> 300 | P11: =IF($A11>=Parameters!$B$27,INDEX(CarData,MATCH($N$5,HeaderCol,0),MATCH(P$6,Header,0)),0) -> 350 | Q11: =Parameters!$B$10*INDEX(CarData,MATCH($N$5,HeaderCol,0),MATCH("Fuel",Header,0))/100*Parameters!$B$24 -> 1845 | R11: =(N11+O11)*(1+Parameters!$B$26)^-($A11-1) -> 256.44126 | S11: =(P11+Q11)*(1+Parameters!$B$26)^-($A11-0.5) -> 1839.8588
A13: Price of Car | G13: =B7 -> 28450 | M13: =H7 -> 36866 | S13: =N7 -> 65585
A14: PV Total cost of ownership | G14: =SUM(F7:G11) -> 36259.548 | M14: =SUM(L7:M11) -> 46370.486 | S14: =SUM(R7:S11) -> 76248.72
A15: Profit | G15: =INDEX(CarData,MATCH($B$5,HeaderCol,0),MATCH("Profit Margin",Header,0))*G13 -> 1422.5 | M15: =INDEX(CarData,MATCH($H$5,HeaderCol,0),MATCH("Profit Margin",Header,0))*M13 -> 2580.62 | S15: =INDEX(CarData,MATCH($N$5,HeaderCol,0),MATCH("Profit Margin",Header,0))*S13 -> 7214.35
A16: Manufacturing costs | G16: =G13-G15 -> 27027.5 | M16: =M13-M15 -> 34285.38 | S16: =S13-S15 -> 58370.65
B19: Small Electric | H19: Medium Electric | N19: Large Electric
A20: Year | B20: Price | C20: Tax | D20: Annual service cost | E20: Electricity | F20: PV start | G20: PV mid | H20: Price | I20: Tax | J20: Annual service cost | K20: Electricity | L20: PV start | M20: PV mid | N20: Price | O20: Tax | P20: Annual service cost | Q20: Electricity | R20: PV start | S20: PV mid
A21: 1 | B21: =INDEX(CarData,MATCH($B$19,HeaderCol,0),MATCH(B$20,Header,0)) -> 39465 | C21: =VLOOKUP(INDEX(CarData,MATCH($B$19,HeaderCol,0),MATCH("CO2",Header,0)),TaxCO2,MIN($A21,2)+2,TRUE) -> 0 | D21: =IF($A21>=Parameters!$B$27,INDEX(CarData,MATCH($B$19,HeaderCol,0),MATCH(D$6,Header,0)),0) -> 0 | E21: =Parameters!$B$10/INDEX(CarData,MATCH($B$19,HeaderCol,0),MATCH("Range",Header,0))*INDEX(CarData,MATCH($B$19,HeaderCol,0),MATCH("Battery capacity",Header,0))*Parameters!$B$23 -> 986.36364 | F21: =(B21+C21)*(1+Parameters!$B$26)^-($A21-1) -> 39465 | G21: =(D21+E21)*(1+Parameters!$B$26)^-($A21-0.5) -> 967.20912 | H21: =INDEX(CarData,MATCH($H$19,HeaderCol,0),MATCH(H$6,Header,0)) -> 47825 | I21: =VLOOKUP(INDEX(CarData,MATCH($H$19,HeaderCol,0),MATCH("CO2",Header,0)),TaxCO2,MIN($A21,2)+2,TRUE) -> 0 | J21: =IF($A21>=Parameters!$B$27,INDEX(CarData,MATCH($H$19,HeaderCol,0),MATCH(J$6,Header,0)),0) -> 0 | K21: =Parameters!$B$10/INDEX(CarData,MATCH($H$19,HeaderCol,0),MATCH("Range",Header,0))*INDEX(CarData,MATCH($H$19,HeaderCol,0),MATCH("Battery capacity",Header,0))*Parameters!$B$23 -> 1093.3333 | L21: =(H21+I21)*(1+Parameters!$B$26)^-($A21-1) -> 47825 | M21: =(J21+K21)*(1+Parameters!$B$26)^-($A21-0.5) -> 1072.1015 | N21: =INDEX(CarData,MATCH($N$19,HeaderCol,0),MATCH(N$6,Header,0)) -> 68834 | O21: =VLOOKUP(INDEX(CarData,MATCH($N$19,HeaderCol,0),MATCH("CO2",Header,0)),TaxCO2,MIN($A21,2)+2,TRUE) -> 0 | P21: =IF($A21>=Parameters!$B$27,INDEX(CarData,MATCH($N$19,HeaderCol,0),MATCH(P$6,Header,0)),0) -> 0 | Q21: =Parameters!$B$10/INDEX(CarData,MATCH($N$19,HeaderCol,0),MATCH("Range",Header,0))*INDEX(CarData,MATCH($N$19,HeaderCol,0),MATCH("Battery capacity",Header,0))*Parameters!$B$23 -> 1304.8544 | R21: =(N21+O21)*(1+Parameters!$B$26)^-($A21-1) -> 68834 | S21: =(P21+Q21)*(1+Parameters!$B$26)^-($A21-0.5) -> 1279.515
A22: 2 | C22: =VLOOKUP(INDEX(CarData,MATCH($B$19,HeaderCol,0),MATCH("CO2",Header,0)),TaxCO2,MIN($A22,2)+2,TRUE) -> 0 | D22: =IF($A22>=Parameters!$B$27,INDEX(CarData,MATCH($B$19,HeaderCol,0),MATCH(D$6,Header,0)),0) -> 0 | E22: =Parameters!$B$10/INDEX(CarData,MATCH($B$19,HeaderCol,0),MATCH("Range",Header,0))*INDEX(CarData,MATCH($B$19,HeaderCol,0),MATCH("Battery capacity",Header,0))*Parameters!$B$23 -> 986.36364 | F22: =(B22+C22)*(1+Parameters!$B$26)^-($A22-1) -> 0 | G22: =(D22+E22)*(1+Parameters!$B$26)^-($A22-0.5) -> 930.00877 | I22: =VLOOKUP(INDEX(CarData,MATCH($H$19,HeaderCol,0),MATCH("CO2",Header,0)),TaxCO2,MIN($A22,2)+2,TRUE) -> 0 | J22: =IF($A22>=Parameters!$B$27,INDEX(CarData,MATCH($H$19,HeaderCol,0),MATCH(J$6,Header,0)),0) -> 0 | K22: =Parameters!$B$10/INDEX(CarData,MATCH($H$19,HeaderCol,0),MATCH("Range",Header,0))*INDEX(CarData,MATCH($H$19,HeaderCol,0),MATCH("Battery capacity",Header,0))*Parameters!$B$23 -> 1093.3333 | L22: =(H22+I22)*(1+Parameters!$B$26)^-($A22-1) -> 0 | M22: =(J22+K22)*(1+Parameters!$B$26)^-($A22-0.5) -> 1030.8669 | O22: =VLOOKUP(INDEX(CarData,MATCH($N$19,HeaderCol,0),MATCH("CO2",Header,0)),TaxCO2,MIN($A22,2)+2,TRUE) -> 0 | P22: =IF($A22>=Parameters!$B$27,INDEX(CarData,MATCH($N$19,HeaderCol,0),MATCH(P$6,Header,0)),0) -> 0 | Q22: =Parameters!$B$10/INDEX(CarData,MATCH($N$19,HeaderCol,0),MATCH("Range",Header,0))*INDEX(CarData,MATCH($N$19,HeaderCol,0),MATCH("Battery capacity",Header,0))*Parameters!$B$23 -> 1304.8544 | R22: =(N22+O22)*(1+Parameters!$B$26)^-($A22-1) -> 0 | S22: =(P22+Q22)*(1+Parameters!$B$26)^-($A22-0.5) -> 1230.3029
A23: 3 | C23: =VLOOKUP(INDEX(CarData,MATCH($B$19,HeaderCol,0),MATCH("CO2",Header,0)),TaxCO2,MIN($A23,2)+2,TRUE) -> 0 | D23: =IF($A23>=Parameters!$B$27,INDEX(CarData,MATCH($B$19,HeaderCol,0),MATCH(D$6,Header,0)),0) -> 0 | E23: =Parameters!$B$10/INDEX(CarData,MATCH($B$19,HeaderCol,0),MATCH("Range",Header,0))*INDEX(CarData,MATCH($B$19,HeaderCol,0),MATCH("Battery capacity",Header,0))*Parameters!$B$23 -> 986.36364 | F23: =(B23+C23)*(1+Parameters!$B$26)^-($A23-1) -> 0 | G23: =(D23+E23)*(1+Parameters!$B$26)^-($A23-0.5) -> 894.2392 | I23: =VLOOKUP(INDEX(CarData,MATCH($H$19,HeaderCol,0),MATCH("CO2",Header,0)),TaxCO2,MIN($A23,2)+2,TRUE) -> 0 | J23: =IF($A23>=Parameters!$B$27,INDEX(CarData,MATCH($H$19,HeaderCol,0),MATCH(J$6,Header,0)),0) -> 0 | K23: =Parameters!$B$10/INDEX(CarData,MATCH($H$19,HeaderCol,0),MATCH("Range",Header,0))*INDEX(CarData,MATCH($H$19,HeaderCol,0),MATCH("Battery capacity",Header,0))*Parameters!$B$23 -> 1093.3333 | L23: =(H23+I23)*(1+Parameters!$B$26)^-($A23-1) -> 0 | M23: =(J23+K23)*(1+Parameters!$B$26)^-($A23-0.5) -> 991.21814 | O23: =VLOOKUP(INDEX(CarData,MATCH($N$19,HeaderCol,0),MATCH("CO2",Header,0)),TaxCO2,MIN($A23,2)+2,TRUE) -> 0 | P23: =IF($A23>=Parameters!$B$27,INDEX(CarData,MATCH($N$19,HeaderCol,0),MATCH(P$6,Header,0)),0) -> 0 | Q23: =Parameters!$B$10/INDEX(CarData,MATCH($N$19,HeaderCol,0),MATCH("Range",Header,0))*INDEX(CarData,MATCH($N$19,HeaderCol,0),MATCH("Battery capacity",Header,0))*Parameters!$B$23 -> 1304.8544 | R23: =(N23+O23)*(1+Parameters!$B$26)^-($A23-1) -> 0 | S23: =(P23+Q23)*(1+Parameters!$B$26)^-($A23-0.5) -> 1182.9835
A24: 4 | C24: =VLOOKUP(INDEX(CarData,MATCH($B$19,HeaderCol,0),MATCH("CO2",Header,0)),TaxCO2,MIN($A24,2)+2,TRUE) -> 0 | D24: =IF($A24>=Parameters!$B$27,INDEX(CarData,MATCH($B$19,HeaderCol,0),MATCH(D$6,Header,0)),0) -> 100 | E24: =Parameters!$B$10/INDEX(CarData,MATCH($B$19,HeaderCol,0),MATCH("Range",Header,0))*INDEX(CarData,MATCH($B$19,HeaderCol,0),MATCH("Battery capacity",Header,0))*Parameters!$B$23 -> 986.36364 | F24: =(B24+C24)*(1+Parameters!$B$26)^-($A24-1) -> 0 | G24: =(D24+E24)*(1+Parameters!$B$26)^-($A24-0.5) -> 947.01865 | I24: =VLOOKUP(INDEX(CarData,MATCH($H$19,HeaderCol,0),MATCH("CO2",Header,0)),TaxCO2,MIN($A24,2)+2,TRUE) -> 0 | J24: =IF($A24>=Parameters!$B$27,INDEX(CarData,MATCH($H$19,HeaderCol,0),MATCH(J$6,Header,0)),0) -> 150 | K24: =Parameters!$B$10/INDEX(CarData,MATCH($H$19,HeaderCol,0),MATCH("Range",Header,0))*INDEX(CarData,MATCH($H$19,HeaderCol,0),MATCH("Battery capacity",Header,0))*Parameters!$B$23 -> 1093.3333 | L24: =(H24+I24)*(1+Parameters!$B$26)^-($A24-1) -> 0 | M24: =(J24+K24)*(1+Parameters!$B$26)^-($A24-0.5) -> 1083.8543 | O24: =VLOOKUP(INDEX(CarData,MATCH($N$19,HeaderCol,0),MATCH("CO2",Header,0)),TaxCO2,MIN($A24,2)+2,TRUE) -> 0 | P24: =IF($A24>=Parameters!$B$27,INDEX(CarData,MATCH($N$19,HeaderCol,0),MATCH(P$6,Header,0)),0) -> 180 | Q24: =Parameters!$B$10/INDEX(CarData,MATCH($N$19,HeaderCol,0),MATCH("Range",Header,0))*INDEX(CarData,MATCH($N$19,HeaderCol,0),MATCH("Battery capacity",Header,0))*Parameters!$B$23 -> 1304.8544 | R24: =(N24+O24)*(1+Parameters!$B$26)^-($A24-1) -> 0 | S24: =(P24+Q24)*(1+Parameters!$B$26)^-($A24-0.5) -> 1294.396
A25: 5 | C25: =VLOOKUP(INDEX(CarData,MATCH($B$19,HeaderCol,0),MATCH("CO2",Header,0)),TaxCO2,MIN($A25,2)+2,TRUE) -> 0 | D25: =IF($A25>=Parameters!$B$27,INDEX(CarData,MATCH($B$19,HeaderCol,0),MATCH(D$6,Header,0)),0) -> 100 | E25: =Parameters!$B$10/INDEX(CarData,MATCH($B$19,HeaderCol,0),MATCH("Range",Header,0))*INDEX(CarData,MATCH($B$19,HeaderCol,0),MATCH("Battery capacity",Header,0))*Parameters!$B$23 -> 986.36364 | F25: =(B25+C25)*(1+Parameters!$B$26)^-($A25-1) -> 0 | G25: =(D25+E25)*(1+Parameters!$B$26)^-($A25-0.5) -> 910.59486 | I25: =VLOOKUP(INDEX(CarData,MATCH($H$19,HeaderCol,0),MATCH("CO2",Header,0)),TaxCO2,MIN($A25,2)+2,TRUE) -> 0 | J25: =IF($A25>=Parameters!$B$27,INDEX(CarData,MATCH($H$19,HeaderCol,0),MATCH(J$6,Header,0)),0) -> 150 | K25: =Parameters!$B$10/INDEX(CarData,MATCH($H$19,HeaderCol,0),MATCH("Range",Header,0))*INDEX(CarData,MATCH($H$19,HeaderCol,0),MATCH("Battery capacity",Header,0))*Parameters!$B$23 -> 1093.3333 | L25: =(H25+I25)*(1+Parameters!$B$26)^-($A25-1) -> 0 | M25: =(J25+K25)*(1+Parameters!$B$26)^-($A25-0.5) -> 1042.1676 | O25: =VLOOKUP(INDEX(CarData,MATCH($N$19,HeaderCol,0),MATCH("CO2",Header,0)),TaxCO2,MIN($A25,2)+2,TRUE) -> 0 | P25: =IF($A25>=Parameters!$B$27,INDEX(CarData,MATCH($N$19,HeaderCol,0),MATCH(P$6,Header,0)),0) -> 180 | Q25: =Parameters!$B$10/INDEX(CarData,MATCH($N$19,HeaderCol,0),MATCH("Range",Header,0))*INDEX(CarData,MATCH($N$19,HeaderCol,0),MATCH("Battery capacity",Header,0))*Parameters!$B$23 -> 1304.8544 | R25: =(N25+O25)*(1+Parameters!$B$26)^-($A25-1) -> 0 | S25: =(P25+Q25)*(1+Parameters!$B$26)^-($A25-0.5) -> 1244.6116
A27: Price of Car | G27: =B21 -> 39465 | M27: =H21 -> 47825 | S27: =N21 -> 68834
A28: PV Total cost of ownership | G28: =SUM(F21:G25) -> 44114.071 | M28: =SUM(L21:M25) -> 53045.208 | S28: =SUM(R21:S25) -> 75065.809
A29: Profit | G29: =INDEX(CarData,MATCH($B$19,HeaderCol,0),MATCH("Profit Margin",Header,0))*G27 -> 4341.15 | M29: =INDEX(CarData,MATCH($H$19,HeaderCol,0),MATCH("Profit Margin",Header,0))*M27 -> 6695.5 | S29: =INDEX(CarData,MATCH($N$19,HeaderCol,0),MATCH("Profit Margin",Header,0))*S27 -> 12390.12
A30: Manufacturing costs | G30: =G27-G29 -> 35123.85 | M30: =M27-M29 -> 41129.5 | S30: =S27-S29 -> 56443.88

Sheet Total profit-Base
A1: Profit calculations
B3: Sales | C3: Profit | D3: Revenue | E3: Cost of Ownership | F3: Manufacturing costs
A4: Small Petrol | B4: =INDEX(Data!N:N,MATCH($A4,Data!A:A,0)) -> 25567 | C4: =$B4*'Calculations-Base'!G15 -> 36369058 | D4: =$B4*'Calculations-Base'!$G13 -> 727381150 | E4: =$B4*'Calculations-Base'!$G14 -> 9.2704787e+08 | F4: =$B4*'Calculations-Base'!$G16 -> 6.9101209e+08
A5: Medium Petrol | B5: =INDEX(Data!N:N,MATCH($A5,Data!A:A,0)) -> 1893 | C5: =$B5*'Calculations-Base'!M15 -> 4885113.7 | D5: =$B5*'Calculations-Base'!$M13 -> 69787338 | E5: =$B5*'Calculations-Base'!$M14 -> 87779329 | F5: =$B5*'Calculations-Base'!$M16 -> 64902224
A6: Large Petrol | B6: =INDEX(Data!N:N,MATCH($A6,Data!A:A,0)) -> 1836 | C6: =$B6*'Calculations-Base'!S15 -> 13245547 | D6: =$B6*'Calculations-Base'!$S13 -> 120414060 | E6: =$B6*'Calculations-Base'!$S14 -> 1.3999265e+08 | F6: =$B6*'Calculations-Base'!$S16 -> 1.0716851e+08
A7: Small Electric | B7: =INDEX(Data!N:N,MATCH($A7,Data!A:A,0)) -> 11146 | C7: =$B7*'Calculations-Base'!G29 -> 48386458 | D7: =$B7*'Calculations-Base'!$G27 -> 439876890 | E7: =$B7*'Calculations-Base'!$G28 -> 4.9169543e+08 | F7: =$B7*'Calculations-Base'!$G30 -> 3.9149043e+08
A8: Medium Electric | B8: =INDEX(Data!N:N,MATCH($A8,Data!A:A,0)) -> 6291 | C8: =$B8*'Calculations-Base'!M29 -> 42121391 | D8: =$B8*'Calculations-Base'!$M27 -> 300867075 | E8: =$B8*'Calculations-Base'!$M28 -> 3.3370741e+08 | F8: =$B8*'Calculations-Base'!$M30 -> 2.5874568e+08
A9: Large Electric | B9: =INDEX(Data!N:N,MATCH($A9,Data!A:A,0)) -> 3848 | C9: =$B9*'Calculations-Base'!S29 -> 47677182 | D9: =$B9*'Calculations-Base'!$S27 -> 264873232 | E9: =$B9*'Calculations-Base'!$S28 -> 2.8885323e+08 | F9: =$B9*'Calculations-Base'!$S30 -> 2.1719605e+08
A11: Total | B11: =SUM(B4:B10) -> 50581 | C11: =SUM(C4:C10) -> 1.9268475e+08 | D11: =SUM(D4:D10) -> 1923199745 | E11: =SUM(E4:E10) -> 2.2690759e+09 | F11: =SUM(F4:F10) -> 1.730515e+09
A13: Check total sales: | B13: =IF(B11=Data!$N$10,"OK","Check") -> OK

Sheet Calculations-Weight
A1: Tax based on Weight
A2: Calculates the total cost of ownership for all cars in the current range under the new tax regime.
B5: Small Petrol | H5: Medium Petrol | N5: Large Petrol
A6: Year | B6: Price | C6: Tax | D6: Annual service cost | E6: Fuel | F6: PV start | G6: PV mid | H6: Price | I6: Tax | J6: Annual service cost | K6: Fuel | L6: PV start | M6: PV mid | N6: Price | O6: Tax | P6: Annual service cost | Q6: Fuel | R6: PV start | S6: PV mid
A7: 1 | B7: =INDEX(CarData,MATCH($B$5,HeaderCol,0),MATCH(B$6,Header,0)) -> 28450 | C7: =VLOOKUP(INDEX(CarData,MATCH($B$5,HeaderCol,0),MATCH("Weight",Header,0)),TaxWeight,3,TRUE) -> 300 | D7: =IF($A7>=Parameters!$B$27,INDEX(CarData,MATCH($B$5,HeaderCol,0),MATCH(D$6,Header,0)),0) -> 0 | E7: =Parameters!$B$10*INDEX(CarData,MATCH($B$5,HeaderCol,0),MATCH("Fuel",Header,0))/100*Parameters!$B$24 -> 1440 | F7: =(B7+C7)*(1+Parameters!$B$26)^-($A7-1) -> 28750 | G7: =(D7+E7)*(1+Parameters!$B$26)^-($A7-0.5) -> 1412.0362 | H7: =INDEX(CarData,MATCH($H$5,HeaderCol,0),MATCH(H$6,Header,0)) -> 36866 | I7: =VLOOKUP(INDEX(CarData,MATCH($H$5,HeaderCol,0),MATCH("Weight",Header,0)),TaxWeight,3,TRUE) -> 300 | J7: =IF($A7>=Parameters!$B$27,INDEX(CarData,MATCH($H$5,HeaderCol,0),MATCH(J$6,Header,0)),0) -> 0 | K7: =Parameters!$B$10*INDEX(CarData,MATCH($H$5,HeaderCol,0),MATCH("Fuel",Header,0))/100*Parameters!$B$24 -> 1732.5 | L7: =(H7+I7)*(1+Parameters!$B$26)^-($A7-1) -> 37166 | M7: =(J7+K7)*(1+Parameters!$B$26)^-($A7-0.5) -> 1698.856 | N7: =INDEX(CarData,MATCH($N$5,HeaderCol,0),MATCH(N$6,Header,0)) -> 65585 | O7: =VLOOKUP(INDEX(CarData,MATCH($N$5,HeaderCol,0),MATCH("Weight",Header,0)),TaxWeight,3,TRUE) -> 600 | P7: =IF($A7>=Parameters!$B$27,INDEX(CarData,MATCH($N$5,HeaderCol,0),MATCH(P$6,Header,0)),0) -> 0 | Q7: =Parameters!$B$10*INDEX(CarData,MATCH($N$5,HeaderCol,0),MATCH("Fuel",Header,0))/100*Parameters!$B$24 -> 1845 | R7: =(N7+O7)*(1+Parameters!$B$26)^-($A7-1) -> 66185 | S7: =(P7+Q7)*(1+Parameters!$B$26)^-($A7-0.5) -> 1809.1713
A8: 2 | C8: =VLOOKUP(INDEX(CarData,MATCH($B$5,HeaderCol,0),MATCH("Weight",Header,0)),TaxWeight,3,TRUE) -> 300 | D8: =IF($A8>=Parameters!$B$27,INDEX(CarData,MATCH($B$5,HeaderCol,0),MATCH(D$6,Header,0)),0) -> 0 | E8: =Parameters!$B$10*INDEX(CarData,MATCH($B$5,HeaderCol,0),MATCH("Fuel",Header,0))/100*Parameters!$B$24 -> 1440 | F8: =(B8+C8)*(1+Parameters!$B$26)^-($A8-1) -> 288.46154 | G8: =(D8+E8)*(1+Parameters!$B$26)^-($A8-0.5) -> 1357.7271 | I8: =VLOOKUP(INDEX(CarData,MATCH($H$5,HeaderCol,0),MATCH("Weight",Header,0)),TaxWeight,3,TRUE) -> 300 | J8: =IF($A8>=Parameters!$B$27,INDEX(CarData,MATCH($H$5,HeaderCol,0),MATCH(J$6,Header,0)),0) -> 0 | K8: =Parameters!$B$10*INDEX(CarData,MATCH($H$5,HeaderCol,0),MATCH("Fuel",Header,0))/100*Parameters!$B$24 -> 1732.5 | L8: =(H8+I8)*(1+Parameters!$B$26)^-($A8-1) -> 288.46154 | M8: =(J8+K8)*(1+Parameters!$B$26)^-($A8-0.5) -> 1633.5154 | O8: =VLOOKUP(INDEX(CarData,MATCH($N$5,HeaderCol,0),MATCH("Weight",Header,0)),TaxWeight,3,TRUE) -> 600 | P8: =IF($A8>=Parameters!$B$27,INDEX(CarData,MATCH($N$5,HeaderCol,0),MATCH(P$6,Header,0)),0) -> 0 | Q8: =Parameters!$B$10*INDEX(CarData,MATCH($N$5,HeaderCol,0),MATCH("Fuel",Header,0))/100*Parameters!$B$24 -> 1845 | R8: =(N8+O8)*(1+Parameters!$B$26)^-($A8-1) -> 576.92308 | S8: =(P8+Q8)*(1+Parameters!$B$26)^-($A8-0.5) -> 1739.5878
A9: 3 | C9: =VLOOKUP(INDEX(CarData,MATCH($B$5,HeaderCol,0),MATCH("Weight",Header,0)),TaxWeight,3,TRUE) -> 300 | D9: =IF($A9>=Parameters!$B$27,INDEX(CarData,MATCH($B$5,HeaderCol,0),MATCH(D$6,Header,0)),0) -> 0 | E9: =Parameters!$B$10*INDEX(CarData,MATCH($B$5,HeaderCol,0),MATCH("Fuel",Header,0))/100*Parameters!$B$24 -> 1440 | F9: =(B9+C9)*(1+Parameters!$B$26)^-($A9-1) -> 277.36686 | G9: =(D9+E9)*(1+Parameters!$B$26)^-($A9-0.5) -> 1305.5068 | I9: =VLOOKUP(INDEX(CarData,MATCH($H$5,HeaderCol,0),MATCH("Weight",Header,0)),TaxWeight,3,TRUE) -> 300 | J9: =IF($A9>=Parameters!$B$27,INDEX(CarData,MATCH($H$5,HeaderCol,0),MATCH(J$6,Header,0)),0) -> 0 | K9: =Parameters!$B$10*INDEX(CarData,MATCH($H$5,HeaderCol,0),MATCH("Fuel",Header,0))/100*Parameters!$B$24 -> 1732.5 | L9: =(H9+I9)*(1+Parameters!$B$26)^-($A9-1) -> 277.36686 | M9: =(J9+K9)*(1+Parameters!$B$26)^-($A9-0.5) -> 1570.6879 | O9: =VLOOKUP(INDEX(CarData,MATCH($N$5,HeaderCol,0),MATCH("Weight",Header,0)),TaxWeight,3,TRUE) -> 600 | P9: =IF($A9>=Parameters!$B$27,INDEX(CarData,MATCH($N$5,HeaderCol,0),MATCH(P$6,Header,0)),0) -> 0 | Q9: =Parameters!$B$10*INDEX(CarData,MATCH($N$5,HeaderCol,0),MATCH("Fuel",Header,0))/100*Parameters!$B$24 -> 1845 | R9: =(N9+O9)*(1+Parameters!$B$26)^-($A9-1) -> 554.73373 | S9: =(P9+Q9)*(1+Parameters!$B$26)^-($A9-0.5) -> 1672.6806
A10: 4 | C10: =VLOOKUP(INDEX(CarData,MATCH($B$5,HeaderCol,0),MATCH("Weight",Header,0)),TaxWeight,3,TRUE) -> 300 | D10: =IF($A10>=Parameters!$B$27,INDEX(CarData,MATCH($B$5,HeaderCol,0),MATCH(D$6,Header,0)),0) -> 250 | E10: =Parameters!$B$10*INDEX(CarData,MATCH($B$5,HeaderCol,0),MATCH("Fuel",Header,0))/100*Parameters!$B$24 -> 1440 | F10: =(B10+C10)*(1+Parameters!$B$26)^-($A10-1) -> 266.69891 | G10: =(D10+E10)*(1+Parameters!$B$26)^-($A10-0.5) -> 1473.2282 | I10: =VLOOKUP(INDEX(CarData,MATCH($H$5,HeaderCol,0),MATCH("Weight",Header,0)),TaxWeight,3,TRUE) -> 300 | J10: =IF($A10>=Parameters!$B$27,INDEX(CarData,MATCH($H$5,HeaderCol,0),MATCH(J$6,Header,0)),0) -> 300 | K10: =Parameters!$B$10*INDEX(CarData,MATCH($H$5,HeaderCol,0),MATCH("Fuel",Header,0))/100*Parameters!$B$24 -> 1732.5 | L10: =(H10+I10)*(1+Parameters!$B$26)^-($A10-1) -> 266.69891 | M10: =(J10+K10)*(1+Parameters!$B$26)^-($A10-0.5) -> 1771.7966 | O10: =VLOOKUP(INDEX(CarData,MATCH($N$5,HeaderCol,0),MATCH("Weight",Header,0)),TaxWeight,3,TRUE) -> 600 | P10: =IF($A10>=Parameters!$B$27,INDEX(CarData,MATCH($N$5,HeaderCol,0),MATCH(P$6,Header,0)),0) -> 350 | Q10: =Parameters!$B$10*INDEX(CarData,MATCH($N$5,HeaderCol,0),MATCH("Fuel",Header,0))/100*Parameters!$B$24 -> 1845 | R10: =(N10+O10)*(1+Parameters!$B$26)^-($A10-1) -> 533.39782 | S10: =(P10+Q10)*(1+Parameters!$B$26)^-($A10-0.5) -> 1913.4532
A11: 5 | C11: =VLOOKUP(INDEX(CarData,MATCH($B$5,HeaderCol,0),MATCH("Weight",Header,0)),TaxWeight,3,TRUE) -> 300 | D11: =IF($A11>=Parameters!$B$27,INDEX(CarData,MATCH($B$5,HeaderCol,0),MATCH(D$6,Header,0)),0) -> 250 | E11: =Parameters!$B$10*INDEX(CarData,MATCH($B$5,HeaderCol,0),MATCH("Fuel",Header,0))/100*Parameters!$B$24 -> 1440 | F11: =(B11+C11)*(1+Parameters!$B$26)^-($A11-1) -> 256.44126 | G11: =(D11+E11)*(1+Parameters!$B$26)^-($A11-0.5) -> 1416.5656 | I11: =VLOOKUP(INDEX(CarData,MATCH($H$5,HeaderCol,0),MATCH("Weight",Header,0)),TaxWeight,3,TRUE) -> 300 | J11: =IF($A11>=Parameters!$B$27,INDEX(CarData,MATCH($H$5,HeaderCol,0),MATCH(J$6,Header,0)),0) -> 300 | K11: =Parameters!$B$10*INDEX(CarData,MATCH($H$5,HeaderCol,0),MATCH("Fuel",Header,0))/100*Parameters!$B$24 -> 1732.5 | L11: =(H11+I11)*(1+Parameters!$B$26)^-($A11-1) -> 256.44126 | M11: =(J11+K11)*(1+Parameters!$B$26)^-($A11-0.5) -> 1703.6506 | O11: =VLOOKUP(INDEX(CarData,MATCH($N$5,HeaderCol,0),MATCH("Weight",Header,0)),TaxWeight,3,TRUE) -> 600 | P11: =IF($A11>=Parameters!$B$27,INDEX(CarData,MATCH($N$5,HeaderCol,0),MATCH(P$6,Header,0)),0) -> 350 | Q11: =Parameters!$B$10*INDEX(CarData,MATCH($N$5,HeaderCol,0),MATCH("Fuel",Header,0))/100*Parameters!$B$24 -> 1845 | R11: =(N11+O11)*(1+Parameters!$B$26)^-($A11-1) -> 512.88251 | S11: =(P11+Q11)*(1+Parameters!$B$26)^-($A11-0.5) -> 1839.8588
A13: Price of Car | G13: =B7 -> 28450 | M13: =H7 -> 36866 | S13: =N7 -> 65585
A14: PV Total cost of ownership | G14: =SUM(F7:G11) -> 36804.032 | M14: =SUM(L7:M11) -> 46633.475 | S14: =SUM(R7:S11) -> 77337.689
A15: Profit | G15: =INDEX(CarData,MATCH($B$5,HeaderCol,0),MATCH("Profit Margin",Header,0))*G13 -> 1422.5 | M15: =INDEX(CarData,MATCH($H$5,HeaderCol,0),MATCH("Profit Margin",Header,0))*M13 -> 2580.62 | S15: =INDEX(CarData,MATCH($N$5,HeaderCol,0),MATCH("Profit Margin",Header,0))*S13 -> 7214.35
A16: Manufacturing costs | G16: =G13-G15 -> 27027.5 | M16: =M13-M15 -> 34285.38 | S16: =S13-S15 -> 58370.65
B19: Small Electric | H19: Medium Electric | N19: Large Electric
A20: Year | B20: Price | C20: Tax | D20: Annual service cost | E20: Electricity | F20: PV start | G20: PV mid | H20: Price | I20: Tax | J20: Annual service cost | K20: Electricity | L20: PV start | M20: PV mid | N20: Price | O20: Tax | P20: Annual service cost | Q20: Electricity | R20: PV start | S20: PV mid
A21: 1 | B21: =INDEX(CarData,MATCH($B$19,HeaderCol,0),MATCH(B$20,Header,0)) -> 39465 | C21: =VLOOKUP(INDEX(CarData,MATCH($B$19,HeaderCol,0),MATCH("Weight",Header,0)),TaxWeight,3,TRUE) -> 300 | D21: =IF($A21>=Parameters!$B$27,INDEX(CarData,MATCH($B$19,HeaderCol,0),MATCH(D$6,Header,0)),0) -> 0 | E21: =Parameters!$B$10/INDEX(CarData,MATCH($B$19,HeaderCol,0),MATCH("Range",Header,0))*INDEX(CarData,MATCH($B$19,HeaderCol,0),MATCH("Battery capacity",Header,0))*(Parameters!$C$23) -> 810.22727 | F21: =(B21+C21)*(1+Parameters!$B$26)^-($A21-1) -> 39765 | G21: =(D21+E21)*(1+Parameters!$B$26)^-($A21-0.5) -> 794.49321 | H21: =INDEX(CarData,MATCH($H$19,HeaderCol,0),MATCH(H$6,Header,0)) -> 47825 | I21: =VLOOKUP(INDEX(CarData,MATCH($H$19,HeaderCol,0),MATCH("Weight",Header,0)),TaxWeight,3,TRUE) -> 600 | J21: =IF($A21>=Parameters!$B$27,INDEX(CarData,MATCH($H$19,HeaderCol,0),MATCH(J$6,Header,0)),0) -> 0 | K21: =Parameters!$B$10/INDEX(CarData,MATCH($H$19,HeaderCol,0),MATCH("Range",Header,0))*INDEX(CarData,MATCH($H$19,HeaderCol,0),MATCH("Battery capacity",Header,0))*Parameters!$C$23 -> 898.09524 | L21: =(H21+I21)*(1+Parameters!$B$26)^-($A21-1) -> 48425 | M21: =(J21+K21)*(1+Parameters!$B$26)^-($A21-0.5) -> 880.65484 | N21: =INDEX(CarData,MATCH($N$19,HeaderCol,0),MATCH(N$6,Header,0)) -> 68834 | O21: =VLOOKUP(INDEX(CarData,MATCH($N$19,HeaderCol,0),MATCH("Weight",Header,0)),TaxWeight,3,TRUE) -> 1200 | P21: =IF($A21>=Parameters!$B$27,INDEX(CarData,MATCH($N$19,HeaderCol,0),MATCH(P$6,Header,0)),0) -> 0 | Q21: =Parameters!$B$10/INDEX(CarData,MATCH($N$19,HeaderCol,0),MATCH("Range",Header,0))*INDEX(CarData,MATCH($N$19,HeaderCol,0),MATCH("Battery capacity",Header,0))*Parameters!$C$23 -> 1071.8447 | R21: =(N21+O21)*(1+Parameters!$B$26)^-($A21-1) -> 70034 | S21: =(P21+Q21)*(1+Parameters!$B$26)^-($A21-0.5) -> 1051.0302
A22: 2 | C22: =VLOOKUP(INDEX(CarData,MATCH($B$19,HeaderCol,0),MATCH("Weight",Header,0)),TaxWeight,3,TRUE) -> 300 | D22: =IF($A22>=Parameters!$B$27,INDEX(CarData,MATCH($B$19,HeaderCol,0),MATCH(D$6,Header,0)),0) -> 0 | E22: =Parameters!$B$10/INDEX(CarData,MATCH($B$19,HeaderCol,0),MATCH("Range",Header,0))*INDEX(CarData,MATCH($B$19,HeaderCol,0),MATCH("Battery capacity",Header,0))*(Parameters!$C$23) -> 810.22727 | F22: =(B22+C22)*(1+Parameters!$B$26)^-($A22-1) -> 288.46154 | G22: =(D22+E22)*(1+Parameters!$B$26)^-($A22-0.5) -> 763.93578 | I22: =VLOOKUP(INDEX(CarData,MATCH($H$19,HeaderCol,0),MATCH("Weight",Header,0)),TaxWeight,3,TRUE) -> 600 | J22: =IF($A22>=Parameters!$B$27,INDEX(CarData,MATCH($H$19,HeaderCol,0),MATCH(J$6,Header,0)),0) -> 0 | K22: =Parameters!$B$10/INDEX(CarData,MATCH($H$19,HeaderCol,0),MATCH("Range",Header,0))*INDEX(CarData,MATCH($H$19,HeaderCol,0),MATCH("Battery capacity",Header,0))*Parameters!$C$23 -> 898.09524 | L22: =(H22+I22)*(1+Parameters!$B$26)^-($A22-1) -> 576.92308 | M22: =(J22+K22)*(1+Parameters!$B$26)^-($A22-0.5) -> 846.7835 | O22: =VLOOKUP(INDEX(CarData,MATCH($N$19,HeaderCol,0),MATCH("Weight",Header,0)),TaxWeight,3,TRUE) -> 1200 | P22: =IF($A22>=Parameters!$B$27,INDEX(CarData,MATCH($N$19,HeaderCol,0),MATCH(P$6,Header,0)),0) -> 0 | Q22: =Parameters!$B$10/INDEX(CarData,MATCH($N$19,HeaderCol,0),MATCH("Range",Header,0))*INDEX(CarData,MATCH($N$19,HeaderCol,0),MATCH("Battery capacity",Header,0))*Parameters!$C$23 -> 1071.8447 | R22: =(N22+O22)*(1+Parameters!$B$26)^-($A22-1) -> 1153.8462 | S22: =(P22+Q22)*(1+Parameters!$B$26)^-($A22-0.5) -> 1010.6059
A23: 3 | C23: =VLOOKUP(INDEX(CarData,MATCH($B$19,HeaderCol,0),MATCH("Weight",Header,0)),TaxWeight,3,TRUE) -> 300 | D23: =IF($A23>=Parameters!$B$27,INDEX(CarData,MATCH($B$19,HeaderCol,0),MATCH(D$6,Header,0)),0) -> 0 | E23: =Parameters!$B$10/INDEX(CarData,MATCH($B$19,HeaderCol,0),MATCH("Range",Header,0))*INDEX(CarData,MATCH($B$19,HeaderCol,0),MATCH("Battery capacity",Header,0))*(Parameters!$C$23) -> 810.22727 | F23: =(B23+C23)*(1+Parameters!$B$26)^-($A23-1) -> 277.36686 | G23: =(D23+E23)*(1+Parameters!$B$26)^-($A23-0.5) -> 734.55363 | I23: =VLOOKUP(INDEX(CarData,MATCH($H$19,HeaderCol,0),MATCH("Weight",Header,0)),TaxWeight,3,TRUE) -> 600 | J23: =IF($A23>=Parameters!$B$27,INDEX(CarData,MATCH($H$19,HeaderCol,0),MATCH(J$6,Header,0)),0) -> 0 | K23: =Parameters!$B$10/INDEX(CarData,MATCH($H$19,HeaderCol,0),MATCH("Range",Header,0))*INDEX(CarData,MATCH($H$19,HeaderCol,0),MATCH("Battery capacity",Header,0))*Parameters!$C$23 -> 898.09524 | L23: =(H23+I23)*(1+Parameters!$B$26)^-($A23-1) -> 554.73373 | M23: =(J23+K23)*(1+Parameters!$B$26)^-($A23-0.5) -> 814.2149 | O23: =VLOOKUP(INDEX(CarData,MATCH($N$19,HeaderCol,0),MATCH("Weight",Header,0)),TaxWeight,3,TRUE) -> 1200 | P23: =IF($A23>=Parameters!$B$27,INDEX(CarData,MATCH($N$19,HeaderCol,0),MATCH(P$6,Header,0)),0) -> 0 | Q23: =Parameters!$B$10/INDEX(CarData,MATCH($N$19,HeaderCol,0),MATCH("Range",Header,0))*INDEX(CarData,MATCH($N$19,HeaderCol,0),MATCH("Battery capacity",Header,0))*Parameters!$C$23 -> 1071.8447 | R23: =(N23+O23)*(1+Parameters!$B$26)^-($A23-1) -> 1109.4675 | S23: =(P23+Q23)*(1+Parameters!$B$26)^-($A23-0.5) -> 971.73647
A24: 4 | C24: =VLOOKUP(INDEX(CarData,MATCH($B$19,HeaderCol,0),MATCH("Weight",Header,0)),TaxWeight,3,TRUE) -> 300 | D24: =IF($A24>=Parameters!$B$27,INDEX(CarData,MATCH($B$19,HeaderCol,0),MATCH(D$6,Header,0)),0) -> 100 | E24: =Parameters!$B$10/INDEX(CarData,MATCH($B$19,HeaderCol,0),MATCH("Range",Header,0))*INDEX(CarData,MATCH($B$19,HeaderCol,0),MATCH("Battery capacity",Header,0))*(Parameters!$C$23) -> 810.22727 | F24: =(B24+C24)*(1+Parameters!$B$26)^-($A24-1) -> 266.69891 | G24: =(D24+E24)*(1+Parameters!$B$26)^-($A24-0.5) -> 793.47483 | I24: =VLOOKUP(INDEX(CarData,MATCH($H$19,HeaderCol,0),MATCH("Weight",Header,0)),TaxWeight,3,TRUE) -> 600 | J24: =IF($A24>=Parameters!$B$27,INDEX(CarData,MATCH($H$19,HeaderCol,0),MATCH(J$6,Header,0)),0) -> 150 | K24: =Parameters!$B$10/INDEX(CarData,MATCH($H$19,HeaderCol,0),MATCH("Range",Header,0))*INDEX(CarData,MATCH($H$19,HeaderCol,0),MATCH("Battery capacity",Header,0))*Parameters!$C$23 -> 898.09524 | L24: =(H24+I24)*(1+Parameters!$B$26)^-($A24-1) -> 533.39782 | M24: =(J24+K24)*(1+Parameters!$B$26)^-($A24-0.5) -> 913.65884 | O24: =VLOOKUP(INDEX(CarData,MATCH($N$19,HeaderCol,0),MATCH("Weight",Header,0)),TaxWeight,3,TRUE) -> 1200 | P24: =IF($A24>=Parameters!$B$27,INDEX(CarData,MATCH($N$19,HeaderCol,0),MATCH(P$6,Header,0)),0) -> 180 | Q24: =Parameters!$B$10/INDEX(CarData,MATCH($N$19,HeaderCol,0),MATCH("Range",Header,0))*INDEX(CarData,MATCH($N$19,HeaderCol,0),MATCH("Battery capacity",Header,0))*Parameters!$C$23 -> 1071.8447 | R24: =(N24+O24)*(1+Parameters!$B$26)^-($A24-1) -> 1066.7956 | S24: =(P24+Q24)*(1+Parameters!$B$26)^-($A24-0.5) -> 1091.2739
A25: 5 | C25: =VLOOKUP(INDEX(CarData,MATCH($B$19,HeaderCol,0),MATCH("Weight",Header,0)),TaxWeight,3,TRUE) -> 300 | D25: =IF($A25>=Parameters!$B$27,INDEX(CarData,MATCH($B$19,HeaderCol,0),MATCH(D$6,Header,0)),0) -> 100 | E25: =Parameters!$B$10/INDEX(CarData,MATCH($B$19,HeaderCol,0),MATCH("Range",Header,0))*INDEX(CarData,MATCH($B$19,HeaderCol,0),MATCH("Battery capacity",Header,0))*(Parameters!$C$23) -> 810.22727 | F25: =(B25+C25)*(1+Parameters!$B$26)^-($A25-1) -> 256.44126 | G25: =(D25+E25)*(1+Parameters!$B$26)^-($A25-0.5) -> 762.95657 | I25: =VLOOKUP(INDEX(CarData,MATCH($H$19,HeaderCol,0),MATCH("Weight",Header,0)),TaxWeight,3,TRUE) -> 600 | J25: =IF($A25>=Parameters!$B$27,INDEX(CarData,MATCH($H$19,HeaderCol,0),MATCH(J$6,Header,0)),0) -> 150 | K25: =Parameters!$B$10/INDEX(CarData,MATCH($H$19,HeaderCol,0),MATCH("Range",Header,0))*INDEX(CarData,MATCH($H$19,HeaderCol,0),MATCH("Battery capacity",Header,0))*Parameters!$C$23 -> 898.09524 | L25: =(H25+I25)*(1+Parameters!$B$26)^-($A25-1) -> 512.88251 | M25: =(J25+K25)*(1+Parameters!$B$26)^-($A25-0.5) -> 878.51811 | O25: =VLOOKUP(INDEX(CarData,MATCH($N$19,HeaderCol,0),MATCH("Weight",Header,0)),TaxWeight,3,TRUE) -> 1200 | P25: =IF($A25>=Parameters!$B$27,INDEX(CarData,MATCH($N$19,HeaderCol,0),MATCH(P$6,Header,0)),0) -> 180 | Q25: =Parameters!$B$10/INDEX(CarData,MATCH($N$19,HeaderCol,0),MATCH("Range",Header,0))*INDEX(CarData,MATCH($N$19,HeaderCol,0),MATCH("Battery capacity",Header,0))*Parameters!$C$23 -> 1071.8447 | R25: =(N25+O25)*(1+Parameters!$B$26)^-($A25-1) -> 1025.765 | S25: =(P25+Q25)*(1+Parameters!$B$26)^-($A25-0.5) -> 1049.3018
A27: Price of Car | G27: =B21 -> 39465 | M27: =H21 -> 47825 | S27: =N21 -> 68834
A28: PV Total cost of ownership | G28: =SUM(F21:G25) -> 44703.383 | M28: =SUM(L21:M25) -> 54936.767 | S28: =SUM(R21:S25) -> 79563.822
A29: Profit | G29: =INDEX(CarData,MATCH($B$19,HeaderCol,0),MATCH("Profit Margin",Header,0))*G27 -> 4341.15 | M29: =INDEX(CarData,MATCH($H$19,HeaderCol,0),MATCH("Profit Margin",Header,0))*M27 -> 6695.5 | S29: =INDEX(CarData,MATCH($N$19,HeaderCol,0),MATCH("Profit Margin",Header,0))*S27 -> 12390.12
A30: Manufacturing costs | G30: =G27-G29 -> 35123.85 | M30: =M27-M29 -> 41129.5 | S30: =S27-S29 -> 56443.88

Sheet Total profit-Weight
A1: Profit calculations
B3: Sales | C3: Profit | D3: Revenue | E3: Cost of Ownership | F3: Manufacturing costs
A4: Small Petrol | B4: =INDEX(Data!N:N,MATCH($A4,Data!A:A,0)) -> 25567 | C4: =$B4*'Calculations-Weight'!G15 -> 36369058 | D4: =$B4*'Calculations-Weight'!G13 -> 727381150 | E4: =$B4*'Calculations-Weight'!G14 -> 9.409687e+08 | F4: =$B4*'Calculations-Weight'!$G16 -> 6.9101209e+08
A5: Medium Petrol | B5: =INDEX(Data!N:N,MATCH($A5,Data!A:A,0)) -> 1893 | C5: =$B5*'Calculations-Weight'!M15 -> 4885113.7 | D5: =$B5*'Calculations-Weight'!M13 -> 69787338 | E5: =$B5*'Calculations-Weight'!M14 -> 88277168 | F5: =$B5*'Calculations-Weight'!$M16 -> 64902224
A6: Large Petrol | B6: =INDEX(Data!N:N,MATCH($A6,Data!A:A,0)) -> 1836 | C6: =$B6*'Calculations-Weight'!S15 -> 13245547 | D6: =$B6*'Calculations-Weight'!S13 -> 120414060 | E6: =$B6*'Calculations-Weight'!S14 -> 1.41992e+08 | F6: =$B6*'Calculations-Weight'!S16 -> 1.0716851e+08
A7: Small Electric | B7: =INDEX(Data!N:N,MATCH($A7,Data!A:A,0)) -> 11146 | C7: =$B7*'Calculations-Weight'!G29 -> 48386458 | D7: =$B7*'Calculations-Weight'!G27 -> 439876890 | E7: =$B7*'Calculations-Weight'!G28 -> 4.982639e+08 | F7: =$B7*'Calculations-Weight'!$G30 -> 3.9149043e+08
A8: Medium Electric | B8: =INDEX(Data!N:N,MATCH($A8,Data!A:A,0)) -> 6291 | C8: =$B8*'Calculations-Weight'!M29 -> 42121391 | D8: =$B8*'Calculations-Weight'!M27 -> 300867075 | E8: =$B8*'Calculations-Weight'!M28 -> 3.456072e+08 | F8: =$B8*'Calculations-Weight'!$M30 -> 2.5874568e+08
A9: Large Electric | B9: =INDEX(Data!N:N,MATCH($A9,Data!A:A,0)) -> 3848 | C9: =$B9*'Calculations-Weight'!S29 -> 47677182 | D9: =$B9*'Calculations-Weight'!S27 -> 264873232 | E9: =$B9*'Calculations-Weight'!S28 -> 3.0616159e+08 | F9: =$B9*'Calculations-Weight'!$S30 -> 2.1719605e+08
A11: Total | B11: =SUM(B4:B10) -> 50581 | C11: =SUM(C4:C10) -> 1.9268475e+08 | D11: =SUM(D4:D10) -> 1923199745 | E11: =SUM(E4:E10) -> 2.3212706e+09 | F11: =SUM(F4:F10) -> 1.730515e+09
A13: Check totals don't change: | B13: =IF(B11='Total profit-Base'!B11,"OK","Check") -> OK | C13: =IF(C11='Total profit-Base'!C11,"OK","Check") -> OK | D13: =IF(D11='Total profit-Base'!D11,"OK","Check") -> OK | F13: =IF(F11='Total profit-Base'!F11,"OK","Check") -> OK
