Workbook

Sheet Raw data (base scenario)
A1: Raw Data
B5: Status | C5: Status
A6: Lives | B6: Start of Year | C6: End of Year
A7: 1 | B7: I | C7: S
A8: 2 | B8: S | C8: H
A9: 3 | B9: D | C9: D
A10: 4 | B10: H | C10: H
A11: 5 | B11: I | C11: I
A12: 6 | B12: I | C12: D
A13: 7 | B13: H | C13: H
A14: 8 | B14: D | C14: D
A15: 9 | B15: H | C15: H
A16: 10 | B16: S | C16: H
A17: 11 | B17: I | C17: I
A18: 12 | B18: H | C18: H
... A12009: 12003 | B12009: D | C12009: D

Sheet Raw data (alternative scenario)
A1: Raw Data
B3: Transition probabilities in the alternative scenario is:
C4: original transition probabilities + (t - 1) * transition improvements
B5: where t = 1 to 30
B7: Transition improvements
D8: End of year
D9: H | E9: S | F9: I | G9: D
B10: Start of year | C10: H | D10: 0.0018 | E10: -0.0012 | F10: -0.00055 | G10: -5e-05
C11: S | D11: 0.00065 | E11: 0.0005 | F11: -0.00083 | G11: -0.00032
C12: I | D12: 0.0005 | E12: 0.001 | F12: 0.0005 | G12: -0.002
C13: D | D13: 0 | E13: 0 | F13: 0 | G13: 0

Sheet Data_checks
A1: Data checking
A3: Permissible statuses
A4: H | B4: Healthy
A5: S | B5: Sick
A6: I | B6: Very sick
A7: D | B7: Dead
K9: WARNING: This data is hardcoded
K11: Same data but with corrupted data removed
A12: Checks | B12: Check no missing lives | C12: Check no missing status | D12: Check no missing status | E12: Number of errors | F12: Number of errors | G12: Number of errors | J12: Checks | K12: Check no missing lives | L12: Check no missing status | M12: Check no missing status | N12: Number of errors | O12: Number of errors | P12: Number of errors
A13: Count: | B13: =COUNT(B15:B12017) -> 12003 | C13: =IF(COUNT(C15:C12017)=0,"No missing statuses","check") -> No missing statuses | D13: =IF(COUNT(D15:D12017)=0,"No missing statuses","check") -> No missing statuses | E13: =COUNTIF(E15:E12017,FALSE) -> 2 | F13: =COUNTIF(F15:F12017,FALSE) -> 1 | G13: =COUNTIF(G15:G12017,FALSE) -> 1 | J13: Count: | K13: =COUNT(K15:K12014) -> 12000 | L13: =IF(COUNT(L15:L12017)=0,"No missing statuses","check") -> No missing statuses | M13: =IF(COUNT(M15:M12017)=0,"No missing statuses","check") -> No missing statuses | N13: =COUNTIF(N15:N12014,FALSE) -> 0 | O13: =COUNTIF(O15:O12014,FALSE) -> 0 | P13: =COUNTIF(P15:P12014,FALSE) -> 0
B14: Lives | C14: Start of Year | D14: End of Year | E14: Check status only contains H, S, I, D | F14: Check status only contains H, S, I, D | G14: Check no resurrection | H14: Note | K14: Lives | L14: Start of Year | M14: End of Year | N14: Check status only contains H, S, I, D | O14: Check status only contains H, S, I, D | P14: Check no resurrection
B15: ='Raw data (base scenario)'!A7 -> 1 | C15: ='Raw data (base scenario)'!B7 -> I | D15: ='Raw data (base scenario)'!C7 -> S | E15: =OR(C15=$A$4,C15=$A$5,C15=$A$6,C15=$A$7) -> TRUE | F15: =OR(D15=$A$4,D15=$A$5,D15=$A$6,D15=$A$7) -> TRUE | G15: =IF(C15="D",D15="D","N/A") -> N/A | K15: 1 | L15: I | M15: S | N15: =OR(L15=$A$4,L15=$A$5,L15=$A$6,L15=$A$7) -> TRUE | O15: =OR(M15=$A$4,M15=$A$5,M15=$A$6,M15=$A$7) -> TRUE | P15: =IF(L15="D",M15="D","N/A") -> N/A
B16: ='Raw data (base scenario)'!A8 -> 2 | C16: ='Raw data (base scenario)'!B8 -> S | D16: ='Raw data (base scenario)'!C8 -> H | E16: =OR(C16=$A$4,C16=$A$5,C16=$A$6,C16=$A$7) -> TRUE | F16: =OR(D16=$A$4,D16=$A$5,D16=$A$6,D16=$A$7) -> TRUE | G16: =IF(C16="D",D16="D","N/A") -> N/A | K16: 2 | L16: S | M16: H | N16: =OR(L16=$A$4,L16=$A$5,L16=$A$6,L16=$A$7) -> TRUE | O16: =OR(M16=$A$4,M16=$A$5,M16=$A$6,M16=$A$7) -> TRUE | P16: =IF(L16="D",M16="D","N/A") -> N/A
B17: ='Raw data (base scenario)'!A9 -> 3 | C17: ='Raw data (base scenario)'!B9 -> D | D17: ='Raw data (base scenario)'!C9 -> D | E17: =OR(C17=$A$4,C17=$A$5,C17=$A$6,C17=$A$7) -> TRUE | F17: =OR(D17=$A$4,D17=$A$5,D17=$A$6,D17=$A$7) -> TRUE | G17: =IF(C17="D",D17="D","N/A") -> TRUE | K17: 3 | L17: D | M17: D | N17: =OR(L17=$A$4,L17=$A$5,L17=$A$6,L17=$A$7) -> TRUE | O17: =OR(M17=$A$4,M17=$A$5,M17=$A$6,M17=$A$7) -> TRUE | P17: =IF(L17="D",M17="D","N/A") -> TRUE
B18: ='Raw data (base scenario)'!A10 -> 4 | C18: ='Raw data (base scenario)'!B10 -> H | D18: ='Raw data (base scenario)'!C10 -> H | E18: =OR(C18=$A$4,C18=$A$5,C18=$A$6,C18=$A$7) -> TRUE | F18: =OR(D18=$A$4,D18=$A$5,D18=$A$6,D18=$A$7) -> TRUE | G18: =IF(C18="D",D18="D","N/A") -> N/A | K18: 4 | L18: H | M18: H | N18: =OR(L18=$A$4,L18=$A$5,L18=$A$6,L18=$A$7) -> TRUE | O18: =OR(M18=$A$4,M18=$A$5,M18=$A$6,M18=$A$7) -> TRUE | P18: =IF(L18="D",M18="D","N/A") -> N/A
B19: ='Raw data (base scenario)'!A11 -> 5 | C19: ='Raw data (base scenario)'!B11 -> I | D19: ='Raw data (base scenario)'!C11 -> I | E19: =OR(C19=$A$4,C19=$A$5,C19=$A$6,C19=$A$7) -> TRUE | F19: =OR(D19=$A$4,D19=$A$5,D19=$A$6,D19=$A$7) -> TRUE | G19: =IF(C19="D",D19="D","N/A") -> N/A | K19: 5 | L19: I | M19: I | N19: =OR(L19=$A$4,L19=$A$5,L19=$A$6,L19=$A$7) -> TRUE | O19: =OR(M19=$A$4,M19=$A$5,M19=$A$6,M19=$A$7) -> TRUE | P19: =IF(L19="D",M19="D","N/A") -> N/A
B20: ='Raw data (base scenario)'!A12 -> 6 | C20: ='Raw data (base scenario)'!B12 -> I | D20: ='Raw data (base scenario)'!C12 -> D | E20: =OR(C20=$A$4,C20=$A$5,C20=$A$6,C20=$A$7) -> TRUE | F20: =OR(D20=$A$4,D20=$A$5,D20=$A$6,D20=$A$7) -> TRUE | G20: =IF(C20="D",D20="D","N/A") -> N/A | K20: 6 | L20: I | M20: D | N20: =OR(L20=$A$4,L20=$A$5,L20=$A$6,L20=$A$7) -> TRUE | O20: =OR(M20=$A$4,M20=$A$5,M20=$A$6,M20=$A$7) -> TRUE | P20: =IF(L20="D",M20="D","N/A") -> N/A
B21: ='Raw data (base scenario)'!A13 -> 7 | C21: ='Raw data (base scenario)'!B13 -> H | D21: ='Raw data (base scenario)'!C13 -> H | E21: =OR(C21=$A$4,C21=$A$5,C21=$A$6,C21=$A$7) -> TRUE | F21: =OR(D21=$A$4,D21=$A$5,D21=$A$6,D21=$A$7) -> TRUE | G21: =IF(C21="D",D21="D","N/A") -> N/A | K21: 7 | L21: H | M21: H | N21: =OR(L21=$A$4,L21=$A$5,L21=$A$6,L21=$A$7) -> TRUE | O21: =OR(M21=$A$4,M21=$A$5,M21=$A$6,M21=$A$7) -> TRUE | P21: =IF(L21="D",M21="D","N/A") -> N/A
B22: ='Raw data (base scenario)'!A14 -> 8 | C22: ='Raw data (base scenario)'!B14 -> D | D22: ='Raw data (base scenario)'!C14 -> D | E22: =OR(C22=$A$4,C22=$A$5,C22=$A$6,C22=$A$7) -> TRUE | F22: =OR(D22=$A$4,D22=$A$5,D22=$A$6,D22=$A$7) -> TRUE | G22: =IF(C22="D",D22="D","N/A") -> TRUE | K22: 8 | L22: D | M22: D | N22: =OR(L22=$A$4,L22=$A$5,L22=$A$6,L22=$A$7) -> TRUE | O22: =OR(M22=$A$4,M22=$A$5,M22=$A$6,M22=$A$7) -> TRUE | P22: =IF(L22="D",M22="D","N/A") -> TRUE
B23: ='Raw data (base scenario)'!A15 -> 9 | C23: ='Raw data (base scenario)'!B15 -> H | D23: ='Raw data (base scenario)'!C15 -> H | E23: =OR(C23=$A$4,C23=$A$5,C23=$A$6,C23=$A$7) -> TRUE | F23: =OR(D23=$A$4,D23=$A$5,D23=$A$6,D23=$A$7) -> TRUE | G23: =IF(C23="D",D23="D","N/A") -> N/A | K23: 9 | L23: H | M23: H | N23: =OR(L23=$A$4,L23=$A$5,L23=$A$6,L23=$A$7) -> TRUE | O23: =OR(M23=$A$4,M23=$A$5,M23=$A$6,M23=$A$7) -> TRUE | P23: =IF(L23="D",M23="D","N/A") -> N/A
B24: ='Raw data (base scenario)'!A16 -> 10 | C24: ='Raw data (base scenario)'!B16 -> S | D24: ='Raw data (base scenario)'!C16 -> H | E24: =OR(C24=$A$4,C24=$A$5,C24=$A$6,C24=$A$7) -> TRUE | F24: =OR(D24=$A$4,D24=$A$5,D24=$A$6,D24=$A$7) -> TRUE | G24: =IF(C24="D",D24="D","N/A") -> N/A | K24: 10 | L24: S | M24: H | N24: =OR(L24=$A$4,L24=$A$5,L24=$A$6,L24=$A$7) -> TRUE | O24: =OR(M24=$A$4,M24=$A$5,M24=$A$6,M24=$A$7) -> TRUE | P24: =IF(L24="D",M24="D","N/A") -> N/A
B25: ='Raw data (base scenario)'!A17 -> 11 | C25: ='Raw data (base scenario)'!B17 -> I | D25: ='Raw data (base scenario)'!C17 -> I | E25: =OR(C25=$A$4,C25=$A$5,C25=$A$6,C25=$A$7) -> TRUE | F25: =OR(D25=$A$4,D25=$A$5,D25=$A$6,D25=$A$7) -> TRUE | G25: =IF(C25="D",D25="D","N/A") -> N/A | K25: 11 | L25: I | M25: I | N25: =OR(L25=$A$4,L25=$A$5,L25=$A$6,L25=$A$7) -> TRUE | O25: =OR(M25=$A$4,M25=$A$5,M25=$A$6,M25=$A$7) -> TRUE | P25: =IF(L25="D",M25="D","N/A") -> N/A
B26: ='Raw data (base scenario)'!A18 -> 12 | C26: ='Raw data (base scenario)'!B18 -> H | D26: ='Raw data (base scenario)'!C18 -> H | E26: =OR(C26=$A$4,C26=$A$5,C26=$A$6,C26=$A$7) -> TRUE | F26: =OR(D26=$A$4,D26=$A$5,D26=$A$6,D26=$A$7) -> TRUE | G26: =IF(C26="D",D26="D","N/A") -> N/A | K26: 12 | L26: H | M26: H | N26: =OR(L26=$A$4,L26=$A$5,L26=$A$6,L26=$A$7) -> TRUE | O26: =OR(M26=$A$4,M26=$A$5,M26=$A$6,M26=$A$7) -> TRUE | P26: =IF(L26="D",M26="D","N/A") -> N/A
... B4466: ='Raw data (base scenario)'!A4458 -> 4452 | C4466: ='Raw data (base scenario)'!B4458 -> D | D4466: ='Raw data (base scenario)'!C4458 -> D | E4466: =OR(C4466=$A$4,C4466=$A$5,C4466=$A$6,C4466=$A$7) -> TRUE | F4466: =OR(D4466=$A$4,D4466=$A$5,D4466=$A$6,D4466=$A$7) -> TRUE | G4466: =IF(C4466="D",D4466="D","N/A") -> TRUE | K4466: 4452 | L4466: D | M4466: D | N4466: =OR(L4466=$A$4,L4466=$A$5,L4466=$A$6,L4466=$A$7) -> TRUE | O4466: =OR(M4466=$A$4,M4466=$A$5,M4466=$A$6,M4466=$A$7) -> TRUE | P4466: =IF(L4466="D",M4466="D","N/A") -> TRUE
B4467: ='Raw data (base scenario)'!A4459 -> 4453 | C4467: ='Raw data (base scenario)'!B4459 -> D | D4467: ='Raw data (base scenario)'!C4459 -> H | E4467: =OR(C4467=$A$4,C4467=$A$5,C4467=$A$6,C4467=$A$7) -> TRUE | F4467: =OR(D4467=$A$4,D4467=$A$5,D4467=$A$6,D4467=$A$7) -> TRUE | G4467: =IF(C4467="D",D4467="D","N/A") -> FALSE | H4467: Corrupted data - remove | K4467: 4453 | L4467: D | M4467: D | N4467: =OR(L4467=$A$4,L4467=$A$5,L4467=$A$6,L4467=$A$7) -> TRUE | O4467: =OR(M4467=$A$4,M4467=$A$5,M4467=$A$6,M4467=$A$7) -> TRUE | P4467: =IF(L4467="D",M4467="D","N/A") -> TRUE
B4468: ='Raw data (base scenario)'!A4460 -> 4454 | C4468: ='Raw data (base scenario)'!B4460 -> D | D4468: ='Raw data (base scenario)'!C4460 -> D | E4468: =OR(C4468=$A$4,C4468=$A$5,C4468=$A$6,C4468=$A$7) -> TRUE | F4468: =OR(D4468=$A$4,D4468=$A$5,D4468=$A$6,D4468=$A$7) -> TRUE | G4468: =IF(C4468="D",D4468="D","N/A") -> TRUE | K4468: 4454 | L4468: H | M4468: H | N4468: =OR(L4468=$A$4,L4468=$A$5,L4468=$A$6,L4468=$A$7) -> TRUE | O4468: =OR(M4468=$A$4,M4468=$A$5,M4468=$A$6,M4468=$A$7) -> TRUE | P4468: =IF(L4468="D",M4468="D","N/A") -> N/A
B4469: ='Raw data (base scenario)'!A4461 -> 4455 | C4469: ='Raw data (base scenario)'!B4461 -> H | D4469: ='Raw data (base scenario)'!C4461 -> H | E4469: =OR(C4469=$A$4,C4469=$A$5,C4469=$A$6,C4469=$A$7) -> TRUE | F4469: =OR(D4469=$A$4,D4469=$A$5,D4469=$A$6,D4469=$A$7) -> TRUE | G4469: =IF(C4469="D",D4469="D","N/A") -> N/A | K4469: 4455 | L4469: H | M4469: H | N4469: =OR(L4469=$A$4,L4469=$A$5,L4469=$A$6,L4469=$A$7) -> TRUE | O4469: =OR(M4469=$A$4,M4469=$A$5,M4469=$A$6,M4469=$A$7) -> TRUE | P4469: =IF(L4469="D",M4469="D","N/A") -> N/A
B4470: ='Raw data (base scenario)'!A4462 -> 4456 | C4470: ='Raw data (base scenario)'!B4462 -> H | D4470: ='Raw data (base scenario)'!C4462 -> H | E4470: =OR(C4470=$A$4,C4470=$A$5,C4470=$A$6,C4470=$A$7) -> TRUE | F4470: =OR(D4470=$A$4,D4470=$A$5,D4470=$A$6,D4470=$A$7) -> TRUE | G4470: =IF(C4470="D",D4470="D","N/A") -> N/A | K4470: 4456 | L4470: I | M4470: H | N4470: =OR(L4470=$A$4,L4470=$A$5,L4470=$A$6,L4470=$A$7) -> TRUE | O4470: =OR(M4470=$A$4,M4470=$A$5,M4470=$A$6,M4470=$A$7) -> TRUE | P4470: =IF(L4470="D",M4470="D","N/A") -> N/A
B4471: ='Raw data (base scenario)'!A4463 -> 4457 | C4471: ='Raw data (base scenario)'!B4463 -> I | D4471: ='Raw data (base scenario)'!C4463 -> H | E4471: =OR(C4471=$A$4,C4471=$A$5,C4471=$A$6,C4471=$A$7) -> TRUE | F4471: =OR(D4471=$A$4,D4471=$A$5,D4471=$A$6,D4471=$A$7) -> TRUE | G4471: =IF(C4471="D",D4471="D","N/A") -> N/A | K4471: 4457 | L4471: S | M4471: I | N4471: =OR(L4471=$A$4,L4471=$A$5,L4471=$A$6,L4471=$A$7) -> TRUE | O4471: =OR(M4471=$A$4,M4471=$A$5,M4471=$A$6,M4471=$A$7) -> TRUE | P4471: =IF(L4471="D",M4471="D","N/A") -> N/A
B4472: ='Raw data (base scenario)'!A4464 -> 4458 | C4472: ='Raw data (base scenario)'!B4464 -> S | D4472: ='Raw data (base scenario)'!C4464 -> I | E4472: =OR(C4472=$A$4,C4472=$A$5,C4472=$A$6,C4472=$A$7) -> TRUE | F4472: =OR(D4472=$A$4,D4472=$A$5,D4472=$A$6,D4472=$A$7) -> TRUE | G4472: =IF(C4472="D",D4472="D","N/A") -> N/A | K4472: 4458 | L4472: S | M4472: H | N4472: =OR(L4472=$A$4,L4472=$A$5,L4472=$A$6,L4472=$A$7) -> TRUE | O4472: =OR(M4472=$A$4,M4472=$A$5,M4472=$A$6,M4472=$A$7) -> TRUE | P4472: =IF(L4472="D",M4472="D","N/A") -> N/A
B4473: ='Raw data (base scenario)'!A4465 -> 4459 | C4473: ='Raw data (base scenario)'!B4465 -> S | D4473: ='Raw data (base scenario)'!C4465 -> H | E4473: =OR(C4473=$A$4,C4473=$A$5,C4473=$A$6,C4473=$A$7) -> TRUE | F4473: =OR(D4473=$A$4,D4473=$A$5,D4473=$A$6,D4473=$A$7) -> TRUE | G4473: =IF(C4473="D",D4473="D","N/A") -> N/A | K4473: 4459 | L4473: S | M4473: H | N4473: =OR(L4473=$A$4,L4473=$A$5,L4473=$A$6,L4473=$A$7) -> TRUE | O4473: =OR(M4473=$A$4,M4473=$A$5,M4473=$A$6,M4473=$A$7) -> TRUE | P4473: =IF(L4473="D",M4473="D","N/A") -> N/A
B4474: ='Raw data (base scenario)'!A4466 -> 4460 | C4474: ='Raw data (base scenario)'!B4466 -> S | D4474: ='Raw data (base scenario)'!C4466 -> H | E4474: =OR(C4474=$A$4,C4474=$A$5,C4474=$A$6,C4474=$A$7) -> TRUE | F4474: =OR(D4474=$A$4,D4474=$A$5,D4474=$A$6,D4474=$A$7) -> TRUE | G4474: =IF(C4474="D",D4474="D","N/A") -> N/A | K4474: 4460 | L4474: D | M4474: D | N4474: =OR(L4474=$A$4,L4474=$A$5,L4474=$A$6,L4474=$A$7) -> TRUE | O4474: =OR(M4474=$A$4,M4474=$A$5,M4474=$A$6,M4474=$A$7) -> TRUE | P4474: =IF(L4474="D",M4474="D","N/A") -> TRUE
B4475: ='Raw data (base scenario)'!A4467 -> 4461 | C4475: ='Raw data (base scenario)'!B4467 -> D | D4475: ='Raw data (base scenario)'!C4467 -> D | E4475: =OR(C4475=$A$4,C4475=$A$5,C4475=$A$6,C4475=$A$7) -> TRUE | F4475: =OR(D4475=$A$4,D4475=$A$5,D4475=$A$6,D4475=$A$7) -> TRUE | G4475: =IF(C4475="D",D4475="D","N/A") -> TRUE | K4475: 4461 | L4475: D | M4475: D | N4475: =OR(L4475=$A$4,L4475=$A$5,L4475=$A$6,L4475=$A$7) -> TRUE | O4475: =OR(M4475=$A$4,M4475=$A$5,M4475=$A$6,M4475=$A$7) -> TRUE | P4475: =IF(L4475="D",M4475="D","N/A") -> TRUE
B4476: ='Raw data (base scenario)'!A4468 -> 4462 | C4476: ='Raw data (base scenario)'!B4468 -> D | D4476: ='Raw data (base scenario)'!C4468 -> D | E4476: =OR(C4476=$A$4,C4476=$A$5,C4476=$A$6,C4476=$A$7) -> TRUE | F4476: =OR(D4476=$A$4,D4476=$A$5,D4476=$A$6,D4476=$A$7) -> TRUE | G4476: =IF(C4476="D",D4476="D","N/A") -> TRUE | K4476: 4462 | L4476: I | M4476: D | N4476: =OR(L4476=$A$4,L4476=$A$5,L4476=$A$6,L4476=$A$7) -> TRUE | O4476: =OR(M4476=$A$4,M4476=$A$5,M4476=$A$6,M4476=$A$7) -> TRUE | P4476: =IF(L4476="D",M4476="D","N/A") -> N/A
B4477: ='Raw data (base scenario)'!A4469 -> 4463 | C4477: ='Raw data (base scenario)'!B4469 -> I | D4477: ='Raw data (base scenario)'!C4469 -> D | E4477: =OR(C4477=$A$4,C4477=$A$5,C4477=$A$6,C4477=$A$7) -> TRUE | F4477: =OR(D4477=$A$4,D4477=$A$5,D4477=$A$6,D4477=$A$7) -> TRUE | G4477: =IF(C4477="D",D4477="D","N/A") -> N/A | K4477: 4463 | L4477: S | M4477: H | N4477: =OR(L4477=$A$4,L4477=$A$5,L4477=$A$6,L4477=$A$7) -> TRUE | O4477: =OR(M4477=$A$4,M4477=$A$5,M4477=$A$6,M4477=$A$7) -> TRUE | P4477: =IF(L4477="D",M4477="D","N/A") -> N/A
B4478: ='Raw data (base scenario)'!A4470 -> 4464 | C4478: ='Raw data (base scenario)'!B4470 -> S | D4478: ='Raw data (base scenario)'!C4470 -> H | E4478: =OR(C4478=$A$4,C4478=$A$5,C4478=$A$6,C4478=$A$7) -> TRUE | F4478: =OR(D4478=$A$4,D4478=$A$5,D4478=$A$6,D4478=$A$7) -> TRUE | G4478: =IF(C4478="D",D4478="D","N/A") -> N/A | K4478: 4464 | L4478: H | M4478: H | N4478: =OR(L4478=$A$4,L4478=$A$5,L4478=$A$6,L4478=$A$7) -> TRUE | O4478: =OR(M4478=$A$4,M4478=$A$5,M4478=$A$6,M4478=$A$7) -> TRUE | P4478: =IF(L4478="D",M4478="D","N/A") -> N/A
B4479: ='Raw data (base scenario)'!A4471 -> 4465 | C4479: ='Raw data (base scenario)'!B4471 -> H | D4479: ='Raw data (base scenario)'!C4471 -> H | E4479: =OR(C4479=$A$4,C4479=$A$5,C4479=$A$6,C4479=$A$7) -> TRUE | F4479: =OR(D4479=$A$4,D4479=$A$5,D4479=$A$6,D4479=$A$7) -> TRUE | G4479: =IF(C4479="D",D4479="D","N/A") -> N/A | K4479: 4465 | L4479: S | M4479: H | N4479: =OR(L4479=$A$4,L4479=$A$5,L4479=$A$6,L4479=$A$7) -> TRUE | O4479: =OR(M4479=$A$4,M4479=$A$5,M4479=$A$6,M4479=$A$7) -> TRUE | P4479: =IF(L4479="D",M4479="D","N/A") -> N/A
... B7120: ='Raw data (base scenario)'!A7112 -> 7106 | C7120: ='Raw data (base scenario)'!B7112 -> S | D7120: ='Raw data (base scenario)'!C7112 -> D | E7120: =OR(C7120=$A$4,C7120=$A$5,C7120=$A$6,C7120=$A$7) -> TRUE | F7120: =OR(D7120=$A$4,D7120=$A$5,D7120=$A$6,D7120=$A$7) -> TRUE | G7120: =IF(C7120="D",D7120="D","N/A") -> N/A | K7120: 7106 | L7120: S | M7120: H | N7120: =OR(L7120=$A$4,L7120=$A$5,L7120=$A$6,L7120=$A$7) -> TRUE | O7120: =OR(M7120=$A$4,M7120=$A$5,M7120=$A$6,M7120=$A$7) -> TRUE | P7120: =IF(L7120="D",M7120="D","N/A") -> N/A
B7121: ='Raw data (base scenario)'!A7113 -> 7107 | C7121: ='Raw data (base scenario)'!B7113 -> U | D7121: ='Raw data (base scenario)'!C7113 -> Q | E7121: =OR(C7121=$A$4,C7121=$A$5,C7121=$A$6,C7121=$A$7) -> FALSE | F7121: =OR(D7121=$A$4,D7121=$A$5,D7121=$A$6,D7121=$A$7) -> FALSE | G7121: =IF(C7121="D",D7121="D","N/A") -> N/A | H7121: Corrupted data - remove | K7121: 7107 | L7121: I | M7121: D | N7121: =OR(L7121=$A$4,L7121=$A$5,L7121=$A$6,L7121=$A$7) -> TRUE | O7121: =OR(M7121=$A$4,M7121=$A$5,M7121=$A$6,M7121=$A$7) -> TRUE | P7121: =IF(L7121="D",M7121="D","N/A") -> N/A
B7122: ='Raw data (base scenario)'!A7114 -> 7108 | C7122: ='Raw data (base scenario)'!B7114 -> S | D7122: ='Raw data (base scenario)'!C7114 -> H | E7122: =OR(C7122=$A$4,C7122=$A$5,C7122=$A$6,C7122=$A$7) -> TRUE | F7122: =OR(D7122=$A$4,D7122=$A$5,D7122=$A$6,D7122=$A$7) -> TRUE | G7122: =IF(C7122="D",D7122="D","N/A") -> N/A | K7122: 7108 | L7122: H | M7122: S | N7122: =OR(L7122=$A$4,L7122=$A$5,L7122=$A$6,L7122=$A$7) -> TRUE | O7122: =OR(M7122=$A$4,M7122=$A$5,M7122=$A$6,M7122=$A$7) -> TRUE | P7122: =IF(L7122="D",M7122="D","N/A") -> N/A
B7123: ='Raw data (base scenario)'!A7115 -> 7109 | C7123: ='Raw data (base scenario)'!B7115 -> I | D7123: ='Raw data (base scenario)'!C7115 -> D | E7123: =OR(C7123=$A$4,C7123=$A$5,C7123=$A$6,C7123=$A$7) -> TRUE | F7123: =OR(D7123=$A$4,D7123=$A$5,D7123=$A$6,D7123=$A$7) -> TRUE | G7123: =IF(C7123="D",D7123="D","N/A") -> N/A | K7123: 7109 | L7123: H | M7123: H | N7123: =OR(L7123=$A$4,L7123=$A$5,L7123=$A$6,L7123=$A$7) -> TRUE | O7123: =OR(M7123=$A$4,M7123=$A$5,M7123=$A$6,M7123=$A$7) -> TRUE | P7123: =IF(L7123="D",M7123="D","N/A") -> N/A
B7124: ='Raw data (base scenario)'!A7116 -> 7110 | C7124: ='Raw data (base scenario)'!B7116 -> H | D7124: ='Raw data (base scenario)'!C7116 -> S | E7124: =OR(C7124=$A$4,C7124=$A$5,C7124=$A$6,C7124=$A$7) -> TRUE | F7124: =OR(D7124=$A$4,D7124=$A$5,D7124=$A$6,D7124=$A$7) -> TRUE | G7124: =IF(C7124="D",D7124="D","N/A") -> N/A | K7124: 7110 | L7124: S | M7124: H | N7124: =OR(L7124=$A$4,L7124=$A$5,L7124=$A$6,L7124=$A$7) -> TRUE | O7124: =OR(M7124=$A$4,M7124=$A$5,M7124=$A$6,M7124=$A$7) -> TRUE | P7124: =IF(L7124="D",M7124="D","N/A") -> N/A
B7125: ='Raw data (base scenario)'!A7117 -> 7111 | C7125: ='Raw data (base scenario)'!B7117 -> H | D7125: ='Raw data (base scenario)'!C7117 -> H | E7125: =OR(C7125=$A$4,C7125=$A$5,C7125=$A$6,C7125=$A$7) -> TRUE | F7125: =OR(D7125=$A$4,D7125=$A$5,D7125=$A$6,D7125=$A$7) -> TRUE | G7125: =IF(C7125="D",D7125="D","N/A") -> N/A | K7125: 7111 | L7125: S | M7125: S | N7125: =OR(L7125=$A$4,L7125=$A$5,L7125=$A$6,L7125=$A$7) -> TRUE | O7125: =OR(M7125=$A$4,M7125=$A$5,M7125=$A$6,M7125=$A$7) -> TRUE | P7125: =IF(L7125="D",M7125="D","N/A") -> N/A
B7126: ='Raw data (base scenario)'!A7118 -> 7112 | C7126: ='Raw data (base scenario)'!B7118 -> S | D7126: ='Raw data (base scenario)'!C7118 -> H | E7126: =OR(C7126=$A$4,C7126=$A$5,C7126=$A$6,C7126=$A$7) -> TRUE | F7126: =OR(D7126=$A$4,D7126=$A$5,D7126=$A$6,D7126=$A$7) -> TRUE | G7126: =IF(C7126="D",D7126="D","N/A") -> N/A | K7126: 7112 | L7126: D | M7126: D | N7126: =OR(L7126=$A$4,L7126=$A$5,L7126=$A$6,L7126=$A$7) -> TRUE | O7126: =OR(M7126=$A$4,M7126=$A$5,M7126=$A$6,M7126=$A$7) -> TRUE | P7126: =IF(L7126="D",M7126="D","N/A") -> TRUE
B7127: ='Raw data (base scenario)'!A7119 -> 7113 | C7127: ='Raw data (base scenario)'!B7119 -> S | D7127: ='Raw data (base scenario)'!C7119 -> S | E7127: =OR(C7127=$A$4,C7127=$A$5,C7127=$A$6,C7127=$A$7) -> TRUE | F7127: =OR(D7127=$A$4,D7127=$A$5,D7127=$A$6,D7127=$A$7) -> TRUE | G7127: =IF(C7127="D",D7127="D","N/A") -> N/A | K7127: 7113 | L7127: S | M7127: H | N7127: =OR(L7127=$A$4,L7127=$A$5,L7127=$A$6,L7127=$A$7) -> TRUE | O7127: =OR(M7127=$A$4,M7127=$A$5,M7127=$A$6,M7127=$A$7) -> TRUE | P7127: =IF(L7127="D",M7127="D","N/A") -> N/A
B7128: ='Raw data (base scenario)'!A7120 -> 7114 | C7128: ='Raw data (base scenario)'!B7120 -> D | D7128: ='Raw data (base scenario)'!C7120 -> D | E7128: =OR(C7128=$A$4,C7128=$A$5,C7128=$A$6,C7128=$A$7) -> TRUE | F7128: =OR(D7128=$A$4,D7128=$A$5,D7128=$A$6,D7128=$A$7) -> TRUE | G7128: =IF(C7128="D",D7128="D","N/A") -> TRUE | K7128: 7114 | L7128: D | M7128: D | N7128: =OR(L7128=$A$4,L7128=$A$5,L7128=$A$6,L7128=$A$7) -> TRUE | O7128: =OR(M7128=$A$4,M7128=$A$5,M7128=$A$6,M7128=$A$7) -> TRUE | P7128: =IF(L7128="D",M7128="D","N/A") -> TRUE
B7129: ='Raw data (base scenario)'!A7121 -> 7115 | C7129: ='Raw data (base scenario)'!B7121 -> S | D7129: ='Raw data (base scenario)'!C7121 -> H | E7129: =OR(C7129=$A$4,C7129=$A$5,C7129=$A$6,C7129=$A$7) -> TRUE | F7129: =OR(D7129=$A$4,D7129=$A$5,D7129=$A$6,D7129=$A$7) -> TRUE | G7129: =IF(C7129="D",D7129="D","N/A") -> N/A | K7129: 7115 | L7129: D | M7129: D | N7129: =OR(L7129=$A$4,L7129=$A$5,L7129=$A$6,L7129=$A$7) -> TRUE | O7129: =OR(M7129=$A$4,M7129=$A$5,M7129=$A$6,M7129=$A$7) -> TRUE | P7129: =IF(L7129="D",M7129="D","N/A") -> TRUE
B7130: ='Raw data (base scenario)'!A7122 -> 7116 | C7130: ='Raw data (base scenario)'!B7122 -> D | D7130: ='Raw data (base scenario)'!C7122 -> D | E7130: =OR(C7130=$A$4,C7130=$A$5,C7130=$A$6,C7130=$A$7) -> TRUE | F7130: =OR(D7130=$A$4,D7130=$A$5,D7130=$A$6,D7130=$A$7) -> TRUE | G7130: =IF(C7130="D",D7130="D","N/A") -> TRUE | K7130: 7116 | L7130: H | M7130: H | N7130: =OR(L7130=$A$4,L7130=$A$5,L7130=$A$6,L7130=$A$7) -> TRUE | O7130: =OR(M7130=$A$4,M7130=$A$5,M7130=$A$6,M7130=$A$7) -> TRUE | P7130: =IF(L7130="D",M7130="D","N/A") -> N/A
B7131: ='Raw data (base scenario)'!A7123 -> 7117 | C7131: ='Raw data (base scenario)'!B7123 -> D | D7131: ='Raw data (base scenario)'!C7123 -> D | E7131: =OR(C7131=$A$4,C7131=$A$5,C7131=$A$6,C7131=$A$7) -> TRUE | F7131: =OR(D7131=$A$4,D7131=$A$5,D7131=$A$6,D7131=$A$7) -> TRUE | G7131: =IF(C7131="D",D7131="D","N/A") -> TRUE | K7131: 7117 | L7131: I | M7131: I | N7131: =OR(L7131=$A$4,L7131=$A$5,L7131=$A$6,L7131=$A$7) -> TRUE | O7131: =OR(M7131=$A$4,M7131=$A$5,M7131=$A$6,M7131=$A$7) -> TRUE | P7131: =IF(L7131="D",M7131="D","N/A") -> N/A
B7132: ='Raw data (base scenario)'!A7124 -> 7118 | C7132: ='Raw data (base scenario)'!B7124 -> H | D7132: ='Raw data (base scenario)'!C7124 -> H | E7132: =OR(C7132=$A$4,C7132=$A$5,C7132=$A$6,C7132=$A$7) -> TRUE | F7132: =OR(D7132=$A$4,D7132=$A$5,D7132=$A$6,D7132=$A$7) -> TRUE | G7132: =IF(C7132="D",D7132="D","N/A") -> N/A | K7132: 7118 | L7132: D | M7132: D | N7132: =OR(L7132=$A$4,L7132=$A$5,L7132=$A$6,L7132=$A$7) -> TRUE | O7132: =OR(M7132=$A$4,M7132=$A$5,M7132=$A$6,M7132=$A$7) -> TRUE | P7132: =IF(L7132="D",M7132="D","N/A") -> TRUE
B7133: ='Raw data (base scenario)'!A7125 -> 7119 | C7133: ='Raw data (base scenario)'!B7125 -> I | D7133: ='Raw data (base scenario)'!C7125 -> I | E7133: =OR(C7133=$A$4,C7133=$A$5,C7133=$A$6,C7133=$A$7) -> TRUE | F7133: =OR(D7133=$A$4,D7133=$A$5,D7133=$A$6,D7133=$A$7) -> TRUE | G7133: =IF(C7133="D",D7133="D","N/A") -> N/A | K7133: 7119 | L7133: I | M7133: I | N7133: =OR(L7133=$A$4,L7133=$A$5,L7133=$A$6,L7133=$A$7) -> TRUE | O7133: =OR(M7133=$A$4,M7133=$A$5,M7133=$A$6,M7133=$A$7) -> TRUE | P7133: =IF(L7133="D",M7133="D","N/A") -> N/A
... B12008: ='Raw data (base scenario)'!A12000 -> 11994 | C12008: ='Raw data (base scenario)'!B12000 -> S | D12008: ='Raw data (base scenario)'!C12000 -> H | E12008: =OR(C12008=$A$4,C12008=$A$5,C12008=$A$6,C12008=$A$7) -> TRUE | F12008: =OR(D12008=$A$4,D12008=$A$5,D12008=$A$6,D12008=$A$7) -> TRUE | G12008: =IF(C12008="D",D12008="D","N/A") -> N/A | K12008: 11994 | L12008: H | M12008: S | N12008: =OR(L12008=$A$4,L12008=$A$5,L12008=$A$6,L12008=$A$7) -> TRUE | O12008: =OR(M12008=$A$4,M12008=$A$5,M12008=$A$6,M12008=$A$7) -> TRUE | P12008: =IF(L12008="D",M12008="D","N/A") -> N/A
B12009: ='Raw data (base scenario)'!A12001 -> 11995 | C12009: ='Raw data (base scenario)'!B12001 -> X | D12009: ='Raw data (base scenario)'!C12001 -> H | E12009: =OR(C12009=$A$4,C12009=$A$5,C12009=$A$6,C12009=$A$7) -> FALSE | F12009: =OR(D12009=$A$4,D12009=$A$5,D12009=$A$6,D12009=$A$7) -> TRUE | G12009: =IF(C12009="D",D12009="D","N/A") -> N/A | H12009: Corrupted data - remove | K12009: 11995 | L12009: S | M12009: H | N12009: =OR(L12009=$A$4,L12009=$A$5,L12009=$A$6,L12009=$A$7) -> TRUE | O12009: =OR(M12009=$A$4,M12009=$A$5,M12009=$A$6,M12009=$A$7) -> TRUE | P12009: =IF(L12009="D",M12009="D","N/A") -> N/A
B12010: ='Raw data (base scenario)'!A12002 -> 11996 | C12010: ='Raw data (base scenario)'!B12002 -> H | D12010: ='Raw data (base scenario)'!C12002 -> S | E12010: =OR(C12010=$A$4,C12010=$A$5,C12010=$A$6,C12010=$A$7) -> TRUE | F12010: =OR(D12010=$A$4,D12010=$A$5,D12010=$A$6,D12010=$A$7) -> TRUE | G12010: =IF(C12010="D",D12010="D","N/A") -> N/A | K12010: 11996 | L12010: I | M12010: S | N12010: =OR(L12010=$A$4,L12010=$A$5,L12010=$A$6,L12010=$A$7) -> TRUE | O12010: =OR(M12010=$A$4,M12010=$A$5,M12010=$A$6,M12010=$A$7) -> TRUE | P12010: =IF(L12010="D",M12010="D","N/A") -> N/A
B12011: ='Raw data (base scenario)'!A12003 -> 11997 | C12011: ='Raw data (base scenario)'!B12003 -> H | D12011: ='Raw data (base scenario)'!C12003 -> S | E12011: =OR(C12011=$A$4,C12011=$A$5,C12011=$A$6,C12011=$A$7) -> TRUE | F12011: =OR(D12011=$A$4,D12011=$A$5,D12011=$A$6,D12011=$A$7) -> TRUE | G12011: =IF(C12011="D",D12011="D","N/A") -> N/A | K12011: 11997 | L12011: D | M12011: D | N12011: =OR(L12011=$A$4,L12011=$A$5,L12011=$A$6,L12011=$A$7) -> TRUE | O12011: =OR(M12011=$A$4,M12011=$A$5,M12011=$A$6,M12011=$A$7) -> TRUE | P12011: =IF(L12011="D",M12011="D","N/A") -> TRUE
B12012: ='Raw data (base scenario)'!A12004 -> 11998 | C12012: ='Raw data (base scenario)'!B12004 -> S | D12012: ='Raw data (base scenario)'!C12004 -> H | E12012: =OR(C12012=$A$4,C12012=$A$5,C12012=$A$6,C12012=$A$7) -> TRUE | F12012: =OR(D12012=$A$4,D12012=$A$5,D12012=$A$6,D12012=$A$7) -> TRUE | G12012: =IF(C12012="D",D12012="D","N/A") -> N/A | K12012: 11998 | L12012: D | M12012: D | N12012: =OR(L12012=$A$4,L12012=$A$5,L12012=$A$6,L12012=$A$7) -> TRUE | O12012: =OR(M12012=$A$4,M12012=$A$5,M12012=$A$6,M12012=$A$7) -> TRUE | P12012: =IF(L12012="D",M12012="D","N/A") -> TRUE
B12013: ='Raw data (base scenario)'!A12005 -> 11999 | C12013: ='Raw data (base scenario)'!B12005 -> I | D12013: ='Raw data (base scenario)'!C12005 -> S | E12013: =OR(C12013=$A$4,C12013=$A$5,C12013=$A$6,C12013=$A$7) -> TRUE | F12013: =OR(D12013=$A$4,D12013=$A$5,D12013=$A$6,D12013=$A$7) -> TRUE | G12013: =IF(C12013="D",D12013="D","N/A") -> N/A | K12013: 11999 | L12013: I | M12013: D | N12013: =OR(L12013=$A$4,L12013=$A$5,L12013=$A$6,L12013=$A$7) -> TRUE | O12013: =OR(M12013=$A$4,M12013=$A$5,M12013=$A$6,M12013=$A$7) -> TRUE | P12013: =IF(L12013="D",M12013="D","N/A") -> N/A
B12014: ='Raw data (base scenario)'!A12006 -> 12000 | C12014: ='Raw data (base scenario)'!B12006 -> D | D12014: ='Raw data (base scenario)'!C12006 -> D | E12014: =OR(C12014=$A$4,C12014=$A$5,C12014=$A$6,C12014=$A$7) -> TRUE | F12014: =OR(D12014=$A$4,D12014=$A$5,D12014=$A$6,D12014=$A$7) -> TRUE | G12014: =IF(C12014="D",D12014="D","N/A") -> TRUE | K12014: 12000 | L12014: D | M12014: D | N12014: =OR(L12014=$A$4,L12014=$A$5,L12014=$A$6,L12014=$A$7) -> TRUE | O12014: =OR(M12014=$A$4,M12014=$A$5,M12014=$A$6,M12014=$A$7) -> TRUE | P12014: =IF(L12014="D",M12014="D","N/A") -> TRUE
B12015: ='Raw data (base scenario)'!A12007 -> 12001 | C12015: ='Raw data (base scenario)'!B12007 -> D | D12015: ='Raw data (base scenario)'!C12007 -> D | E12015: =OR(C12015=$A$4,C12015=$A$5,C12015=$A$6,C12015=$A$7) -> TRUE | F12015: =OR(D12015=$A$4,D12015=$A$5,D12015=$A$6,D12015=$A$7) -> TRUE | G12015: =IF(C12015="D",D12015="D","N/A") -> TRUE
B12016: ='Raw data (base scenario)'!A12008 -> 12002 | C12016: ='Raw data (base scenario)'!B12008 -> I | D12016: ='Raw data (base scenario)'!C12008 -> D | E12016: =OR(C12016=$A$4,C12016=$A$5,C12016=$A$6,C12016=$A$7) -> TRUE | F12016: =OR(D12016=$A$4,D12016=$A$5,D12016=$A$6,D12016=$A$7) -> TRUE | G12016: =IF(C12016="D",D12016="D","N/A") -> N/A
B12017: ='Raw data (base scenario)'!A12009 -> 12003 | C12017: ='Raw data (base scenario)'!B12009 -> D | D12017: ='Raw data (base scenario)'!C12009 -> D | E12017: =OR(C12017=$A$4,C12017=$A$5,C12017=$A$6,C12017=$A$7) -> TRUE | F12017: =OR(D12017=$A$4,D12017=$A$5,D12017=$A$6,D12017=$A$7) -> TRUE | G12017: =IF(C12017="D",D12017="D","N/A") -> TRUE

Sheet Clean_data
A1: Clean data
B6: Status | C6: Status
A7: Lives | B7: Start of Year | C7: End of Year
A8: =Data_checks!K15 -> 1 | B8: =Data_checks!L15 -> I | C8: =Data_checks!M15 -> S | G8: End of Year
A9: =Data_checks!K16 -> 2 | B9: =Data_checks!L16 -> S | C9: =Data_checks!M16 -> H | G9: Healthy | H9: Sick | I9: Very sick | J9: Dead | P9: Reassonableness checks
A10: =Data_checks!K17 -> 3 | B10: =Data_checks!L17 -> D | C10: =Data_checks!M17 -> D | E10: Start of Year | G10: H | H10: S | I10: I | J10: D | K10: Total | P10: Dead stays dead (absorbing state)
A11: =Data_checks!K18 -> 4 | B11: =Data_checks!L18 -> H | C11: =Data_checks!M18 -> H | E11: Healthy | F11: H | G11: =COUNTIFS($B$8:$B$12007,$F11,$C$8:$C$12007,G$10) -> 2400 | H11: =COUNTIFS($B$8:$B$12007,$F11,$C$8:$C$12007,H$10) -> 480 | I11: =COUNTIFS($B$8:$B$12007,$F11,$C$8:$C$12007,I$10) -> 90 | J11: =COUNTIFS($B$8:$B$12007,$F11,$C$8:$C$12007,J$10) -> 30 | K11: =SUM(G11:J11) -> 3000
A12: =Data_checks!K19 -> 5 | B12: =Data_checks!L19 -> I | C12: =Data_checks!M19 -> I | E12: Sick | F12: S | G12: =COUNTIFS($B$8:$B$12007,$F12,$C$8:$C$12007,G$10) -> 2250 | H12: =COUNTIFS($B$8:$B$12007,$F12,$C$8:$C$12007,H$10) -> 300 | I12: =COUNTIFS($B$8:$B$12007,$F12,$C$8:$C$12007,I$10) -> 300 | J12: =COUNTIFS($B$8:$B$12007,$F12,$C$8:$C$12007,J$10) -> 150 | K12: =SUM(G12:J12) -> 3000
A13: =Data_checks!K20 -> 6 | B13: =Data_checks!L20 -> I | C13: =Data_checks!M20 -> D | E13: Very sick | F13: I | G13: =COUNTIFS($B$8:$B$12007,$F13,$C$8:$C$12007,G$10) -> 450 | H13: =COUNTIFS($B$8:$B$12007,$F13,$C$8:$C$12007,H$10) -> 750 | I13: =COUNTIFS($B$8:$B$12007,$F13,$C$8:$C$12007,I$10) -> 900 | J13: =COUNTIFS($B$8:$B$12007,$F13,$C$8:$C$12007,J$10) -> 900 | K13: =SUM(G13:J13) -> 3000
A14: =Data_checks!K21 -> 7 | B14: =Data_checks!L21 -> H | C14: =Data_checks!M21 -> H | E14: Dead | F14: D | G14: =COUNTIFS($B$8:$B$12007,$F14,$C$8:$C$12007,G$10) -> 0 | H14: =COUNTIFS($B$8:$B$12007,$F14,$C$8:$C$12007,H$10) -> 0 | I14: =COUNTIFS($B$8:$B$12007,$F14,$C$8:$C$12007,I$10) -> 0 | J14: =COUNTIFS($B$8:$B$12007,$F14,$C$8:$C$12007,J$10) -> 3000 | K14: =SUM(G14:J14) -> 3000
A15: =Data_checks!K22 -> 8 | B15: =Data_checks!L22 -> D | C15: =Data_checks!M22 -> D | F15: Total | G15: =SUM(G11:G14) -> 5100 | H15: =SUM(H11:H14) -> 1530 | I15: =SUM(I11:I14) -> 1290 | J15: =SUM(J11:J14) -> 4080 | K15: =SUM(K11:K14)=SUM(G15:J15) -> TRUE
A16: =Data_checks!K23 -> 9 | B16: =Data_checks!L23 -> H | C16: =Data_checks!M23 -> H
A17: =Data_checks!K24 -> 10 | B17: =Data_checks!L24 -> S | C17: =Data_checks!M24 -> H
A18: =Data_checks!K25 -> 11 | B18: =Data_checks!L25 -> I | C18: =Data_checks!M25 -> I
A19: =Data_checks!K26 -> 12 | B19: =Data_checks!L26 -> H | C19: =Data_checks!M26 -> H
A20: =Data_checks!K27 -> 13 | B20: =Data_checks!L27 -> H | C20: =Data_checks!M27 -> H
A21: =Data_checks!K28 -> 14 | B21: =Data_checks!L28 -> S | C21: =Data_checks!M28 -> H
A22: =Data_checks!K29 -> 15 | B22: =Data_checks!L29 -> H | C22: =Data_checks!M29 -> H
A23: =Data_checks!K30 -> 16 | B23: =Data_checks!L30 -> H | C23: =Data_checks!M30 -> H
A24: =Data_checks!K31 -> 17 | B24: =Data_checks!L31 -> H | C24: =Data_checks!M31 -> H
A25: =Data_checks!K32 -> 18 | B25: =Data_checks!L32 -> D | C25: =Data_checks!M32 -> D
A26: =Data_checks!K33 -> 19 | B26: =Data_checks!L33 -> D | C26: =Data_checks!M33 -> D
A27: =Data_checks!K34 -> 20 | B27: =Data_checks!L34 -> I | C27: =Data_checks!M34 -> S
... A12007: =Data_checks!K12014 -> 12000 | B12007: =Data_checks!L12014 -> D | C12007: =Data_checks!M12014 -> D

Sheet Parameters
A1: Parameters: Derived from raw data or provided in background information
A3: Transition probabilities
C4: End of year
C5: H | D5: S | E5: I | F5: D | G5: Check sum to 1?
A6: Start of year | B6: H | C6: =Clean_data!G11/Clean_data!$K11 -> 0.8 | D6: =Clean_data!H11/Clean_data!$K11 -> 0.16 | E6: =Clean_data!I11/Clean_data!$K11 -> 0.03 | F6: =Clean_data!J11/Clean_data!$K11 -> 0.01 | G6: =SUM(C6:F6)=1 -> TRUE
B7: S | C7: =Clean_data!G12/Clean_data!$K12 -> 0.75 | D7: =Clean_data!H12/Clean_data!$K12 -> 0.1 | E7: =Clean_data!I12/Clean_data!$K12 -> 0.1 | F7: =Clean_data!J12/Clean_data!$K12 -> 0.05 | G7: =SUM(C7:F7)=1 -> TRUE
B8: I | C8: =Clean_data!G13/Clean_data!$K13 -> 0.15 | D8: =Clean_data!H13/Clean_data!$K13 -> 0.25 | E8: =Clean_data!I13/Clean_data!$K13 -> 0.3 | F8: =Clean_data!J13/Clean_data!$K13 -> 0.3 | G8: =SUM(C8:F8)=1 -> TRUE
B9: D | C9: =Clean_data!G14/Clean_data!$K14 -> 0 | D9: =Clean_data!H14/Clean_data!$K14 -> 0 | E9: =Clean_data!I14/Clean_data!$K14 -> 0 | F9: =Clean_data!J14/Clean_data!$K14 -> 1 | G9: =SUM(C9:F9)=1 -> TRUE
A11: Number of lives | B11: H | C11: S | D11: I | E11: D
A12: Initial state | B12: 1000000 | C12: 0 | D12: 0 | E12: 0
A14: Overheads at each health state
A15: Healthy | B15: 50
A16: Sick | B16: 200
A17: Very sick | B17: 3000
A18: Dead | B18: 250
A20: Drug cost
A21: Sick | B21: 150
A22: Very sick | B22: 4000
A24: General inflation (overheads) | B24: 0.02
A25: Drug inflation | B25: 0.05
A26: Discount rate | B26: 0.04
A28: Alternative transition
A29: Transition improvements
C30: End of year
C31: H | D31: S | E31: I | F31: D | G31: Check sum to 0?
A32: Start of year | B32: H | C32: 0.0018 | D32: -0.0012 | E32: -0.00055 | F32: -5e-05 | G32: =SUM(C32:F32)=0 -> TRUE
B33: S | C33: 0.00065 | D33: 0.0005 | E33: -0.00083 | F33: -0.00032 | G33: =SUM(C33:F33)=0 -> TRUE
B34: I | C34: 0.0005 | D34: 0.001 | E34: 0.0005 | F34: -0.002 | G34: =SUM(C34:F34)=0 -> TRUE
B35: D | C35: 0 | D35: 0 | E35: 0 | F35: 0 | G35: =SUM(C35:F35)=0 -> TRUE
A36: New drug cost
A37: Sick | B37: 250
A38: Very sick | B38: 6000
A40: Negotiated drug cost
A41: Sick | B41: 236.97678
A42: Very sick | B42: =B41*20 -> 4739.5356
A44: Negotiated drug cost (if using SoY status)
A45: Sick | B45: 176.55465
A46: Very sick | B46: =B45*20 -> 3531.0929

Sheet Base Scenario
A1: Initial position
A3: * This is an example approach to determining the solution. An reasonable attempt is awarded credit.
C5: Different formulae - do not drag
Y8: Total PV
G9: Total | Y9: =SUM(Y13:Y43) -> 8.8497636e+09
G10: =SUM(G14:G43) -> 19110751
I11: Overheads | M11: Drug | O11: Combined cost | S11: Cost per state x population | W11: Total cost | X11: v | Y11: PV of cost | Z11: Real cost per life alive
B12: Year | C12: Healthy | D12: Sick | E12: Very sick | F12: Dead | G12: Lives alive | H12: Excess deaths | I12: H | J12: S | K12: I | L12: D | M12: S | N12: I | O12: H | P12: S | Q12: I | R12: D | S12: H | T12: S | U12: I | V12: D
B13: 0 | C13: =Parameters!B12 -> 1000000 | D13: =Parameters!C12 -> 0 | E13: =Parameters!D12 -> 0 | F13: =Parameters!E12 -> 0 | G13: =SUM(C13:E13) -> 1000000 | H13: =F13 -> 0 | W13: =C13*O13+D13*P13+E13*Q13+H13*R13 -> 0 | X13: 1 | Y13: =W13*X13 -> 0
B14: 1 | C14: {=SUMPRODUCT($C13:$F13,TRANSPOSE(Parameters!C$6:C$9))} -> 800000 | D14: {=SUMPRODUCT($C13:$F13,TRANSPOSE(Parameters!D$6:D$9))} -> 160000 | E14: {=SUMPRODUCT($C13:$F13,TRANSPOSE(Parameters!E$6:E$9))} -> 30000 | F14: {=SUMPRODUCT($C13:$F13,TRANSPOSE(Parameters!F$6:F$9))} -> 10000 | G14: =SUM(C14:E14) -> 990000 | H14: =F14-F13 -> 10000 | I14: =Parameters!B15 -> 50 | J14: =Parameters!B16 -> 200 | K14: =Parameters!B17 -> 3000 | L14: =Parameters!B18 -> 250 | M14: =Parameters!B21 -> 150 | N14: =Parameters!B22 -> 4000 | O14: =I14 -> 50 | P14: =J14+M14 -> 350 | Q14: =K14+N14 -> 7000 | R14: =L14 -> 250 | S14: =C13*Parameters!$C$6*O14+D13*Parameters!$C$7*(O14+P14)/2+E13*Parameters!$C$8*(O14+Q14)/2 -> 40000000 | T14: =C13*Parameters!$D$6*(O14+P14)/2+D13*Parameters!$D$7*P14+E13*Parameters!$D$8*(P14+Q14)/2 -> 32000000 | U14: =C13*Parameters!$E$6*(O14+Q14)/2+D13*Parameters!$E$7*(P14+Q14)/2+E13*Parameters!$E$8*Q14 -> 105750000 | V14: =C13*Parameters!$F$6*(O14/2+R14)+D13*Parameters!$F$7*(P14/2+R14)+E13*Parameters!$F$8*(Q14/2+R14) -> 2750000 | W14: =S14+T14+U14+V14 -> 180500000 | X14: =1/(1+Parameters!$B$26) -> 0.96153846 | Y14: =W14*X14 -> 1.7355769e+08 | Z14: =Y14/G13 -> 173.55769
B15: 2 | C15: {=SUMPRODUCT($C14:$F14,TRANSPOSE(Parameters!C$6:C$9))} -> 764500 | D15: {=SUMPRODUCT($C14:$F14,TRANSPOSE(Parameters!D$6:D$9))} -> 151500 | E15: {=SUMPRODUCT($C14:$F14,TRANSPOSE(Parameters!E$6:E$9))} -> 49000 | F15: {=SUMPRODUCT($C14:$F14,TRANSPOSE(Parameters!F$6:F$9))} -> 35000 | G15: =SUM(C15:E15) -> 965000 | H15: =F15-F14 -> 25000 | I15: =I14*(1+Parameters!$B$24) -> 51 | J15: =J14*(1+Parameters!$B$24) -> 204 | K15: =K14*(1+Parameters!$B$24) -> 3060 | L15: =L14*(1+Parameters!$B$24) -> 255 | M15: =M14*(1+Parameters!$B$25) -> 157.5 | N15: =N14*(1+Parameters!$B$25) -> 4200 | O15: =I15 -> 51 | P15: =J15+M15 -> 361.5 | Q15: =K15+N15 -> 7260 | R15: =L15 -> 255 | S15: =C14*Parameters!$C$6*O15+D14*Parameters!$C$7*(O15+P15)/2+E14*Parameters!$C$8*(O15+Q15)/2 -> 73839750 | T15: =C14*Parameters!$D$6*(O15+P15)/2+D14*Parameters!$D$7*P15+E14*Parameters!$D$8*(P15+Q15)/2 -> 60764625 | U15: =C14*Parameters!$E$6*(O15+Q15)/2+D14*Parameters!$E$7*(P15+Q15)/2+E14*Parameters!$E$8*Q15 -> 214044000 | V15: =C14*Parameters!$F$6*(O15/2+R15)+D14*Parameters!$F$7*(P15/2+R15)+E14*Parameters!$F$8*(Q15/2+R15) -> 40695000 | W15: =S15+T15+U15+V15 -> 389343375 | X15: =X14/(1+Parameters!$B$26) -> 0.92455621 | Y15: =W15*X15 -> 3.5996984e+08 | Z15: =Y15/G14 -> 363.6059
B16: 3 | C16: {=SUMPRODUCT($C15:$F15,TRANSPOSE(Parameters!C$6:C$9))} -> 732575 | D16: {=SUMPRODUCT($C15:$F15,TRANSPOSE(Parameters!D$6:D$9))} -> 149720 | E16: {=SUMPRODUCT($C15:$F15,TRANSPOSE(Parameters!E$6:E$9))} -> 52785 | F16: {=SUMPRODUCT($C15:$F15,TRANSPOSE(Parameters!F$6:F$9))} -> 64920 | G16: =SUM(C16:E16) -> 935080 | H16: =F16-F15 -> 29920 | I16: =I15*(1+Parameters!$B$24) -> 52.02 | J16: =J15*(1+Parameters!$B$24) -> 208.08 | K16: =K15*(1+Parameters!$B$24) -> 3121.2 | L16: =L15*(1+Parameters!$B$24) -> 260.1 | M16: =M15*(1+Parameters!$B$25) -> 165.375 | N16: =N15*(1+Parameters!$B$25) -> 4410 | O16: =I16 -> 52.02 | P16: =J16+M16 -> 373.455 | Q16: =K16+N16 -> 7531.2 | R16: =L16 -> 260.1 | S16: =C15*Parameters!$C$6*O16+D15*Parameters!$C$7*(O16+P16)/2+E15*Parameters!$C$8*(O16+Q16)/2 -> 83856064 | T16: =C15*Parameters!$D$6*(O16+P16)/2+D15*Parameters!$D$7*P16+E15*Parameters!$D$8*(P16+Q16)/2 -> 80095906 | U16: =C15*Parameters!$E$6*(O16+Q16)/2+D15*Parameters!$E$7*(P16+Q16)/2+E15*Parameters!$E$8*Q16 -> 2.5754698e+08 | V16: =C15*Parameters!$F$6*(O16/2+R16)+D15*Parameters!$F$7*(P16/2+R16)+E15*Parameters!$F$8*(Q16/2+R16) -> 64749819 | W16: =S16+T16+U16+V16 -> 4.8624877e+08 | X16: =X15/(1+Parameters!$B$26) -> 0.88899636 | Y16: =W16*X16 -> 4.3227338e+08 | Z16: =Y16/G15 -> 447.95169
B17: 4 | C17: {=SUMPRODUCT($C16:$F16,TRANSPOSE(Parameters!C$6:C$9))} -> 706267.75 | D17: {=SUMPRODUCT($C16:$F16,TRANSPOSE(Parameters!D$6:D$9))} -> 145380.25 | E17: {=SUMPRODUCT($C16:$F16,TRANSPOSE(Parameters!E$6:E$9))} -> 52784.75 | F17: {=SUMPRODUCT($C16:$F16,TRANSPOSE(Parameters!F$6:F$9))} -> 95567.25 | G17: =SUM(C17:E17) -> 904432.75 | H17: =F17-F16 -> 30647.25 | I17: =I16*(1+Parameters!$B$24) -> 53.0604 | J17: =J16*(1+Parameters!$B$24) -> 212.2416 | K17: =K16*(1+Parameters!$B$24) -> 3183.624 | L17: =L16*(1+Parameters!$B$24) -> 265.302 | M17: =M16*(1+Parameters!$B$25) -> 173.64375 | N17: =N16*(1+Parameters!$B$25) -> 4630.5 | O17: =I17 -> 53.0604 | P17: =J17+M17 -> 385.88535 | Q17: =K17+N17 -> 7814.124 | R17: =L17 -> 265.302 | S17: =C16*Parameters!$C$6*O17+D16*Parameters!$C$7*(O17+P17)/2+E16*Parameters!$C$8*(O17+Q17)/2 -> 86886387 | T17: =C16*Parameters!$D$6*(O17+P17)/2+D16*Parameters!$D$7*P17+E16*Parameters!$D$8*(P17+Q17)/2 -> 85607017 | U17: =C16*Parameters!$E$6*(O17+Q17)/2+D16*Parameters!$E$7*(P17+Q17)/2+E16*Parameters!$E$8*Q17 -> 2.7157537e+08 | V17: =C16*Parameters!$F$6*(O17/2+R17)+D16*Parameters!$F$7*(P17/2+R17)+E16*Parameters!$F$8*(Q17/2+R17) -> 71639779 | W17: =S17+T17+U17+V17 -> 5.1570855e+08 | X17: =X16/(1+Parameters!$B$26) -> 0.85480419 | Y17: =W17*X17 -> 4.4082983e+08 | Z17: =Y17/G16 -> 471.43542
B18: 5 | C18: {=SUMPRODUCT($C17:$F17,TRANSPOSE(Parameters!C$6:C$9))} -> 681967.1 | D18: {=SUMPRODUCT($C17:$F17,TRANSPOSE(Parameters!D$6:D$9))} -> 140737.05 | E18: {=SUMPRODUCT($C17:$F17,TRANSPOSE(Parameters!E$6:E$9))} -> 51561.482 | F18: {=SUMPRODUCT($C17:$F17,TRANSPOSE(Parameters!F$6:F$9))} -> 125734.36 | G18: =SUM(C18:E18) -> 874265.64 | H18: =F18-F17 -> 30167.115 | I18: =I17*(1+Parameters!$B$24) -> 54.121608 | J18: =J17*(1+Parameters!$B$24) -> 216.48643 | K18: =K17*(1+Parameters!$B$24) -> 3247.2965 | L18: =L17*(1+Parameters!$B$24) -> 270.60804 | M18: =M17*(1+Parameters!$B$25) -> 182.32594 | N18: =N17*(1+Parameters!$B$25) -> 4862.025 | O18: =I18 -> 54.121608 | P18: =J18+M18 -> 398.81237 | Q18: =K18+N18 -> 8109.3215 | R18: =L18 -> 270.60804 | S18: =C17*Parameters!$C$6*O18+D17*Parameters!$C$7*(O18+P18)/2+E17*Parameters!$C$8*(O18+Q18)/2 -> 87590245 | T18: =C17*Parameters!$D$6*(O18+P18)/2+D17*Parameters!$D$7*P18+E17*Parameters!$D$8*(P18+Q18)/2 -> 87526822 | U18: =C17*Parameters!$E$6*(O18+Q18)/2+D17*Parameters!$E$7*(P18+Q18)/2+E17*Parameters!$E$8*Q18 -> 2.7674393e+08 | V18: =C17*Parameters!$F$6*(O18/2+R18)+D17*Parameters!$F$7*(P18/2+R18)+E17*Parameters!$F$8*(Q18/2+R18) -> 74011348 | W18: =S18+T18+U18+V18 -> 5.2587235e+08 | X18: =X17/(1+Parameters!$B$26) -> 0.82192711 | Y18: =W18*X18 -> 4.3222874e+08 | Z18: =Y18/G17 -> 477.90036
B19: 6 | C19: {=SUMPRODUCT($C18:$F18,TRANSPOSE(Parameters!C$6:C$9))} -> 658860.69 | D19: {=SUMPRODUCT($C18:$F18,TRANSPOSE(Parameters!D$6:D$9))} -> 136078.81 | E19: {=SUMPRODUCT($C18:$F18,TRANSPOSE(Parameters!E$6:E$9))} -> 50001.163 | F19: {=SUMPRODUCT($C18:$F18,TRANSPOSE(Parameters!F$6:F$9))} -> 155059.33 | G19: =SUM(C19:E19) -> 844940.67 | H19: =F19-F18 -> 29324.968 | I19: =I18*(1+Parameters!$B$24) -> 55.20404 | J19: =J18*(1+Parameters!$B$24) -> 220.81616 | K19: =K18*(1+Parameters!$B$24) -> 3312.2424 | L19: =L18*(1+Parameters!$B$24) -> 276.0202 | M19: =M18*(1+Parameters!$B$25) -> 191.44223 | N19: =N18*(1+Parameters!$B$25) -> 5105.1263 | O19: =I19 -> 55.20404 | P19: =J19+M19 -> 412.2584 | Q19: =K19+N19 -> 8417.3687 | R19: =L19 -> 276.0202 | S19: =C18*Parameters!$C$6*O19+D18*Parameters!$C$7*(O19+P19)/2+E18*Parameters!$C$8*(O19+Q19)/2 -> 87553234 | T19: =C18*Parameters!$D$6*(O19+P19)/2+D18*Parameters!$D$7*P19+E18*Parameters!$D$8*(P19+Q19)/2 -> 88214106 | U19: =C18*Parameters!$E$6*(O19+Q19)/2+D18*Parameters!$E$7*(P19+Q19)/2+E18*Parameters!$E$8*Q19 -> 2.7900662e+08 | V19: =C18*Parameters!$F$6*(O19/2+R19)+D18*Parameters!$F$7*(P19/2+R19)+E18*Parameters!$F$8*(Q19/2+R19) -> 74834822 | W19: =S19+T19+U19+V19 -> 5.2960879e+08 | X19: =X18/(1+Parameters!$B$26) -> 0.79031453 | Y19: =W19*X19 -> 4.1855752e+08 | Z19: =Y19/G18 -> 478.75325
B20: 7 | C20: {=SUMPRODUCT($C19:$F19,TRANSPOSE(Parameters!C$6:C$9))} -> 636647.84 | D20: {=SUMPRODUCT($C19:$F19,TRANSPOSE(Parameters!D$6:D$9))} -> 131525.88 | E20: {=SUMPRODUCT($C19:$F19,TRANSPOSE(Parameters!E$6:E$9))} -> 48374.051 | F20: {=SUMPRODUCT($C19:$F19,TRANSPOSE(Parameters!F$6:F$9))} -> 183452.23 | G20: =SUM(C20:E20) -> 816547.77 | H20: =F20-F19 -> 28392.896 | I20: =I19*(1+Parameters!$B$24) -> 56.308121 | J20: =J19*(1+Parameters!$B$24) -> 225.23248 | K20: =K19*(1+Parameters!$B$24) -> 3378.4873 | L20: =L19*(1+Parameters!$B$24) -> 281.5406 | M20: =M19*(1+Parameters!$B$25) -> 201.01435 | N20: =N19*(1+Parameters!$B$25) -> 5360.3826 | O20: =I20 -> 56.308121 | P20: =J20+M20 -> 426.24683 | Q20: =K20+N20 -> 8738.8698 | R20: =L20 -> 281.5406 | S20: =C19*Parameters!$C$6*O20+D19*Parameters!$C$7*(O20+P20)/2+E19*Parameters!$C$8*(O20+Q20)/2 -> 87286615 | T20: =C19*Parameters!$D$6*(O20+P20)/2+D19*Parameters!$D$7*P20+E19*Parameters!$D$8*(P20+Q20)/2 -> 88518547 | U20: =C19*Parameters!$E$6*(O20+Q20)/2+D19*Parameters!$E$7*(P20+Q20)/2+E19*Parameters!$E$8*Q20 -> 2.8036696e+08 | V20: =C19*Parameters!$F$6*(O20/2+R20)+D19*Parameters!$F$7*(P20/2+R20)+E19*Parameters!$F$8*(Q20/2+R20) -> 75172376 | W20: =S20+T20+U20+V20 -> 5.313445e+08 | X20: =X19/(1+Parameters!$B$26) -> 0.75991781 | Y20: =W20*X20 -> 4.0377815e+08 | Z20: =Y20/G19 -> 477.87752
B21: 8 | C21: {=SUMPRODUCT($C20:$F20,TRANSPOSE(Parameters!C$6:C$9))} -> 615218.79 | D21: {=SUMPRODUCT($C20:$F20,TRANSPOSE(Parameters!D$6:D$9))} -> 127109.75 | E21: {=SUMPRODUCT($C20:$F20,TRANSPOSE(Parameters!E$6:E$9))} -> 46764.239 | F21: {=SUMPRODUCT($C20:$F20,TRANSPOSE(Parameters!F$6:F$9))} -> 210907.22 | G21: =SUM(C21:E21) -> 789092.78 | H21: =F21-F20 -> 27454.988 | I21: =I20*(1+Parameters!$B$24) -> 57.434283 | J21: =J20*(1+Parameters!$B$24) -> 229.73713 | K21: =K20*(1+Parameters!$B$24) -> 3446.057 | L21: =L20*(1+Parameters!$B$24) -> 287.17142 | M21: =M20*(1+Parameters!$B$25) -> 211.06506 | N21: =N20*(1+Parameters!$B$25) -> 5628.4017 | O21: =I21 -> 57.434283 | P21: =J21+M21 -> 440.8022 | Q21: =K21+N21 -> 9074.4587 | R21: =L21 -> 287.17142 | S21: =C20*Parameters!$C$6*O21+D20*Parameters!$C$7*(O21+P21)/2+E20*Parameters!$C$8*(O21+Q21)/2 -> 86957451 | T21: =C20*Parameters!$D$6*(O21+P21)/2+D20*Parameters!$D$7*P21+E20*Parameters!$D$8*(P21+Q21)/2 -> 88710248 | U21: =C20*Parameters!$E$6*(O21+Q21)/2+D20*Parameters!$E$7*(P21+Q21)/2+E20*Parameters!$E$8*Q21 -> 2.8147265e+08 | V21: =C20*Parameters!$F$6*(O21/2+R21)+D20*Parameters!$F$7*(P21/2+R21)+E20*Parameters!$F$8*(Q21/2+R21) -> 75361786 | W21: =S21+T21+U21+V21 -> 5.3250214e+08 | X21: =X20/(1+Parameters!$B$26) -> 0.73069021 | Y21: =W21*X21 -> 3.890941e+08 | Z21: =Y21/G20 -> 476.51112
B22: 9 | C22: {=SUMPRODUCT($C21:$F21,TRANSPOSE(Parameters!C$6:C$9))} -> 594521.98 | D22: {=SUMPRODUCT($C21:$F21,TRANSPOSE(Parameters!D$6:D$9))} -> 122837.04 | E22: {=SUMPRODUCT($C21:$F21,TRANSPOSE(Parameters!E$6:E$9))} -> 45196.811 | F22: {=SUMPRODUCT($C21:$F21,TRANSPOSE(Parameters!F$6:F$9))} -> 237444.16 | G22: =SUM(C22:E22) -> 762555.84 | H22: =F22-F21 -> 26536.947 | I22: =I21*(1+Parameters!$B$24) -> 58.582969 | J22: =J21*(1+Parameters!$B$24) -> 234.33188 | K22: =K21*(1+Parameters!$B$24) -> 3514.9781 | L22: =L21*(1+Parameters!$B$24) -> 292.91485 | M22: =M21*(1+Parameters!$B$25) -> 221.61832 | N22: =N21*(1+Parameters!$B$25) -> 5909.8218 | O22: =I22 -> 58.582969 | P22: =J22+M22 -> 455.95019 | Q22: =K22+N22 -> 9424.7999 | R22: =L22 -> 292.91485 | S22: =C21*Parameters!$C$6*O22+D21*Parameters!$C$7*(O22+P22)/2+E21*Parameters!$C$8*(O22+Q22)/2 -> 86620132 | T22: =C21*Parameters!$D$6*(O22+P22)/2+D21*Parameters!$D$7*P22+E21*Parameters!$D$8*(P22+Q22)/2 -> 88877829 | U22: =C21*Parameters!$E$6*(O22+Q22)/2+D21*Parameters!$E$7*(P22+Q22)/2+E21*Parameters!$E$8*Q22 -> 2.8253539e+08 | V22: =C21*Parameters!$F$6*(O22/2+R22)+D21*Parameters!$F$7*(P22/2+R22)+E21*Parameters!$F$8*(Q22/2+R22) -> 75513704 | W22: =S22+T22+U22+V22 -> 5.3354706e+08 | X22: =X21/(1+Parameters!$B$26) -> 0.70258674 | Y22: =W22*X22 -> 3.7486309e+08 | Z22: =Y22/G21 -> 475.05578
B23: 10 | C23: {=SUMPRODUCT($C22:$F22,TRANSPOSE(Parameters!C$6:C$9))} -> 574524.89 | D23: {=SUMPRODUCT($C22:$F22,TRANSPOSE(Parameters!D$6:D$9))} -> 118706.42 | E23: {=SUMPRODUCT($C22:$F22,TRANSPOSE(Parameters!E$6:E$9))} -> 43678.407 | F23: {=SUMPRODUCT($C22:$F22,TRANSPOSE(Parameters!F$6:F$9))} -> 263090.28 | G23: =SUM(C23:E23) -> 736909.72 | H23: =F23-F22 -> 25646.115 | I23: =I22*(1+Parameters!$B$24) -> 59.754628 | J23: =J22*(1+Parameters!$B$24) -> 239.01851 | K23: =K22*(1+Parameters!$B$24) -> 3585.2777 | L23: =L22*(1+Parameters!$B$24) -> 298.77314 | M23: =M22*(1+Parameters!$B$25) -> 232.69923 | N23: =N22*(1+Parameters!$B$25) -> 6205.3129 | O23: =I23 -> 59.754628 | P23: =J23+M23 -> 471.71775 | Q23: =K23+N23 -> 9790.5906 | R23: =L23 -> 298.77314 | S23: =C22*Parameters!$C$6*O23+D22*Parameters!$C$7*(O23+P23)/2+E22*Parameters!$C$8*(O23+Q23)/2 -> 86292352 | T23: =C22*Parameters!$D$6*(O23+P23)/2+D22*Parameters!$D$7*P23+E22*Parameters!$D$8*(P23+Q23)/2 -> 89050153 | U23: =C22*Parameters!$E$6*(O23+Q23)/2+D22*Parameters!$E$7*(P23+Q23)/2+E22*Parameters!$E$8*Q23 -> 2.8362432e+08 | V23: =C22*Parameters!$F$6*(O23/2+R23)+D22*Parameters!$F$7*(P23/2+R23)+E22*Parameters!$F$8*(Q23/2+R23) -> 75664128 | W23: =S23+T23+U23+V23 -> 5.3463095e+08 | X23: =X22/(1+Parameters!$B$26) -> 0.67556417 | Y23: =W23*X23 -> 3.6117752e+08 | Z23: =Y23/G22 -> 473.64075
B24: 11 | C24: {=SUMPRODUCT($C23:$F23,TRANSPOSE(Parameters!C$6:C$9))} -> 555201.49 | D24: {=SUMPRODUCT($C23:$F23,TRANSPOSE(Parameters!D$6:D$9))} -> 114714.23 | E24: {=SUMPRODUCT($C23:$F23,TRANSPOSE(Parameters!E$6:E$9))} -> 42209.911 | F24: {=SUMPRODUCT($C23:$F23,TRANSPOSE(Parameters!F$6:F$9))} -> 287874.37 | G24: =SUM(C24:E24) -> 712125.63 | H24: =F24-F23 -> 24784.092 | I24: =I23*(1+Parameters!$B$24) -> 60.949721 | J24: =J23*(1+Parameters!$B$24) -> 243.79888 | K24: =K23*(1+Parameters!$B$24) -> 3656.9833 | L24: =L23*(1+Parameters!$B$24) -> 304.7486 | M24: =M23*(1+Parameters!$B$25) -> 244.33419 | N24: =N23*(1+Parameters!$B$25) -> 6515.5785 | O24: =I24 -> 60.949721 | P24: =J24+M24 -> 488.13308 | Q24: =K24+N24 -> 10172.562 | R24: =L24 -> 304.7486 | S24: =C23*Parameters!$C$6*O24+D23*Parameters!$C$7*(O24+P24)/2+E23*Parameters!$C$8*(O24+Q24)/2 -> 85979837 | T24: =C23*Parameters!$D$6*(O24+P24)/2+D23*Parameters!$D$7*P24+E23*Parameters!$D$8*(P24+Q24)/2 -> 89236663 | U24: =C23*Parameters!$E$6*(O24+Q24)/2+D23*Parameters!$E$7*(P24+Q24)/2+E23*Parameters!$E$8*Q24 -> 2.8476214e+08 | V24: =C23*Parameters!$F$6*(O24/2+R24)+D23*Parameters!$F$7*(P24/2+R24)+E23*Parameters!$F$8*(Q24/2+R24) -> 75824810 | W24: =S24+T24+U24+V24 -> 5.3580345e+08 | X24: =X23/(1+Parameters!$B$26) -> 0.64958093 | Y24: =W24*X24 -> 3.4804771e+08 | Z24: =Y24/G23 -> 472.30712
B25: 12 | C25: {=SUMPRODUCT($C24:$F24,TRANSPOSE(Parameters!C$6:C$9))} -> 536528.35 | D25: {=SUMPRODUCT($C24:$F24,TRANSPOSE(Parameters!D$6:D$9))} -> 110856.14 | E25: {=SUMPRODUCT($C24:$F24,TRANSPOSE(Parameters!E$6:E$9))} -> 40790.441 | F25: {=SUMPRODUCT($C24:$F24,TRANSPOSE(Parameters!F$6:F$9))} -> 311825.07 | G25: =SUM(C25:E25) -> 688174.93 | H25: =F25-F24 -> 23950.7 | I25: =I24*(1+Parameters!$B$24) -> 62.168715 | J25: =J24*(1+Parameters!$B$24) -> 248.67486 | K25: =K24*(1+Parameters!$B$24) -> 3730.1229 | L25: =L24*(1+Parameters!$B$24) -> 310.84358 | M25: =M24*(1+Parameters!$B$25) -> 256.5509 | N25: =N24*(1+Parameters!$B$25) -> 6841.3574 | O25: =I25 -> 62.168715 | P25: =J25+M25 -> 505.22577 | Q25: =K25+N25 -> 10571.48 | R25: =L25 -> 310.84358 | S25: =C24*Parameters!$C$6*O25+D24*Parameters!$C$7*(O25+P25)/2+E24*Parameters!$C$8*(O25+Q25)/2 -> 85684417 | T25: =C24*Parameters!$D$6*(O25+P25)/2+D24*Parameters!$D$7*P25+E24*Parameters!$D$8*(P25+Q25)/2 -> 89440467 | U25: =C24*Parameters!$E$6*(O25+Q25)/2+D24*Parameters!$E$7*(P25+Q25)/2+E24*Parameters!$E$8*Q25 -> 2.8595643e+08 | V25: =C24*Parameters!$F$6*(O25/2+R25)+D24*Parameters!$F$7*(P25/2+R25)+E24*Parameters!$F$8*(Q25/2+R25) -> 75999603 | W25: =S25+T25+U25+V25 -> 5.3708092e+08 | X25: =X24/(1+Parameters!$B$26) -> 0.62459705 | Y25: =W25*X25 -> 3.3545916e+08 | Z25: =Y25/G24 -> 471.06738
B26: 13 | C26: {=SUMPRODUCT($C25:$F25,TRANSPOSE(Parameters!C$6:C$9))} -> 518483.35 | D26: {=SUMPRODUCT($C25:$F25,TRANSPOSE(Parameters!D$6:D$9))} -> 107127.76 | E26: {=SUMPRODUCT($C25:$F25,TRANSPOSE(Parameters!E$6:E$9))} -> 39418.597 | F26: {=SUMPRODUCT($C25:$F25,TRANSPOSE(Parameters!F$6:F$9))} -> 334970.29 | G26: =SUM(C26:E26) -> 665029.71 | H26: =F26-F25 -> 23145.223 | I26: =I25*(1+Parameters!$B$24) -> 63.41209 | J26: =J25*(1+Parameters!$B$24) -> 253.64836 | K26: =K25*(1+Parameters!$B$24) -> 3804.7254 | L26: =L25*(1+Parameters!$B$24) -> 317.06045 | M26: =M25*(1+Parameters!$B$25) -> 269.37845 | N26: =N25*(1+Parameters!$B$25) -> 7183.4253 | O26: =I26 -> 63.41209 | P26: =J26+M26 -> 523.02681 | Q26: =K26+N26 -> 10988.151 | R26: =L26 -> 317.06045 | S26: =C25*Parameters!$C$6*O26+D25*Parameters!$C$7*(O26+P26)/2+E25*Parameters!$C$8*(O26+Q26)/2 -> 85406648 | T26: =C25*Parameters!$D$6*(O26+P26)/2+D25*Parameters!$D$7*P26+E25*Parameters!$D$8*(P26+Q26)/2 -> 89662611 | U26: =C25*Parameters!$E$6*(O26+Q26)/2+D25*Parameters!$E$7*(P26+Q26)/2+E25*Parameters!$E$8*Q26 -> 2.8720984e+08 | V26: =C25*Parameters!$F$6*(O26/2+R26)+D25*Parameters!$F$7*(P26/2+R26)+E25*Parameters!$F$8*(Q26/2+R26) -> 76189791 | W26: =S26+T26+U26+V26 -> 5.3846889e+08 | X26: =X25/(1+Parameters!$B$26) -> 0.60057409 | Y26: =W26*X26 -> 3.2339046e+08 | Z26: =Y26/G25 -> 469.92479
... B43: 30 | C43: {=SUMPRODUCT($C42:$F42,TRANSPOSE(Parameters!C$6:C$9))} -> 289835.72 | D43: {=SUMPRODUCT($C42:$F42,TRANSPOSE(Parameters!D$6:D$9))} -> 59885.155 | E43: {=SUMPRODUCT($C42:$F42,TRANSPOSE(Parameters!E$6:E$9))} -> 22035.279 | F43: {=SUMPRODUCT($C42:$F42,TRANSPOSE(Parameters!F$6:F$9))} -> 628243.85 | G43: =SUM(C43:E43) -> 371756.15 | H43: =F43-F42 -> 12938.351 | I43: =I42*(1+Parameters!$B$24) -> 88.792235 | J43: =J42*(1+Parameters!$B$24) -> 355.16894 | K43: =K42*(1+Parameters!$B$24) -> 5327.5341 | L43: =L42*(1+Parameters!$B$24) -> 443.96117 | M43: =M42*(1+Parameters!$B$25) -> 617.42034 | N43: =N42*(1+Parameters!$B$25) -> 16464.542 | O43: =I43 -> 88.792235 | P43: =J43+M43 -> 972.58928 | Q43: =K43+N43 -> 21792.076 | R43: =L43 -> 443.96117 | S43: =C42*Parameters!$C$6*O43+D42*Parameters!$C$7*(O43+P43)/2+E42*Parameters!$C$8*(O43+Q43)/2 -> 83389451 | T43: =C42*Parameters!$D$6*(O43+P43)/2+D42*Parameters!$D$7*P43+E42*Parameters!$D$8*(P43+Q43)/2 -> 96379188 | U43: =C42*Parameters!$E$6*(O43+Q43)/2+D42*Parameters!$E$7*(P43+Q43)/2+E42*Parameters!$E$8*Q43 -> 3.1804626e+08 | V43: =C42*Parameters!$F$6*(O43/2+R43)+D42*Parameters!$F$7*(P43/2+R43)+E42*Parameters!$F$8*(Q43/2+R43) -> 81920075 | W43: =S43+T43+U43+V43 -> 5.7973498e+08 | X43: =X42/(1+Parameters!$B$26) -> 0.30831867 | Y43: =W43*X43 -> 1.7874312e+08 | Z43: =Y43/G42 -> 464.63652

Sheet Alt Scenario_1
A1: Alternative position - allowing for alternative drugs
C5: Different formulae - do not drag
Y8: Total PV
G9: Total | Y9: =SUM(Y13:Y43) -> 1.01543e+10
G10: =SUM(G14:G43) -> 20149312
I11: Overheads | M11: Drug | O11: Combined cost | S11: Cost per state x population | W11: Total cost | X11: v | Y11: PV of cost | Z11: Real cost per life alive
B12: Year | C12: Healthy | D12: Sick | E12: Very sick | F12: Dead | G12: Lives alive | H12: Excess deaths | I12: H | J12: S | K12: I | L12: D | M12: S | N12: I | O12: H | P12: S | Q12: I | R12: D | S12: H | T12: S | U12: I | V12: D
B13: 0 | C13: =Parameters!B12 -> 1000000 | D13: =Parameters!C12 -> 0 | E13: =Parameters!D12 -> 0 | F13: =Parameters!E12 -> 0 | G13: =SUM(C13:E13) -> 1000000 | H13: =F13 -> 0 | W13: =C13*O13+D13*P13+E13*Q13+H13*R13 -> 0 | X13: 1 | Y13: =W13*X13 -> 0
B14: 1 | C14: {=SUMPRODUCT($C13:$F13,TRANSPOSE(Parameters!C$6:C$9))+($B14-1)*SUMPRODUCT($C13:$F13,TRANSPOSE(Parameters!C$32:C$35))} -> 800000 | D14: {=SUMPRODUCT($C13:$F13,TRANSPOSE(Parameters!D$6:D$9))+($B14-1)*SUMPRODUCT($C13:$F13,TRANSPOSE(Parameters!D$32:D$35))} -> 160000 | E14: {=SUMPRODUCT($C13:$F13,TRANSPOSE(Parameters!E$6:E$9))+($B14-1)*SUMPRODUCT($C13:$F13,TRANSPOSE(Parameters!E$32:E$35))} -> 30000 | F14: {=SUMPRODUCT($C13:$F13,TRANSPOSE(Parameters!F$6:F$9))+($B14-1)*SUMPRODUCT($C13:$F13,TRANSPOSE(Parameters!F$32:F$35))} -> 10000 | G14: =SUM(C14:E14) -> 990000 | H14: =F14-F13 -> 10000 | I14: =Parameters!B15 -> 50 | J14: =Parameters!B16 -> 200 | K14: =Parameters!B17 -> 3000 | L14: =Parameters!B18 -> 250 | M14: =Parameters!B37 -> 250 | N14: =Parameters!B38 -> 6000 | O14: =I14 -> 50 | P14: =J14+M14 -> 450 | Q14: =K14+N14 -> 9000 | R14: =L14 -> 250 | S14: =C13*(Parameters!$C$6+($B14-1)*Parameters!$C$32)*O14+D13*(Parameters!$C$7+($B14-1)*Parameters!$C$33)*(O14+P14)/2+E13*(Parameters!$C$8+($B14-1)*Parameters!$C$34)*(O14+Q14)/2 -> 40000000 | T14: =C13*(Parameters!$D$6+($B14-1)*Parameters!$D$32)*(O14+P14)/2+D13*(Parameters!$D$7+($B14-1)*Parameters!$D$33)*P14+E13*(Parameters!$D$8+($B14-1)*Parameters!$D$34)*(P14+Q14)/2 -> 40000000 | U14: =C13*(Parameters!$E$6+($B14-1)*Parameters!$E$32)*(O14+Q14)/2+D13*(Parameters!$E$7+($B14-1)*Parameters!$E$33)*(P14+Q14)/2+E13*(Parameters!$E$8+($B14-1)*Parameters!$E$34)*Q14 -> 135750000 | V14: =C13*(Parameters!$F$6+($B14-1)*Parameters!$F$32)*(O14/2+R14)+D13*(Parameters!$F$7+($B14-1)*Parameters!$F$33)*(P14/2+R14)+E13*(Parameters!$F$8+($B14-1)*Parameters!$F$34)*(Q14/2+R14) -> 2750000 | W14: =S14+T14+U14+V14 -> 218500000 | X14: =1/(1+Parameters!$B$26) -> 0.96153846 | Y14: =W14*X14 -> 2.1009615e+08 | Z14: =Y14/G13 -> 210.09615
B15: 2 | C15: {=SUMPRODUCT($C14:$F14,TRANSPOSE(Parameters!C$6:C$9))+($B15-1)*SUMPRODUCT($C14:$F14,TRANSPOSE(Parameters!C$32:C$35))} -> 766059 | D15: {=SUMPRODUCT($C14:$F14,TRANSPOSE(Parameters!D$6:D$9))+($B15-1)*SUMPRODUCT($C14:$F14,TRANSPOSE(Parameters!D$32:D$35))} -> 150650 | E15: {=SUMPRODUCT($C14:$F14,TRANSPOSE(Parameters!E$6:E$9))+($B15-1)*SUMPRODUCT($C14:$F14,TRANSPOSE(Parameters!E$32:E$35))} -> 48442.2 | F15: {=SUMPRODUCT($C14:$F14,TRANSPOSE(Parameters!F$6:F$9))+($B15-1)*SUMPRODUCT($C14:$F14,TRANSPOSE(Parameters!F$32:F$35))} -> 34848.8 | G15: =SUM(C15:E15) -> 965151.2 | H15: =F15-F14 -> 24848.8 | I15: =I14*(1+Parameters!$B$24) -> 51 | J15: =J14*(1+Parameters!$B$24) -> 204 | K15: =K14*(1+Parameters!$B$24) -> 3060 | L15: =L14*(1+Parameters!$B$24) -> 255 | M15: =M14*(1+Parameters!$B$25) -> 262.5 | N15: =N14*(1+Parameters!$B$25) -> 6300 | O15: =I15 -> 51 | P15: =J15+M15 -> 466.5 | Q15: =K15+N15 -> 9360 | R15: =L15 -> 255 | S15: =C14*(Parameters!$C$6+($B15-1)*Parameters!$C$32)*O15+D14*(Parameters!$C$7+($B15-1)*Parameters!$C$33)*(O15+P15)/2+E14*(Parameters!$C$8+($B15-1)*Parameters!$C$34)*(O15+Q15)/2 -> 85035682 | T15: =C14*(Parameters!$D$6+($B15-1)*Parameters!$D$32)*(O15+P15)/2+D14*(Parameters!$D$7+($B15-1)*Parameters!$D$33)*P15+E14*(Parameters!$D$8+($B15-1)*Parameters!$D$34)*(P15+Q15)/2 -> 77369692 | U15: =C14*(Parameters!$E$6+($B15-1)*Parameters!$E$32)*(O15+Q15)/2+D14*(Parameters!$E$7+($B15-1)*Parameters!$E$33)*(P15+Q15)/2+E14*(Parameters!$E$8+($B15-1)*Parameters!$E$34)*Q15 -> 2.732015e+08 | V15: =C14*(Parameters!$F$6+($B15-1)*Parameters!$F$32)*(O15/2+R15)+D14*(Parameters!$F$7+($B15-1)*Parameters!$F$33)*(P15/2+R15)+E14*(Parameters!$F$8+($B15-1)*Parameters!$F$34)*(Q15/2+R15) -> 50232682 | W15: =S15+T15+U15+V15 -> 485839557 | X15: =X14/(1+Parameters!$B$26) -> 0.92455621 | Y15: =W15*X15 -> 4.4918598e+08 | Z15: =Y15/G14 -> 453.72321
B16: 3 | C16: {=SUMPRODUCT($C15:$F15,TRANSPOSE(Parameters!C$6:C$9))+($B16-1)*SUMPRODUCT($C15:$F15,TRANSPOSE(Parameters!C$32:C$35))} -> 736103.13 | D16: {=SUMPRODUCT($C15:$F15,TRANSPOSE(Parameters!D$6:D$9))+($B16-1)*SUMPRODUCT($C15:$F15,TRANSPOSE(Parameters!D$32:D$35))} -> 148153.98 | E16: {=SUMPRODUCT($C15:$F15,TRANSPOSE(Parameters!E$6:E$9))+($B16-1)*SUMPRODUCT($C15:$F15,TRANSPOSE(Parameters!E$32:E$35))} -> 51535.128 | F16: {=SUMPRODUCT($C15:$F15,TRANSPOSE(Parameters!F$6:F$9))+($B16-1)*SUMPRODUCT($C15:$F15,TRANSPOSE(Parameters!F$32:F$35))} -> 64207.759 | G16: =SUM(C16:E16) -> 935792.24 | H16: =F16-F15 -> 29358.959 | I16: =I15*(1+Parameters!$B$24) -> 52.02 | J16: =J15*(1+Parameters!$B$24) -> 208.08 | K16: =K15*(1+Parameters!$B$24) -> 3121.2 | L16: =L15*(1+Parameters!$B$24) -> 260.1 | M16: =M15*(1+Parameters!$B$25) -> 275.625 | N16: =N15*(1+Parameters!$B$25) -> 6615 | O16: =I16 -> 52.02 | P16: =J16+M16 -> 483.705 | Q16: =K16+N16 -> 9736.2 | R16: =L16 -> 260.1 | S16: =C15*(Parameters!$C$6+($B16-1)*Parameters!$C$32)*O16+D15*(Parameters!$C$7+($B16-1)*Parameters!$C$33)*(O16+P16)/2+E15*(Parameters!$C$8+($B16-1)*Parameters!$C$34)*(O16+Q16)/2 -> 98140646 | T16: =C15*(Parameters!$D$6+($B16-1)*Parameters!$D$32)*(O16+P16)/2+D15*(Parameters!$D$7+($B16-1)*Parameters!$D$33)*P16+E15*(Parameters!$D$8+($B16-1)*Parameters!$D$34)*(P16+Q16)/2 -> 1.0207858e+08 | U16: =C15*(Parameters!$E$6+($B16-1)*Parameters!$E$32)*(O16+Q16)/2+D15*(Parameters!$E$7+($B16-1)*Parameters!$E$33)*(P16+Q16)/2+E15*(Parameters!$E$8+($B16-1)*Parameters!$E$34)*Q16 -> 3.2601929e+08 | V16: =C15*(Parameters!$F$6+($B16-1)*Parameters!$F$32)*(O16/2+R16)+D15*(Parameters!$F$7+($B16-1)*Parameters!$F$33)*(P16/2+R16)+E15*(Parameters!$F$8+($B16-1)*Parameters!$F$34)*(Q16/2+R16) -> 79435116 | W16: =S16+T16+U16+V16 -> 6.0567362e+08 | X16: =X15/(1+Parameters!$B$26) -> 0.88899636 | Y16: =W16*X16 -> 5.3844165e+08 | Z16: =Y16/G15 -> 557.88321
B17: 4 | C17: {=SUMPRODUCT($C16:$F16,TRANSPOSE(Parameters!C$6:C$9))+($B17-1)*SUMPRODUCT($C16:$F16,TRANSPOSE(Parameters!C$32:C$35))} -> 712069.42 | D17: {=SUMPRODUCT($C16:$F16,TRANSPOSE(Parameters!D$6:D$9))+($B17-1)*SUMPRODUCT($C16:$F16,TRANSPOSE(Parameters!D$32:D$35))} -> 143202.55 | E17: {=SUMPRODUCT($C16:$F16,TRANSPOSE(Parameters!E$6:E$9))+($B17-1)*SUMPRODUCT($C16:$F16,TRANSPOSE(Parameters!E$32:E$35))} -> 50852.86 | F17: {=SUMPRODUCT($C16:$F16,TRANSPOSE(Parameters!F$6:F$9))+($B17-1)*SUMPRODUCT($C16:$F16,TRANSPOSE(Parameters!F$32:F$35))} -> 93875.174 | G17: =SUM(C17:E17) -> 906124.83 | H17: =F17-F16 -> 29667.415 | I17: =I16*(1+Parameters!$B$24) -> 53.0604 | J17: =J16*(1+Parameters!$B$24) -> 212.2416 | K17: =K16*(1+Parameters!$B$24) -> 3183.624 | L17: =L16*(1+Parameters!$B$24) -> 265.302 | M17: =M16*(1+Parameters!$B$25) -> 289.40625 | N17: =N16*(1+Parameters!$B$25) -> 6945.75 | O17: =I17 -> 53.0604 | P17: =J17+M17 -> 501.64785 | Q17: =K17+N17 -> 10129.374 | R17: =L17 -> 265.302 | S17: =C16*(Parameters!$C$6+($B17-1)*Parameters!$C$32)*O17+D16*(Parameters!$C$7+($B17-1)*Parameters!$C$33)*(O17+P17)/2+E16*(Parameters!$C$8+($B17-1)*Parameters!$C$34)*(O17+Q17)/2 -> 1.0210576e+08 | T17: =C16*(Parameters!$D$6+($B17-1)*Parameters!$D$32)*(O17+P17)/2+D16*(Parameters!$D$7+($B17-1)*Parameters!$D$33)*P17+E16*(Parameters!$D$8+($B17-1)*Parameters!$D$34)*(P17+Q17)/2 -> 1.087801e+08 | U17: =C16*(Parameters!$E$6+($B17-1)*Parameters!$E$32)*(O17+Q17)/2+D16*(Parameters!$E$7+($B17-1)*Parameters!$E$33)*(P17+Q17)/2+E16*(Parameters!$E$8+($B17-1)*Parameters!$E$34)*Q17 -> 3.4042529e+08 | V17: =C16*(Parameters!$F$6+($B17-1)*Parameters!$F$32)*(O17/2+R17)+D16*(Parameters!$F$7+($B17-1)*Parameters!$F$33)*(P17/2+R17)+E16*(Parameters!$F$8+($B17-1)*Parameters!$F$34)*(Q17/2+R17) -> 86622271 | W17: =S17+T17+U17+V17 -> 6.3793343e+08 | X17: =X16/(1+Parameters!$B$26) -> 0.85480419 | Y17: =W17*X17 -> 5.4530817e+08 | Z17: =Y17/G16 -> 582.72354
B18: 5 | C18: {=SUMPRODUCT($C17:$F17,TRANSPOSE(Parameters!C$6:C$9))+($B18-1)*SUMPRODUCT($C17:$F17,TRANSPOSE(Parameters!C$32:C$35))} -> 690286.31 | D18: {=SUMPRODUCT($C17:$F17,TRANSPOSE(Parameters!D$6:D$9))+($B18-1)*SUMPRODUCT($C17:$F17,TRANSPOSE(Parameters!D$32:D$35))} -> 138036.46 | E18: {=SUMPRODUCT($C17:$F17,TRANSPOSE(Parameters!E$6:E$9))+($B18-1)*SUMPRODUCT($C17:$F17,TRANSPOSE(Parameters!E$32:E$35))} -> 48997.916 | F18: {=SUMPRODUCT($C17:$F17,TRANSPOSE(Parameters!F$6:F$9))+($B18-1)*SUMPRODUCT($C17:$F17,TRANSPOSE(Parameters!F$32:F$35))} -> 122679.32 | G18: =SUM(C18:E18) -> 877320.68 | H18: =F18-F17 -> 28804.143 | I18: =I17*(1+Parameters!$B$24) -> 54.121608 | J18: =J17*(1+Parameters!$B$24) -> 216.48643 | K18: =K17*(1+Parameters!$B$24) -> 3247.2965 | L18: =L17*(1+Parameters!$B$24) -> 270.60804 | M18: =M17*(1+Parameters!$B$25) -> 303.87656 | N18: =N17*(1+Parameters!$B$25) -> 7293.0375 | O18: =I18 -> 54.121608 | P18: =J18+M18 -> 520.36299 | Q18: =K18+N18 -> 10540.334 | R18: =L18 -> 270.60804 | S18: =C17*(Parameters!$C$6+($B18-1)*Parameters!$C$32)*O18+D17*(Parameters!$C$7+($B18-1)*Parameters!$C$33)*(O18+P18)/2+E17*(Parameters!$C$8+($B18-1)*Parameters!$C$34)*(O18+Q18)/2 -> 1.0301111e+08 | T18: =C17*(Parameters!$D$6+($B18-1)*Parameters!$D$32)*(O18+P18)/2+D17*(Parameters!$D$7+($B18-1)*Parameters!$D$33)*P18+E17*(Parameters!$D$8+($B18-1)*Parameters!$D$34)*(P18+Q18)/2 -> 1.1077827e+08 | U18: =C17*(Parameters!$E$6+($B18-1)*Parameters!$E$32)*(O18+Q18)/2+D17*(Parameters!$E$7+($B18-1)*Parameters!$E$33)*(P18+Q18)/2+E17*(Parameters!$E$8+($B18-1)*Parameters!$E$34)*Q18 -> 3.4330197e+08 | V18: =C17*(Parameters!$F$6+($B18-1)*Parameters!$F$32)*(O18/2+R18)+D17*(Parameters!$F$7+($B18-1)*Parameters!$F$33)*(P18/2+R18)+E17*(Parameters!$F$8+($B18-1)*Parameters!$F$34)*(Q18/2+R18) -> 88055607 | W18: =S18+T18+U18+V18 -> 6.4514695e+08 | X18: =X17/(1+Parameters!$B$26) -> 0.82192711 | Y18: =W18*X18 -> 5.3026377e+08 | Z18: =Y18/G17 -> 585.19947
B19: 6 | C19: {=SUMPRODUCT($C18:$F18,TRANSPOSE(Parameters!C$6:C$9))+($B19-1)*SUMPRODUCT($C18:$F18,TRANSPOSE(Parameters!C$32:C$35))} -> 669889.77 | D19: {=SUMPRODUCT($C18:$F18,TRANSPOSE(Parameters!D$6:D$9))+($B19-1)*SUMPRODUCT($C18:$F18,TRANSPOSE(Parameters!D$32:D$35))} -> 132947.3 | E19: {=SUMPRODUCT($C18:$F18,TRANSPOSE(Parameters!E$6:E$9))+($B19-1)*SUMPRODUCT($C18:$F18,TRANSPOSE(Parameters!E$32:E$35))} -> 46862.966 | F19: {=SUMPRODUCT($C18:$F18,TRANSPOSE(Parameters!F$6:F$9))+($B19-1)*SUMPRODUCT($C18:$F18,TRANSPOSE(Parameters!F$32:F$35))} -> 150299.97 | G19: =SUM(C19:E19) -> 849700.03 | H19: =F19-F18 -> 27620.652 | I19: =I18*(1+Parameters!$B$24) -> 55.20404 | J19: =J18*(1+Parameters!$B$24) -> 220.81616 | K19: =K18*(1+Parameters!$B$24) -> 3312.2424 | L19: =L18*(1+Parameters!$B$24) -> 276.0202 | M19: =M18*(1+Parameters!$B$25) -> 319.07039 | N19: =N18*(1+Parameters!$B$25) -> 7657.6894 | O19: =I19 -> 55.20404 | P19: =J19+M19 -> 539.88655 | Q19: =K19+N19 -> 10969.932 | R19: =L19 -> 276.0202 | S19: =C18*(Parameters!$C$6+($B19-1)*Parameters!$C$32)*O19+D18*(Parameters!$C$7+($B19-1)*Parameters!$C$33)*(O19+P19)/2+E18*(Parameters!$C$8+($B19-1)*Parameters!$C$34)*(O19+Q19)/2 -> 1.029567e+08 | T19: =C18*(Parameters!$D$6+($B19-1)*Parameters!$D$32)*(O19+P19)/2+D18*(Parameters!$D$7+($B19-1)*Parameters!$D$33)*P19+E18*(Parameters!$D$8+($B19-1)*Parameters!$D$34)*(P19+Q19)/2 -> 1.1117353e+08 | U19: =C18*(Parameters!$E$6+($B19-1)*Parameters!$E$32)*(O19+Q19)/2+D18*(Parameters!$E$7+($B19-1)*Parameters!$E$33)*(P19+Q19)/2+E18*(Parameters!$E$8+($B19-1)*Parameters!$E$34)*Q19 -> 3.4242999e+08 | V19: =C18*(Parameters!$F$6+($B19-1)*Parameters!$F$32)*(O19/2+R19)+D18*(Parameters!$F$7+($B19-1)*Parameters!$F$33)*(P19/2+R19)+E18*(Parameters!$F$8+($B19-1)*Parameters!$F$34)*(Q19/2+R19) -> 87551159 | W19: =S19+T19+U19+V19 -> 6.4411137e+08 | X19: =X18/(1+Parameters!$B$26) -> 0.79031453 | Y19: =W19*X19 -> 5.0905058e+08 | Z19: =Y19/G18 -> 580.23319
B20: 7 | C20: {=SUMPRODUCT($C19:$F19,TRANSPOSE(Parameters!C$6:C$9))+($B20-1)*SUMPRODUCT($C19:$F19,TRANSPOSE(Parameters!C$32:C$35))} -> 650545.62 | D20: {=SUMPRODUCT($C19:$F19,TRANSPOSE(Parameters!D$6:D$9))+($B20-1)*SUMPRODUCT($C19:$F19,TRANSPOSE(Parameters!D$32:D$35))} -> 128049.65 | E20: {=SUMPRODUCT($C19:$F19,TRANSPOSE(Parameters!E$6:E$9))+($B20-1)*SUMPRODUCT($C19:$F19,TRANSPOSE(Parameters!E$32:E$35))} -> 44718.188 | F20: {=SUMPRODUCT($C19:$F19,TRANSPOSE(Parameters!F$6:F$9))+($B20-1)*SUMPRODUCT($C19:$F19,TRANSPOSE(Parameters!F$32:F$35))} -> 176686.54 | G20: =SUM(C20:E20) -> 823313.46 | H20: =F20-F19 -> 26386.571 | I20: =I19*(1+Parameters!$B$24) -> 56.308121 | J20: =J19*(1+Parameters!$B$24) -> 225.23248 | K20: =K19*(1+Parameters!$B$24) -> 3378.4873 | L20: =L19*(1+Parameters!$B$24) -> 281.5406 | M20: =M19*(1+Parameters!$B$25) -> 335.02391 | N20: =N19*(1+Parameters!$B$25) -> 8040.5738 | O20: =I20 -> 56.308121 | P20: =J20+M20 -> 560.25639 | Q20: =K20+N20 -> 11419.061 | R20: =L20 -> 281.5406 | S20: =C19*(Parameters!$C$6+($B20-1)*Parameters!$C$32)*O20+D19*(Parameters!$C$7+($B20-1)*Parameters!$C$33)*(O20+P20)/2+E19*(Parameters!$C$8+($B20-1)*Parameters!$C$34)*(O20+Q20)/2 -> 1.0262177e+08 | T20: =C19*(Parameters!$D$6+($B20-1)*Parameters!$D$32)*(O20+P20)/2+D19*(Parameters!$D$7+($B20-1)*Parameters!$D$33)*P20+E19*(Parameters!$D$8+($B20-1)*Parameters!$D$34)*(P20+Q20)/2 -> 1.1108488e+08 | U20: =C19*(Parameters!$E$6+($B20-1)*Parameters!$E$32)*(O20+Q20)/2+D19*(Parameters!$E$7+($B20-1)*Parameters!$E$33)*(P20+Q20)/2+E19*(Parameters!$E$8+($B20-1)*Parameters!$E$34)*Q20 -> 3.4043454e+08 | V20: =C19*(Parameters!$F$6+($B20-1)*Parameters!$F$32)*(O20/2+R20)+D19*(Parameters!$F$7+($B20-1)*Parameters!$F$33)*(P20/2+R20)+E19*(Parameters!$F$8+($B20-1)*Parameters!$F$34)*(Q20/2+R20) -> 86461318 | W20: =S20+T20+U20+V20 -> 6.4060251e+08 | X20: =X19/(1+Parameters!$B$26) -> 0.75991781 | Y20: =W20*X20 -> 4.8680526e+08 | Z20: =Y20/G19 -> 572.91425
B21: 8 | C21: {=SUMPRODUCT($C20:$F20,TRANSPOSE(Parameters!C$6:C$9))+($B21-1)*SUMPRODUCT($C20:$F20,TRANSPOSE(Parameters!C$32:C$35))} -> 632117.48 | D21: {=SUMPRODUCT($C20:$F20,TRANSPOSE(Parameters!D$6:D$9))+($B21-1)*SUMPRODUCT($C20:$F20,TRANSPOSE(Parameters!D$32:D$35))} -> 123368.43 | E21: {=SUMPRODUCT($C20:$F20,TRANSPOSE(Parameters!E$6:E$9))+($B21-1)*SUMPRODUCT($C20:$F20,TRANSPOSE(Parameters!E$32:E$35))} -> 42644.734 | F21: {=SUMPRODUCT($C20:$F20,TRANSPOSE(Parameters!F$6:F$9))+($B21-1)*SUMPRODUCT($C20:$F20,TRANSPOSE(Parameters!F$32:F$35))} -> 201869.36 | G21: =SUM(C21:E21) -> 798130.64 | H21: =F21-F20 -> 25182.818 | I21: =I20*(1+Parameters!$B$24) -> 57.434283 | J21: =J20*(1+Parameters!$B$24) -> 229.73713 | K21: =K20*(1+Parameters!$B$24) -> 3446.057 | L21: =L20*(1+Parameters!$B$24) -> 287.17142 | M21: =M20*(1+Parameters!$B$25) -> 351.77511 | N21: =N20*(1+Parameters!$B$25) -> 8442.6025 | O21: =I21 -> 57.434283 | P21: =J21+M21 -> 581.51224 | Q21: =K21+N21 -> 11888.66 | R21: =L21 -> 287.17142 | S21: =C20*(Parameters!$C$6+($B21-1)*Parameters!$C$32)*O21+D20*(Parameters!$C$7+($B21-1)*Parameters!$C$33)*(O21+P21)/2+E20*(Parameters!$C$8+($B21-1)*Parameters!$C$34)*(O21+Q21)/2 -> 1.0222958e+08 | T21: =C20*(Parameters!$D$6+($B21-1)*Parameters!$D$32)*(O21+P21)/2+D20*(Parameters!$D$7+($B21-1)*Parameters!$D$33)*P21+E20*(Parameters!$D$8+($B21-1)*Parameters!$D$34)*(P21+Q21)/2 -> 1.1087137e+08 | U21: =C20*(Parameters!$E$6+($B21-1)*Parameters!$E$32)*(O21+Q21)/2+D20*(Parameters!$E$7+($B21-1)*Parameters!$E$33)*(P21+Q21)/2+E20*(Parameters!$E$8+($B21-1)*Parameters!$E$34)*Q21 -> 3.3816597e+08 | V21: =C20*(Parameters!$F$6+($B21-1)*Parameters!$F$32)*(O21/2+R21)+D20*(Parameters!$F$7+($B21-1)*Parameters!$F$33)*(P21/2+R21)+E20*(Parameters!$F$8+($B21-1)*Parameters!$F$34)*(Q21/2+R21) -> 85214649 | W21: =S21+T21+U21+V21 -> 6.3648157e+08 | X21: =X20/(1+Parameters!$B$26) -> 0.73069021 | Y21: =W21*X21 -> 4.6507085e+08 | Z21: =Y21/G20 -> 564.87701
B22: 9 | C22: {=SUMPRODUCT($C21:$F21,TRANSPOSE(Parameters!C$6:C$9))+($B22-1)*SUMPRODUCT($C21:$F21,TRANSPOSE(Parameters!C$32:C$35))} -> 614531.6 | D22: {=SUMPRODUCT($C21:$F21,TRANSPOSE(Parameters!D$6:D$9))+($B22-1)*SUMPRODUCT($C21:$F21,TRANSPOSE(Parameters!D$32:D$35))} -> 118903.13 | E22: {=SUMPRODUCT($C21:$F21,TRANSPOSE(Parameters!E$6:E$9))+($B22-1)*SUMPRODUCT($C21:$F21,TRANSPOSE(Parameters!E$32:E$35))} -> 40663.883 | F22: {=SUMPRODUCT($C21:$F21,TRANSPOSE(Parameters!F$6:F$9))+($B22-1)*SUMPRODUCT($C21:$F21,TRANSPOSE(Parameters!F$32:F$35))} -> 225901.39 | G22: =SUM(C22:E22) -> 774098.61 | H22: =F22-F21 -> 24032.031 | I22: =I21*(1+Parameters!$B$24) -> 58.582969 | J22: =J21*(1+Parameters!$B$24) -> 234.33188 | K22: =K21*(1+Parameters!$B$24) -> 3514.9781 | L22: =L21*(1+Parameters!$B$24) -> 292.91485 | M22: =M21*(1+Parameters!$B$25) -> 369.36386 | N22: =N21*(1+Parameters!$B$25) -> 8864.7327 | O22: =I22 -> 58.582969 | P22: =J22+M22 -> 603.69574 | Q22: =K22+N22 -> 12379.711 | R22: =L22 -> 292.91485 | S22: =C21*(Parameters!$C$6+($B22-1)*Parameters!$C$32)*O22+D21*(Parameters!$C$7+($B22-1)*Parameters!$C$33)*(O22+P22)/2+E21*(Parameters!$C$8+($B22-1)*Parameters!$C$34)*(O22+Q22)/2 -> 1.0185278e+08 | T22: =C21*(Parameters!$D$6+($B22-1)*Parameters!$D$32)*(O22+P22)/2+D21*(Parameters!$D$7+($B22-1)*Parameters!$D$33)*P22+E21*(Parameters!$D$8+($B22-1)*Parameters!$D$34)*(P22+Q22)/2 -> 1.1065112e+08 | U22: =C21*(Parameters!$E$6+($B22-1)*Parameters!$E$32)*(O22+Q22)/2+D21*(Parameters!$E$7+($B22-1)*Parameters!$E$33)*(P22+Q22)/2+E21*(Parameters!$E$8+($B22-1)*Parameters!$E$34)*Q22 -> 3.3589943e+08 | V22: =C21*(Parameters!$F$6+($B22-1)*Parameters!$F$32)*(O22/2+R22)+D21*(Parameters!$F$7+($B22-1)*Parameters!$F$33)*(P22/2+R22)+E21*(Parameters!$F$8+($B22-1)*Parameters!$F$34)*(Q22/2+R22) -> 83949669 | W22: =S22+T22+U22+V22 -> 6.3235299e+08 | X22: =X21/(1+Parameters!$B$26) -> 0.70258674 | Y22: =W22*X22 -> 4.4428282e+08 | Z22: =Y22/G21 -> 556.65426
B23: 10 | C23: {=SUMPRODUCT($C22:$F22,TRANSPOSE(Parameters!C$6:C$9))+($B23-1)*SUMPRODUCT($C22:$F22,TRANSPOSE(Parameters!C$32:C$35))} -> 597736.19 | D23: {=SUMPRODUCT($C22:$F22,TRANSPOSE(Parameters!D$6:D$9))+($B23-1)*SUMPRODUCT($C22:$F22,TRANSPOSE(Parameters!D$32:D$35))} -> 114645.44 | E23: {=SUMPRODUCT($C22:$F22,TRANSPOSE(Parameters!E$6:E$9))+($B23-1)*SUMPRODUCT($C22:$F22,TRANSPOSE(Parameters!E$32:E$35))} -> 38778.275 | F23: {=SUMPRODUCT($C22:$F22,TRANSPOSE(Parameters!F$6:F$9))+($B23-1)*SUMPRODUCT($C22:$F22,TRANSPOSE(Parameters!F$32:F$35))} -> 248840.1 | G23: =SUM(C23:E23) -> 751159.9 | H23: =F23-F22 -> 22938.707 | I23: =I22*(1+Parameters!$B$24) -> 59.754628 | J23: =J22*(1+Parameters!$B$24) -> 239.01851 | K23: =K22*(1+Parameters!$B$24) -> 3585.2777 | L23: =L22*(1+Parameters!$B$24) -> 298.77314 | M23: =M22*(1+Parameters!$B$25) -> 387.83205 | N23: =N22*(1+Parameters!$B$25) -> 9307.9693 | O23: =I23 -> 59.754628 | P23: =J23+M23 -> 626.85057 | Q23: =K23+N23 -> 12893.247 | R23: =L23 -> 298.77314 | S23: =C22*(Parameters!$C$6+($B23-1)*Parameters!$C$32)*O23+D22*(Parameters!$C$7+($B23-1)*Parameters!$C$33)*(O23+P23)/2+E22*(Parameters!$C$8+($B23-1)*Parameters!$C$34)*(O23+Q23)/2 -> 1.0151445e+08 | T23: =C22*(Parameters!$D$6+($B23-1)*Parameters!$D$32)*(O23+P23)/2+D22*(Parameters!$D$7+($B23-1)*Parameters!$D$33)*P23+E22*(Parameters!$D$8+($B23-1)*Parameters!$D$34)*(P23+Q23)/2 -> 1.1046209e+08 | U23: =C22*(Parameters!$E$6+($B23-1)*Parameters!$E$32)*(O23+Q23)/2+D22*(Parameters!$E$7+($B23-1)*Parameters!$E$33)*(P23+Q23)/2+E22*(Parameters!$E$8+($B23-1)*Parameters!$E$34)*Q23 -> 3.3372029e+08 | V23: =C22*(Parameters!$F$6+($B23-1)*Parameters!$F$32)*(O23/2+R23)+D22*(Parameters!$F$7+($B23-1)*Parameters!$F$33)*(P23/2+R23)+E22*(Parameters!$F$8+($B23-1)*Parameters!$F$34)*(Q23/2+R23) -> 82709664 | W23: =S23+T23+U23+V23 -> 6.2840649e+08 | X23: =X22/(1+Parameters!$B$26) -> 0.67556417 | Y23: =W23*X23 -> 4.2452891e+08 | Z23: =Y23/G22 -> 548.41709
B24: 11 | C24: {=SUMPRODUCT($C23:$F23,TRANSPOSE(Parameters!C$6:C$9))+($B24-1)*SUMPRODUCT($C23:$F23,TRANSPOSE(Parameters!C$32:C$35))} -> 581688.11 | D24: {=SUMPRODUCT($C23:$F23,TRANSPOSE(Parameters!D$6:D$9))+($B24-1)*SUMPRODUCT($C23:$F23,TRANSPOSE(Parameters!D$32:D$35))} -> 110585.08 | E24: {=SUMPRODUCT($C23:$F23,TRANSPOSE(Parameters!E$6:E$9))+($B24-1)*SUMPRODUCT($C23:$F23,TRANSPOSE(Parameters!E$32:E$35))} -> 36984.897 | F24: {=SUMPRODUCT($C23:$F23,TRANSPOSE(Parameters!F$6:F$9))+($B24-1)*SUMPRODUCT($C23:$F23,TRANSPOSE(Parameters!F$32:F$35))} -> 270741.91 | G24: =SUM(C24:E24) -> 729258.09 | H24: =F24-F23 -> 21901.817 | I24: =I23*(1+Parameters!$B$24) -> 60.949721 | J24: =J23*(1+Parameters!$B$24) -> 243.79888 | K24: =K23*(1+Parameters!$B$24) -> 3656.9833 | L24: =L23*(1+Parameters!$B$24) -> 304.7486 | M24: =M23*(1+Parameters!$B$25) -> 407.22366 | N24: =N23*(1+Parameters!$B$25) -> 9773.3678 | O24: =I24 -> 60.949721 | P24: =J24+M24 -> 651.02254 | Q24: =K24+N24 -> 13430.351 | R24: =L24 -> 304.7486 | S24: =C23*(Parameters!$C$6+($B24-1)*Parameters!$C$32)*O24+D23*(Parameters!$C$7+($B24-1)*Parameters!$C$33)*(O24+P24)/2+E23*(Parameters!$C$8+($B24-1)*Parameters!$C$34)*(O24+Q24)/2 -> 1.012213e+08 | T24: =C23*(Parameters!$D$6+($B24-1)*Parameters!$D$32)*(O24+P24)/2+D23*(Parameters!$D$7+($B24-1)*Parameters!$D$33)*P24+E23*(Parameters!$D$8+($B24-1)*Parameters!$D$34)*(P24+Q24)/2 -> 1.1031584e+08 | U24: =C23*(Parameters!$E$6+($B24-1)*Parameters!$E$32)*(O24+Q24)/2+D23*(Parameters!$E$7+($B24-1)*Parameters!$E$33)*(P24+Q24)/2+E23*(Parameters!$E$8+($B24-1)*Parameters!$E$34)*Q24 -> 3.3165135e+08 | V24: =C23*(Parameters!$F$6+($B24-1)*Parameters!$F$32)*(O24/2+R24)+D23*(Parameters!$F$7+($B24-1)*Parameters!$F$33)*(P24/2+R24)+E23*(Parameters!$F$8+($B24-1)*Parameters!$F$34)*(Q24/2+R24) -> 81506919 | W24: =S24+T24+U24+V24 -> 6.2469541e+08 | X24: =X23/(1+Parameters!$B$26) -> 0.64958093 | Y24: =W24*X24 -> 4.0579023e+08 | Z24: =Y24/G23 -> 540.21817
B25: 12 | C25: {=SUMPRODUCT($C24:$F24,TRANSPOSE(Parameters!C$6:C$9))+($B25-1)*SUMPRODUCT($C24:$F24,TRANSPOSE(Parameters!C$32:C$35))} -> 566348.56 | D25: {=SUMPRODUCT($C24:$F24,TRANSPOSE(Parameters!D$6:D$9))+($B25-1)*SUMPRODUCT($C24:$F24,TRANSPOSE(Parameters!D$32:D$35))} -> 106711.6 | E25: {=SUMPRODUCT($C24:$F24,TRANSPOSE(Parameters!E$6:E$9))+($B25-1)*SUMPRODUCT($C24:$F24,TRANSPOSE(Parameters!E$32:E$35))} -> 35279.182 | F25: {=SUMPRODUCT($C24:$F24,TRANSPOSE(Parameters!F$6:F$9))+($B25-1)*SUMPRODUCT($C24:$F24,TRANSPOSE(Parameters!F$32:F$35))} -> 291660.66 | G25: =SUM(C25:E25) -> 708339.34 | H25: =F25-F24 -> 20918.749 | I25: =I24*(1+Parameters!$B$24) -> 62.168715 | J25: =J24*(1+Parameters!$B$24) -> 248.67486 | K25: =K24*(1+Parameters!$B$24) -> 3730.1229 | L25: =L24*(1+Parameters!$B$24) -> 310.84358 | M25: =M24*(1+Parameters!$B$25) -> 427.58484 | N25: =N24*(1+Parameters!$B$25) -> 10262.036 | O25: =I25 -> 62.168715 | P25: =J25+M25 -> 676.2597 | Q25: =K25+N25 -> 13992.159 | R25: =L25 -> 310.84358 | S25: =C24*(Parameters!$C$6+($B25-1)*Parameters!$C$32)*O25+D24*(Parameters!$C$7+($B25-1)*Parameters!$C$33)*(O25+P25)/2+E24*(Parameters!$C$8+($B25-1)*Parameters!$C$34)*(O25+Q25)/2 -> 1.0097467e+08 | T25: =C24*(Parameters!$D$6+($B25-1)*Parameters!$D$32)*(O25+P25)/2+D24*(Parameters!$D$7+($B25-1)*Parameters!$D$33)*P25+E24*(Parameters!$D$8+($B25-1)*Parameters!$D$34)*(P25+Q25)/2 -> 1.1021516e+08 | U25: =C24*(Parameters!$E$6+($B25-1)*Parameters!$E$32)*(O25+Q25)/2+D24*(Parameters!$E$7+($B25-1)*Parameters!$E$33)*(P25+Q25)/2+E24*(Parameters!$E$8+($B25-1)*Parameters!$E$34)*Q25 -> 3.2969474e+08 | V25: =C24*(Parameters!$F$6+($B25-1)*Parameters!$F$32)*(O25/2+R25)+D24*(Parameters!$F$7+($B25-1)*Parameters!$F$33)*(P25/2+R25)+E24*(Parameters!$F$8+($B25-1)*Parameters!$F$34)*(Q25/2+R25) -> 80343614 | W25: =S25+T25+U25+V25 -> 6.2122818e+08 | X25: =X24/(1+Parameters!$B$26) -> 0.62459705 | Y25: =W25*X25 -> 3.8801729e+08 | Z25: =Y25/G24 -> 532.07129
B26: 13 | C26: {=SUMPRODUCT($C25:$F25,TRANSPOSE(Parameters!C$6:C$9))+($B26-1)*SUMPRODUCT($C25:$F25,TRANSPOSE(Parameters!C$32:C$35))} -> 551681.58 | D26: {=SUMPRODUCT($C25:$F25,TRANSPOSE(Parameters!D$6:D$9))+($B26-1)*SUMPRODUCT($C25:$F25,TRANSPOSE(Parameters!D$32:D$35))} -> 103014.93 | E26: {=SUMPRODUCT($C25:$F25,TRANSPOSE(Parameters!E$6:E$9))+($B26-1)*SUMPRODUCT($C25:$F25,TRANSPOSE(Parameters!E$32:E$35))} -> 33656.298 | F26: {=SUMPRODUCT($C25:$F25,TRANSPOSE(Parameters!F$6:F$9))+($B26-1)*SUMPRODUCT($C25:$F25,TRANSPOSE(Parameters!F$32:F$35))} -> 311647.2 | G26: =SUM(C26:E26) -> 688352.8 | H26: =F26-F25 -> 19986.538 | I26: =I25*(1+Parameters!$B$24) -> 63.41209 | J26: =J25*(1+Parameters!$B$24) -> 253.64836 | K26: =K25*(1+Parameters!$B$24) -> 3804.7254 | L26: =L25*(1+Parameters!$B$24) -> 317.06045 | M26: =M25*(1+Parameters!$B$25) -> 448.96408 | N26: =N25*(1+Parameters!$B$25) -> 10775.138 | O26: =I26 -> 63.41209 | P26: =J26+M26 -> 702.61244 | Q26: =K26+N26 -> 14579.863 | R26: =L26 -> 317.06045 | S26: =C25*(Parameters!$C$6+($B26-1)*Parameters!$C$32)*O26+D25*(Parameters!$C$7+($B26-1)*Parameters!$C$33)*(O26+P26)/2+E25*(Parameters!$C$8+($B26-1)*Parameters!$C$34)*(O26+Q26)/2 -> 1.0077411e+08 | T26: =C25*(Parameters!$D$6+($B26-1)*Parameters!$D$32)*(O26+P26)/2+D25*(Parameters!$D$7+($B26-1)*Parameters!$D$33)*P26+E25*(Parameters!$D$8+($B26-1)*Parameters!$D$34)*(P26+Q26)/2 -> 1.1015995e+08 | U26: =C25*(Parameters!$E$6+($B26-1)*Parameters!$E$32)*(O26+Q26)/2+D25*(Parameters!$E$7+($B26-1)*Parameters!$E$33)*(P26+Q26)/2+E25*(Parameters!$E$8+($B26-1)*Parameters!$E$34)*Q26 -> 3.2784571e+08 | V26: =C25*(Parameters!$F$6+($B26-1)*Parameters!$F$32)*(O26/2+R26)+D25*(Parameters!$F$7+($B26-1)*Parameters!$F$33)*(P26/2+R26)+E25*(Parameters!$F$8+($B26-1)*Parameters!$F$34)*(Q26/2+R26) -> 79218661 | W26: =S26+T26+U26+V26 -> 6.1799843e+08 | X26: =X25/(1+Parameters!$B$26) -> 0.60057409 | Y26: =W26*X26 -> 3.7115384e+08 | Z26: =Y26/G25 -> 523.97745
... B43: 30 | C43: {=SUMPRODUCT($C42:$F42,TRANSPOSE(Parameters!C$6:C$9))+($B43-1)*SUMPRODUCT($C42:$F42,TRANSPOSE(Parameters!C$32:C$35))} -> 378968.58 | D43: {=SUMPRODUCT($C42:$F42,TRANSPOSE(Parameters!D$6:D$9))+($B43-1)*SUMPRODUCT($C42:$F42,TRANSPOSE(Parameters!D$32:D$35))} -> 59805.317 | E43: {=SUMPRODUCT($C42:$F42,TRANSPOSE(Parameters!E$6:E$9))+($B43-1)*SUMPRODUCT($C42:$F42,TRANSPOSE(Parameters!E$32:E$35))} -> 15079.693 | F43: {=SUMPRODUCT($C42:$F42,TRANSPOSE(Parameters!F$6:F$9))+($B43-1)*SUMPRODUCT($C42:$F42,TRANSPOSE(Parameters!F$32:F$35))} -> 546146.41 | G43: =SUM(C43:E43) -> 453853.59 | H43: =F43-F42 -> 9640.0108 | I43: =I42*(1+Parameters!$B$24) -> 88.792235 | J43: =J42*(1+Parameters!$B$24) -> 355.16894 | K43: =K42*(1+Parameters!$B$24) -> 5327.5341 | L43: =L42*(1+Parameters!$B$24) -> 443.96117 | M43: =M42*(1+Parameters!$B$25) -> 1029.0339 | N43: =N42*(1+Parameters!$B$25) -> 24696.814 | O43: =I43 -> 88.792235 | P43: =J43+M43 -> 1384.2028 | Q43: =K43+N43 -> 30024.348 | R43: =L43 -> 443.96117 | S43: =C42*(Parameters!$C$6+($B43-1)*Parameters!$C$32)*O43+D42*(Parameters!$C$7+($B43-1)*Parameters!$C$33)*(O43+P43)/2+E42*(Parameters!$C$8+($B43-1)*Parameters!$C$34)*(O43+Q43)/2 -> 1.0329962e+08 | T43: =C42*(Parameters!$D$6+($B43-1)*Parameters!$D$32)*(O43+P43)/2+D42*(Parameters!$D$7+($B43-1)*Parameters!$D$33)*P43+E42*(Parameters!$D$8+($B43-1)*Parameters!$D$34)*(P43+Q43)/2 -> 1.1472681e+08 | U43: =C42*(Parameters!$E$6+($B43-1)*Parameters!$E$32)*(O43+Q43)/2+D42*(Parameters!$E$7+($B43-1)*Parameters!$E$33)*(P43+Q43)/2+E42*(Parameters!$E$8+($B43-1)*Parameters!$E$34)*Q43 -> 3.0460244e+08 | V43: =C42*(Parameters!$F$6+($B43-1)*Parameters!$F$32)*(O43/2+R43)+D42*(Parameters!$F$7+($B43-1)*Parameters!$F$33)*(P43/2+R43)+E42*(Parameters!$F$8+($B43-1)*Parameters!$F$34)*(Q43/2+R43) -> 63677348 | W43: =S43+T43+U43+V43 -> 5.8630622e+08 | X43: =X42/(1+Parameters!$B$26) -> 0.30831867 | Y43: =W43*X43 -> 1.8076915e+08 | Z43: =Y43/G42 -> 390.01435

Sheet Alt Scenario_1 (alt)
C5: Different formulae - do not drag
AL9: Total PV
U10: =SUM(U13:U42) -> 20149312 | AL10: =SUM(AL13:AL42) -> 1.01543e+10
C11: Transition during the year | O11: End of year | V11: Cost | Z11: Drug | AB11: Combined cost | AF11: Cost per state x population
B12: Year | C12: HH | D12: HS | E12: HI | F12: HD | G12: SH | H12: SS | I12: SI | J12: SD | K12: IH | L12: IS | M12: II | N12: ID | O12: H | P12: S | Q12: I | R12: D | S12: Cumulative Deaths | T12: Check sum population | U12: Lives alive | V12: H | W12: S | X12: I | Y12: D | Z12: S | AA12: I | AB12: H | AC12: S | AD12: I | AE12: D | AF12: H | AG12: S | AH12: I | AI12: D | AJ12: Total | AK12: v | AL12: PV | AM12: PV cost per life alive
B13: 1 | C13: =Parameters!$B$12*(Parameters!C$6+($B13-1)*Parameters!C$32) -> 800000 | D13: =Parameters!$B$12*(Parameters!D$6+($B13-1)*Parameters!D$32) -> 160000 | E13: =Parameters!$B$12*(Parameters!E$6+($B13-1)*Parameters!E$32) -> 30000 | F13: =Parameters!$B$12*(Parameters!F$6+($B13-1)*Parameters!F$32) -> 10000 | O13: =C13+G13+K13 -> 800000 | P13: =D13+H13+L13 -> 160000 | Q13: =E13+I13+M13 -> 30000 | R13: =F13+J13+N13 -> 10000 | S13: =SUM($R$13:R13) -> 10000 | T13: =SUM(O13:Q13,S13) -> 1000000 | U13: =SUM(O13:Q13) -> 990000 | V13: =Parameters!B15 -> 50 | W13: =Parameters!B16 -> 200 | X13: =Parameters!B17 -> 3000 | Y13: =Parameters!B18 -> 250 | Z13: =Parameters!B37 -> 250 | AA13: =Parameters!B38 -> 6000 | AB13: =V13 -> 50 | AC13: =W13+Z13 -> 450 | AD13: =X13+AA13 -> 9000 | AE13: =Y13 -> 250 | AF13: =C13*AB13+G13*(AB13+AC13)/2+K13*(AB13+AD13)/2 -> 40000000 | AG13: =D13*(AB13+AC13)/2+H13*AC13+L13*(AC13+AD13)/2 -> 40000000 | AH13: =E13*(AB13+AD13)/2+I13*(AC13+AD13)/2+M13*AD13 -> 135750000 | AI13: =(F13*AB13+J13*AC13+N13*AD13)/2+R13*AE13 -> 2750000 | AJ13: =SUM(AF13:AI13) -> 218500000 | AK13: =1/(1+Parameters!$B$26) -> 0.96153846 | AL13: =AK13*AJ13 -> 2.1009615e+08 | AM13: =AL13/Parameters!$B$12 -> 210.09615
B14: 2 | C14: =$O13*(Parameters!C$6+($B14-1)*Parameters!C$32) -> 641440 | D14: =$O13*(Parameters!D$6+($B14-1)*Parameters!D$32) -> 127040 | E14: =$O13*(Parameters!E$6+($B14-1)*Parameters!E$32) -> 23560 | F14: =$O13*(Parameters!F$6+($B14-1)*Parameters!F$32) -> 7960 | G14: =$P13*(Parameters!C$7+($B14-1)*Parameters!C$33) -> 120104 | H14: =$P13*(Parameters!D$7+($B14-1)*Parameters!D$33) -> 16080 | I14: =$P13*(Parameters!E$7+($B14-1)*Parameters!E$33) -> 15867.2 | J14: =$P13*(Parameters!F$7+($B14-1)*Parameters!F$33) -> 7948.8 | K14: =$Q13*(Parameters!C$8+($B14-1)*Parameters!C$34) -> 4515 | L14: =$Q13*(Parameters!D$8+($B14-1)*Parameters!D$34) -> 7530 | M14: =$Q13*(Parameters!E$8+($B14-1)*Parameters!E$34) -> 9015 | N14: =$Q13*(Parameters!F$8+($B14-1)*Parameters!F$34) -> 8940 | O14: =C14+G14+K14 -> 766059 | P14: =D14+H14+L14 -> 150650 | Q14: =E14+I14+M14 -> 48442.2 | R14: =F14+J14+N14 -> 24848.8 | S14: =SUM($R$13:R14) -> 34848.8 | T14: =SUM(O14:Q14,S14) -> 1000000 | U14: =SUM(O14:Q14) -> 965151.2 | V14: =V13*(1+Parameters!$B$24) -> 51 | W14: =W13*(1+Parameters!$B$24) -> 204 | X14: =X13*(1+Parameters!$B$24) -> 3060 | Y14: =Y13*(1+Parameters!$B$24) -> 255 | Z14: =Z13*(1+Parameters!$B$25) -> 262.5 | AA14: =AA13*(1+Parameters!$B$25) -> 6300 | AB14: =V14 -> 51 | AC14: =W14+Z14 -> 466.5 | AD14: =X14+AA14 -> 9360 | AE14: =Y14 -> 255 | AF14: =C14*AB14+G14*(AB14+AC14)/2+K14*(AB14+AD14)/2 -> 85035682 | AG14: =D14*(AB14+AC14)/2+H14*AC14+L14*(AC14+AD14)/2 -> 77369692 | AH14: =E14*(AB14+AD14)/2+I14*(AC14+AD14)/2+M14*AD14 -> 2.732015e+08 | AI14: =(F14*AB14+J14*AC14+N14*AD14)/2+R14*AE14 -> 50232682 | AJ14: =SUM(AF14:AI14) -> 485839557 | AK14: =AK13/(1+Parameters!$B$26) -> 0.92455621 | AL14: =AK14*AJ14 -> 4.4918598e+08 | AM14: =AL14/SUM(O13:Q13) -> 453.72321
B15: 3 | C15: =$O14*(Parameters!C$6+$B14*Parameters!C$32) -> 615605.01 | D15: =$O14*(Parameters!D$6+$B14*Parameters!D$32) -> 120730.9 | E15: =$O14*(Parameters!E$6+$B14*Parameters!E$32) -> 22139.105 | F15: =$O14*(Parameters!F$6+$B14*Parameters!F$32) -> 7583.9841 | G15: =$P14*(Parameters!C$7+$B14*Parameters!C$33) -> 113183.35 | H15: =$P14*(Parameters!D$7+$B14*Parameters!D$33) -> 15215.65 | I15: =$P14*(Parameters!E$7+$B14*Parameters!E$33) -> 14814.921 | J15: =$P14*(Parameters!F$7+$B14*Parameters!F$33) -> 7436.084 | K15: =$Q14*(Parameters!C$8+$B14*Parameters!C$34) -> 7314.7722 | L15: =$Q14*(Parameters!D$8+$B14*Parameters!D$34) -> 12207.434 | M15: =$Q14*(Parameters!E$8+$B14*Parameters!E$34) -> 14581.102 | N15: =$Q14*(Parameters!F$8+$B14*Parameters!F$34) -> 14338.891 | O15: =C15+G15+K15 -> 736103.13 | P15: =D15+H15+L15 -> 148153.98 | Q15: =E15+I15+M15 -> 51535.128 | R15: =N15+J15+F15 -> 29358.959 | S15: =SUM($R$13:R15) -> 64207.759 | T15: =SUM(O15:Q15,S15) -> 1000000 | U15: =SUM(O15:Q15) -> 935792.24 | V15: =V14*(1+Parameters!$B$24) -> 52.02 | W15: =W14*(1+Parameters!$B$24) -> 208.08 | X15: =X14*(1+Parameters!$B$24) -> 3121.2 | Y15: =Y14*(1+Parameters!$B$24) -> 260.1 | Z15: =Z14*(1+Parameters!$B$25) -> 275.625 | AA15: =AA14*(1+Parameters!$B$25) -> 6615 | AB15: =V15 -> 52.02 | AC15: =W15+Z15 -> 483.705 | AD15: =X15+AA15 -> 9736.2 | AE15: =Y15 -> 260.1 | AF15: =C15*AB15+G15*(AB15+AC15)/2+K15*(AB15+AD15)/2 -> 98140646 | AG15: =D15*(AB15+AC15)/2+H15*AC15+L15*(AC15+AD15)/2 -> 1.0207858e+08 | AH15: =E15*(AB15+AD15)/2+I15*(AC15+AD15)/2+M15*AD15 -> 3.2601929e+08 | AI15: =(F15*AB15+J15*AC15+N15*AD15)/2+R15*AE15 -> 79435116 | AJ15: =SUM(AF15:AI15) -> 6.0567362e+08 | AK15: =AK14/(1+Parameters!$B$26) -> 0.88899636 | AL15: =AK15*AJ15 -> 5.3844165e+08 | AM15: =AL15/SUM(O14:Q14) -> 557.88321
B16: 4 | C16: =$O15*(Parameters!C$6+$B15*Parameters!C$32) -> 592857.46 | D16: =$O15*(Parameters!D$6+$B15*Parameters!D$32) -> 115126.53 | E16: =$O15*(Parameters!E$6+$B15*Parameters!E$32) -> 20868.524 | F16: =$O15*(Parameters!F$6+$B15*Parameters!F$32) -> 7250.6158 | G16: =$P15*(Parameters!C$7+$B15*Parameters!C$33) -> 111404.39 | H16: =$P15*(Parameters!D$7+$B15*Parameters!D$33) -> 15037.629 | I16: =$P15*(Parameters!E$7+$B15*Parameters!E$33) -> 14446.495 | J16: =$P15*(Parameters!F$7+$B15*Parameters!F$33) -> 7265.4713 | K16: =$Q15*(Parameters!C$8+$B15*Parameters!C$34) -> 7807.5719 | L16: =$Q15*(Parameters!D$8+$B15*Parameters!D$34) -> 13038.387 | M16: =$Q15*(Parameters!E$8+$B15*Parameters!E$34) -> 15537.841 | N16: =$Q15*(Parameters!F$8+$B15*Parameters!F$34) -> 15151.328 | O16: =C16+G16+K16 -> 712069.42 | P16: =D16+H16+L16 -> 143202.55 | Q16: =E16+I16+M16 -> 50852.86 | R16: =N16+J16+F16 -> 29667.415 | S16: =SUM($R$13:R16) -> 93875.174 | T16: =SUM(O16:Q16,S16) -> 1000000 | U16: =SUM(O16:Q16) -> 906124.83 | V16: =V15*(1+Parameters!$B$24) -> 53.0604 | W16: =W15*(1+Parameters!$B$24) -> 212.2416 | X16: =X15*(1+Parameters!$B$24) -> 3183.624 | Y16: =Y15*(1+Parameters!$B$24) -> 265.302 | Z16: =Z15*(1+Parameters!$B$25) -> 289.40625 | AA16: =AA15*(1+Parameters!$B$25) -> 6945.75 | AB16: =V16 -> 53.0604 | AC16: =W16+Z16 -> 501.64785 | AD16: =X16+AA16 -> 10129.374 | AE16: =Y16 -> 265.302 | AF16: =C16*AB16+G16*(AB16+AC16)/2+K16*(AB16+AD16)/2 -> 1.0210576e+08 | AG16: =D16*(AB16+AC16)/2+H16*AC16+L16*(AC16+AD16)/2 -> 1.087801e+08 | AH16: =E16*(AB16+AD16)/2+I16*(AC16+AD16)/2+M16*AD16 -> 3.4042529e+08 | AI16: =(F16*AB16+J16*AC16+N16*AD16)/2+R16*AE16 -> 86622271 | AJ16: =SUM(AF16:AI16) -> 6.3793343e+08 | AK16: =AK15/(1+Parameters!$B$26) -> 0.85480419 | AL16: =AK16*AJ16 -> 5.4530817e+08 | AM16: =AL16/SUM(O15:Q15) -> 582.72354
B17: 5 | C17: =$O16*(Parameters!C$6+$B16*Parameters!C$32) -> 574782.44 | D17: =$O16*(Parameters!D$6+$B16*Parameters!D$32) -> 110513.17 | E17: =$O16*(Parameters!E$6+$B16*Parameters!E$32) -> 19795.53 | F17: =$O16*(Parameters!F$6+$B16*Parameters!F$32) -> 6978.2803 | G17: =$P16*(Parameters!C$7+$B16*Parameters!C$33) -> 107774.24 | H17: =$P16*(Parameters!D$7+$B16*Parameters!D$33) -> 14606.66 | I17: =$P16*(Parameters!E$7+$B16*Parameters!E$33) -> 13844.822 | J17: =$P16*(Parameters!F$7+$B16*Parameters!F$33) -> 6976.8281 | K17: =$Q16*(Parameters!C$8+$B16*Parameters!C$34) -> 7729.6347 | L17: =$Q16*(Parameters!D$8+$B16*Parameters!D$34) -> 12916.626 | M17: =$Q16*(Parameters!E$8+$B16*Parameters!E$34) -> 15357.564 | N17: =$Q16*(Parameters!F$8+$B16*Parameters!F$34) -> 14849.035 | O17: =C17+G17+K17 -> 690286.31 | P17: =D17+H17+L17 -> 138036.46 | Q17: =E17+I17+M17 -> 48997.916 | R17: =N17+J17+F17 -> 28804.143 | S17: =SUM($R$13:R17) -> 122679.32 | T17: =SUM(O17:Q17,S17) -> 1000000 | U17: =SUM(O17:Q17) -> 877320.68 | V17: =V16*(1+Parameters!$B$24) -> 54.121608 | W17: =W16*(1+Parameters!$B$24) -> 216.48643 | X17: =X16*(1+Parameters!$B$24) -> 3247.2965 | Y17: =Y16*(1+Parameters!$B$24) -> 270.60804 | Z17: =Z16*(1+Parameters!$B$25) -> 303.87656 | AA17: =AA16*(1+Parameters!$B$25) -> 7293.0375 | AB17: =V17 -> 54.121608 | AC17: =W17+Z17 -> 520.36299 | AD17: =X17+AA17 -> 10540.334 | AE17: =Y17 -> 270.60804 | AF17: =C17*AB17+G17*(AB17+AC17)/2+K17*(AB17+AD17)/2 -> 1.0301111e+08 | AG17: =D17*(AB17+AC17)/2+H17*AC17+L17*(AC17+AD17)/2 -> 1.1077827e+08 | AH17: =E17*(AB17+AD17)/2+I17*(AC17+AD17)/2+M17*AD17 -> 3.4330197e+08 | AI17: =(F17*AB17+J17*AC17+N17*AD17)/2+R17*AE17 -> 88055607 | AJ17: =SUM(AF17:AI17) -> 6.4514695e+08 | AK17: =AK16/(1+Parameters!$B$26) -> 0.82192711 | AL17: =AK17*AJ17 -> 5.3026377e+08 | AM17: =AL17/SUM(O16:Q16) -> 585.19947
B18: 6 | C18: =$O17*(Parameters!C$6+$B17*Parameters!C$32) -> 558441.62 | D18: =$O17*(Parameters!D$6+$B17*Parameters!D$32) -> 106304.09 | E18: =$O17*(Parameters!E$6+$B17*Parameters!E$32) -> 18810.302 | F18: =$O17*(Parameters!F$6+$B17*Parameters!F$32) -> 6730.2915 | G18: =$P17*(Parameters!C$7+$B17*Parameters!C$33) -> 103975.96 | H18: =$P17*(Parameters!D$7+$B17*Parameters!D$33) -> 14148.737 | I18: =$P17*(Parameters!E$7+$B17*Parameters!E$33) -> 13230.795 | J18: =$P17*(Parameters!F$7+$B17*Parameters!F$33) -> 6680.9647 | K18: =$Q17*(Parameters!C$8+$B17*Parameters!C$34) -> 7472.1821 | L18: =$Q17*(Parameters!D$8+$B17*Parameters!D$34) -> 12494.469 | M18: =$Q17*(Parameters!E$8+$B17*Parameters!E$34) -> 14821.869 | N18: =$Q17*(Parameters!F$8+$B17*Parameters!F$34) -> 14209.396 | O18: =C18+G18+K18 -> 669889.77 | P18: =D18+H18+L18 -> 132947.3 | Q18: =E18+I18+M18 -> 46862.966 | R18: =N18+J18+F18 -> 27620.652 | S18: =SUM($R$13:R18) -> 150299.97 | T18: =SUM(O18:Q18,S18) -> 1000000 | U18: =SUM(O18:Q18) -> 849700.03 | V18: =V17*(1+Parameters!$B$24) -> 55.20404 | W18: =W17*(1+Parameters!$B$24) -> 220.81616 | X18: =X17*(1+Parameters!$B$24) -> 3312.2424 | Y18: =Y17*(1+Parameters!$B$24) -> 276.0202 | Z18: =Z17*(1+Parameters!$B$25) -> 319.07039 | AA18: =AA17*(1+Parameters!$B$25) -> 7657.6894 | AB18: =V18 -> 55.20404 | AC18: =W18+Z18 -> 539.88655 | AD18: =X18+AA18 -> 10969.932 | AE18: =Y18 -> 276.0202 | AF18: =C18*AB18+G18*(AB18+AC18)/2+K18*(AB18+AD18)/2 -> 1.029567e+08 | AG18: =D18*(AB18+AC18)/2+H18*AC18+L18*(AC18+AD18)/2 -> 1.1117353e+08 | AH18: =E18*(AB18+AD18)/2+I18*(AC18+AD18)/2+M18*AD18 -> 3.4242999e+08 | AI18: =(F18*AB18+J18*AC18+N18*AD18)/2+R18*AE18 -> 87551159 | AJ18: =SUM(AF18:AI18) -> 6.4411137e+08 | AK18: =AK17/(1+Parameters!$B$26) -> 0.79031453 | AL18: =AK18*AJ18 -> 5.0905058e+08 | AM18: =AL18/SUM(O17:Q17) -> 580.23319
B19: 7 | C19: =$O18*(Parameters!C$6+$B18*Parameters!C$32) -> 543146.62 | D19: =$O18*(Parameters!D$6+$B18*Parameters!D$32) -> 102359.16 | E19: =$O18*(Parameters!E$6+$B18*Parameters!E$32) -> 17886.057 | F19: =$O18*(Parameters!F$6+$B18*Parameters!F$32) -> 6497.9307 | G19: =$P18*(Parameters!C$7+$B18*Parameters!C$33) -> 100228.97 | H19: =$P18*(Parameters!D$7+$B18*Parameters!D$33) -> 13693.572 | I19: =$P18*(Parameters!E$7+$B18*Parameters!E$33) -> 12632.652 | J19: =$P18*(Parameters!F$7+$B18*Parameters!F$33) -> 6392.106 | K19: =$Q18*(Parameters!C$8+$B18*Parameters!C$34) -> 7170.0338 | L19: =$Q18*(Parameters!D$8+$B18*Parameters!D$34) -> 11996.919 | M19: =$Q18*(Parameters!E$8+$B18*Parameters!E$34) -> 14199.479 | N19: =$Q18*(Parameters!F$8+$B18*Parameters!F$34) -> 13496.534 | O19: =C19+G19+K19 -> 650545.62 | P19: =D19+H19+L19 -> 128049.65 | Q19: =E19+I19+M19 -> 44718.188 | R19: =N19+J19+F19 -> 26386.571 | S19: =SUM($R$13:R19) -> 176686.54 | T19: =SUM(O19:Q19,S19) -> 1000000 | U19: =SUM(O19:Q19) -> 823313.46 | V19: =V18*(1+Parameters!$B$24) -> 56.308121 | W19: =W18*(1+Parameters!$B$24) -> 225.23248 | X19: =X18*(1+Parameters!$B$24) -> 3378.4873 | Y19: =Y18*(1+Parameters!$B$24) -> 281.5406 | Z19: =Z18*(1+Parameters!$B$25) -> 335.02391 | AA19: =AA18*(1+Parameters!$B$25) -> 8040.5738 | AB19: =V19 -> 56.308121 | AC19: =W19+Z19 -> 560.25639 | AD19: =X19+AA19 -> 11419.061 | AE19: =Y19 -> 281.5406 | AF19: =C19*AB19+G19*(AB19+AC19)/2+K19*(AB19+AD19)/2 -> 1.0262177e+08 | AG19: =D19*(AB19+AC19)/2+H19*AC19+L19*(AC19+AD19)/2 -> 1.1108488e+08 | AH19: =E19*(AB19+AD19)/2+I19*(AC19+AD19)/2+M19*AD19 -> 3.4043454e+08 | AI19: =(F19*AB19+J19*AC19+N19*AD19)/2+R19*AE19 -> 86461318 | AJ19: =SUM(AF19:AI19) -> 6.4060251e+08 | AK19: =AK18/(1+Parameters!$B$26) -> 0.75991781 | AL19: =AK19*AJ19 -> 4.8680526e+08 | AM19: =AL19/SUM(O18:Q18) -> 572.91425
B20: 8 | C20: =$O19*(Parameters!C$6+$B19*Parameters!C$32) -> 528633.37 | D20: =$O19*(Parameters!D$6+$B19*Parameters!D$32) -> 98622.717 | E20: =$O19*(Parameters!E$6+$B19*Parameters!E$32) -> 17011.768 | F20: =$O19*(Parameters!F$6+$B19*Parameters!F$32) -> 6277.7653 | G20: =$P19*(Parameters!C$7+$B19*Parameters!C$33) -> 96619.861 | H20: =$P19*(Parameters!D$7+$B19*Parameters!D$33) -> 13253.139 | I20: =$P19*(Parameters!E$7+$B19*Parameters!E$33) -> 12060.996 | J20: =$P19*(Parameters!F$7+$B19*Parameters!F$33) -> 6115.6512 | K20: =$Q19*(Parameters!C$8+$B19*Parameters!C$34) -> 6864.2418 | L20: =$Q19*(Parameters!D$8+$B19*Parameters!D$34) -> 11492.574 | M20: =$Q19*(Parameters!E$8+$B19*Parameters!E$34) -> 13571.97 | N20: =$Q19*(Parameters!F$8+$B19*Parameters!F$34) -> 12789.402 | O20: =C20+G20+K20 -> 632117.48 | P20: =D20+H20+L20 -> 123368.43 | Q20: =E20+I20+M20 -> 42644.734 | R20: =N20+J20+F20 -> 25182.818 | S20: =SUM($R$13:R20) -> 201869.36 | T20: =SUM(O20:Q20,S20) -> 1000000 | U20: =SUM(O20:Q20) -> 798130.64 | V20: =V19*(1+Parameters!$B$24) -> 57.434283 | W20: =W19*(1+Parameters!$B$24) -> 229.73713 | X20: =X19*(1+Parameters!$B$24) -> 3446.057 | Y20: =Y19*(1+Parameters!$B$24) -> 287.17142 | Z20: =Z19*(1+Parameters!$B$25) -> 351.77511 | AA20: =AA19*(1+Parameters!$B$25) -> 8442.6025 | AB20: =V20 -> 57.434283 | AC20: =W20+Z20 -> 581.51224 | AD20: =X20+AA20 -> 11888.66 | AE20: =Y20 -> 287.17142 | AF20: =C20*AB20+G20*(AB20+AC20)/2+K20*(AB20+AD20)/2 -> 1.0222958e+08 | AG20: =D20*(AB20+AC20)/2+H20*AC20+L20*(AC20+AD20)/2 -> 1.1087137e+08 | AH20: =E20*(AB20+AD20)/2+I20*(AC20+AD20)/2+M20*AD20 -> 3.3816597e+08 | AI20: =(F20*AB20+J20*AC20+N20*AD20)/2+R20*AE20 -> 85214649 | AJ20: =SUM(AF20:AI20) -> 6.3648157e+08 | AK20: =AK19/(1+Parameters!$B$26) -> 0.73069021 | AL20: =AK20*AJ20 -> 4.6507085e+08 | AM20: =AL20/SUM(O19:Q19) -> 564.87701
B21: 9 | C21: =$O20*(Parameters!C$6+$B20*Parameters!C$32) -> 514796.47 | D21: =$O20*(Parameters!D$6+$B20*Parameters!D$32) -> 95070.469 | E21: =$O20*(Parameters!E$6+$B20*Parameters!E$32) -> 16182.207 | F21: =$O20*(Parameters!F$6+$B20*Parameters!F$32) -> 6068.3278 | G21: =$P20*(Parameters!C$7+$B20*Parameters!C$33) -> 93167.838 | H21: =$P20*(Parameters!D$7+$B20*Parameters!D$33) -> 12830.317 | I21: =$P20*(Parameters!E$7+$B20*Parameters!E$33) -> 11517.677 | J21: =$P20*(Parameters!F$7+$B20*Parameters!F$33) -> 5852.5983 | K21: =$Q20*(Parameters!C$8+$B20*Parameters!C$34) -> 6567.2891 | L21: =$Q20*(Parameters!D$8+$B20*Parameters!D$34) -> 11002.341 | M21: =$Q20*(Parameters!E$8+$B20*Parameters!E$34) -> 12963.999 | N21: =$Q20*(Parameters!F$8+$B20*Parameters!F$34) -> 12111.105 | O21: =C21+G21+K21 -> 614531.6 | P21: =D21+H21+L21 -> 118903.13 | Q21: =E21+I21+M21 -> 40663.883 | R21: =N21+J21+F21 -> 24032.031 | S21: =SUM($R$13:R21) -> 225901.39 | T21: =SUM(O21:Q21,S21) -> 1000000 | U21: =SUM(O21:Q21) -> 774098.61 | V21: =V20*(1+Parameters!$B$24) -> 58.582969 | W21: =W20*(1+Parameters!$B$24) -> 234.33188 | X21: =X20*(1+Parameters!$B$24) -> 3514.9781 | Y21: =Y20*(1+Parameters!$B$24) -> 292.91485 | Z21: =Z20*(1+Parameters!$B$25) -> 369.36386 | AA21: =AA20*(1+Parameters!$B$25) -> 8864.7327 | AB21: =V21 -> 58.582969 | AC21: =W21+Z21 -> 603.69574 | AD21: =X21+AA21 -> 12379.711 | AE21: =Y21 -> 292.91485 | AF21: =C21*AB21+G21*(AB21+AC21)/2+K21*(AB21+AD21)/2 -> 1.0185278e+08 | AG21: =D21*(AB21+AC21)/2+H21*AC21+L21*(AC21+AD21)/2 -> 1.1065112e+08 | AH21: =E21*(AB21+AD21)/2+I21*(AC21+AD21)/2+M21*AD21 -> 3.3589943e+08 | AI21: =(F21*AB21+J21*AC21+N21*AD21)/2+R21*AE21 -> 83949669 | AJ21: =SUM(AF21:AI21) -> 6.3235299e+08 | AK21: =AK20/(1+Parameters!$B$26) -> 0.70258674 | AL21: =AK21*AJ21 -> 4.4428282e+08 | AM21: =AL21/SUM(O20:Q20) -> 556.65426
B22: 10 | C22: =$O21*(Parameters!C$6+$B21*Parameters!C$32) -> 501580.69 | D22: =$O21*(Parameters!D$6+$B21*Parameters!D$32) -> 91688.115 | E22: =$O21*(Parameters!E$6+$B21*Parameters!E$32) -> 15394.017 | F22: =$O21*(Parameters!F$6+$B21*Parameters!F$32) -> 5868.7768 | G22: =$P21*(Parameters!C$7+$B21*Parameters!C$33) -> 89872.928 | H22: =$P21*(Parameters!D$7+$B21*Parameters!D$33) -> 12425.377 | I22: =$P21*(Parameters!E$7+$B21*Parameters!E$33) -> 11002.106 | J22: =$P21*(Parameters!F$7+$B21*Parameters!F$33) -> 5602.7153 | K22: =$Q21*(Parameters!C$8+$B21*Parameters!C$34) -> 6282.57 | L22: =$Q21*(Parameters!D$8+$B21*Parameters!D$34) -> 10531.946 | M22: =$Q21*(Parameters!E$8+$B21*Parameters!E$34) -> 12382.152 | N22: =$Q21*(Parameters!F$8+$B21*Parameters!F$34) -> 11467.215 | O22: =C22+G22+K22 -> 597736.19 | P22: =D22+H22+L22 -> 114645.44 | Q22: =E22+I22+M22 -> 38778.275 | R22: =N22+J22+F22 -> 22938.707 | S22: =SUM($R$13:R22) -> 248840.1 | T22: =SUM(O22:Q22,S22) -> 1000000 | U22: =SUM(O22:Q22) -> 751159.9 | V22: =V21*(1+Parameters!$B$24) -> 59.754628 | W22: =W21*(1+Parameters!$B$24) -> 239.01851 | X22: =X21*(1+Parameters!$B$24) -> 3585.2777 | Y22: =Y21*(1+Parameters!$B$24) -> 298.77314 | Z22: =Z21*(1+Parameters!$B$25) -> 387.83205 | AA22: =AA21*(1+Parameters!$B$25) -> 9307.9693 | AB22: =V22 -> 59.754628 | AC22: =W22+Z22 -> 626.85057 | AD22: =X22+AA22 -> 12893.247 | AE22: =Y22 -> 298.77314 | AF22: =C22*AB22+G22*(AB22+AC22)/2+K22*(AB22+AD22)/2 -> 1.0151445e+08 | AG22: =D22*(AB22+AC22)/2+H22*AC22+L22*(AC22+AD22)/2 -> 1.1046209e+08 | AH22: =E22*(AB22+AD22)/2+I22*(AC22+AD22)/2+M22*AD22 -> 3.3372029e+08 | AI22: =(F22*AB22+J22*AC22+N22*AD22)/2+R22*AE22 -> 82709664 | AJ22: =SUM(AF22:AI22) -> 6.2840649e+08 | AK22: =AK21/(1+Parameters!$B$26) -> 0.67556417 | AL22: =AK22*AJ22 -> 4.2452891e+08 | AM22: =AL22/SUM(O21:Q21) -> 548.41709
B23: 11 | C23: =$O22*(Parameters!C$6+$B22*Parameters!C$32) -> 488948.2 | D23: =$O22*(Parameters!D$6+$B22*Parameters!D$32) -> 88464.956 | E23: =$O22*(Parameters!E$6+$B22*Parameters!E$32) -> 14644.537 | F23: =$O22*(Parameters!F$6+$B22*Parameters!F$32) -> 5678.4938 | G23: =$P22*(Parameters!C$7+$B22*Parameters!C$33) -> 86729.273 | H23: =$P22*(Parameters!D$7+$B22*Parameters!D$33) -> 12037.771 | I23: =$P22*(Parameters!E$7+$B22*Parameters!E$33) -> 10512.987 | J23: =$P22*(Parameters!F$7+$B22*Parameters!F$33) -> 5365.4065 | K23: =$Q22*(Parameters!C$8+$B22*Parameters!C$34) -> 6010.6327 | L23: =$Q22*(Parameters!D$8+$B22*Parameters!D$34) -> 10082.352 | M23: =$Q22*(Parameters!E$8+$B22*Parameters!E$34) -> 11827.374 | N23: =$Q22*(Parameters!F$8+$B22*Parameters!F$34) -> 10857.917 | O23: =C23+G23+K23 -> 581688.11 | P23: =D23+H23+L23 -> 110585.08 | Q23: =E23+I23+M23 -> 36984.897 | R23: =N23+J23+F23 -> 21901.817 | S23: =SUM($R$13:R23) -> 270741.91 | T23: =SUM(O23:Q23,S23) -> 1000000 | U23: =SUM(O23:Q23) -> 729258.09 | V23: =V22*(1+Parameters!$B$24) -> 60.949721 | W23: =W22*(1+Parameters!$B$24) -> 243.79888 | X23: =X22*(1+Parameters!$B$24) -> 3656.9833 | Y23: =Y22*(1+Parameters!$B$24) -> 304.7486 | Z23: =Z22*(1+Parameters!$B$25) -> 407.22366 | AA23: =AA22*(1+Parameters!$B$25) -> 9773.3678 | AB23: =V23 -> 60.949721 | AC23: =W23+Z23 -> 651.02254 | AD23: =X23+AA23 -> 13430.351 | AE23: =Y23 -> 304.7486 | AF23: =C23*AB23+G23*(AB23+AC23)/2+K23*(AB23+AD23)/2 -> 1.012213e+08 | AG23: =D23*(AB23+AC23)/2+H23*AC23+L23*(AC23+AD23)/2 -> 1.1031584e+08 | AH23: =E23*(AB23+AD23)/2+I23*(AC23+AD23)/2+M23*AD23 -> 3.3165135e+08 | AI23: =(F23*AB23+J23*AC23+N23*AD23)/2+R23*AE23 -> 81506919 | AJ23: =SUM(AF23:AI23) -> 6.2469541e+08 | AK23: =AK22/(1+Parameters!$B$26) -> 0.64958093 | AL23: =AK23*AJ23 -> 4.0579023e+08 | AM23: =AL23/SUM(O22:Q22) -> 540.21817
B24: 12 | C24: =$O23*(Parameters!C$6+$B23*Parameters!C$32) -> 476867.91 | D24: =$O23*(Parameters!D$6+$B23*Parameters!D$32) -> 85391.815 | E24: =$O23*(Parameters!E$6+$B23*Parameters!E$32) -> 13931.43 | F24: =$O23*(Parameters!F$6+$B23*Parameters!F$32) -> 5496.9526 | G24: =$P23*(Parameters!C$7+$B23*Parameters!C$33) -> 83729.492 | H24: =$P23*(Parameters!D$7+$B23*Parameters!D$33) -> 11666.726 | I24: =$P23*(Parameters!E$7+$B23*Parameters!E$33) -> 10048.866 | J24: =$P23*(Parameters!F$7+$B23*Parameters!F$33) -> 5139.9945 | K24: =$Q23*(Parameters!C$8+$B23*Parameters!C$34) -> 5751.1515 | L24: =$Q23*(Parameters!D$8+$B23*Parameters!D$34) -> 9653.0582 | M24: =$Q23*(Parameters!E$8+$B23*Parameters!E$34) -> 11298.886 | N24: =$Q23*(Parameters!F$8+$B23*Parameters!F$34) -> 10281.801 | O24: =C24+G24+K24 -> 566348.56 | P24: =D24+H24+L24 -> 106711.6 | Q24: =E24+I24+M24 -> 35279.182 | R24: =N24+J24+F24 -> 20918.749 | S24: =SUM($R$13:R24) -> 291660.66 | T24: =SUM(O24:Q24,S24) -> 1000000 | U24: =SUM(O24:Q24) -> 708339.34 | V24: =V23*(1+Parameters!$B$24) -> 62.168715 | W24: =W23*(1+Parameters!$B$24) -> 248.67486 | X24: =X23*(1+Parameters!$B$24) -> 3730.1229 | Y24: =Y23*(1+Parameters!$B$24) -> 310.84358 | Z24: =Z23*(1+Parameters!$B$25) -> 427.58484 | AA24: =AA23*(1+Parameters!$B$25) -> 10262.036 | AB24: =V24 -> 62.168715 | AC24: =W24+Z24 -> 676.2597 | AD24: =X24+AA24 -> 13992.159 | AE24: =Y24 -> 310.84358 | AF24: =C24*AB24+G24*(AB24+AC24)/2+K24*(AB24+AD24)/2 -> 1.0097467e+08 | AG24: =D24*(AB24+AC24)/2+H24*AC24+L24*(AC24+AD24)/2 -> 1.1021516e+08 | AH24: =E24*(AB24+AD24)/2+I24*(AC24+AD24)/2+M24*AD24 -> 3.2969474e+08 | AI24: =(F24*AB24+J24*AC24+N24*AD24)/2+R24*AE24 -> 80343614 | AJ24: =SUM(AF24:AI24) -> 6.2122818e+08 | AK24: =AK23/(1+Parameters!$B$26) -> 0.62459705 | AL24: =AK24*AJ24 -> 3.8801729e+08 | AM24: =AL24/SUM(O23:Q23) -> 532.07129
B25: 13 | C25: =$O24*(Parameters!C$6+$B24*Parameters!C$32) -> 465311.97 | D25: =$O24*(Parameters!D$6+$B24*Parameters!D$32) -> 82460.35 | E25: =$O24*(Parameters!E$6+$B24*Parameters!E$32) -> 13252.556 | F25: =$O24*(Parameters!F$6+$B24*Parameters!F$32) -> 5323.6764 | G25: =$P24*(Parameters!C$7+$B24*Parameters!C$33) -> 80866.049 | H25: =$P24*(Parameters!D$7+$B24*Parameters!D$33) -> 11311.429 | I25: =$P24*(Parameters!E$7+$B24*Parameters!E$33) -> 9608.3123 | J25: =$P24*(Parameters!F$7+$B24*Parameters!F$33) -> 4925.8074 | K25: =$Q24*(Parameters!C$8+$B24*Parameters!C$34) -> 5503.5525 | L25: =$Q24*(Parameters!D$8+$B24*Parameters!D$34) -> 9243.1458 | M25: =$Q24*(Parameters!E$8+$B24*Parameters!E$34) -> 10795.43 | N25: =$Q24*(Parameters!F$8+$B24*Parameters!F$34) -> 9737.0544 | O25: =C25+G25+K25 -> 551681.58 | P25: =D25+H25+L25 -> 103014.93 | Q25: =E25+I25+M25 -> 33656.298 | R25: =N25+J25+F25 -> 19986.538 | S25: =SUM($R$13:R25) -> 311647.2 | T25: =SUM(O25:Q25,S25) -> 1000000 | U25: =SUM(O25:Q25) -> 688352.8 | V25: =V24*(1+Parameters!$B$24) -> 63.41209 | W25: =W24*(1+Parameters!$B$24) -> 253.64836 | X25: =X24*(1+Parameters!$B$24) -> 3804.7254 | Y25: =Y24*(1+Parameters!$B$24) -> 317.06045 | Z25: =Z24*(1+Parameters!$B$25) -> 448.96408 | AA25: =AA24*(1+Parameters!$B$25) -> 10775.138 | AB25: =V25 -> 63.41209 | AC25: =W25+Z25 -> 702.61244 | AD25: =X25+AA25 -> 14579.863 | AE25: =Y25 -> 317.06045 | AF25: =C25*AB25+G25*(AB25+AC25)/2+K25*(AB25+AD25)/2 -> 1.0077411e+08 | AG25: =D25*(AB25+AC25)/2+H25*AC25+L25*(AC25+AD25)/2 -> 1.1015995e+08 | AH25: =E25*(AB25+AD25)/2+I25*(AC25+AD25)/2+M25*AD25 -> 3.2784571e+08 | AI25: =(F25*AB25+J25*AC25+N25*AD25)/2+R25*AE25 -> 79218661 | AJ25: =SUM(AF25:AI25) -> 6.1799843e+08 | AK25: =AK24/(1+Parameters!$B$26) -> 0.60057409 | AL25: =AK25*AJ25 -> 3.7115384e+08 | AM25: =AL25/SUM(O24:Q24) -> 523.97745
B26: 14 | C26: =$O25*(Parameters!C$6+$B25*Parameters!C$32) -> 454254.61 | D26: =$O25*(Parameters!D$6+$B25*Parameters!D$32) -> 79662.82 | E26: =$O25*(Parameters!E$6+$B25*Parameters!E$32) -> 12605.924 | F26: =$O25*(Parameters!F$6+$B25*Parameters!F$32) -> 5158.2227 | G26: =$P25*(Parameters!C$7+$B25*Parameters!C$33) -> 78131.67 | H26: =$P25*(Parameters!D$7+$B25*Parameters!D$33) -> 10971.09 | I26: =$P25*(Parameters!E$7+$B25*Parameters!E$33) -> 9189.9615 | J26: =$P25*(Parameters!F$7+$B25*Parameters!F$33) -> 4722.2042 | K26: =$Q25*(Parameters!C$8+$B25*Parameters!C$34) -> 5267.2107 | L26: =$Q25*(Parameters!D$8+$B25*Parameters!D$34) -> 8851.6065 | M26: =$Q25*(Parameters!E$8+$B25*Parameters!E$34) -> 10315.655 | N26: =$Q25*(Parameters!F$8+$B25*Parameters!F$34) -> 9221.8258 | O26: =C26+G26+K26 -> 537653.49 | P26: =D26+H26+L26 -> 99485.516 | Q26: =E26+I26+M26 -> 32111.541 | R26: =N26+J26+F26 -> 19102.253 | S26: =SUM($R$13:R26) -> 330749.45 | T26: =SUM(O26:Q26,S26) -> 1000000 | U26: =SUM(O26:Q26) -> 669250.55 | V26: =V25*(1+Parameters!$B$24) -> 64.680332 | W26: =W25*(1+Parameters!$B$24) -> 258.72133 | X26: =X25*(1+Parameters!$B$24) -> 3880.8199 | Y26: =Y25*(1+Parameters!$B$24) -> 323.40166 | Z26: =Z25*(1+Parameters!$B$25) -> 471.41229 | AA26: =AA25*(1+Parameters!$B$25) -> 11313.895 | AB26: =V26 -> 64.680332 | AC26: =W26+Z26 -> 730.13361 | AD26: =X26+AA26 -> 15194.715 | AE26: =Y26 -> 323.40166 | AF26: =C26*AB26+G26*(AB26+AC26)/2+K26*(AB26+AD26)/2 -> 1.0061863e+08 | AG26: =D26*(AB26+AC26)/2+H26*AC26+L26*(AC26+AD26)/2 -> 1.1014917e+08 | AH26: =E26*(AB26+AD26)/2+I26*(AC26+AD26)/2+M26*AD26 -> 3.260972e+08 | AI26: =(F26*AB26+J26*AC26+N26*AD26)/2+R26*AE26 -> 78129944 | AJ26: =SUM(AF26:AI26) -> 6.1499495e+08 | AK26: =AK25/(1+Parameters!$B$26) -> 0.57747508 | AL26: =AK26*AJ26 -> 3.5514426e+08 | AM26: =AL26/SUM(O25:Q25) -> 515.93348
... B42: 30 | C42: =$O41*(Parameters!C$6+$B41*Parameters!C$32) -> 329013.11 | D42: =$O41*(Parameters!D$6+$B41*Parameters!D$32) -> 48336.589 | E42: =$O41*(Parameters!E$6+$B41*Parameters!E$32) -> 5424.3536 | F42: =$O41*(Parameters!F$6+$B41*Parameters!F$32) -> 3300.9412 | G42: =$P41*(Parameters!C$7+$B41*Parameters!C$33) -> 47351.171 | H42: =$P41*(Parameters!D$7+$B41*Parameters!D$33) -> 7051.7124 | I42: =$P41*(Parameters!E$7+$B41*Parameters!E$33) -> 4676.3015 | J42: =$P41*(Parameters!F$7+$B41*Parameters!F$33) -> 2507.823 | K42: =$Q41*(Parameters!C$8+$B41*Parameters!C$34) -> 2604.2978 | L42: =$Q41*(Parameters!D$8+$B41*Parameters!D$34) -> 4417.0158 | M42: =$Q41*(Parameters!E$8+$B41*Parameters!E$34) -> 4979.0375 | N42: =$Q41*(Parameters!F$8+$B41*Parameters!F$34) -> 3831.2467 | O42: =C42+G42+K42 -> 378968.58 | P42: =D42+H42+L42 -> 59805.317 | Q42: =E42+I42+M42 -> 15079.693 | R42: =N42+J42+F42 -> 9640.0108 | S42: =SUM($R$13:R42) -> 546146.41 | T42: =SUM(O42:Q42,S42) -> 1000000 | U42: =SUM(O42:Q42) -> 453853.59 | V42: =V41*(1+Parameters!$B$24) -> 88.792235 | W42: =W41*(1+Parameters!$B$24) -> 355.16894 | X42: =X41*(1+Parameters!$B$24) -> 5327.5341 | Y42: =Y41*(1+Parameters!$B$24) -> 443.96117 | Z42: =Z41*(1+Parameters!$B$25) -> 1029.0339 | AA42: =AA41*(1+Parameters!$B$25) -> 24696.814 | AB42: =V42 -> 88.792235 | AC42: =W42+Z42 -> 1384.2028 | AD42: =X42+AA42 -> 30024.348 | AE42: =Y42 -> 443.96117 | AF42: =C42*AB42+G42*(AB42+AC42)/2+K42*(AB42+AD42)/2 -> 1.0329962e+08 | AG42: =D42*(AB42+AC42)/2+H42*AC42+L42*(AC42+AD42)/2 -> 1.1472681e+08 | AH42: =E42*(AB42+AD42)/2+I42*(AC42+AD42)/2+M42*AD42 -> 3.0460244e+08 | AI42: =(F42*AB42+J42*AC42+N42*AD42)/2+R42*AE42 -> 63677348 | AJ42: =SUM(AF42:AI42) -> 5.8630622e+08 | AK42: =AK41/(1+Parameters!$B$26) -> 0.30831867 | AL42: =AK42*AJ42 -> 1.8076915e+08 | AM42: =AL42/SUM(O41:Q41) -> 390.01435

Sheet Alt Scenario_2
A1: Alternative position - allowing for alternative drugs
A2: Determine cost for NPV to be equivalent to that from the initial position
C5: Different formulae - do not drag
Y8: Total PV | Z8: Goal seek
G9: Total | Y9: =SUM(Y13:Y43) -> 8.8497636e+09 | Z9: =Y9-'Base Scenario'!Y9 -> 0 | AA9: =IF(ABS(Z9-0)<0.1,"Goal seek okay","Need to goal seek") -> Goal seek okay
G10: =SUM(G14:G43) -> 20149312
I11: Overheads | M11: Drug | O11: Combined cost | S11: Cost per state x population | W11: Total cost | X11: v | Y11: PV of cost | Z11: Real cost per life alive
B12: Year | C12: Healthy | D12: Sick | E12: Very sick | F12: Dead | G12: Lives alive | H12: Excess deaths | I12: H | J12: S | K12: I | L12: D | M12: S | N12: I | O12: H | P12: S | Q12: I | R12: D | S12: H | T12: S | U12: I | V12: D
B13: 0 | C13: =Parameters!B12 -> 1000000 | D13: =Parameters!C12 -> 0 | E13: =Parameters!D12 -> 0 | F13: =Parameters!E12 -> 0 | G13: =SUM(C13:E13) -> 1000000 | H13: =F13 -> 0 | W13: =C13*O13+D13*P13+E13*Q13+H13*R13 -> 0 | X13: 1 | Y13: =W13*X13 -> 0
B14: 1 | C14: {=SUMPRODUCT($C13:$F13,TRANSPOSE(Parameters!C$6:C$9))+($B14-1)*SUMPRODUCT($C13:$F13,TRANSPOSE(Parameters!C$32:C$35))} -> 800000 | D14: {=SUMPRODUCT($C13:$F13,TRANSPOSE(Parameters!D$6:D$9))+($B14-1)*SUMPRODUCT($C13:$F13,TRANSPOSE(Parameters!D$32:D$35))} -> 160000 | E14: {=SUMPRODUCT($C13:$F13,TRANSPOSE(Parameters!E$6:E$9))+($B14-1)*SUMPRODUCT($C13:$F13,TRANSPOSE(Parameters!E$32:E$35))} -> 30000 | F14: {=SUMPRODUCT($C13:$F13,TRANSPOSE(Parameters!F$6:F$9))+($B14-1)*SUMPRODUCT($C13:$F13,TRANSPOSE(Parameters!F$32:F$35))} -> 10000 | G14: =SUM(C14:E14) -> 990000 | H14: =F14-F13 -> 10000 | I14: =Parameters!B15 -> 50 | J14: =Parameters!B16 -> 200 | K14: =Parameters!B17 -> 3000 | L14: =Parameters!B18 -> 250 | M14: =Parameters!B41 -> 236.97678 | N14: =Parameters!B42 -> 4739.5356 | O14: =I14 -> 50 | P14: =J14+M14 -> 436.97678 | Q14: =K14+N14 -> 7739.5356 | R14: =L14 -> 250 | S14: =C13*(Parameters!$C$6+($B14-1)*Parameters!$C$32)*O14+D13*(Parameters!$C$7+($B14-1)*Parameters!$C$33)*(O14+P14)/2+E13*(Parameters!$C$8+($B14-1)*Parameters!$C$34)*(O14+Q14)/2 -> 40000000 | T14: =C13*(Parameters!$D$6+($B14-1)*Parameters!$D$32)*(O14+P14)/2+D13*(Parameters!$D$7+($B14-1)*Parameters!$D$33)*P14+E13*(Parameters!$D$8+($B14-1)*Parameters!$D$34)*(P14+Q14)/2 -> 38958143 | U14: =C13*(Parameters!$E$6+($B14-1)*Parameters!$E$32)*(O14+Q14)/2+D13*(Parameters!$E$7+($B14-1)*Parameters!$E$33)*(P14+Q14)/2+E13*(Parameters!$E$8+($B14-1)*Parameters!$E$34)*Q14 -> 1.1684303e+08 | V14: =C13*(Parameters!$F$6+($B14-1)*Parameters!$F$32)*(O14/2+R14)+D13*(Parameters!$F$7+($B14-1)*Parameters!$F$33)*(P14/2+R14)+E13*(Parameters!$F$8+($B14-1)*Parameters!$F$34)*(Q14/2+R14) -> 2750000 | W14: =S14+T14+U14+V14 -> 1.9855118e+08 | X14: =1/(1+Parameters!$B$26) -> 0.96153846 | Y14: =W14*X14 -> 1.9091459e+08 | Z14: =Y14/G13 -> 190.91459
B15: 2 | C15: {=SUMPRODUCT($C14:$F14,TRANSPOSE(Parameters!C$6:C$9))+($B15-1)*SUMPRODUCT($C14:$F14,TRANSPOSE(Parameters!C$32:C$35))} -> 766059 | D15: {=SUMPRODUCT($C14:$F14,TRANSPOSE(Parameters!D$6:D$9))+($B15-1)*SUMPRODUCT($C14:$F14,TRANSPOSE(Parameters!D$32:D$35))} -> 150650 | E15: {=SUMPRODUCT($C14:$F14,TRANSPOSE(Parameters!E$6:E$9))+($B15-1)*SUMPRODUCT($C14:$F14,TRANSPOSE(Parameters!E$32:E$35))} -> 48442.2 | F15: {=SUMPRODUCT($C14:$F14,TRANSPOSE(Parameters!F$6:F$9))+($B15-1)*SUMPRODUCT($C14:$F14,TRANSPOSE(Parameters!F$32:F$35))} -> 34848.8 | G15: =SUM(C15:E15) -> 965151.2 | H15: =F15-F14 -> 24848.8 | I15: =I14*(1+Parameters!$B$24) -> 51 | J15: =J14*(1+Parameters!$B$24) -> 204 | K15: =K14*(1+Parameters!$B$24) -> 3060 | L15: =L14*(1+Parameters!$B$24) -> 255 | M15: =M14*(1+Parameters!$B$25) -> 248.82562 | N15: =N14*(1+Parameters!$B$25) -> 4976.5124 | O15: =I15 -> 51 | P15: =J15+M15 -> 452.82562 | Q15: =K15+N15 -> 8036.5124 | R15: =L15 -> 255 | S15: =C14*(Parameters!$C$6+($B15-1)*Parameters!$C$32)*O15+D14*(Parameters!$C$7+($B15-1)*Parameters!$C$33)*(O15+P15)/2+E14*(Parameters!$C$8+($B15-1)*Parameters!$C$34)*(O15+Q15)/2 -> 81226735 | T15: =C14*(Parameters!$D$6+($B15-1)*Parameters!$D$32)*(O15+P15)/2+D14*(Parameters!$D$7+($B15-1)*Parameters!$D$33)*P15+E14*(Parameters!$D$8+($B15-1)*Parameters!$D$34)*(P15+Q15)/2 -> 71246797 | U15: =C14*(Parameters!$E$6+($B15-1)*Parameters!$E$32)*(O15+Q15)/2+D14*(Parameters!$E$7+($B15-1)*Parameters!$E$33)*(P15+Q15)/2+E14*(Parameters!$E$8+($B15-1)*Parameters!$E$34)*Q15 -> 2.3507107e+08 | V15: =C14*(Parameters!$F$6+($B15-1)*Parameters!$F$32)*(O15/2+R15)+D14*(Parameters!$F$7+($B15-1)*Parameters!$F$33)*(P15/2+R15)+E14*(Parameters!$F$8+($B15-1)*Parameters!$F$34)*(Q15/2+R15) -> 44262345 | W15: =S15+T15+U15+V15 -> 4.3180694e+08 | X15: =X14/(1+Parameters!$B$26) -> 0.92455621 | Y15: =W15*X15 -> 3.9922979e+08 | Z15: =Y15/G14 -> 403.26242
B16: 3 | C16: {=SUMPRODUCT($C15:$F15,TRANSPOSE(Parameters!C$6:C$9))+($B16-1)*SUMPRODUCT($C15:$F15,TRANSPOSE(Parameters!C$32:C$35))} -> 736103.13 | D16: {=SUMPRODUCT($C15:$F15,TRANSPOSE(Parameters!D$6:D$9))+($B16-1)*SUMPRODUCT($C15:$F15,TRANSPOSE(Parameters!D$32:D$35))} -> 148153.98 | E16: {=SUMPRODUCT($C15:$F15,TRANSPOSE(Parameters!E$6:E$9))+($B16-1)*SUMPRODUCT($C15:$F15,TRANSPOSE(Parameters!E$32:E$35))} -> 51535.128 | F16: {=SUMPRODUCT($C15:$F15,TRANSPOSE(Parameters!F$6:F$9))+($B16-1)*SUMPRODUCT($C15:$F15,TRANSPOSE(Parameters!F$32:F$35))} -> 64207.759 | G16: =SUM(C16:E16) -> 935792.24 | H16: =F16-F15 -> 29358.959 | I16: =I15*(1+Parameters!$B$24) -> 52.02 | J16: =J15*(1+Parameters!$B$24) -> 208.08 | K16: =K15*(1+Parameters!$B$24) -> 3121.2 | L16: =L15*(1+Parameters!$B$24) -> 260.1 | M16: =M15*(1+Parameters!$B$25) -> 261.2669 | N16: =N15*(1+Parameters!$B$25) -> 5225.338 | O16: =I16 -> 52.02 | P16: =J16+M16 -> 469.3469 | Q16: =K16+N16 -> 8346.538 | R16: =L16 -> 260.1 | S16: =C15*(Parameters!$C$6+($B16-1)*Parameters!$C$32)*O16+D15*(Parameters!$C$7+($B16-1)*Parameters!$C$33)*(O16+P16)/2+E15*(Parameters!$C$8+($B16-1)*Parameters!$C$34)*(O16+Q16)/2 -> 92245567 | T16: =C15*(Parameters!$D$6+($B16-1)*Parameters!$D$32)*(O16+P16)/2+D15*(Parameters!$D$7+($B16-1)*Parameters!$D$33)*P16+E15*(Parameters!$D$8+($B16-1)*Parameters!$D$34)*(P16+Q16)/2 -> 92423634 | U16: =C15*(Parameters!$E$6+($B16-1)*Parameters!$E$32)*(O16+Q16)/2+D15*(Parameters!$E$7+($B16-1)*Parameters!$E$33)*(P16+Q16)/2+E15*(Parameters!$E$8+($B16-1)*Parameters!$E$34)*Q16 -> 2.7997332e+08 | V16: =C15*(Parameters!$F$6+($B16-1)*Parameters!$F$32)*(O16/2+R16)+D15*(Parameters!$F$7+($B16-1)*Parameters!$F$33)*(P16/2+R16)+E15*(Parameters!$F$8+($B16-1)*Parameters!$F$34)*(Q16/2+R16) -> 69418627 | W16: =S16+T16+U16+V16 -> 5.3406115e+08 | X16: =X15/(1+Parameters!$B$26) -> 0.88899636 | Y16: =W16*X16 -> 4.7477842e+08 | Z16: =Y16/G15 -> 491.92128
B17: 4 | C17: {=SUMPRODUCT($C16:$F16,TRANSPOSE(Parameters!C$6:C$9))+($B17-1)*SUMPRODUCT($C16:$F16,TRANSPOSE(Parameters!C$32:C$35))} -> 712069.42 | D17: {=SUMPRODUCT($C16:$F16,TRANSPOSE(Parameters!D$6:D$9))+($B17-1)*SUMPRODUCT($C16:$F16,TRANSPOSE(Parameters!D$32:D$35))} -> 143202.55 | E17: {=SUMPRODUCT($C16:$F16,TRANSPOSE(Parameters!E$6:E$9))+($B17-1)*SUMPRODUCT($C16:$F16,TRANSPOSE(Parameters!E$32:E$35))} -> 50852.86 | F17: {=SUMPRODUCT($C16:$F16,TRANSPOSE(Parameters!F$6:F$9))+($B17-1)*SUMPRODUCT($C16:$F16,TRANSPOSE(Parameters!F$32:F$35))} -> 93875.174 | G17: =SUM(C17:E17) -> 906124.83 | H17: =F17-F16 -> 29667.415 | I17: =I16*(1+Parameters!$B$24) -> 53.0604 | J17: =J16*(1+Parameters!$B$24) -> 212.2416 | K17: =K16*(1+Parameters!$B$24) -> 3183.624 | L17: =L16*(1+Parameters!$B$24) -> 265.302 | M17: =M16*(1+Parameters!$B$25) -> 274.33025 | N17: =N16*(1+Parameters!$B$25) -> 5486.6049 | O17: =I17 -> 53.0604 | P17: =J17+M17 -> 486.57185 | Q17: =K17+N17 -> 8670.2289 | R17: =L17 -> 265.302 | S17: =C16*(Parameters!$C$6+($B17-1)*Parameters!$C$32)*O17+D16*(Parameters!$C$7+($B17-1)*Parameters!$C$33)*(O17+P17)/2+E16*(Parameters!$C$8+($B17-1)*Parameters!$C$34)*(O17+Q17)/2 -> 95569808 | T17: =C16*(Parameters!$D$6+($B17-1)*Parameters!$D$32)*(O17+P17)/2+D16*(Parameters!$D$7+($B17-1)*Parameters!$D$33)*P17+E16*(Parameters!$D$8+($B17-1)*Parameters!$D$34)*(P17+Q17)/2 -> 98074839 | U17: =C16*(Parameters!$E$6+($B17-1)*Parameters!$E$32)*(O17+Q17)/2+D16*(Parameters!$E$7+($B17-1)*Parameters!$E$33)*(P17+Q17)/2+E16*(Parameters!$E$8+($B17-1)*Parameters!$E$34)*Q17 -> 2.9187956e+08 | V17: =C16*(Parameters!$F$6+($B17-1)*Parameters!$F$32)*(O17/2+R17)+D16*(Parameters!$F$7+($B17-1)*Parameters!$F$33)*(P17/2+R17)+E16*(Parameters!$F$8+($B17-1)*Parameters!$F$34)*(Q17/2+R17) -> 75513512 | W17: =S17+T17+U17+V17 -> 5.6103772e+08 | X17: =X16/(1+Parameters!$B$26) -> 0.85480419 | Y17: =W17*X17 -> 4.795774e+08 | Z17: =Y17/G16 -> 512.48277
B18: 5 | C18: {=SUMPRODUCT($C17:$F17,TRANSPOSE(Parameters!C$6:C$9))+($B18-1)*SUMPRODUCT($C17:$F17,TRANSPOSE(Parameters!C$32:C$35))} -> 690286.31 | D18: {=SUMPRODUCT($C17:$F17,TRANSPOSE(Parameters!D$6:D$9))+($B18-1)*SUMPRODUCT($C17:$F17,TRANSPOSE(Parameters!D$32:D$35))} -> 138036.46 | E18: {=SUMPRODUCT($C17:$F17,TRANSPOSE(Parameters!E$6:E$9))+($B18-1)*SUMPRODUCT($C17:$F17,TRANSPOSE(Parameters!E$32:E$35))} -> 48997.916 | F18: {=SUMPRODUCT($C17:$F17,TRANSPOSE(Parameters!F$6:F$9))+($B18-1)*SUMPRODUCT($C17:$F17,TRANSPOSE(Parameters!F$32:F$35))} -> 122679.32 | G18: =SUM(C18:E18) -> 877320.68 | H18: =F18-F17 -> 28804.143 | I18: =I17*(1+Parameters!$B$24) -> 54.121608 | J18: =J17*(1+Parameters!$B$24) -> 216.48643 | K18: =K17*(1+Parameters!$B$24) -> 3247.2965 | L18: =L17*(1+Parameters!$B$24) -> 270.60804 | M18: =M17*(1+Parameters!$B$25) -> 288.04676 | N18: =N17*(1+Parameters!$B$25) -> 5760.9352 | O18: =I18 -> 54.121608 | P18: =J18+M18 -> 504.53319 | Q18: =K18+N18 -> 9008.2317 | R18: =L18 -> 270.60804 | S18: =C17*(Parameters!$C$6+($B18-1)*Parameters!$C$32)*O18+D17*(Parameters!$C$7+($B18-1)*Parameters!$C$33)*(O18+P18)/2+E17*(Parameters!$C$8+($B18-1)*Parameters!$C$34)*(O18+Q18)/2 -> 96236787 | T18: =C17*(Parameters!$D$6+($B18-1)*Parameters!$D$32)*(O18+P18)/2+D17*(Parameters!$D$7+($B18-1)*Parameters!$D$33)*P18+E17*(Parameters!$D$8+($B18-1)*Parameters!$D$34)*(P18+Q18)/2 -> 99675317 | U18: =C17*(Parameters!$E$6+($B18-1)*Parameters!$E$32)*(O18+Q18)/2+D17*(Parameters!$E$7+($B18-1)*Parameters!$E$33)*(P18+Q18)/2+E17*(Parameters!$E$8+($B18-1)*Parameters!$E$34)*Q18 -> 2.938928e+08 | V18: =C17*(Parameters!$F$6+($B18-1)*Parameters!$F$32)*(O18/2+R18)+D17*(Parameters!$F$7+($B18-1)*Parameters!$F$33)*(P18/2+R18)+E17*(Parameters!$F$8+($B18-1)*Parameters!$F$34)*(Q18/2+R18) -> 76625265 | W18: =S18+T18+U18+V18 -> 5.6643017e+08 | X18: =X17/(1+Parameters!$B$26) -> 0.82192711 | Y18: =W18*X18 -> 4.6556431e+08 | Z18: =Y18/G17 -> 513.7971
B19: 6 | C19: {=SUMPRODUCT($C18:$F18,TRANSPOSE(Parameters!C$6:C$9))+($B19-1)*SUMPRODUCT($C18:$F18,TRANSPOSE(Parameters!C$32:C$35))} -> 669889.77 | D19: {=SUMPRODUCT($C18:$F18,TRANSPOSE(Parameters!D$6:D$9))+($B19-1)*SUMPRODUCT($C18:$F18,TRANSPOSE(Parameters!D$32:D$35))} -> 132947.3 | E19: {=SUMPRODUCT($C18:$F18,TRANSPOSE(Parameters!E$6:E$9))+($B19-1)*SUMPRODUCT($C18:$F18,TRANSPOSE(Parameters!E$32:E$35))} -> 46862.966 | F19: {=SUMPRODUCT($C18:$F18,TRANSPOSE(Parameters!F$6:F$9))+($B19-1)*SUMPRODUCT($C18:$F18,TRANSPOSE(Parameters!F$32:F$35))} -> 150299.97 | G19: =SUM(C19:E19) -> 849700.03 | H19: =F19-F18 -> 27620.652 | I19: =I18*(1+Parameters!$B$24) -> 55.20404 | J19: =J18*(1+Parameters!$B$24) -> 220.81616 | K19: =K18*(1+Parameters!$B$24) -> 3312.2424 | L19: =L18*(1+Parameters!$B$24) -> 276.0202 | M19: =M18*(1+Parameters!$B$25) -> 302.4491 | N19: =N18*(1+Parameters!$B$25) -> 6048.9819 | O19: =I19 -> 55.20404 | P19: =J19+M19 -> 523.26526 | Q19: =K19+N19 -> 9361.2243 | R19: =L19 -> 276.0202 | S19: =C18*(Parameters!$C$6+($B19-1)*Parameters!$C$32)*O19+D18*(Parameters!$C$7+($B19-1)*Parameters!$C$33)*(O19+P19)/2+E18*(Parameters!$C$8+($B19-1)*Parameters!$C$34)*(O19+Q19)/2 -> 96082319 | T19: =C18*(Parameters!$D$6+($B19-1)*Parameters!$D$32)*(O19+P19)/2+D18*(Parameters!$D$7+($B19-1)*Parameters!$D$33)*P19+E18*(Parameters!$D$8+($B19-1)*Parameters!$D$34)*(P19+Q19)/2 -> 99901091 | U19: =C18*(Parameters!$E$6+($B19-1)*Parameters!$E$32)*(O19+Q19)/2+D18*(Parameters!$E$7+($B19-1)*Parameters!$E$33)*(P19+Q19)/2+E18*(Parameters!$E$8+($B19-1)*Parameters!$E$34)*Q19 -> 2.927036e+08 | V19: =C18*(Parameters!$F$6+($B19-1)*Parameters!$F$32)*(O19/2+R19)+D18*(Parameters!$F$7+($B19-1)*Parameters!$F$33)*(P19/2+R19)+E18*(Parameters!$F$8+($B19-1)*Parameters!$F$34)*(Q19/2+R19) -> 76066256 | W19: =S19+T19+U19+V19 -> 5.6475327e+08 | X19: =X18/(1+Parameters!$B$26) -> 0.79031453 | Y19: =W19*X19 -> 4.4633271e+08 | Z19: =Y19/G18 -> 508.74523
B20: 7 | C20: {=SUMPRODUCT($C19:$F19,TRANSPOSE(Parameters!C$6:C$9))+($B20-1)*SUMPRODUCT($C19:$F19,TRANSPOSE(Parameters!C$32:C$35))} -> 650545.62 | D20: {=SUMPRODUCT($C19:$F19,TRANSPOSE(Parameters!D$6:D$9))+($B20-1)*SUMPRODUCT($C19:$F19,TRANSPOSE(Parameters!D$32:D$35))} -> 128049.65 | E20: {=SUMPRODUCT($C19:$F19,TRANSPOSE(Parameters!E$6:E$9))+($B20-1)*SUMPRODUCT($C19:$F19,TRANSPOSE(Parameters!E$32:E$35))} -> 44718.188 | F20: {=SUMPRODUCT($C19:$F19,TRANSPOSE(Parameters!F$6:F$9))+($B20-1)*SUMPRODUCT($C19:$F19,TRANSPOSE(Parameters!F$32:F$35))} -> 176686.54 | G20: =SUM(C20:E20) -> 823313.46 | H20: =F20-F19 -> 26386.571 | I20: =I19*(1+Parameters!$B$24) -> 56.308121 | J20: =J19*(1+Parameters!$B$24) -> 225.23248 | K20: =K19*(1+Parameters!$B$24) -> 3378.4873 | L20: =L19*(1+Parameters!$B$24) -> 281.5406 | M20: =M19*(1+Parameters!$B$25) -> 317.57155 | N20: =N19*(1+Parameters!$B$25) -> 6351.431 | O20: =I20 -> 56.308121 | P20: =J20+M20 -> 542.80404 | Q20: =K20+N20 -> 9729.9183 | R20: =L20 -> 281.5406 | S20: =C19*(Parameters!$C$6+($B20-1)*Parameters!$C$32)*O20+D19*(Parameters!$C$7+($B20-1)*Parameters!$C$33)*(O20+P20)/2+E19*(Parameters!$C$8+($B20-1)*Parameters!$C$34)*(O20+Q20)/2 -> 95691549 | T20: =C19*(Parameters!$D$6+($B20-1)*Parameters!$D$32)*(O20+P20)/2+D19*(Parameters!$D$7+($B20-1)*Parameters!$D$33)*P20+E19*(Parameters!$D$8+($B20-1)*Parameters!$D$34)*(P20+Q20)/2 -> 99715744 | U20: =C19*(Parameters!$E$6+($B20-1)*Parameters!$E$32)*(O20+Q20)/2+D19*(Parameters!$E$7+($B20-1)*Parameters!$E$33)*(P20+Q20)/2+E19*(Parameters!$E$8+($B20-1)*Parameters!$E$34)*Q20 -> 2.9056413e+08 | V20: =C19*(Parameters!$F$6+($B20-1)*Parameters!$F$32)*(O20/2+R20)+D19*(Parameters!$F$7+($B20-1)*Parameters!$F$33)*(P20/2+R20)+E19*(Parameters!$F$8+($B20-1)*Parameters!$F$34)*(Q20/2+R20) -> 75006752 | W20: =S20+T20+U20+V20 -> 5.6097818e+08 | X20: =X19/(1+Parameters!$B$26) -> 0.75991781 | Y20: =W20*X20 -> 4.2629731e+08 | Z20: =Y20/G19 -> 501.7033
B21: 8 | C21: {=SUMPRODUCT($C20:$F20,TRANSPOSE(Parameters!C$6:C$9))+($B21-1)*SUMPRODUCT($C20:$F20,TRANSPOSE(Parameters!C$32:C$35))} -> 632117.48 | D21: {=SUMPRODUCT($C20:$F20,TRANSPOSE(Parameters!D$6:D$9))+($B21-1)*SUMPRODUCT($C20:$F20,TRANSPOSE(Parameters!D$32:D$35))} -> 123368.43 | E21: {=SUMPRODUCT($C20:$F20,TRANSPOSE(Parameters!E$6:E$9))+($B21-1)*SUMPRODUCT($C20:$F20,TRANSPOSE(Parameters!E$32:E$35))} -> 42644.734 | F21: {=SUMPRODUCT($C20:$F20,TRANSPOSE(Parameters!F$6:F$9))+($B21-1)*SUMPRODUCT($C20:$F20,TRANSPOSE(Parameters!F$32:F$35))} -> 201869.36 | G21: =SUM(C21:E21) -> 798130.64 | H21: =F21-F20 -> 25182.818 | I21: =I20*(1+Parameters!$B$24) -> 57.434283 | J21: =J20*(1+Parameters!$B$24) -> 229.73713 | K21: =K20*(1+Parameters!$B$24) -> 3446.057 | L21: =L20*(1+Parameters!$B$24) -> 287.17142 | M21: =M20*(1+Parameters!$B$25) -> 333.45013 | N21: =N20*(1+Parameters!$B$25) -> 6669.0026 | O21: =I21 -> 57.434283 | P21: =J21+M21 -> 563.18726 | Q21: =K21+N21 -> 10115.06 | R21: =L21 -> 287.17142 | S21: =C20*(Parameters!$C$6+($B21-1)*Parameters!$C$32)*O21+D20*(Parameters!$C$7+($B21-1)*Parameters!$C$33)*(O21+P21)/2+E20*(Parameters!$C$8+($B21-1)*Parameters!$C$34)*(O21+Q21)/2 -> 95257092 | T21: =C20*(Parameters!$D$6+($B21-1)*Parameters!$D$32)*(O21+P21)/2+D20*(Parameters!$D$7+($B21-1)*Parameters!$D$33)*P21+E20*(Parameters!$D$8+($B21-1)*Parameters!$D$34)*(P21+Q21)/2 -> 99427963 | U21: =C20*(Parameters!$E$6+($B21-1)*Parameters!$E$32)*(O21+Q21)/2+D20*(Parameters!$E$7+($B21-1)*Parameters!$E$33)*(P21+Q21)/2+E20*(Parameters!$E$8+($B21-1)*Parameters!$E$34)*Q21 -> 2.8820249e+08 | V21: =C20*(Parameters!$F$6+($B21-1)*Parameters!$F$32)*(O21/2+R21)+D20*(Parameters!$F$7+($B21-1)*Parameters!$F$33)*(P21/2+R21)+E20*(Parameters!$F$8+($B21-1)*Parameters!$F$34)*(Q21/2+R21) -> 73816973 | W21: =S21+T21+U21+V21 -> 5.5670451e+08 | X21: =X20/(1+Parameters!$B$26) -> 0.73069021 | Y21: =W21*X21 -> 4.0677854e+08 | Z21: =Y21/G20 -> 494.07492
B22: 9 | C22: {=SUMPRODUCT($C21:$F21,TRANSPOSE(Parameters!C$6:C$9))+($B22-1)*SUMPRODUCT($C21:$F21,TRANSPOSE(Parameters!C$32:C$35))} -> 614531.6 | D22: {=SUMPRODUCT($C21:$F21,TRANSPOSE(Parameters!D$6:D$9))+($B22-1)*SUMPRODUCT($C21:$F21,TRANSPOSE(Parameters!D$32:D$35))} -> 118903.13 | E22: {=SUMPRODUCT($C21:$F21,TRANSPOSE(Parameters!E$6:E$9))+($B22-1)*SUMPRODUCT($C21:$F21,TRANSPOSE(Parameters!E$32:E$35))} -> 40663.883 | F22: {=SUMPRODUCT($C21:$F21,TRANSPOSE(Parameters!F$6:F$9))+($B22-1)*SUMPRODUCT($C21:$F21,TRANSPOSE(Parameters!F$32:F$35))} -> 225901.39 | G22: =SUM(C22:E22) -> 774098.61 | H22: =F22-F21 -> 24032.031 | I22: =I21*(1+Parameters!$B$24) -> 58.582969 | J22: =J21*(1+Parameters!$B$24) -> 234.33188 | K22: =K21*(1+Parameters!$B$24) -> 3514.9781 | L22: =L21*(1+Parameters!$B$24) -> 292.91485 | M22: =M21*(1+Parameters!$B$25) -> 350.12264 | N22: =N21*(1+Parameters!$B$25) -> 7002.4527 | O22: =I22 -> 58.582969 | P22: =J22+M22 -> 584.45451 | Q22: =K22+N22 -> 10517.431 | R22: =L22 -> 292.91485 | S22: =C21*(Parameters!$C$6+($B22-1)*Parameters!$C$32)*O22+D21*(Parameters!$C$7+($B22-1)*Parameters!$C$33)*(O22+P22)/2+E21*(Parameters!$C$8+($B22-1)*Parameters!$C$34)*(O22+Q22)/2 -> 94841382 | T22: =C21*(Parameters!$D$6+($B22-1)*Parameters!$D$32)*(O22+P22)/2+D21*(Parameters!$D$7+($B22-1)*Parameters!$D$33)*P22+E21*(Parameters!$D$8+($B22-1)*Parameters!$D$34)*(P22+Q22)/2 -> 99139041 | U22: =C21*(Parameters!$E$6+($B22-1)*Parameters!$E$32)*(O22+Q22)/2+D21*(Parameters!$E$7+($B22-1)*Parameters!$E$33)*(P22+Q22)/2+E21*(Parameters!$E$8+($B22-1)*Parameters!$E$34)*Q22 -> 2.8585355e+08 | V22: =C21*(Parameters!$F$6+($B22-1)*Parameters!$F$32)*(O22/2+R22)+D21*(Parameters!$F$7+($B22-1)*Parameters!$F$33)*(P22/2+R22)+E21*(Parameters!$F$8+($B22-1)*Parameters!$F$34)*(Q22/2+R22) -> 72616230 | W22: =S22+T22+U22+V22 -> 5.5245021e+08 | X22: =X21/(1+Parameters!$B$26) -> 0.70258674 | Y22: =W22*X22 -> 3.8814419e+08 | Z22: =Y22/G21 -> 486.31661
B23: 10 | C23: {=SUMPRODUCT($C22:$F22,TRANSPOSE(Parameters!C$6:C$9))+($B23-1)*SUMPRODUCT($C22:$F22,TRANSPOSE(Parameters!C$32:C$35))} -> 597736.19 | D23: {=SUMPRODUCT($C22:$F22,TRANSPOSE(Parameters!D$6:D$9))+($B23-1)*SUMPRODUCT($C22:$F22,TRANSPOSE(Parameters!D$32:D$35))} -> 114645.44 | E23: {=SUMPRODUCT($C22:$F22,TRANSPOSE(Parameters!E$6:E$9))+($B23-1)*SUMPRODUCT($C22:$F22,TRANSPOSE(Parameters!E$32:E$35))} -> 38778.275 | F23: {=SUMPRODUCT($C22:$F22,TRANSPOSE(Parameters!F$6:F$9))+($B23-1)*SUMPRODUCT($C22:$F22,TRANSPOSE(Parameters!F$32:F$35))} -> 248840.1 | G23: =SUM(C23:E23) -> 751159.9 | H23: =F23-F22 -> 22938.707 | I23: =I22*(1+Parameters!$B$24) -> 59.754628 | J23: =J22*(1+Parameters!$B$24) -> 239.01851 | K23: =K22*(1+Parameters!$B$24) -> 3585.2777 | L23: =L22*(1+Parameters!$B$24) -> 298.77314 | M23: =M22*(1+Parameters!$B$25) -> 367.62877 | N23: =N22*(1+Parameters!$B$25) -> 7352.5754 | O23: =I23 -> 59.754628 | P23: =J23+M23 -> 606.64728 | Q23: =K23+N23 -> 10937.853 | R23: =L23 -> 298.77314 | S23: =C22*(Parameters!$C$6+($B23-1)*Parameters!$C$32)*O23+D22*(Parameters!$C$7+($B23-1)*Parameters!$C$33)*(O23+P23)/2+E22*(Parameters!$C$8+($B23-1)*Parameters!$C$34)*(O23+Q23)/2 -> 94464133 | T23: =C22*(Parameters!$D$6+($B23-1)*Parameters!$D$32)*(O23+P23)/2+D22*(Parameters!$D$7+($B23-1)*Parameters!$D$33)*P23+E22*(Parameters!$D$8+($B23-1)*Parameters!$D$34)*(P23+Q23)/2 -> 98881414 | U23: =C22*(Parameters!$E$6+($B23-1)*Parameters!$E$32)*(O23+Q23)/2+D22*(Parameters!$E$7+($B23-1)*Parameters!$E$33)*(P23+Q23)/2+E22*(Parameters!$E$8+($B23-1)*Parameters!$E$34)*Q23 -> 2.8358975e+08 | V23: =C22*(Parameters!$F$6+($B23-1)*Parameters!$F$32)*(O23/2+R23)+D22*(Parameters!$F$7+($B23-1)*Parameters!$F$33)*(P23/2+R23)+E22*(Parameters!$F$8+($B23-1)*Parameters!$F$34)*(Q23/2+R23) -> 71441606 | W23: =S23+T23+U23+V23 -> 5.483769e+08 | X23: =X22/(1+Parameters!$B$26) -> 0.67556417 | Y23: =W23*X23 -> 3.7046379e+08 | Z23: =Y23/G22 -> 478.57441
B24: 11 | C24: {=SUMPRODUCT($C23:$F23,TRANSPOSE(Parameters!C$6:C$9))+($B24-1)*SUMPRODUCT($C23:$F23,TRANSPOSE(Parameters!C$32:C$35))} -> 581688.11 | D24: {=SUMPRODUCT($C23:$F23,TRANSPOSE(Parameters!D$6:D$9))+($B24-1)*SUMPRODUCT($C23:$F23,TRANSPOSE(Parameters!D$32:D$35))} -> 110585.08 | E24: {=SUMPRODUCT($C23:$F23,TRANSPOSE(Parameters!E$6:E$9))+($B24-1)*SUMPRODUCT($C23:$F23,TRANSPOSE(Parameters!E$32:E$35))} -> 36984.897 | F24: {=SUMPRODUCT($C23:$F23,TRANSPOSE(Parameters!F$6:F$9))+($B24-1)*SUMPRODUCT($C23:$F23,TRANSPOSE(Parameters!F$32:F$35))} -> 270741.91 | G24: =SUM(C24:E24) -> 729258.09 | H24: =F24-F23 -> 21901.817 | I24: =I23*(1+Parameters!$B$24) -> 60.949721 | J24: =J23*(1+Parameters!$B$24) -> 243.79888 | K24: =K23*(1+Parameters!$B$24) -> 3656.9833 | L24: =L23*(1+Parameters!$B$24) -> 304.7486 | M24: =M23*(1+Parameters!$B$25) -> 386.01021 | N24: =N23*(1+Parameters!$B$25) -> 7720.2041 | O24: =I24 -> 60.949721 | P24: =J24+M24 -> 629.80909 | Q24: =K24+N24 -> 11377.187 | R24: =L24 -> 304.7486 | S24: =C23*(Parameters!$C$6+($B24-1)*Parameters!$C$32)*O24+D23*(Parameters!$C$7+($B24-1)*Parameters!$C$33)*(O24+P24)/2+E23*(Parameters!$C$8+($B24-1)*Parameters!$C$34)*(O24+Q24)/2 -> 94130982 | T24: =C23*(Parameters!$D$6+($B24-1)*Parameters!$D$32)*(O24+P24)/2+D23*(Parameters!$D$7+($B24-1)*Parameters!$D$33)*P24+E23*(Parameters!$D$8+($B24-1)*Parameters!$D$34)*(P24+Q24)/2 -> 98664852 | U24: =C23*(Parameters!$E$6+($B24-1)*Parameters!$E$32)*(O24+Q24)/2+D23*(Parameters!$E$7+($B24-1)*Parameters!$E$33)*(P24+Q24)/2+E23*(Parameters!$E$8+($B24-1)*Parameters!$E$34)*Q24 -> 2.8143006e+08 | V24: =C23*(Parameters!$F$6+($B24-1)*Parameters!$F$32)*(O24/2+R24)+D23*(Parameters!$F$7+($B24-1)*Parameters!$F$33)*(P24/2+R24)+E23*(Parameters!$F$8+($B24-1)*Parameters!$F$34)*(Q24/2+R24) -> 70303469 | W24: =S24+T24+U24+V24 -> 5.4452936e+08 | X24: =X23/(1+Parameters!$B$26) -> 0.64958093 | Y24: =W24*X24 -> 3.5371589e+08 | Z24: =Y24/G23 -> 470.89293
B25: 12 | C25: {=SUMPRODUCT($C24:$F24,TRANSPOSE(Parameters!C$6:C$9))+($B25-1)*SUMPRODUCT($C24:$F24,TRANSPOSE(Parameters!C$32:C$35))} -> 566348.56 | D25: {=SUMPRODUCT($C24:$F24,TRANSPOSE(Parameters!D$6:D$9))+($B25-1)*SUMPRODUCT($C24:$F24,TRANSPOSE(Parameters!D$32:D$35))} -> 106711.6 | E25: {=SUMPRODUCT($C24:$F24,TRANSPOSE(Parameters!E$6:E$9))+($B25-1)*SUMPRODUCT($C24:$F24,TRANSPOSE(Parameters!E$32:E$35))} -> 35279.182 | F25: {=SUMPRODUCT($C24:$F24,TRANSPOSE(Parameters!F$6:F$9))+($B25-1)*SUMPRODUCT($C24:$F24,TRANSPOSE(Parameters!F$32:F$35))} -> 291660.66 | G25: =SUM(C25:E25) -> 708339.34 | H25: =F25-F24 -> 20918.749 | I25: =I24*(1+Parameters!$B$24) -> 62.168715 | J25: =J24*(1+Parameters!$B$24) -> 248.67486 | K25: =K24*(1+Parameters!$B$24) -> 3730.1229 | L25: =L24*(1+Parameters!$B$24) -> 310.84358 | M25: =M24*(1+Parameters!$B$25) -> 405.31072 | N25: =N24*(1+Parameters!$B$25) -> 8106.2143 | O25: =I25 -> 62.168715 | P25: =J25+M25 -> 653.98558 | Q25: =K25+N25 -> 11836.337 | R25: =L25 -> 310.84358 | S25: =C24*(Parameters!$C$6+($B25-1)*Parameters!$C$32)*O25+D24*(Parameters!$C$7+($B25-1)*Parameters!$C$33)*(O25+P25)/2+E24*(Parameters!$C$8+($B25-1)*Parameters!$C$34)*(O25+Q25)/2 -> 93842939 | T25: =C24*(Parameters!$D$6+($B25-1)*Parameters!$D$32)*(O25+P25)/2+D24*(Parameters!$D$7+($B25-1)*Parameters!$D$33)*P25+E24*(Parameters!$D$8+($B25-1)*Parameters!$D$34)*(P25+Q25)/2 -> 98491634 | U25: =C24*(Parameters!$E$6+($B25-1)*Parameters!$E$32)*(O25+Q25)/2+D24*(Parameters!$E$7+($B25-1)*Parameters!$E$33)*(P25+Q25)/2+E24*(Parameters!$E$8+($B25-1)*Parameters!$E$34)*Q25 -> 2.7937582e+08 | V25: =C24*(Parameters!$F$6+($B25-1)*Parameters!$F$32)*(O25/2+R25)+D24*(Parameters!$F$7+($B25-1)*Parameters!$F$33)*(P25/2+R25)+E24*(Parameters!$F$8+($B25-1)*Parameters!$F$34)*(Q25/2+R25) -> 69203504 | W25: =S25+T25+U25+V25 -> 5.409139e+08 | X25: =X24/(1+Parameters!$B$26) -> 0.62459705 | Y25: =W25*X25 -> 3.3785322e+08 | Z25: =Y25/G24 -> 463.28348
B26: 13 | C26: {=SUMPRODUCT($C25:$F25,TRANSPOSE(Parameters!C$6:C$9))+($B26-1)*SUMPRODUCT($C25:$F25,TRANSPOSE(Parameters!C$32:C$35))} -> 551681.58 | D26: {=SUMPRODUCT($C25:$F25,TRANSPOSE(Parameters!D$6:D$9))+($B26-1)*SUMPRODUCT($C25:$F25,TRANSPOSE(Parameters!D$32:D$35))} -> 103014.93 | E26: {=SUMPRODUCT($C25:$F25,TRANSPOSE(Parameters!E$6:E$9))+($B26-1)*SUMPRODUCT($C25:$F25,TRANSPOSE(Parameters!E$32:E$35))} -> 33656.298 | F26: {=SUMPRODUCT($C25:$F25,TRANSPOSE(Parameters!F$6:F$9))+($B26-1)*SUMPRODUCT($C25:$F25,TRANSPOSE(Parameters!F$32:F$35))} -> 311647.2 | G26: =SUM(C26:E26) -> 688352.8 | H26: =F26-F25 -> 19986.538 | I26: =I25*(1+Parameters!$B$24) -> 63.41209 | J26: =J25*(1+Parameters!$B$24) -> 253.64836 | K26: =K25*(1+Parameters!$B$24) -> 3804.7254 | L26: =L25*(1+Parameters!$B$24) -> 317.06045 | M26: =M25*(1+Parameters!$B$25) -> 425.57625 | N26: =N25*(1+Parameters!$B$25) -> 8511.525 | O26: =I26 -> 63.41209 | P26: =J26+M26 -> 679.22461 | Q26: =K26+N26 -> 12316.25 | R26: =L26 -> 317.06045 | S26: =C25*(Parameters!$C$6+($B26-1)*Parameters!$C$32)*O26+D25*(Parameters!$C$7+($B26-1)*Parameters!$C$33)*(O26+P26)/2+E25*(Parameters!$C$8+($B26-1)*Parameters!$C$34)*(O26+Q26)/2 -> 93599514 | T26: =C25*(Parameters!$D$6+($B26-1)*Parameters!$D$32)*(O26+P26)/2+D25*(Parameters!$D$7+($B26-1)*Parameters!$D$33)*P26+E25*(Parameters!$D$8+($B26-1)*Parameters!$D$34)*(P26+Q26)/2 -> 98361578 | U26: =C25*(Parameters!$E$6+($B26-1)*Parameters!$E$32)*(O26+Q26)/2+D25*(Parameters!$E$7+($B26-1)*Parameters!$E$33)*(P26+Q26)/2+E25*(Parameters!$E$8+($B26-1)*Parameters!$E$34)*Q26 -> 2.774226e+08 | V26: =C25*(Parameters!$F$6+($B26-1)*Parameters!$F$32)*(O26/2+R26)+D25*(Parameters!$F$7+($B26-1)*Parameters!$F$33)*(P26/2+R26)+E25*(Parameters!$F$8+($B26-1)*Parameters!$F$34)*(Q26/2+R26) -> 68140598 | W26: =S26+T26+U26+V26 -> 5.3752429e+08 | X26: =X25/(1+Parameters!$B$26) -> 0.60057409 | Y26: =W26*X26 -> 3.2282316e+08 | Z26: =Y26/G25 -> 455.74648
... B43: 30 | C43: {=SUMPRODUCT($C42:$F42,TRANSPOSE(Parameters!C$6:C$9))+($B43-1)*SUMPRODUCT($C42:$F42,TRANSPOSE(Parameters!C$32:C$35))} -> 378968.58 | D43: {=SUMPRODUCT($C42:$F42,TRANSPOSE(Parameters!D$6:D$9))+($B43-1)*SUMPRODUCT($C42:$F42,TRANSPOSE(Parameters!D$32:D$35))} -> 59805.317 | E43: {=SUMPRODUCT($C42:$F42,TRANSPOSE(Parameters!E$6:E$9))+($B43-1)*SUMPRODUCT($C42:$F42,TRANSPOSE(Parameters!E$32:E$35))} -> 15079.693 | F43: {=SUMPRODUCT($C42:$F42,TRANSPOSE(Parameters!F$6:F$9))+($B43-1)*SUMPRODUCT($C42:$F42,TRANSPOSE(Parameters!F$32:F$35))} -> 546146.41 | G43: =SUM(C43:E43) -> 453853.59 | H43: =F43-F42 -> 9640.0108 | I43: =I42*(1+Parameters!$B$24) -> 88.792235 | J43: =J42*(1+Parameters!$B$24) -> 355.16894 | K43: =K42*(1+Parameters!$B$24) -> 5327.5341 | L43: =L42*(1+Parameters!$B$24) -> 443.96117 | M43: =M42*(1+Parameters!$B$25) -> 975.42857 | N43: =N42*(1+Parameters!$B$25) -> 19508.571 | O43: =I43 -> 88.792235 | P43: =J43+M43 -> 1330.5975 | Q43: =K43+N43 -> 24836.105 | R43: =L43 -> 443.96117 | S43: =C42*(Parameters!$C$6+($B43-1)*Parameters!$C$32)*O43+D42*(Parameters!$C$7+($B43-1)*Parameters!$C$33)*(O43+P43)/2+E42*(Parameters!$C$8+($B43-1)*Parameters!$C$34)*(O43+Q43)/2 -> 95274621 | T43: =C42*(Parameters!$D$6+($B43-1)*Parameters!$D$32)*(O43+P43)/2+D42*(Parameters!$D$7+($B43-1)*Parameters!$D$33)*P43+E42*(Parameters!$D$8+($B43-1)*Parameters!$D$34)*(P43+Q43)/2 -> 1.0147659e+08 | U43: =C42*(Parameters!$E$6+($B43-1)*Parameters!$E$32)*(O43+Q43)/2+D42*(Parameters!$E$7+($B43-1)*Parameters!$E$33)*(P43+Q43)/2+E42*(Parameters!$E$8+($B43-1)*Parameters!$E$34)*Q43 -> 2.5244233e+08 | V43: =C42*(Parameters!$F$6+($B43-1)*Parameters!$F$32)*(O43/2+R43)+D42*(Parameters!$F$7+($B43-1)*Parameters!$F$33)*(P43/2+R43)+E42*(Parameters!$F$8+($B43-1)*Parameters!$F$34)*(Q43/2+R43) -> 53671414 | W43: =S43+T43+U43+V43 -> 5.0286495e+08 | X43: =X42/(1+Parameters!$B$26) -> 0.30831867 | Y43: =W43*X43 -> 1.5504265e+08 | Z43: =Y43/G42 -> 334.50872

Sheet Charts
A1: Charts
B6: Lives alive | F6: Real cost per life
A7: Year | B7: Base | C7: Alternative | E7: Year | F7: Base | G7: Alternative | H7: Negotiated
A8: 1 | B8: ='Base Scenario (alt)'!U13 -> 990000 | C8: ='Alt Scenario_1 (alt)'!U13 -> 990000 | E8: 1 | F8: ='Base Scenario (alt)'!AM13 -> 173.55769 | G8: ='Alt Scenario_1 (alt)'!AM13 -> 210.09615 | H8: ='Alt Scenario_2 (alt)'!AM13 -> 190.91459
A9: 2 | B9: ='Base Scenario (alt)'!U14 -> 965000 | C9: ='Alt Scenario_1 (alt)'!U14 -> 965151.2 | E9: 2 | F9: ='Base Scenario (alt)'!AM14 -> 363.6059 | G9: ='Alt Scenario_1 (alt)'!AM14 -> 453.72321 | H9: ='Alt Scenario_2 (alt)'!AM14 -> 403.26242
A10: 3 | B10: ='Base Scenario (alt)'!U15 -> 935080 | C10: ='Alt Scenario_1 (alt)'!U15 -> 935792.24 | E10: 3 | F10: ='Base Scenario (alt)'!AM15 -> 447.95169 | G10: ='Alt Scenario_1 (alt)'!AM15 -> 557.88321 | H10: ='Alt Scenario_2 (alt)'!AM15 -> 491.92128
A11: 4 | B11: ='Base Scenario (alt)'!U16 -> 904432.75 | C11: ='Alt Scenario_1 (alt)'!U16 -> 906124.83 | E11: 4 | F11: ='Base Scenario (alt)'!AM16 -> 471.43542 | G11: ='Alt Scenario_1 (alt)'!AM16 -> 582.72354 | H11: ='Alt Scenario_2 (alt)'!AM16 -> 512.48277 | R11: More people alive at each point in time under the alternative scenario
A12: 5 | B12: ='Base Scenario (alt)'!U17 -> 874265.64 | C12: ='Alt Scenario_1 (alt)'!U17 -> 877320.68 | E12: 5 | F12: ='Base Scenario (alt)'!AM17 -> 477.90036 | G12: ='Alt Scenario_1 (alt)'!AM17 -> 585.19947 | H12: ='Alt Scenario_2 (alt)'!AM17 -> 513.7971
A13: 6 | B13: ='Base Scenario (alt)'!U18 -> 844940.67 | C13: ='Alt Scenario_1 (alt)'!U18 -> 849700.03 | E13: 6 | F13: ='Base Scenario (alt)'!AM18 -> 478.75325 | G13: ='Alt Scenario_1 (alt)'!AM18 -> 580.23319 | H13: ='Alt Scenario_2 (alt)'!AM18 -> 508.74523
A14: 7 | B14: ='Base Scenario (alt)'!U19 -> 816547.77 | C14: ='Alt Scenario_1 (alt)'!U19 -> 823313.46 | E14: 7 | F14: ='Base Scenario (alt)'!AM19 -> 477.87752 | G14: ='Alt Scenario_1 (alt)'!AM19 -> 572.91425 | H14: ='Alt Scenario_2 (alt)'!AM19 -> 501.7033
A15: 8 | B15: ='Base Scenario (alt)'!U20 -> 789092.78 | C15: ='Alt Scenario_1 (alt)'!U20 -> 798130.64 | E15: 8 | F15: ='Base Scenario (alt)'!AM20 -> 476.51112 | G15: ='Alt Scenario_1 (alt)'!AM20 -> 564.87701 | H15: ='Alt Scenario_2 (alt)'!AM20 -> 494.07492
A16: 9 | B16: ='Base Scenario (alt)'!U21 -> 762555.84 | C16: ='Alt Scenario_1 (alt)'!U21 -> 774098.61 | E16: 9 | F16: ='Base Scenario (alt)'!AM21 -> 475.05578 | G16: ='Alt Scenario_1 (alt)'!AM21 -> 556.65426 | H16: ='Alt Scenario_2 (alt)'!AM21 -> 486.31661
A17: 10 | B17: ='Base Scenario (alt)'!U22 -> 736909.72 | C17: ='Alt Scenario_1 (alt)'!U22 -> 751159.9 | E17: 10 | F17: ='Base Scenario (alt)'!AM22 -> 473.64075 | G17: ='Alt Scenario_1 (alt)'!AM22 -> 548.41709 | H17: ='Alt Scenario_2 (alt)'!AM22 -> 478.57441
A18: 11 | B18: ='Base Scenario (alt)'!U23 -> 712125.63 | C18: ='Alt Scenario_1 (alt)'!U23 -> 729258.09 | E18: 11 | F18: ='Base Scenario (alt)'!AM23 -> 472.30712 | G18: ='Alt Scenario_1 (alt)'!AM23 -> 540.21817 | H18: ='Alt Scenario_2 (alt)'!AM23 -> 470.89293
A19: 12 | B19: ='Base Scenario (alt)'!U24 -> 688174.93 | C19: ='Alt Scenario_1 (alt)'!U24 -> 708339.34 | E19: 12 | F19: ='Base Scenario (alt)'!AM24 -> 471.06738 | G19: ='Alt Scenario_1 (alt)'!AM24 -> 532.07129 | H19: ='Alt Scenario_2 (alt)'!AM24 -> 463.28348
A20: 13 | B20: ='Base Scenario (alt)'!U25 -> 665029.71 | C20: ='Alt Scenario_1 (alt)'!U25 -> 688352.8 | E20: 13 | F20: ='Base Scenario (alt)'!AM25 -> 469.92479 | G20: ='Alt Scenario_1 (alt)'!AM25 -> 523.97745 | H20: ='Alt Scenario_2 (alt)'!AM25 -> 455.74648
A21: 14 | B21: ='Base Scenario (alt)'!U26 -> 642662.91 | C21: ='Alt Scenario_1 (alt)'!U26 -> 669250.55 | E21: 14 | F21: ='Base Scenario (alt)'!AM26 -> 468.87961 | G21: ='Alt Scenario_1 (alt)'!AM26 -> 515.93348 | H21: ='Alt Scenario_2 (alt)'!AM26 -> 448.27877
A22: 15 | B22: ='Base Scenario (alt)'!U27 -> 621048.36 | C22: ='Alt Scenario_1 (alt)'!U27 -> 650987.45 | E22: 15 | F22: ='Base Scenario (alt)'!AM27 -> 467.93115 | G22: ='Alt Scenario_1 (alt)'!AM27 -> 507.93484 | H22: ='Alt Scenario_2 (alt)'!AM27 -> 440.87607
A23: 16 | B23: ='Base Scenario (alt)'!U28 -> 600160.77 | C23: ='Alt Scenario_1 (alt)'!U28 -> 633521.01 | E23: 16 | F23: ='Base Scenario (alt)'!AM28 -> 467.07843 | G23: ='Alt Scenario_1 (alt)'!AM28 -> 499.97657 | H23: ='Alt Scenario_2 (alt)'!AM28 -> 433.53376
... A37: 30 | B37: ='Base Scenario (alt)'!U42 -> 371756.15 | C37: ='Alt Scenario_1 (alt)'!U42 -> 453853.59 | E37: 30 | F37: ='Base Scenario (alt)'!AM42 -> 464.63652 | G37: ='Alt Scenario_1 (alt)'!AM42 -> 390.01435 | H37: ='Alt Scenario_2 (alt)'!AM42 -> 334.50872

Sheet Base Scenario alt timing
A1: Initial position
A3: * This is an example approach to determining the solution. An reasonable attempt is awarded credit.
A4: * This is an example showing discounting at the start of the year. Some credits will be lost following this approach
C5: Different formulae - do not drag
Y8: Total PV
G9: Total | Y9: =SUM(Y13:Y43) -> 1.0370013e+10
G10: =SUM(G14:G43) -> 19110751
I11: Overheads | M11: Drug | O11: Combined cost | S11: Cost per state x population | W11: Total cost | X11: v | Y11: PV of cost | Z11: Real cost per life alive
B12: Year | C12: Healthy | D12: Sick | E12: Very sick | F12: Dead | G12: Lives alive | H12: Excess deaths | I12: H | J12: S | K12: I | L12: D | M12: S | N12: I | O12: H | P12: S | Q12: I | R12: D | S12: H | T12: S | U12: I | V12: D
B13: 0 | C13: =Parameters!B12 -> 1000000 | D13: =Parameters!C12 -> 0 | E13: =Parameters!D12 -> 0 | F13: =Parameters!E12 -> 0 | G13: =SUM(C13:E13) -> 1000000 | H13: =F13 -> 0 | W13: =C13*O13+D13*P13+E13*Q13+H13*R13 -> 0 | X13: 1 | Y13: =W13*X13 -> 0
B14: 1 | C14: {=SUMPRODUCT($C13:$F13,TRANSPOSE(Parameters!C$6:C$9))} -> 800000 | D14: {=SUMPRODUCT($C13:$F13,TRANSPOSE(Parameters!D$6:D$9))} -> 160000 | E14: {=SUMPRODUCT($C13:$F13,TRANSPOSE(Parameters!E$6:E$9))} -> 30000 | F14: {=SUMPRODUCT($C13:$F13,TRANSPOSE(Parameters!F$6:F$9))} -> 10000 | G14: =SUM(C14:E14) -> 990000 | H14: =F14-F13 -> 10000 | I14: =Parameters!B15 -> 50 | J14: =Parameters!B16 -> 200 | K14: =Parameters!B17 -> 3000 | L14: =Parameters!B18 -> 250 | M14: =Parameters!B21 -> 150 | N14: =Parameters!B22 -> 4000 | O14: =I14 -> 50 | P14: =J14+M14 -> 350 | Q14: =K14+N14 -> 7000 | R14: =L14 -> 250 | S14: =C13*O14 -> 50000000 | T14: =D13*P14 -> 0 | U14: =E13*Q14 -> 0 | V14: =F13*R14 -> 0 | W14: =S14+T14+U14+V14 -> 50000000 | X14: =1/(1+Parameters!$B$26) -> 0.96153846 | Y14: =W14*X14 -> 48076923 | Z14: =Y14/G13 -> 48.076923
B15: 2 | C15: {=SUMPRODUCT($C14:$F14,TRANSPOSE(Parameters!C$6:C$9))} -> 764500 | D15: {=SUMPRODUCT($C14:$F14,TRANSPOSE(Parameters!D$6:D$9))} -> 151500 | E15: {=SUMPRODUCT($C14:$F14,TRANSPOSE(Parameters!E$6:E$9))} -> 49000 | F15: {=SUMPRODUCT($C14:$F14,TRANSPOSE(Parameters!F$6:F$9))} -> 35000 | G15: =SUM(C15:E15) -> 965000 | H15: =F15-F14 -> 25000 | I15: =I14*(1+Parameters!$B$24) -> 51 | J15: =J14*(1+Parameters!$B$24) -> 204 | K15: =K14*(1+Parameters!$B$24) -> 3060 | L15: =L14*(1+Parameters!$B$24) -> 255 | M15: =M14*(1+Parameters!$B$25) -> 157.5 | N15: =N14*(1+Parameters!$B$25) -> 4200 | O15: =I15 -> 51 | P15: =J15+M15 -> 361.5 | Q15: =K15+N15 -> 7260 | R15: =L15 -> 255 | S15: =C14*O15 -> 40800000 | T15: =D14*P15 -> 57840000 | U15: =E14*Q15 -> 217800000 | V15: =F14*R15 -> 2550000 | W15: =S15+T15+U15+V15 -> 318990000 | X15: =X14/(1+Parameters!$B$26) -> 0.92455621 | Y15: =W15*X15 -> 2.9492419e+08 | Z15: =Y15/G14 -> 297.90322
B16: 3 | C16: {=SUMPRODUCT($C15:$F15,TRANSPOSE(Parameters!C$6:C$9))} -> 732575 | D16: {=SUMPRODUCT($C15:$F15,TRANSPOSE(Parameters!D$6:D$9))} -> 149720 | E16: {=SUMPRODUCT($C15:$F15,TRANSPOSE(Parameters!E$6:E$9))} -> 52785 | F16: {=SUMPRODUCT($C15:$F15,TRANSPOSE(Parameters!F$6:F$9))} -> 64920 | G16: =SUM(C16:E16) -> 935080 | H16: =F16-F15 -> 29920 | I16: =I15*(1+Parameters!$B$24) -> 52.02 | J16: =J15*(1+Parameters!$B$24) -> 208.08 | K16: =K15*(1+Parameters!$B$24) -> 3121.2 | L16: =L15*(1+Parameters!$B$24) -> 260.1 | M16: =M15*(1+Parameters!$B$25) -> 165.375 | N16: =N15*(1+Parameters!$B$25) -> 4410 | O16: =I16 -> 52.02 | P16: =J16+M16 -> 373.455 | Q16: =K16+N16 -> 7531.2 | R16: =L16 -> 260.1 | S16: =C15*O16 -> 39769290 | T16: =D15*P16 -> 56578433 | U16: =E15*Q16 -> 3.690288e+08 | V16: =F15*R16 -> 9103500 | W16: =S16+T16+U16+V16 -> 4.7448002e+08 | X16: =X15/(1+Parameters!$B$26) -> 0.88899636 | Y16: =W16*X16 -> 4.2181101e+08 | Z16: =Y16/G15 -> 437.10986
B17: 4 | C17: {=SUMPRODUCT($C16:$F16,TRANSPOSE(Parameters!C$6:C$9))} -> 706267.75 | D17: {=SUMPRODUCT($C16:$F16,TRANSPOSE(Parameters!D$6:D$9))} -> 145380.25 | E17: {=SUMPRODUCT($C16:$F16,TRANSPOSE(Parameters!E$6:E$9))} -> 52784.75 | F17: {=SUMPRODUCT($C16:$F16,TRANSPOSE(Parameters!F$6:F$9))} -> 95567.25 | G17: =SUM(C17:E17) -> 904432.75 | H17: =F17-F16 -> 30647.25 | I17: =I16*(1+Parameters!$B$24) -> 53.0604 | J17: =J16*(1+Parameters!$B$24) -> 212.2416 | K17: =K16*(1+Parameters!$B$24) -> 3183.624 | L17: =L16*(1+Parameters!$B$24) -> 265.302 | M17: =M16*(1+Parameters!$B$25) -> 173.64375 | N17: =N16*(1+Parameters!$B$25) -> 4630.5 | O17: =I17 -> 53.0604 | P17: =J17+M17 -> 385.88535 | Q17: =K17+N17 -> 7814.124 | R17: =L17 -> 265.302 | S17: =C16*O17 -> 38870723 | T17: =D16*P17 -> 57774755 | U17: =E16*Q17 -> 4.1246854e+08 | V17: =F16*R17 -> 17223406 | W17: =S17+T17+U17+V17 -> 5.2633742e+08 | X17: =X16/(1+Parameters!$B$26) -> 0.85480419 | Y17: =W17*X17 -> 4.4991543e+08 | Z17: =Y17/G16 -> 481.15181
B18: 5 | C18: {=SUMPRODUCT($C17:$F17,TRANSPOSE(Parameters!C$6:C$9))} -> 681967.1 | D18: {=SUMPRODUCT($C17:$F17,TRANSPOSE(Parameters!D$6:D$9))} -> 140737.05 | E18: {=SUMPRODUCT($C17:$F17,TRANSPOSE(Parameters!E$6:E$9))} -> 51561.482 | F18: {=SUMPRODUCT($C17:$F17,TRANSPOSE(Parameters!F$6:F$9))} -> 125734.36 | G18: =SUM(C18:E18) -> 874265.64 | H18: =F18-F17 -> 30167.115 | I18: =I17*(1+Parameters!$B$24) -> 54.121608 | J18: =J17*(1+Parameters!$B$24) -> 216.48643 | K18: =K17*(1+Parameters!$B$24) -> 3247.2965 | L18: =L17*(1+Parameters!$B$24) -> 270.60804 | M18: =M17*(1+Parameters!$B$25) -> 182.32594 | N18: =N17*(1+Parameters!$B$25) -> 4862.025 | O18: =I18 -> 54.121608 | P18: =J18+M18 -> 398.81237 | Q18: =K18+N18 -> 8109.3215 | R18: =L18 -> 270.60804 | S18: =C17*O18 -> 38224346 | T18: =D17*P18 -> 57979442 | U18: =E17*Q18 -> 4.2804851e+08 | V18: =F17*R18 -> 25861266 | W18: =S18+T18+U18+V18 -> 5.5011356e+08 | X18: =X17/(1+Parameters!$B$26) -> 0.82192711 | Y18: =W18*X18 -> 4.5215325e+08 | Z18: =Y18/G17 -> 499.9302
B19: 6 | C19: {=SUMPRODUCT($C18:$F18,TRANSPOSE(Parameters!C$6:C$9))} -> 658860.69 | D19: {=SUMPRODUCT($C18:$F18,TRANSPOSE(Parameters!D$6:D$9))} -> 136078.81 | E19: {=SUMPRODUCT($C18:$F18,TRANSPOSE(Parameters!E$6:E$9))} -> 50001.163 | F19: {=SUMPRODUCT($C18:$F18,TRANSPOSE(Parameters!F$6:F$9))} -> 155059.33 | G19: =SUM(C19:E19) -> 844940.67 | H19: =F19-F18 -> 29324.968 | I19: =I18*(1+Parameters!$B$24) -> 55.20404 | J19: =J18*(1+Parameters!$B$24) -> 220.81616 | K19: =K18*(1+Parameters!$B$24) -> 3312.2424 | L19: =L18*(1+Parameters!$B$24) -> 276.0202 | M19: =M18*(1+Parameters!$B$25) -> 191.44223 | N19: =N18*(1+Parameters!$B$25) -> 5105.1263 | O19: =I19 -> 55.20404 | P19: =J19+M19 -> 412.2584 | Q19: =K19+N19 -> 8417.3687 | R19: =L19 -> 276.0202 | S19: =C18*O19 -> 37647339 | T19: =D18*P19 -> 58020031 | U19: =E18*Q19 -> 4.3401201e+08 | V19: =F18*R19 -> 34705225 | W19: =S19+T19+U19+V19 -> 5.643846e+08 | X19: =X18/(1+Parameters!$B$26) -> 0.79031453 | Y19: =W19*X19 -> 4.4604135e+08 | Z19: =Y19/G18 -> 510.18973
B20: 7 | C20: {=SUMPRODUCT($C19:$F19,TRANSPOSE(Parameters!C$6:C$9))} -> 636647.84 | D20: {=SUMPRODUCT($C19:$F19,TRANSPOSE(Parameters!D$6:D$9))} -> 131525.88 | E20: {=SUMPRODUCT($C19:$F19,TRANSPOSE(Parameters!E$6:E$9))} -> 48374.051 | F20: {=SUMPRODUCT($C19:$F19,TRANSPOSE(Parameters!F$6:F$9))} -> 183452.23 | G20: =SUM(C20:E20) -> 816547.77 | H20: =F20-F19 -> 28392.896 | I20: =I19*(1+Parameters!$B$24) -> 56.308121 | J20: =J19*(1+Parameters!$B$24) -> 225.23248 | K20: =K19*(1+Parameters!$B$24) -> 3378.4873 | L20: =L19*(1+Parameters!$B$24) -> 281.5406 | M20: =M19*(1+Parameters!$B$25) -> 201.01435 | N20: =N19*(1+Parameters!$B$25) -> 5360.3826 | O20: =I20 -> 56.308121 | P20: =J20+M20 -> 426.24683 | Q20: =K20+N20 -> 8738.8698 | R20: =L20 -> 281.5406 | S20: =C19*O20 -> 37099208 | T20: =D19*P20 -> 58003162 | U20: =E19*Q20 -> 4.3695365e+08 | V20: =F19*R20 -> 43655499 | W20: =S20+T20+U20+V20 -> 5.7571152e+08 | X20: =X19/(1+Parameters!$B$26) -> 0.75991781 | Y20: =W20*X20 -> 4.3749344e+08 | Z20: =Y20/G19 -> 517.78007
B21: 8 | C21: {=SUMPRODUCT($C20:$F20,TRANSPOSE(Parameters!C$6:C$9))} -> 615218.79 | D21: {=SUMPRODUCT($C20:$F20,TRANSPOSE(Parameters!D$6:D$9))} -> 127109.75 | E21: {=SUMPRODUCT($C20:$F20,TRANSPOSE(Parameters!E$6:E$9))} -> 46764.239 | F21: {=SUMPRODUCT($C20:$F20,TRANSPOSE(Parameters!F$6:F$9))} -> 210907.22 | G21: =SUM(C21:E21) -> 789092.78 | H21: =F21-F20 -> 27454.988 | I21: =I20*(1+Parameters!$B$24) -> 57.434283 | J21: =J20*(1+Parameters!$B$24) -> 229.73713 | K21: =K20*(1+Parameters!$B$24) -> 3446.057 | L21: =L20*(1+Parameters!$B$24) -> 287.17142 | M21: =M20*(1+Parameters!$B$25) -> 211.06506 | N21: =N20*(1+Parameters!$B$25) -> 5628.4017 | O21: =I21 -> 57.434283 | P21: =J21+M21 -> 440.8022 | Q21: =K21+N21 -> 9074.4587 | R21: =L21 -> 287.17142 | S21: =C20*O21 -> 36565412 | T21: =D20*P21 -> 57976898 | U21: =E20*Q21 -> 4.3896833e+08 | V21: =F20*R21 -> 52682237 | W21: =S21+T21+U21+V21 -> 5.8619287e+08 | X21: =X20/(1+Parameters!$B$26) -> 0.73069021 | Y21: =W21*X21 -> 4.2832539e+08 | Z21: =Y21/G20 -> 524.55644
B22: 9 | C22: {=SUMPRODUCT($C21:$F21,TRANSPOSE(Parameters!C$6:C$9))} -> 594521.98 | D22: {=SUMPRODUCT($C21:$F21,TRANSPOSE(Parameters!D$6:D$9))} -> 122837.04 | E22: {=SUMPRODUCT($C21:$F21,TRANSPOSE(Parameters!E$6:E$9))} -> 45196.811 | F22: {=SUMPRODUCT($C21:$F21,TRANSPOSE(Parameters!F$6:F$9))} -> 237444.16 | G22: =SUM(C22:E22) -> 762555.84 | H22: =F22-F21 -> 26536.947 | I22: =I21*(1+Parameters!$B$24) -> 58.582969 | J22: =J21*(1+Parameters!$B$24) -> 234.33188 | K22: =K21*(1+Parameters!$B$24) -> 3514.9781 | L22: =L21*(1+Parameters!$B$24) -> 292.91485 | M22: =M21*(1+Parameters!$B$25) -> 221.61832 | N22: =N21*(1+Parameters!$B$25) -> 5909.8218 | O22: =I22 -> 58.582969 | P22: =J22+M22 -> 455.95019 | Q22: =K22+N22 -> 9424.7999 | R22: =L22 -> 292.91485 | S22: =C21*O22 -> 36041343 | T22: =D21*P22 -> 57955717 | U22: =E21*Q22 -> 4.4074359e+08 | V22: =F21*R22 -> 61777855 | W22: =S22+T22+U22+V22 -> 5.9651851e+08 | X22: =X21/(1+Parameters!$B$26) -> 0.70258674 | Y22: =W22*X22 -> 4.1910599e+08 | Z22: =Y22/G21 -> 531.12384
B23: 10 | C23: {=SUMPRODUCT($C22:$F22,TRANSPOSE(Parameters!C$6:C$9))} -> 574524.89 | D23: {=SUMPRODUCT($C22:$F22,TRANSPOSE(Parameters!D$6:D$9))} -> 118706.42 | E23: {=SUMPRODUCT($C22:$F22,TRANSPOSE(Parameters!E$6:E$9))} -> 43678.407 | F23: {=SUMPRODUCT($C22:$F22,TRANSPOSE(Parameters!F$6:F$9))} -> 263090.28 | G23: =SUM(C23:E23) -> 736909.72 | H23: =F23-F22 -> 25646.115 | I23: =I22*(1+Parameters!$B$24) -> 59.754628 | J23: =J22*(1+Parameters!$B$24) -> 239.01851 | K23: =K22*(1+Parameters!$B$24) -> 3585.2777 | L23: =L22*(1+Parameters!$B$24) -> 298.77314 | M23: =M22*(1+Parameters!$B$25) -> 232.69923 | N23: =N22*(1+Parameters!$B$25) -> 6205.3129 | O23: =I23 -> 59.754628 | P23: =J23+M23 -> 471.71775 | Q23: =K23+N23 -> 9790.5906 | R23: =L23 -> 298.77314 | S23: =C22*O23 -> 35525440 | T23: =D22*P23 -> 57944412 | U23: =E22*Q23 -> 4.4250347e+08 | V23: =F22*R23 -> 70941939 | W23: =S23+T23+U23+V23 -> 6.0691526e+08 | X23: =X22/(1+Parameters!$B$26) -> 0.67556417 | Y23: =W23*X23 -> 4.100102e+08 | Z23: =Y23/G22 -> 537.67893
B24: 11 | C24: {=SUMPRODUCT($C23:$F23,TRANSPOSE(Parameters!C$6:C$9))} -> 555201.49 | D24: {=SUMPRODUCT($C23:$F23,TRANSPOSE(Parameters!D$6:D$9))} -> 114714.23 | E24: {=SUMPRODUCT($C23:$F23,TRANSPOSE(Parameters!E$6:E$9))} -> 42209.911 | F24: {=SUMPRODUCT($C23:$F23,TRANSPOSE(Parameters!F$6:F$9))} -> 287874.37 | G24: =SUM(C24:E24) -> 712125.63 | H24: =F24-F23 -> 24784.092 | I24: =I23*(1+Parameters!$B$24) -> 60.949721 | J24: =J23*(1+Parameters!$B$24) -> 243.79888 | K24: =K23*(1+Parameters!$B$24) -> 3656.9833 | L24: =L23*(1+Parameters!$B$24) -> 304.7486 | M24: =M23*(1+Parameters!$B$25) -> 244.33419 | N24: =N23*(1+Parameters!$B$25) -> 6515.5785 | O24: =I24 -> 60.949721 | P24: =J24+M24 -> 488.13308 | Q24: =K24+N24 -> 10172.562 | R24: =L24 -> 304.7486 | S24: =C23*O24 -> 35017132 | T24: =D23*P24 -> 57944532 | U24: =E23*Q24 -> 4.4432129e+08 | V24: =F23*R24 -> 80176396 | W24: =S24+T24+U24+V24 -> 6.1745935e+08 | X24: =X23/(1+Parameters!$B$26) -> 0.64958093 | Y24: =W24*X24 -> 4.0108982e+08 | Z24: =Y24/G23 -> 544.28624
B25: 12 | C25: {=SUMPRODUCT($C24:$F24,TRANSPOSE(Parameters!C$6:C$9))} -> 536528.35 | D25: {=SUMPRODUCT($C24:$F24,TRANSPOSE(Parameters!D$6:D$9))} -> 110856.14 | E25: {=SUMPRODUCT($C24:$F24,TRANSPOSE(Parameters!E$6:E$9))} -> 40790.441 | F25: {=SUMPRODUCT($C24:$F24,TRANSPOSE(Parameters!F$6:F$9))} -> 311825.07 | G25: =SUM(C25:E25) -> 688174.93 | H25: =F25-F24 -> 23950.7 | I25: =I24*(1+Parameters!$B$24) -> 62.168715 | J25: =J24*(1+Parameters!$B$24) -> 248.67486 | K25: =K24*(1+Parameters!$B$24) -> 3730.1229 | L25: =L24*(1+Parameters!$B$24) -> 310.84358 | M25: =M24*(1+Parameters!$B$25) -> 256.5509 | N25: =N24*(1+Parameters!$B$25) -> 6841.3574 | O25: =I25 -> 62.168715 | P25: =J25+M25 -> 505.22577 | Q25: =K25+N25 -> 10571.48 | R25: =L25 -> 310.84358 | S25: =C24*O25 -> 34516163 | T25: =D24*P25 -> 57956583 | U25: =E24*Q25 -> 4.4622125e+08 | V25: =F24*R25 -> 89483900 | W25: =S25+T25+U25+V25 -> 6.2817789e+08 | X25: =X24/(1+Parameters!$B$26) -> 0.62459705 | Y25: =W25*X25 -> 3.9235806e+08 | Z25: =Y25/G24 -> 550.96747
B26: 13 | C26: {=SUMPRODUCT($C25:$F25,TRANSPOSE(Parameters!C$6:C$9))} -> 518483.35 | D26: {=SUMPRODUCT($C25:$F25,TRANSPOSE(Parameters!D$6:D$9))} -> 107127.76 | E26: {=SUMPRODUCT($C25:$F25,TRANSPOSE(Parameters!E$6:E$9))} -> 39418.597 | F26: {=SUMPRODUCT($C25:$F25,TRANSPOSE(Parameters!F$6:F$9))} -> 334970.29 | G26: =SUM(C26:E26) -> 665029.71 | H26: =F26-F25 -> 23145.223 | I26: =I25*(1+Parameters!$B$24) -> 63.41209 | J26: =J25*(1+Parameters!$B$24) -> 253.64836 | K26: =K25*(1+Parameters!$B$24) -> 3804.7254 | L26: =L25*(1+Parameters!$B$24) -> 317.06045 | M26: =M25*(1+Parameters!$B$25) -> 269.37845 | N26: =N25*(1+Parameters!$B$25) -> 7183.4253 | O26: =I26 -> 63.41209 | P26: =J26+M26 -> 523.02681 | Q26: =K26+N26 -> 10988.151 | R26: =L26 -> 317.06045 | S26: =C25*O26 -> 34022384 | T26: =D25*P26 -> 57980732 | U26: =E25*Q26 -> 4.4821151e+08 | V26: =F25*R26 -> 98867397 | W26: =S26+T26+U26+V26 -> 6.3908202e+08 | X26: =X25/(1+Parameters!$B$26) -> 0.60057409 | Y26: =W26*X26 -> 3.838161e+08 | Z26: =Y26/G25 -> 557.73043
... B43: 30 | C43: {=SUMPRODUCT($C42:$F42,TRANSPOSE(Parameters!C$6:C$9))} -> 289835.72 | D43: {=SUMPRODUCT($C42:$F42,TRANSPOSE(Parameters!D$6:D$9))} -> 59885.155 | E43: {=SUMPRODUCT($C42:$F42,TRANSPOSE(Parameters!E$6:E$9))} -> 22035.279 | F43: {=SUMPRODUCT($C42:$F42,TRANSPOSE(Parameters!F$6:F$9))} -> 628243.85 | G43: =SUM(C43:E43) -> 371756.15 | H43: =F43-F42 -> 12938.351 | I43: =I42*(1+Parameters!$B$24) -> 88.792235 | J43: =J42*(1+Parameters!$B$24) -> 355.16894 | K43: =K42*(1+Parameters!$B$24) -> 5327.5341 | L43: =L42*(1+Parameters!$B$24) -> 443.96117 | M43: =M42*(1+Parameters!$B$25) -> 617.42034 | N43: =N42*(1+Parameters!$B$25) -> 16464.542 | O43: =I43 -> 88.792235 | P43: =J43+M43 -> 972.58928 | Q43: =K43+N43 -> 21792.076 | R43: =L43 -> 443.96117 | S43: =C42*O43 -> 26630830 | T43: =D42*P43 -> 60270733 | U43: =E42*Q43 -> 4.9690684e+08 | V43: =F42*R43 -> 2.7317175e+08 | W43: =S43+T43+U43+V43 -> 8.5698016e+08 | X43: =X42/(1+Parameters!$B$26) -> 0.30831867 | Y43: =W43*X43 -> 2.6422298e+08 | Z43: =Y43/G42 -> 686.83846

Sheet Alt Scenario_1 alt timing
A1: Alternative position - allowing for alternative drugs
A3: * This is an example showing discounting at the start of the year. Some credits will be lost following this approach
C5: Different formulae - do not drag
Y8: Total PV
G9: Total | Y9: =SUM(Y13:Y43) -> 1.1545746e+10
G10: =SUM(G14:G43) -> 20149312
I11: Overheads | M11: Drug | O11: Combined cost | S11: Cost per state x population | W11: Total cost | X11: v | Y11: PV of cost | Z11: Real cost per life alive
B12: Year | C12: Healthy | D12: Sick | E12: Very sick | F12: Dead | G12: Lives alive | H12: Excess deaths | I12: H | J12: S | K12: I | L12: D | M12: S | N12: I | O12: H | P12: S | Q12: I | R12: D | S12: H | T12: S | U12: I | V12: D
B13: 0 | C13: =Parameters!B12 -> 1000000 | D13: =Parameters!C12 -> 0 | E13: =Parameters!D12 -> 0 | F13: =Parameters!E12 -> 0 | G13: =SUM(C13:E13) -> 1000000 | H13: =F13 -> 0 | W13: =C13*O13+D13*P13+E13*Q13+H13*R13 -> 0 | X13: 1 | Y13: =W13*X13 -> 0
B14: 1 | C14: {=SUMPRODUCT($C13:$F13,TRANSPOSE(Parameters!C$6:C$9))+($B14-1)*SUMPRODUCT($C13:$F13,TRANSPOSE(Parameters!C$32:C$35))} -> 800000 | D14: {=SUMPRODUCT($C13:$F13,TRANSPOSE(Parameters!D$6:D$9))+($B14-1)*SUMPRODUCT($C13:$F13,TRANSPOSE(Parameters!D$32:D$35))} -> 160000 | E14: {=SUMPRODUCT($C13:$F13,TRANSPOSE(Parameters!E$6:E$9))+($B14-1)*SUMPRODUCT($C13:$F13,TRANSPOSE(Parameters!E$32:E$35))} -> 30000 | F14: {=SUMPRODUCT($C13:$F13,TRANSPOSE(Parameters!F$6:F$9))+($B14-1)*SUMPRODUCT($C13:$F13,TRANSPOSE(Parameters!F$32:F$35))} -> 10000 | G14: =SUM(C14:E14) -> 990000 | H14: =F14-F13 -> 10000 | I14: =Parameters!B15 -> 50 | J14: =Parameters!B16 -> 200 | K14: =Parameters!B17 -> 3000 | L14: =Parameters!B18 -> 250 | M14: =Parameters!B37 -> 250 | N14: =Parameters!B38 -> 6000 | O14: =I14 -> 50 | P14: =J14+M14 -> 450 | Q14: =K14+N14 -> 9000 | R14: =L14 -> 250 | S14: =O14*C13 -> 50000000 | T14: =P14*D13 -> 0 | U14: =Q14*E13 -> 0 | V14: =R14*F13 -> 0 | W14: =S14+T14+U14+V14 -> 50000000 | X14: =1/(1+Parameters!$B$26) -> 0.96153846 | Y14: =W14*X14 -> 48076923 | Z14: =Y14/G13 -> 48.076923
B15: 2 | C15: {=SUMPRODUCT($C14:$F14,TRANSPOSE(Parameters!C$6:C$9))+($B15-1)*SUMPRODUCT($C14:$F14,TRANSPOSE(Parameters!C$32:C$35))} -> 766059 | D15: {=SUMPRODUCT($C14:$F14,TRANSPOSE(Parameters!D$6:D$9))+($B15-1)*SUMPRODUCT($C14:$F14,TRANSPOSE(Parameters!D$32:D$35))} -> 150650 | E15: {=SUMPRODUCT($C14:$F14,TRANSPOSE(Parameters!E$6:E$9))+($B15-1)*SUMPRODUCT($C14:$F14,TRANSPOSE(Parameters!E$32:E$35))} -> 48442.2 | F15: {=SUMPRODUCT($C14:$F14,TRANSPOSE(Parameters!F$6:F$9))+($B15-1)*SUMPRODUCT($C14:$F14,TRANSPOSE(Parameters!F$32:F$35))} -> 34848.8 | G15: =SUM(C15:E15) -> 965151.2 | H15: =F15-F14 -> 24848.8 | I15: =I14*(1+Parameters!$B$24) -> 51 | J15: =J14*(1+Parameters!$B$24) -> 204 | K15: =K14*(1+Parameters!$B$24) -> 3060 | L15: =L14*(1+Parameters!$B$24) -> 255 | M15: =M14*(1+Parameters!$B$25) -> 262.5 | N15: =N14*(1+Parameters!$B$25) -> 6300 | O15: =I15 -> 51 | P15: =J15+M15 -> 466.5 | Q15: =K15+N15 -> 9360 | R15: =L15 -> 255 | S15: =O15*C14 -> 40800000 | T15: =P15*D14 -> 74640000 | U15: =Q15*E14 -> 280800000 | V15: =R15*F14 -> 2550000 | W15: =S15+T15+U15+V15 -> 398790000 | X15: =X14/(1+Parameters!$B$26) -> 0.92455621 | Y15: =W15*X15 -> 3.6870377e+08 | Z15: =Y15/G14 -> 372.42805
B16: 3 | C16: {=SUMPRODUCT($C15:$F15,TRANSPOSE(Parameters!C$6:C$9))+($B16-1)*SUMPRODUCT($C15:$F15,TRANSPOSE(Parameters!C$32:C$35))} -> 736103.13 | D16: {=SUMPRODUCT($C15:$F15,TRANSPOSE(Parameters!D$6:D$9))+($B16-1)*SUMPRODUCT($C15:$F15,TRANSPOSE(Parameters!D$32:D$35))} -> 148153.98 | E16: {=SUMPRODUCT($C15:$F15,TRANSPOSE(Parameters!E$6:E$9))+($B16-1)*SUMPRODUCT($C15:$F15,TRANSPOSE(Parameters!E$32:E$35))} -> 51535.128 | F16: {=SUMPRODUCT($C15:$F15,TRANSPOSE(Parameters!F$6:F$9))+($B16-1)*SUMPRODUCT($C15:$F15,TRANSPOSE(Parameters!F$32:F$35))} -> 64207.759 | G16: =SUM(C16:E16) -> 935792.24 | H16: =F16-F15 -> 29358.959 | I16: =I15*(1+Parameters!$B$24) -> 52.02 | J16: =J15*(1+Parameters!$B$24) -> 208.08 | K16: =K15*(1+Parameters!$B$24) -> 3121.2 | L16: =L15*(1+Parameters!$B$24) -> 260.1 | M16: =M15*(1+Parameters!$B$25) -> 275.625 | N16: =N15*(1+Parameters!$B$25) -> 6615 | O16: =I16 -> 52.02 | P16: =J16+M16 -> 483.705 | Q16: =K16+N16 -> 9736.2 | R16: =L16 -> 260.1 | S16: =O16*C15 -> 39850389 | T16: =P16*D15 -> 72870158 | U16: =Q16*E15 -> 4.7164295e+08 | V16: =R16*F15 -> 9064172.9 | W16: =S16+T16+U16+V16 -> 5.9342767e+08 | X16: =X15/(1+Parameters!$B$26) -> 0.88899636 | Y16: =W16*X16 -> 5.2755504e+08 | Z16: =Y16/G15 -> 546.60351
B17: 4 | C17: {=SUMPRODUCT($C16:$F16,TRANSPOSE(Parameters!C$6:C$9))+($B17-1)*SUMPRODUCT($C16:$F16,TRANSPOSE(Parameters!C$32:C$35))} -> 712069.42 | D17: {=SUMPRODUCT($C16:$F16,TRANSPOSE(Parameters!D$6:D$9))+($B17-1)*SUMPRODUCT($C16:$F16,TRANSPOSE(Parameters!D$32:D$35))} -> 143202.55 | E17: {=SUMPRODUCT($C16:$F16,TRANSPOSE(Parameters!E$6:E$9))+($B17-1)*SUMPRODUCT($C16:$F16,TRANSPOSE(Parameters!E$32:E$35))} -> 50852.86 | F17: {=SUMPRODUCT($C16:$F16,TRANSPOSE(Parameters!F$6:F$9))+($B17-1)*SUMPRODUCT($C16:$F16,TRANSPOSE(Parameters!F$32:F$35))} -> 93875.174 | G17: =SUM(C17:E17) -> 906124.83 | H17: =F17-F16 -> 29667.415 | I17: =I16*(1+Parameters!$B$24) -> 53.0604 | J17: =J16*(1+Parameters!$B$24) -> 212.2416 | K17: =K16*(1+Parameters!$B$24) -> 3183.624 | L17: =L16*(1+Parameters!$B$24) -> 265.302 | M17: =M16*(1+Parameters!$B$25) -> 289.40625 | N17: =N16*(1+Parameters!$B$25) -> 6945.75 | O17: =I17 -> 53.0604 | P17: =J17+M17 -> 501.64785 | Q17: =K17+N17 -> 10129.374 | R17: =L17 -> 265.302 | S17: =O17*C16 -> 39057926 | T17: =P17*D16 -> 74321127 | U17: =Q17*E16 -> 5.2201859e+08 | V17: =R17*F16 -> 17034447 | W17: =S17+T17+U17+V17 -> 6.5243209e+08 | X17: =X16/(1+Parameters!$B$26) -> 0.85480419 | Y17: =W17*X17 -> 5.5770168e+08 | Z17: =Y17/G16 -> 595.96742
B18: 5 | C18: {=SUMPRODUCT($C17:$F17,TRANSPOSE(Parameters!C$6:C$9))+($B18-1)*SUMPRODUCT($C17:$F17,TRANSPOSE(Parameters!C$32:C$35))} -> 690286.31 | D18: {=SUMPRODUCT($C17:$F17,TRANSPOSE(Parameters!D$6:D$9))+($B18-1)*SUMPRODUCT($C17:$F17,TRANSPOSE(Parameters!D$32:D$35))} -> 138036.46 | E18: {=SUMPRODUCT($C17:$F17,TRANSPOSE(Parameters!E$6:E$9))+($B18-1)*SUMPRODUCT($C17:$F17,TRANSPOSE(Parameters!E$32:E$35))} -> 48997.916 | F18: {=SUMPRODUCT($C17:$F17,TRANSPOSE(Parameters!F$6:F$9))+($B18-1)*SUMPRODUCT($C17:$F17,TRANSPOSE(Parameters!F$32:F$35))} -> 122679.32 | G18: =SUM(C18:E18) -> 877320.68 | H18: =F18-F17 -> 28804.143 | I18: =I17*(1+Parameters!$B$24) -> 54.121608 | J18: =J17*(1+Parameters!$B$24) -> 216.48643 | K18: =K17*(1+Parameters!$B$24) -> 3247.2965 | L18: =L17*(1+Parameters!$B$24) -> 270.60804 | M18: =M17*(1+Parameters!$B$25) -> 303.87656 | N18: =N17*(1+Parameters!$B$25) -> 7293.0375 | O18: =I18 -> 54.121608 | P18: =J18+M18 -> 520.36299 | Q18: =K18+N18 -> 10540.334 | R18: =L18 -> 270.60804 | S18: =O18*C17 -> 38538342 | T18: =P18*D17 -> 74517306 | U18: =Q18*E17 -> 5.3600613e+08 | V18: =R18*F17 -> 25403377 | W18: =S18+T18+U18+V18 -> 6.7446515e+08 | X18: =X17/(1+Parameters!$B$26) -> 0.82192711 | Y18: =W18*X18 -> 5.5436119e+08 | Z18: =Y18/G17 -> 611.7934
B19: 6 | C19: {=SUMPRODUCT($C18:$F18,TRANSPOSE(Parameters!C$6:C$9))+($B19-1)*SUMPRODUCT($C18:$F18,TRANSPOSE(Parameters!C$32:C$35))} -> 669889.77 | D19: {=SUMPRODUCT($C18:$F18,TRANSPOSE(Parameters!D$6:D$9))+($B19-1)*SUMPRODUCT($C18:$F18,TRANSPOSE(Parameters!D$32:D$35))} -> 132947.3 | E19: {=SUMPRODUCT($C18:$F18,TRANSPOSE(Parameters!E$6:E$9))+($B19-1)*SUMPRODUCT($C18:$F18,TRANSPOSE(Parameters!E$32:E$35))} -> 46862.966 | F19: {=SUMPRODUCT($C18:$F18,TRANSPOSE(Parameters!F$6:F$9))+($B19-1)*SUMPRODUCT($C18:$F18,TRANSPOSE(Parameters!F$32:F$35))} -> 150299.97 | G19: =SUM(C19:E19) -> 849700.03 | H19: =F19-F18 -> 27620.652 | I19: =I18*(1+Parameters!$B$24) -> 55.20404 | J19: =J18*(1+Parameters!$B$24) -> 220.81616 | K19: =K18*(1+Parameters!$B$24) -> 3312.2424 | L19: =L18*(1+Parameters!$B$24) -> 276.0202 | M19: =M18*(1+Parameters!$B$25) -> 319.07039 | N19: =N18*(1+Parameters!$B$25) -> 7657.6894 | O19: =I19 -> 55.20404 | P19: =J19+M19 -> 539.88655 | Q19: =K19+N19 -> 10969.932 | R19: =L19 -> 276.0202 | S19: =O19*C18 -> 38106593 | T19: =P19*D18 -> 74524028 | U19: =Q19*E18 -> 5.3750379e+08 | V19: =R19*F18 -> 33861970 | W19: =S19+T19+U19+V19 -> 6.8399638e+08 | X19: =X18/(1+Parameters!$B$26) -> 0.79031453 | Y19: =W19*X19 -> 5.4057228e+08 | Z19: =Y19/G18 -> 616.1627
B20: 7 | C20: {=SUMPRODUCT($C19:$F19,TRANSPOSE(Parameters!C$6:C$9))+($B20-1)*SUMPRODUCT($C19:$F19,TRANSPOSE(Parameters!C$32:C$35))} -> 650545.62 | D20: {=SUMPRODUCT($C19:$F19,TRANSPOSE(Parameters!D$6:D$9))+($B20-1)*SUMPRODUCT($C19:$F19,TRANSPOSE(Parameters!D$32:D$35))} -> 128049.65 | E20: {=SUMPRODUCT($C19:$F19,TRANSPOSE(Parameters!E$6:E$9))+($B20-1)*SUMPRODUCT($C19:$F19,TRANSPOSE(Parameters!E$32:E$35))} -> 44718.188 | F20: {=SUMPRODUCT($C19:$F19,TRANSPOSE(Parameters!F$6:F$9))+($B20-1)*SUMPRODUCT($C19:$F19,TRANSPOSE(Parameters!F$32:F$35))} -> 176686.54 | G20: =SUM(C20:E20) -> 823313.46 | H20: =F20-F19 -> 26386.571 | I20: =I19*(1+Parameters!$B$24) -> 56.308121 | J20: =J19*(1+Parameters!$B$24) -> 225.23248 | K20: =K19*(1+Parameters!$B$24) -> 3378.4873 | L20: =L19*(1+Parameters!$B$24) -> 281.5406 | M20: =M19*(1+Parameters!$B$25) -> 335.02391 | N20: =N19*(1+Parameters!$B$25) -> 8040.5738 | O20: =I20 -> 56.308121 | P20: =J20+M20 -> 560.25639 | Q20: =K20+N20 -> 11419.061 | R20: =L20 -> 281.5406 | S20: =O20*C19 -> 37720234 | T20: =P20*D19 -> 74484573 | U20: =Q20*E19 -> 5.3513107e+08 | V20: =R20*F19 -> 42315544 | W20: =S20+T20+U20+V20 -> 6.8965142e+08 | X20: =X19/(1+Parameters!$B$26) -> 0.75991781 | Y20: =W20*X20 -> 5.240784e+08 | Z20: =Y20/G19 -> 616.78049
B21: 8 | C21: {=SUMPRODUCT($C20:$F20,TRANSPOSE(Parameters!C$6:C$9))+($B21-1)*SUMPRODUCT($C20:$F20,TRANSPOSE(Parameters!C$32:C$35))} -> 632117.48 | D21: {=SUMPRODUCT($C20:$F20,TRANSPOSE(Parameters!D$6:D$9))+($B21-1)*SUMPRODUCT($C20:$F20,TRANSPOSE(Parameters!D$32:D$35))} -> 123368.43 | E21: {=SUMPRODUCT($C20:$F20,TRANSPOSE(Parameters!E$6:E$9))+($B21-1)*SUMPRODUCT($C20:$F20,TRANSPOSE(Parameters!E$32:E$35))} -> 42644.734 | F21: {=SUMPRODUCT($C20:$F20,TRANSPOSE(Parameters!F$6:F$9))+($B21-1)*SUMPRODUCT($C20:$F20,TRANSPOSE(Parameters!F$32:F$35))} -> 201869.36 | G21: =SUM(C21:E21) -> 798130.64 | H21: =F21-F20 -> 25182.818 | I21: =I20*(1+Parameters!$B$24) -> 57.434283 | J21: =J20*(1+Parameters!$B$24) -> 229.73713 | K21: =K20*(1+Parameters!$B$24) -> 3446.057 | L21: =L20*(1+Parameters!$B$24) -> 287.17142 | M21: =M20*(1+Parameters!$B$25) -> 351.77511 | N21: =N20*(1+Parameters!$B$25) -> 8442.6025 | O21: =I21 -> 57.434283 | P21: =J21+M21 -> 581.51224 | Q21: =K21+N21 -> 11888.66 | R21: =L21 -> 287.17142 | S21: =O21*C20 -> 37363622 | T21: =P21*D20 -> 74462437 | U21: =Q21*E20 -> 5.3163931e+08 | V21: =R21*F20 -> 50739324 | W21: =S21+T21+U21+V21 -> 6.9420469e+08 | X21: =X20/(1+Parameters!$B$26) -> 0.73069021 | Y21: =W21*X21 -> 5.0724857e+08 | Z21: =Y21/G20 -> 616.10625
B22: 9 | C22: {=SUMPRODUCT($C21:$F21,TRANSPOSE(Parameters!C$6:C$9))+($B22-1)*SUMPRODUCT($C21:$F21,TRANSPOSE(Parameters!C$32:C$35))} -> 614531.6 | D22: {=SUMPRODUCT($C21:$F21,TRANSPOSE(Parameters!D$6:D$9))+($B22-1)*SUMPRODUCT($C21:$F21,TRANSPOSE(Parameters!D$32:D$35))} -> 118903.13 | E22: {=SUMPRODUCT($C21:$F21,TRANSPOSE(Parameters!E$6:E$9))+($B22-1)*SUMPRODUCT($C21:$F21,TRANSPOSE(Parameters!E$32:E$35))} -> 40663.883 | F22: {=SUMPRODUCT($C21:$F21,TRANSPOSE(Parameters!F$6:F$9))+($B22-1)*SUMPRODUCT($C21:$F21,TRANSPOSE(Parameters!F$32:F$35))} -> 225901.39 | G22: =SUM(C22:E22) -> 774098.61 | H22: =F22-F21 -> 24032.031 | I22: =I21*(1+Parameters!$B$24) -> 58.582969 | J22: =J21*(1+Parameters!$B$24) -> 234.33188 | K22: =K21*(1+Parameters!$B$24) -> 3514.9781 | L22: =L21*(1+Parameters!$B$24) -> 292.91485 | M22: =M21*(1+Parameters!$B$25) -> 369.36386 | N22: =N21*(1+Parameters!$B$25) -> 8864.7327 | O22: =I22 -> 58.582969 | P22: =J22+M22 -> 603.69574 | Q22: =K22+N22 -> 12379.711 | R22: =L22 -> 292.91485 | S22: =O22*C21 -> 37031319 | T22: =P22*D21 -> 74476995 | U22: =Q22*E21 -> 5.2792948e+08 | V22: =R22*F21 -> 59130532 | W22: =S22+T22+U22+V22 -> 6.9856832e+08 | X22: =X21/(1+Parameters!$B$26) -> 0.70258674 | Y22: =W22*X22 -> 4.9080484e+08 | Z22: =Y22/G21 -> 614.94298
B23: 10 | C23: {=SUMPRODUCT($C22:$F22,TRANSPOSE(Parameters!C$6:C$9))+($B23-1)*SUMPRODUCT($C22:$F22,TRANSPOSE(Parameters!C$32:C$35))} -> 597736.19 | D23: {=SUMPRODUCT($C22:$F22,TRANSPOSE(Parameters!D$6:D$9))+($B23-1)*SUMPRODUCT($C22:$F22,TRANSPOSE(Parameters!D$32:D$35))} -> 114645.44 | E23: {=SUMPRODUCT($C22:$F22,TRANSPOSE(Parameters!E$6:E$9))+($B23-1)*SUMPRODUCT($C22:$F22,TRANSPOSE(Parameters!E$32:E$35))} -> 38778.275 | F23: {=SUMPRODUCT($C22:$F22,TRANSPOSE(Parameters!F$6:F$9))+($B23-1)*SUMPRODUCT($C22:$F22,TRANSPOSE(Parameters!F$32:F$35))} -> 248840.1 | G23: =SUM(C23:E23) -> 751159.9 | H23: =F23-F22 -> 22938.707 | I23: =I22*(1+Parameters!$B$24) -> 59.754628 | J23: =J22*(1+Parameters!$B$24) -> 239.01851 | K23: =K22*(1+Parameters!$B$24) -> 3585.2777 | L23: =L22*(1+Parameters!$B$24) -> 298.77314 | M23: =M22*(1+Parameters!$B$25) -> 387.83205 | N23: =N22*(1+Parameters!$B$25) -> 9307.9693 | O23: =I23 -> 59.754628 | P23: =J23+M23 -> 626.85057 | Q23: =K23+N23 -> 12893.247 | R23: =L23 -> 298.77314 | S23: =O23*C22 -> 36721107 | T23: =P23*D22 -> 74534493 | U23: =Q23*E22 -> 5.2428949e+08 | V23: =R23*F22 -> 67493268 | W23: =S23+T23+U23+V23 -> 7.0303836e+08 | X23: =X22/(1+Parameters!$B$26) -> 0.67556417 | Y23: =W23*X23 -> 4.7494752e+08 | Z23: =Y23/G22 -> 613.54912
B24: 11 | C24: {=SUMPRODUCT($C23:$F23,TRANSPOSE(Parameters!C$6:C$9))+($B24-1)*SUMPRODUCT($C23:$F23,TRANSPOSE(Parameters!C$32:C$35))} -> 581688.11 | D24: {=SUMPRODUCT($C23:$F23,TRANSPOSE(Parameters!D$6:D$9))+($B24-1)*SUMPRODUCT($C23:$F23,TRANSPOSE(Parameters!D$32:D$35))} -> 110585.08 | E24: {=SUMPRODUCT($C23:$F23,TRANSPOSE(Parameters!E$6:E$9))+($B24-1)*SUMPRODUCT($C23:$F23,TRANSPOSE(Parameters!E$32:E$35))} -> 36984.897 | F24: {=SUMPRODUCT($C23:$F23,TRANSPOSE(Parameters!F$6:F$9))+($B24-1)*SUMPRODUCT($C23:$F23,TRANSPOSE(Parameters!F$32:F$35))} -> 270741.91 | G24: =SUM(C24:E24) -> 729258.09 | H24: =F24-F23 -> 21901.817 | I24: =I23*(1+Parameters!$B$24) -> 60.949721 | J24: =J23*(1+Parameters!$B$24) -> 243.79888 | K24: =K23*(1+Parameters!$B$24) -> 3656.9833 | L24: =L23*(1+Parameters!$B$24) -> 304.7486 | M24: =M23*(1+Parameters!$B$25) -> 407.22366 | N24: =N23*(1+Parameters!$B$25) -> 9773.3678 | O24: =I24 -> 60.949721 | P24: =J24+M24 -> 651.02254 | Q24: =K24+N24 -> 13430.351 | R24: =L24 -> 304.7486 | S24: =O24*C23 -> 36431854 | T24: =P24*D23 -> 74636764 | U24: =Q24*E23 -> 5.2080585e+08 | V24: =R24*F23 -> 75833672 | W24: =S24+T24+U24+V24 -> 7.0770814e+08 | X24: =X23/(1+Parameters!$B$26) -> 0.64958093 | Y24: =W24*X24 -> 4.5971371e+08 | Z24: =Y24/G23 -> 612.00513
B25: 12 | C25: {=SUMPRODUCT($C24:$F24,TRANSPOSE(Parameters!C$6:C$9))+($B25-1)*SUMPRODUCT($C24:$F24,TRANSPOSE(Parameters!C$32:C$35))} -> 566348.56 | D25: {=SUMPRODUCT($C24:$F24,TRANSPOSE(Parameters!D$6:D$9))+($B25-1)*SUMPRODUCT($C24:$F24,TRANSPOSE(Parameters!D$32:D$35))} -> 106711.6 | E25: {=SUMPRODUCT($C24:$F24,TRANSPOSE(Parameters!E$6:E$9))+($B25-1)*SUMPRODUCT($C24:$F24,TRANSPOSE(Parameters!E$32:E$35))} -> 35279.182 | F25: {=SUMPRODUCT($C24:$F24,TRANSPOSE(Parameters!F$6:F$9))+($B25-1)*SUMPRODUCT($C24:$F24,TRANSPOSE(Parameters!F$32:F$35))} -> 291660.66 | G25: =SUM(C25:E25) -> 708339.34 | H25: =F25-F24 -> 20918.749 | I25: =I24*(1+Parameters!$B$24) -> 62.168715 | J25: =J24*(1+Parameters!$B$24) -> 248.67486 | K25: =K24*(1+Parameters!$B$24) -> 3730.1229 | L25: =L24*(1+Parameters!$B$24) -> 310.84358 | M25: =M24*(1+Parameters!$B$25) -> 427.58484 | N25: =N24*(1+Parameters!$B$25) -> 10262.036 | O25: =I25 -> 62.168715 | P25: =J25+M25 -> 676.2597 | Q25: =K25+N25 -> 13992.159 | R25: =L25 -> 310.84358 | S25: =O25*C24 -> 36162803 | T25: =P25*D24 -> 74784232 | U25: =Q25*E24 -> 5.1749857e+08 | V25: =R25*F24 -> 84158385 | W25: =S25+T25+U25+V25 -> 7.1260399e+08 | X25: =X24/(1+Parameters!$B$26) -> 0.62459705 | Y25: =W25*X25 -> 4.4509035e+08 | Z25: =Y25/G24 -> 610.3331
B26: 13 | C26: {=SUMPRODUCT($C25:$F25,TRANSPOSE(Parameters!C$6:C$9))+($B26-1)*SUMPRODUCT($C25:$F25,TRANSPOSE(Parameters!C$32:C$35))} -> 551681.58 | D26: {=SUMPRODUCT($C25:$F25,TRANSPOSE(Parameters!D$6:D$9))+($B26-1)*SUMPRODUCT($C25:$F25,TRANSPOSE(Parameters!D$32:D$35))} -> 103014.93 | E26: {=SUMPRODUCT($C25:$F25,TRANSPOSE(Parameters!E$6:E$9))+($B26-1)*SUMPRODUCT($C25:$F25,TRANSPOSE(Parameters!E$32:E$35))} -> 33656.298 | F26: {=SUMPRODUCT($C25:$F25,TRANSPOSE(Parameters!F$6:F$9))+($B26-1)*SUMPRODUCT($C25:$F25,TRANSPOSE(Parameters!F$32:F$35))} -> 311647.2 | G26: =SUM(C26:E26) -> 688352.8 | H26: =F26-F25 -> 19986.538 | I26: =I25*(1+Parameters!$B$24) -> 63.41209 | J26: =J25*(1+Parameters!$B$24) -> 253.64836 | K26: =K25*(1+Parameters!$B$24) -> 3804.7254 | L26: =L25*(1+Parameters!$B$24) -> 317.06045 | M26: =M25*(1+Parameters!$B$25) -> 448.96408 | N26: =N25*(1+Parameters!$B$25) -> 10775.138 | O26: =I26 -> 63.41209 | P26: =J26+M26 -> 702.61244 | Q26: =K26+N26 -> 14579.863 | R26: =L26 -> 317.06045 | S26: =O26*C25 -> 35913345 | T26: =P26*D25 -> 74976897 | U26: =Q26*E25 -> 5.1436566e+08 | V26: =R26*F25 -> 92474060 | W26: =S26+T26+U26+V26 -> 7.1772996e+08 | X26: =X25/(1+Parameters!$B$26) -> 0.60057409 | Y26: =W26*X26 -> 4.3105002e+08 | Z26: =Y26/G25 -> 608.53604
... B43: 30 | C43: {=SUMPRODUCT($C42:$F42,TRANSPOSE(Parameters!C$6:C$9))+($B43-1)*SUMPRODUCT($C42:$F42,TRANSPOSE(Parameters!C$32:C$35))} -> 378968.58 | D43: {=SUMPRODUCT($C42:$F42,TRANSPOSE(Parameters!D$6:D$9))+($B43-1)*SUMPRODUCT($C42:$F42,TRANSPOSE(Parameters!D$32:D$35))} -> 59805.317 | E43: {=SUMPRODUCT($C42:$F42,TRANSPOSE(Parameters!E$6:E$9))+($B43-1)*SUMPRODUCT($C42:$F42,TRANSPOSE(Parameters!E$32:E$35))} -> 15079.693 | F43: {=SUMPRODUCT($C42:$F42,TRANSPOSE(Parameters!F$6:F$9))+($B43-1)*SUMPRODUCT($C42:$F42,TRANSPOSE(Parameters!F$32:F$35))} -> 546146.41 | G43: =SUM(C43:E43) -> 453853.59 | H43: =F43-F42 -> 9640.0108 | I43: =I42*(1+Parameters!$B$24) -> 88.792235 | J43: =J42*(1+Parameters!$B$24) -> 355.16894 | K43: =K42*(1+Parameters!$B$24) -> 5327.5341 | L43: =L42*(1+Parameters!$B$24) -> 443.96117 | M43: =M42*(1+Parameters!$B$25) -> 1029.0339 | N43: =N42*(1+Parameters!$B$25) -> 24696.814 | O43: =I43 -> 88.792235 | P43: =J43+M43 -> 1384.2028 | Q43: =K43+N43 -> 30024.348 | R43: =L43 -> 443.96117 | S43: =O43*C42 -> 34280461 | T43: =P43*D42 -> 85248911 | U43: =Q43*E42 -> 4.753334e+08 | V43: =R43*F42 -> 2.3818801e+08 | W43: =S43+T43+U43+V43 -> 8.3305078e+08 | X43: =X42/(1+Parameters!$B$26) -> 0.30831867 | Y43: =W43*X43 -> 2.5684511e+08 | Z43: =Y43/G42 -> 554.15028

Sheet Alt Scenario_2 alt timing
A1: Alternative position - allowing for alternative drugs
A2: Determine cost for NPV to be equivalent to that from the initial position
A4: * This is an example showing discounting at the start of the year. Some credits will be lost following this approach
C5: Different formulae - do not drag
Y8: Total PV | Z8: Goal seek
G9: Total | Y9: =SUM(Y13:Y43) -> 8.8497636e+09 | Z9: =Y9-'Base Scenario'!Y9 -> 0 | AA9: =IF(ABS(Z9-0)<0.1,"Goal seek okay","Need to goal seek") -> Goal seek okay
G10: =SUM(G14:G43) -> 20149312
I11: Overheads | M11: Drug | O11: Combined cost | S11: Cost per state x population | W11: Total cost | X11: v | Y11: PV of cost | Z11: Real cost per life alive
B12: Year | C12: Healthy | D12: Sick | E12: Very sick | F12: Dead | G12: Lives alive | H12: Excess deaths | I12: H | J12: S | K12: I | L12: D | M12: S | N12: I | O12: H | P12: S | Q12: I | R12: D | S12: H | T12: S | U12: I | V12: D
B13: 0 | C13: =Parameters!B12 -> 1000000 | D13: =Parameters!C12 -> 0 | E13: =Parameters!D12 -> 0 | F13: =Parameters!E12 -> 0 | G13: =SUM(C13:E13) -> 1000000 | H13: =F13 -> 0 | W13: =C13*O13+D13*P13+E13*Q13+H13*R13 -> 0 | X13: 1 | Y13: =W13*X13 -> 0
B14: 1 | C14: {=SUMPRODUCT($C13:$F13,TRANSPOSE(Parameters!C$6:C$9))+($B14-1)*SUMPRODUCT($C13:$F13,TRANSPOSE(Parameters!C$32:C$35))} -> 800000 | D14: {=SUMPRODUCT($C13:$F13,TRANSPOSE(Parameters!D$6:D$9))+($B14-1)*SUMPRODUCT($C13:$F13,TRANSPOSE(Parameters!D$32:D$35))} -> 160000 | E14: {=SUMPRODUCT($C13:$F13,TRANSPOSE(Parameters!E$6:E$9))+($B14-1)*SUMPRODUCT($C13:$F13,TRANSPOSE(Parameters!E$32:E$35))} -> 30000 | F14: {=SUMPRODUCT($C13:$F13,TRANSPOSE(Parameters!F$6:F$9))+($B14-1)*SUMPRODUCT($C13:$F13,TRANSPOSE(Parameters!F$32:F$35))} -> 10000 | G14: =SUM(C14:E14) -> 990000 | H14: =F14-F13 -> 10000 | I14: =Parameters!B15 -> 50 | J14: =Parameters!B16 -> 200 | K14: =Parameters!B17 -> 3000 | L14: =Parameters!B18 -> 250 | M14: =Parameters!B45 -> 176.55465 | N14: =Parameters!B46 -> 3531.0929 | O14: =I14 -> 50 | P14: =J14+M14 -> 376.55465 | Q14: =K14+N14 -> 6531.0929 | R14: =L14 -> 250 | S14: =O14*C13 -> 50000000 | T14: =P14*D13 -> 0 | U14: =Q14*E13 -> 0 | V14: =R14*F13 -> 0 | W14: =S14+T14+U14+V14 -> 50000000 | X14: =1/(1+Parameters!$B$26) -> 0.96153846 | Y14: =W14*X14 -> 48076923 | Z14: =Y14/G13 -> 48.076923
B15: 2 | C15: {=SUMPRODUCT($C14:$F14,TRANSPOSE(Parameters!C$6:C$9))+($B15-1)*SUMPRODUCT($C14:$F14,TRANSPOSE(Parameters!C$32:C$35))} -> 766059 | D15: {=SUMPRODUCT($C14:$F14,TRANSPOSE(Parameters!D$6:D$9))+($B15-1)*SUMPRODUCT($C14:$F14,TRANSPOSE(Parameters!D$32:D$35))} -> 150650 | E15: {=SUMPRODUCT($C14:$F14,TRANSPOSE(Parameters!E$6:E$9))+($B15-1)*SUMPRODUCT($C14:$F14,TRANSPOSE(Parameters!E$32:E$35))} -> 48442.2 | F15: {=SUMPRODUCT($C14:$F14,TRANSPOSE(Parameters!F$6:F$9))+($B15-1)*SUMPRODUCT($C14:$F14,TRANSPOSE(Parameters!F$32:F$35))} -> 34848.8 | G15: =SUM(C15:E15) -> 965151.2 | H15: =F15-F14 -> 24848.8 | I15: =I14*(1+Parameters!$B$24) -> 51 | J15: =J14*(1+Parameters!$B$24) -> 204 | K15: =K14*(1+Parameters!$B$24) -> 3060 | L15: =L14*(1+Parameters!$B$24) -> 255 | M15: =M14*(1+Parameters!$B$25) -> 185.38238 | N15: =N14*(1+Parameters!$B$25) -> 3707.6476 | O15: =I15 -> 51 | P15: =J15+M15 -> 389.38238 | Q15: =K15+N15 -> 6767.6476 | R15: =L15 -> 255 | S15: =O15*C14 -> 40800000 | T15: =P15*D14 -> 62301181 | U15: =Q15*E14 -> 2.0302943e+08 | V15: =R15*F14 -> 2550000 | W15: =S15+T15+U15+V15 -> 3.0868061e+08 | X15: =X14/(1+Parameters!$B$26) -> 0.92455621 | Y15: =W15*X15 -> 2.8539257e+08 | Z15: =Y15/G14 -> 288.27533
B16: 3 | C16: {=SUMPRODUCT($C15:$F15,TRANSPOSE(Parameters!C$6:C$9))+($B16-1)*SUMPRODUCT($C15:$F15,TRANSPOSE(Parameters!C$32:C$35))} -> 736103.13 | D16: {=SUMPRODUCT($C15:$F15,TRANSPOSE(Parameters!D$6:D$9))+($B16-1)*SUMPRODUCT($C15:$F15,TRANSPOSE(Parameters!D$32:D$35))} -> 148153.98 | E16: {=SUMPRODUCT($C15:$F15,TRANSPOSE(Parameters!E$6:E$9))+($B16-1)*SUMPRODUCT($C15:$F15,TRANSPOSE(Parameters!E$32:E$35))} -> 51535.128 | F16: {=SUMPRODUCT($C15:$F15,TRANSPOSE(Parameters!F$6:F$9))+($B16-1)*SUMPRODUCT($C15:$F15,TRANSPOSE(Parameters!F$32:F$35))} -> 64207.759 | G16: =SUM(C16:E16) -> 935792.24 | H16: =F16-F15 -> 29358.959 | I16: =I15*(1+Parameters!$B$24) -> 52.02 | J16: =J15*(1+Parameters!$B$24) -> 208.08 | K16: =K15*(1+Parameters!$B$24) -> 3121.2 | L16: =L15*(1+Parameters!$B$24) -> 260.1 | M16: =M15*(1+Parameters!$B$25) -> 194.6515 | N16: =N15*(1+Parameters!$B$25) -> 3893.03 | O16: =I16 -> 52.02 | P16: =J16+M16 -> 402.7315 | Q16: =K16+N16 -> 7014.23 | R16: =L16 -> 260.1 | S16: =O16*C15 -> 39850389 | T16: =P16*D15 -> 60671500 | U16: =Q16*E15 -> 3.3978473e+08 | V16: =R16*F15 -> 9064172.9 | W16: =S16+T16+U16+V16 -> 4.4937079e+08 | X16: =X15/(1+Parameters!$B$26) -> 0.88899636 | Y16: =W16*X16 -> 3.99489e+08 | Z16: =Y16/G15 -> 413.91338
B17: 4 | C17: {=SUMPRODUCT($C16:$F16,TRANSPOSE(Parameters!C$6:C$9))+($B17-1)*SUMPRODUCT($C16:$F16,TRANSPOSE(Parameters!C$32:C$35))} -> 712069.42 | D17: {=SUMPRODUCT($C16:$F16,TRANSPOSE(Parameters!D$6:D$9))+($B17-1)*SUMPRODUCT($C16:$F16,TRANSPOSE(Parameters!D$32:D$35))} -> 143202.55 | E17: {=SUMPRODUCT($C16:$F16,TRANSPOSE(Parameters!E$6:E$9))+($B17-1)*SUMPRODUCT($C16:$F16,TRANSPOSE(Parameters!E$32:E$35))} -> 50852.86 | F17: {=SUMPRODUCT($C16:$F16,TRANSPOSE(Parameters!F$6:F$9))+($B17-1)*SUMPRODUCT($C16:$F16,TRANSPOSE(Parameters!F$32:F$35))} -> 93875.174 | G17: =SUM(C17:E17) -> 906124.83 | H17: =F17-F16 -> 29667.415 | I17: =I16*(1+Parameters!$B$24) -> 53.0604 | J17: =J16*(1+Parameters!$B$24) -> 212.2416 | K17: =K16*(1+Parameters!$B$24) -> 3183.624 | L17: =L16*(1+Parameters!$B$24) -> 265.302 | M17: =M16*(1+Parameters!$B$25) -> 204.38407 | N17: =N16*(1+Parameters!$B$25) -> 4087.6815 | O17: =I17 -> 53.0604 | P17: =J17+M17 -> 416.62567 | Q17: =K17+N17 -> 7271.3055 | R17: =L17 -> 265.302 | S17: =O17*C16 -> 39057926 | T17: =P17*D16 -> 61724753 | U17: =Q17*E16 -> 3.7472766e+08 | V17: =R17*F16 -> 17034447 | W17: =S17+T17+U17+V17 -> 4.9254479e+08 | X17: =X16/(1+Parameters!$B$26) -> 0.85480419 | Y17: =W17*X17 -> 4.2102935e+08 | Z17: =Y17/G16 -> 449.91755
B18: 5 | C18: {=SUMPRODUCT($C17:$F17,TRANSPOSE(Parameters!C$6:C$9))+($B18-1)*SUMPRODUCT($C17:$F17,TRANSPOSE(Parameters!C$32:C$35))} -> 690286.31 | D18: {=SUMPRODUCT($C17:$F17,TRANSPOSE(Parameters!D$6:D$9))+($B18-1)*SUMPRODUCT($C17:$F17,TRANSPOSE(Parameters!D$32:D$35))} -> 138036.46 | E18: {=SUMPRODUCT($C17:$F17,TRANSPOSE(Parameters!E$6:E$9))+($B18-1)*SUMPRODUCT($C17:$F17,TRANSPOSE(Parameters!E$32:E$35))} -> 48997.916 | F18: {=SUMPRODUCT($C17:$F17,TRANSPOSE(Parameters!F$6:F$9))+($B18-1)*SUMPRODUCT($C17:$F17,TRANSPOSE(Parameters!F$32:F$35))} -> 122679.32 | G18: =SUM(C18:E18) -> 877320.68 | H18: =F18-F17 -> 28804.143 | I18: =I17*(1+Parameters!$B$24) -> 54.121608 | J18: =J17*(1+Parameters!$B$24) -> 216.48643 | K18: =K17*(1+Parameters!$B$24) -> 3247.2965 | L18: =L17*(1+Parameters!$B$24) -> 270.60804 | M18: =M17*(1+Parameters!$B$25) -> 214.60328 | N18: =N17*(1+Parameters!$B$25) -> 4292.0655 | O18: =I18 -> 54.121608 | P18: =J18+M18 -> 431.08971 | Q18: =K18+N18 -> 7539.362 | R18: =L18 -> 270.60804 | S18: =O18*C17 -> 38538342 | T18: =P18*D17 -> 61733144 | U18: =Q18*E17 -> 3.8339812e+08 | V18: =R18*F17 -> 25403377 | W18: =S18+T18+U18+V18 -> 5.0907298e+08 | X18: =X17/(1+Parameters!$B$26) -> 0.82192711 | Y18: =W18*X18 -> 4.1842088e+08 | Z18: =Y18/G17 -> 461.76958
B19: 6 | C19: {=SUMPRODUCT($C18:$F18,TRANSPOSE(Parameters!C$6:C$9))+($B19-1)*SUMPRODUCT($C18:$F18,TRANSPOSE(Parameters!C$32:C$35))} -> 669889.77 | D19: {=SUMPRODUCT($C18:$F18,TRANSPOSE(Parameters!D$6:D$9))+($B19-1)*SUMPRODUCT($C18:$F18,TRANSPOSE(Parameters!D$32:D$35))} -> 132947.3 | E19: {=SUMPRODUCT($C18:$F18,TRANSPOSE(Parameters!E$6:E$9))+($B19-1)*SUMPRODUCT($C18:$F18,TRANSPOSE(Parameters!E$32:E$35))} -> 46862.966 | F19: {=SUMPRODUCT($C18:$F18,TRANSPOSE(Parameters!F$6:F$9))+($B19-1)*SUMPRODUCT($C18:$F18,TRANSPOSE(Parameters!F$32:F$35))} -> 150299.97 | G19: =SUM(C19:E19) -> 849700.03 | H19: =F19-F18 -> 27620.652 | I19: =I18*(1+Parameters!$B$24) -> 55.20404 | J19: =J18*(1+Parameters!$B$24) -> 220.81616 | K19: =K18*(1+Parameters!$B$24) -> 3312.2424 | L19: =L18*(1+Parameters!$B$24) -> 276.0202 | M19: =M18*(1+Parameters!$B$25) -> 225.33344 | N19: =N18*(1+Parameters!$B$25) -> 4506.6688 | O19: =I19 -> 55.20404 | P19: =J19+M19 -> 446.1496 | Q19: =K19+N19 -> 7818.9112 | R19: =L19 -> 276.0202 | S19: =O19*C18 -> 38106593 | T19: =P19*D18 -> 61584912 | U19: =Q19*E18 -> 3.8311035e+08 | V19: =R19*F18 -> 33861970 | W19: =S19+T19+U19+V19 -> 5.1666383e+08 | X19: =X18/(1+Parameters!$B$26) -> 0.79031453 | Y19: =W19*X19 -> 4.0832693e+08 | Z19: =Y19/G18 -> 465.42494
B20: 7 | C20: {=SUMPRODUCT($C19:$F19,TRANSPOSE(Parameters!C$6:C$9))+($B20-1)*SUMPRODUCT($C19:$F19,TRANSPOSE(Parameters!C$32:C$35))} -> 650545.62 | D20: {=SUMPRODUCT($C19:$F19,TRANSPOSE(Parameters!D$6:D$9))+($B20-1)*SUMPRODUCT($C19:$F19,TRANSPOSE(Parameters!D$32:D$35))} -> 128049.65 | E20: {=SUMPRODUCT($C19:$F19,TRANSPOSE(Parameters!E$6:E$9))+($B20-1)*SUMPRODUCT($C19:$F19,TRANSPOSE(Parameters!E$32:E$35))} -> 44718.188 | F20: {=SUMPRODUCT($C19:$F19,TRANSPOSE(Parameters!F$6:F$9))+($B20-1)*SUMPRODUCT($C19:$F19,TRANSPOSE(Parameters!F$32:F$35))} -> 176686.54 | G20: =SUM(C20:E20) -> 823313.46 | H20: =F20-F19 -> 26386.571 | I20: =I19*(1+Parameters!$B$24) -> 56.308121 | J20: =J19*(1+Parameters!$B$24) -> 225.23248 | K20: =K19*(1+Parameters!$B$24) -> 3378.4873 | L20: =L19*(1+Parameters!$B$24) -> 281.5406 | M20: =M19*(1+Parameters!$B$25) -> 236.60011 | N20: =N19*(1+Parameters!$B$25) -> 4732.0023 | O20: =I20 -> 56.308121 | P20: =J20+M20 -> 461.8326 | Q20: =K20+N20 -> 8110.4895 | R20: =L20 -> 281.5406 | S20: =O20*C19 -> 37720234 | T20: =P20*D19 -> 61399395 | U20: =Q20*E19 -> 3.800816e+08 | V20: =R20*F19 -> 42315544 | W20: =S20+T20+U20+V20 -> 5.2151677e+08 | X20: =X19/(1+Parameters!$B$26) -> 0.75991781 | Y20: =W20*X20 -> 3.9630988e+08 | Z20: =Y20/G19 -> 466.41152
B21: 8 | C21: {=SUMPRODUCT($C20:$F20,TRANSPOSE(Parameters!C$6:C$9))+($B21-1)*SUMPRODUCT($C20:$F20,TRANSPOSE(Parameters!C$32:C$35))} -> 632117.48 | D21: {=SUMPRODUCT($C20:$F20,TRANSPOSE(Parameters!D$6:D$9))+($B21-1)*SUMPRODUCT($C20:$F20,TRANSPOSE(Parameters!D$32:D$35))} -> 123368.43 | E21: {=SUMPRODUCT($C20:$F20,TRANSPOSE(Parameters!E$6:E$9))+($B21-1)*SUMPRODUCT($C20:$F20,TRANSPOSE(Parameters!E$32:E$35))} -> 42644.734 | F21: {=SUMPRODUCT($C20:$F20,TRANSPOSE(Parameters!F$6:F$9))+($B21-1)*SUMPRODUCT($C20:$F20,TRANSPOSE(Parameters!F$32:F$35))} -> 201869.36 | G21: =SUM(C21:E21) -> 798130.64 | H21: =F21-F20 -> 25182.818 | I21: =I20*(1+Parameters!$B$24) -> 57.434283 | J21: =J20*(1+Parameters!$B$24) -> 229.73713 | K21: =K20*(1+Parameters!$B$24) -> 3446.057 | L21: =L20*(1+Parameters!$B$24) -> 287.17142 | M21: =M20*(1+Parameters!$B$25) -> 248.43012 | N21: =N20*(1+Parameters!$B$25) -> 4968.6024 | O21: =I21 -> 57.434283 | P21: =J21+M21 -> 478.16725 | Q21: =K21+N21 -> 8414.6594 | R21: =L21 -> 287.17142 | S21: =O21*C20 -> 37363622 | T21: =P21*D20 -> 61229148 | U21: =Q21*E20 -> 3.7628832e+08 | V21: =R21*F20 -> 50739324 | W21: =S21+T21+U21+V21 -> 5.2562041e+08 | X21: =X20/(1+Parameters!$B$26) -> 0.73069021 | Y21: =W21*X21 -> 3.8406569e+08 | Z21: =Y21/G20 -> 466.4878
B22: 9 | C22: {=SUMPRODUCT($C21:$F21,TRANSPOSE(Parameters!C$6:C$9))+($B22-1)*SUMPRODUCT($C21:$F21,TRANSPOSE(Parameters!C$32:C$35))} -> 614531.6 | D22: {=SUMPRODUCT($C21:$F21,TRANSPOSE(Parameters!D$6:D$9))+($B22-1)*SUMPRODUCT($C21:$F21,TRANSPOSE(Parameters!D$32:D$35))} -> 118903.13 | E22: {=SUMPRODUCT($C21:$F21,TRANSPOSE(Parameters!E$6:E$9))+($B22-1)*SUMPRODUCT($C21:$F21,TRANSPOSE(Parameters!E$32:E$35))} -> 40663.883 | F22: {=SUMPRODUCT($C21:$F21,TRANSPOSE(Parameters!F$6:F$9))+($B22-1)*SUMPRODUCT($C21:$F21,TRANSPOSE(Parameters!F$32:F$35))} -> 225901.39 | G22: =SUM(C22:E22) -> 774098.61 | H22: =F22-F21 -> 24032.031 | I22: =I21*(1+Parameters!$B$24) -> 58.582969 | J22: =J21*(1+Parameters!$B$24) -> 234.33188 | K22: =K21*(1+Parameters!$B$24) -> 3514.9781 | L22: =L21*(1+Parameters!$B$24) -> 292.91485 | M22: =M21*(1+Parameters!$B$25) -> 260.85162 | N22: =N21*(1+Parameters!$B$25) -> 5217.0325 | O22: =I22 -> 58.582969 | P22: =J22+M22 -> 495.1835 | Q22: =K22+N22 -> 8732.0106 | R22: =L22 -> 292.91485 | S22: =O22*C21 -> 37031319 | T22: =P22*D21 -> 61090011 | U22: =Q22*E21 -> 3.7237427e+08 | V22: =R22*F21 -> 59130532 | W22: =S22+T22+U22+V22 -> 5.2962614e+08 | X22: =X21/(1+Parameters!$B$26) -> 0.70258674 | Y22: =W22*X22 -> 3.721083e+08 | Z22: =Y22/G21 -> 466.2248
B23: 10 | C23: {=SUMPRODUCT($C22:$F22,TRANSPOSE(Parameters!C$6:C$9))+($B23-1)*SUMPRODUCT($C22:$F22,TRANSPOSE(Parameters!C$32:C$35))} -> 597736.19 | D23: {=SUMPRODUCT($C22:$F22,TRANSPOSE(Parameters!D$6:D$9))+($B23-1)*SUMPRODUCT($C22:$F22,TRANSPOSE(Parameters!D$32:D$35))} -> 114645.44 | E23: {=SUMPRODUCT($C22:$F22,TRANSPOSE(Parameters!E$6:E$9))+($B23-1)*SUMPRODUCT($C22:$F22,TRANSPOSE(Parameters!E$32:E$35))} -> 38778.275 | F23: {=SUMPRODUCT($C22:$F22,TRANSPOSE(Parameters!F$6:F$9))+($B23-1)*SUMPRODUCT($C22:$F22,TRANSPOSE(Parameters!F$32:F$35))} -> 248840.1 | G23: =SUM(C23:E23) -> 751159.9 | H23: =F23-F22 -> 22938.707 | I23: =I22*(1+Parameters!$B$24) -> 59.754628 | J23: =J22*(1+Parameters!$B$24) -> 239.01851 | K23: =K22*(1+Parameters!$B$24) -> 3585.2777 | L23: =L22*(1+Parameters!$B$24) -> 298.77314 | M23: =M22*(1+Parameters!$B$25) -> 273.89421 | N23: =N22*(1+Parameters!$B$25) -> 5477.8841 | O23: =I23 -> 59.754628 | P23: =J23+M23 -> 512.91272 | Q23: =K23+N23 -> 9063.1618 | R23: =L23 -> 298.77314 | S23: =O23*C22 -> 36721107 | T23: =P23*D22 -> 60986926 | U23: =Q23*E22 -> 3.6854335e+08 | V23: =R23*F22 -> 67493268 | W23: =S23+T23+U23+V23 -> 5.3374466e+08 | X23: =X22/(1+Parameters!$B$26) -> 0.67556417 | Y23: =W23*X23 -> 3.6057876e+08 | Z23: =Y23/G22 -> 465.80469
B24: 11 | C24: {=SUMPRODUCT($C23:$F23,TRANSPOSE(Parameters!C$6:C$9))+($B24-1)*SUMPRODUCT($C23:$F23,TRANSPOSE(Parameters!C$32:C$35))} -> 581688.11 | D24: {=SUMPRODUCT($C23:$F23,TRANSPOSE(Parameters!D$6:D$9))+($B24-1)*SUMPRODUCT($C23:$F23,TRANSPOSE(Parameters!D$32:D$35))} -> 110585.08 | E24: {=SUMPRODUCT($C23:$F23,TRANSPOSE(Parameters!E$6:E$9))+($B24-1)*SUMPRODUCT($C23:$F23,TRANSPOSE(Parameters!E$32:E$35))} -> 36984.897 | F24: {=SUMPRODUCT($C23:$F23,TRANSPOSE(Parameters!F$6:F$9))+($B24-1)*SUMPRODUCT($C23:$F23,TRANSPOSE(Parameters!F$32:F$35))} -> 270741.91 | G24: =SUM(C24:E24) -> 729258.09 | H24: =F24-F23 -> 21901.817 | I24: =I23*(1+Parameters!$B$24) -> 60.949721 | J24: =J23*(1+Parameters!$B$24) -> 243.79888 | K24: =K23*(1+Parameters!$B$24) -> 3656.9833 | L24: =L23*(1+Parameters!$B$24) -> 304.7486 | M24: =M23*(1+Parameters!$B$25) -> 287.58892 | N24: =N23*(1+Parameters!$B$25) -> 5751.7783 | O24: =I24 -> 60.949721 | P24: =J24+M24 -> 531.3878 | Q24: =K24+N24 -> 9408.7616 | R24: =L24 -> 304.7486 | S24: =O24*C23 -> 36431854 | T24: =P24*D23 -> 60921187 | U24: =Q24*E23 -> 3.6485555e+08 | V24: =R24*F23 -> 75833672 | W24: =S24+T24+U24+V24 -> 5.3804226e+08 | X24: =X23/(1+Parameters!$B$26) -> 0.64958093 | Y24: =W24*X24 -> 3.4950199e+08 | Z24: =Y24/G23 -> 465.28308
B25: 12 | C25: {=SUMPRODUCT($C24:$F24,TRANSPOSE(Parameters!C$6:C$9))+($B25-1)*SUMPRODUCT($C24:$F24,TRANSPOSE(Parameters!C$32:C$35))} -> 566348.56 | D25: {=SUMPRODUCT($C24:$F24,TRANSPOSE(Parameters!D$6:D$9))+($B25-1)*SUMPRODUCT($C24:$F24,TRANSPOSE(Parameters!D$32:D$35))} -> 106711.6 | E25: {=SUMPRODUCT($C24:$F24,TRANSPOSE(Parameters!E$6:E$9))+($B25-1)*SUMPRODUCT($C24:$F24,TRANSPOSE(Parameters!E$32:E$35))} -> 35279.182 | F25: {=SUMPRODUCT($C24:$F24,TRANSPOSE(Parameters!F$6:F$9))+($B25-1)*SUMPRODUCT($C24:$F24,TRANSPOSE(Parameters!F$32:F$35))} -> 291660.66 | G25: =SUM(C25:E25) -> 708339.34 | H25: =F25-F24 -> 20918.749 | I25: =I24*(1+Parameters!$B$24) -> 62.168715 | J25: =J24*(1+Parameters!$B$24) -> 248.67486 | K25: =K24*(1+Parameters!$B$24) -> 3730.1229 | L25: =L24*(1+Parameters!$B$24) -> 310.84358 | M25: =M24*(1+Parameters!$B$25) -> 301.96836 | N25: =N24*(1+Parameters!$B$25) -> 6039.3672 | O25: =I25 -> 62.168715 | P25: =J25+M25 -> 550.64322 | Q25: =K25+N25 -> 9769.4902 | R25: =L25 -> 310.84358 | S25: =O25*C24 -> 36162803 | T25: =P25*D24 -> 60892924 | U25: =Q25*E24 -> 3.6132359e+08 | V25: =R25*F24 -> 84158385 | W25: =S25+T25+U25+V25 -> 5.425377e+08 | X25: =X24/(1+Parameters!$B$26) -> 0.62459705 | Y25: =W25*X25 -> 3.3886745e+08 | Z25: =Y25/G24 -> 464.67424
B26: 13 | C26: {=SUMPRODUCT($C25:$F25,TRANSPOSE(Parameters!C$6:C$9))+($B26-1)*SUMPRODUCT($C25:$F25,TRANSPOSE(Parameters!C$32:C$35))} -> 551681.58 | D26: {=SUMPRODUCT($C25:$F25,TRANSPOSE(Parameters!D$6:D$9))+($B26-1)*SUMPRODUCT($C25:$F25,TRANSPOSE(Parameters!D$32:D$35))} -> 103014.93 | E26: {=SUMPRODUCT($C25:$F25,TRANSPOSE(Parameters!E$6:E$9))+($B26-1)*SUMPRODUCT($C25:$F25,TRANSPOSE(Parameters!E$32:E$35))} -> 33656.298 | F26: {=SUMPRODUCT($C25:$F25,TRANSPOSE(Parameters!F$6:F$9))+($B26-1)*SUMPRODUCT($C25:$F25,TRANSPOSE(Parameters!F$32:F$35))} -> 311647.2 | G26: =SUM(C26:E26) -> 688352.8 | H26: =F26-F25 -> 19986.538 | I26: =I25*(1+Parameters!$B$24) -> 63.41209 | J26: =J25*(1+Parameters!$B$24) -> 253.64836 | K26: =K25*(1+Parameters!$B$24) -> 3804.7254 | L26: =L25*(1+Parameters!$B$24) -> 317.06045 | M26: =M25*(1+Parameters!$B$25) -> 317.06678 | N26: =N25*(1+Parameters!$B$25) -> 6341.3356 | O26: =I26 -> 63.41209 | P26: =J26+M26 -> 570.71514 | Q26: =K26+N26 -> 10146.061 | R26: =L26 -> 317.06045 | S26: =O26*C25 -> 35913345 | T26: =P26*D25 -> 60901925 | U26: =Q26*E25 -> 3.5794474e+08 | V26: =R26*F25 -> 92474060 | W26: =S26+T26+U26+V26 -> 5.4723407e+08 | X26: =X25/(1+Parameters!$B$26) -> 0.60057409 | Y26: =W26*X26 -> 3.286546e+08 | Z26: =Y26/G25 -> 463.97903
... B43: 30 | C43: {=SUMPRODUCT($C42:$F42,TRANSPOSE(Parameters!C$6:C$9))+($B43-1)*SUMPRODUCT($C42:$F42,TRANSPOSE(Parameters!C$32:C$35))} -> 378968.58 | D43: {=SUMPRODUCT($C42:$F42,TRANSPOSE(Parameters!D$6:D$9))+($B43-1)*SUMPRODUCT($C42:$F42,TRANSPOSE(Parameters!D$32:D$35))} -> 59805.317 | E43: {=SUMPRODUCT($C42:$F42,TRANSPOSE(Parameters!E$6:E$9))+($B43-1)*SUMPRODUCT($C42:$F42,TRANSPOSE(Parameters!E$32:E$35))} -> 15079.693 | F43: {=SUMPRODUCT($C42:$F42,TRANSPOSE(Parameters!F$6:F$9))+($B43-1)*SUMPRODUCT($C42:$F42,TRANSPOSE(Parameters!F$32:F$35))} -> 546146.41 | G43: =SUM(C43:E43) -> 453853.59 | H43: =F43-F42 -> 9640.0108 | I43: =I42*(1+Parameters!$B$24) -> 88.792235 | J43: =J42*(1+Parameters!$B$24) -> 355.16894 | K43: =K42*(1+Parameters!$B$24) -> 5327.5341 | L43: =L42*(1+Parameters!$B$24) -> 443.96117 | M43: =M42*(1+Parameters!$B$25) -> 726.72287 | N43: =N42*(1+Parameters!$B$25) -> 14534.457 | O43: =I43 -> 88.792235 | P43: =J43+M43 -> 1081.8918 | Q43: =K43+N43 -> 19861.991 | R43: =L43 -> 443.96117 | S43: =O43*C42 -> 34280461 | T43: =P43*D42 -> 66630480 | U43: =Q43*E42 -> 3.1444706e+08 | V43: =R43*F42 -> 2.3818801e+08 | W43: =S43+T43+U43+V43 -> 6.5354601e+08 | X43: =X42/(1+Parameters!$B$26) -> 0.30831867 | Y43: =W43*X43 -> 2.0150044e+08 | Z43: =Y43/G42 -> 434.74265

Sheet Base Scenario (alt)
A1: Initial position
A3: * This is an example approach to determining the solution. An reaosnable attempt is awarded credit.
A4: * This is a duplication of the modelling done on the 'base scenario' worksheet which illustrates an alternative approach to determining a solution to the initial position
C5: Different formulae - do not drag
U9: Total alive | AL9: Total PV
U10: =SUM(U13:U42) -> 19110751 | AL10: =SUM(AL13:AL42) -> 8.8497636e+09
C11: Transition during the year | O11: End of year | V11: Cost | Z11: Drug | AB11: Combined cost | AF11: Cost per state x population
B12: Year | C12: HH | D12: HS | E12: HI | F12: HD | G12: SH | H12: SS | I12: SI | J12: SD | K12: IH | L12: IS | M12: II | N12: ID | O12: H | P12: S | Q12: I | R12: D | S12: Cumulative Deaths | T12: Check sum population | U12: Lives alive | V12: H | W12: S | X12: I | Y12: D | Z12: S | AA12: I | AB12: H | AC12: S | AD12: I | AE12: D | AF12: H | AG12: S | AH12: I | AI12: D | AJ12: Total | AK12: v | AL12: PV | AM12: PV cost per life alive
B13: 1 | C13: =Parameters!$B$12*Parameters!C$6 -> 800000 | D13: =Parameters!$B$12*Parameters!D$6 -> 160000 | E13: =Parameters!$B$12*Parameters!E$6 -> 30000 | F13: =Parameters!$B$12*Parameters!F$6 -> 10000 | O13: =C13+G13+K13 -> 800000 | P13: =D13+H13+L13 -> 160000 | Q13: =E13+I13+M13 -> 30000 | R13: =F13+J13+N13 -> 10000 | S13: =SUM($R$13:R13) -> 10000 | T13: =SUM(O13:Q13,S13) -> 1000000 | U13: =SUM(O13:Q13) -> 990000 | V13: =Parameters!B15 -> 50 | W13: =Parameters!B16 -> 200 | X13: =Parameters!B17 -> 3000 | Y13: =Parameters!B18 -> 250 | Z13: =Parameters!B21 -> 150 | AA13: =Parameters!B22 -> 4000 | AB13: =V13 -> 50 | AC13: =W13+Z13 -> 350 | AD13: =X13+AA13 -> 7000 | AE13: =Y13 -> 250 | AF13: =C13*AB13+G13*(AB13+AC13)/2+K13*(AB13+AD13)/2 -> 40000000 | AG13: =D13*(AB13+AC13)/2+H13*AC13+L13*(AC13+AD13)/2 -> 32000000 | AH13: =E13*(AB13+AD13)/2+I13*(AC13+AD13)/2+M13*AD13 -> 105750000 | AI13: =(F13*AB13+J13*AC13+N13*AD13)/2+R13*AE13 -> 2750000 | AJ13: =SUM(AF13:AI13) -> 180500000 | AK13: =1/(1+Parameters!$B$26) -> 0.96153846 | AL13: =AK13*AJ13 -> 1.7355769e+08 | AM13: =AL13/Parameters!$B$12 -> 173.55769
B14: 2 | C14: =$O13*Parameters!$C$6 -> 640000 | D14: =$O13*Parameters!$D$6 -> 128000 | E14: =$O13*Parameters!$E$6 -> 24000 | F14: =$O13*Parameters!$F$6 -> 8000 | G14: =$P13*Parameters!$C$7 -> 120000 | H14: =$P13*Parameters!$D$7 -> 16000 | I14: =$P13*Parameters!$E$7 -> 16000 | J14: =$P13*Parameters!$F$7 -> 8000 | K14: =$Q13*Parameters!$C$8 -> 4500 | L14: =$Q13*Parameters!$D$8 -> 7500 | M14: =$Q13*Parameters!$E$8 -> 9000 | N14: =$Q13*Parameters!$F$8 -> 9000 | O14: =C14+G14+K14 -> 764500 | P14: =D14+H14+L14 -> 151500 | Q14: =E14+I14+M14 -> 49000 | R14: =F14+J14+N14 -> 25000 | S14: =SUM($R$13:R14) -> 35000 | T14: =SUM(O14:Q14,S14) -> 1000000 | U14: =SUM(O14:Q14) -> 965000 | V14: =V13*(1+Parameters!$B$24) -> 51 | W14: =W13*(1+Parameters!$B$24) -> 204 | X14: =X13*(1+Parameters!$B$24) -> 3060 | Y14: =Y13*(1+Parameters!$B$24) -> 255 | Z14: =Z13*(1+Parameters!$B$25) -> 157.5 | AA14: =AA13*(1+Parameters!$B$25) -> 4200 | AB14: =V14 -> 51 | AC14: =W14+Z14 -> 361.5 | AD14: =X14+AA14 -> 7260 | AE14: =Y14 -> 255 | AF14: =C14*AB14+G14*(AB14+AC14)/2+K14*(AB14+AD14)/2 -> 73839750 | AG14: =D14*(AB14+AC14)/2+H14*AC14+L14*(AC14+AD14)/2 -> 60764625 | AH14: =E14*(AB14+AD14)/2+I14*(AC14+AD14)/2+M14*AD14 -> 214044000 | AI14: =(F14*AB14+J14*AC14+N14*AD14)/2+R14*AE14 -> 40695000 | AJ14: =SUM(AF14:AI14) -> 389343375 | AK14: =AK13/(1+Parameters!$B$26) -> 0.92455621 | AL14: =AK14*AJ14 -> 3.5996984e+08 | AM14: =AL14/U13 -> 363.6059
B15: 3 | C15: =$O14*Parameters!$C$6 -> 611600 | D15: =$O14*Parameters!$D$6 -> 122320 | E15: =$O14*Parameters!$E$6 -> 22935 | F15: =$O14*Parameters!$F$6 -> 7645 | G15: =$P14*Parameters!$C$7 -> 113625 | H15: =$P14*Parameters!$D$7 -> 15150 | I15: =$P14*Parameters!$E$7 -> 15150 | J15: =$P14*Parameters!$F$7 -> 7575 | K15: =$Q14*Parameters!$C$8 -> 7350 | L15: =$Q14*Parameters!$D$8 -> 12250 | M15: =$Q14*Parameters!$E$8 -> 14700 | N15: =$Q14*Parameters!$F$8 -> 14700 | O15: =C15+G15+K15 -> 732575 | P15: =D15+H15+L15 -> 149720 | Q15: =E15+I15+M15 -> 52785 | R15: =N15+J15+F15 -> 29920 | S15: =SUM($R$13:R15) -> 64920 | T15: =SUM(O15:Q15,S15) -> 1000000 | U15: =SUM(O15:Q15) -> 935080 | V15: =V14*(1+Parameters!$B$24) -> 52.02 | W15: =W14*(1+Parameters!$B$24) -> 208.08 | X15: =X14*(1+Parameters!$B$24) -> 3121.2 | Y15: =Y14*(1+Parameters!$B$24) -> 260.1 | Z15: =Z14*(1+Parameters!$B$25) -> 165.375 | AA15: =AA14*(1+Parameters!$B$25) -> 4410 | AB15: =V15 -> 52.02 | AC15: =W15+Z15 -> 373.455 | AD15: =X15+AA15 -> 7531.2 | AE15: =Y15 -> 260.1 | AF15: =C15*AB15+G15*(AB15+AC15)/2+K15*(AB15+AD15)/2 -> 83856064 | AG15: =D15*(AB15+AC15)/2+H15*AC15+L15*(AC15+AD15)/2 -> 80095906 | AH15: =E15*(AB15+AD15)/2+I15*(AC15+AD15)/2+M15*AD15 -> 2.5754698e+08 | AI15: =(F15*AB15+J15*AC15+N15*AD15)/2+R15*AE15 -> 64749819 | AJ15: =SUM(AF15:AI15) -> 4.8624877e+08 | AK15: =AK14/(1+Parameters!$B$26) -> 0.88899636 | AL15: =AK15*AJ15 -> 4.3227338e+08 | AM15: =AL15/U14 -> 447.95169
