Workbook

Sheet Data
B1: Raw data provided by the client
B4: Movie schedule and seating capacity by screen
B5: Screen | C5: Capacity | D5: Jan | E5: Feb | F5: Mar | G5: Apr | H5: May | I5: Jun | J5: Jul | K5: Aug | L5: Sep | M5: Oct | N5: Nov | O5: Dec
B6: 1 | C6: 850 | D6: Major 1 | E6: Major 1 | F6: Regular 3 | G6: Major 2 | H6: Major 2 | I6: Regular 6 | J6: Epic 1 | K6: Epic 1 | L6: Regular 7 | M6: Major | N6: Major 3 | O6: Regular 10
B7: 2 | C7: 450 | D7: Major 1 | E7: Regular 1 | F7: Major 1 | G7: Major 2 | H7: Regular 5 | I7: Major 2 | J7: Epic 1 | K7: Epic 1 | L7: Epic 1 | M7: Major 3 | N7: Regular 10 | O7: Major 3
B8: 3 | C8: 200 | D8: Regular 1 | E8: Regular 2 | F8: Regular 3 | G8: Regular 4 | H8: Regular 4 | I8: Regular 5 | J8: Epic 1 | K8: Regular 7 | L8: Epic 1 | M8: Epic 1 | N8: Regular 9 | O8: Regular 10
B9: 4 | C9: 150 | D9: Regular 2 | E9: Regular 2 | F9: Regular 1 | G9: Regular 3 | H9: Regular 4 | I9: Regular 4 | J9: Regular 6 | K9: Regular 8 | L9: Regular 8 | M9: Regular 9 | N9: Regular 9 | O9: Regular 9
B12: Projected utilisation rate | C12: Regular | D12: Major | E12: Epic | H12: Commission arrangement with movie distributors (% of ticket price) | I12: Regular | J12: Major | K12: Epic
B13: Month | C13: R | D13: M | E13: E | H13: Month | I13: R | J13: M | K13: E
B14: 1 | C14: 0.85 | D14: 0.93 | E14: 0.98 | H14: 1 | I14: 0.45 | J14: 0.55 | K14: 0.65
B15: 2 | C15: 0.65 | D15: 0.8 | E15: 0.85 | H15: 2 | I15: 0.35 | J15: 0.45 | K15: 0.55
B16: 3 | C16: 0.45 | D16: 0.65 | E16: 0.7 | H16: 3 | I16: 0.15 | J16: 0.3 | K16: 0.45
B17: 4 | C17: 0 | D17: 0 | E17: 0.6 | H17: 4 | I17: 0 | J17: 0 | K17: 0.2
B20: A. Number of movies seen over a year | C20: B. Unique Cinemagoers (annual) | D20: C. Proportion buying snacks
B21: 1 | C21: 185220 | D21: 0.22257935
B22: 2 | C22: 270000 | D22: =D21*1.3 -> 0.28935316
B23: 3 | C23: 180000 | D23: =D21*1.35 -> 0.30048212
B24: 4 | C24: 135000 | D24: 0.39
B25: 5 | C25: 81000 | D25: 0.35
B26: 6 | C26: 54000 | D26: 0.42
B27: 7 | C27: 27000 | D27: 0.4
B28: 8 | C28: 5400 | D28: 0.5
B29: 9 | C29: 3600 | D29: 0.65
B30: 10 | C30: 1080 | D30: 0.57
B31: 11 | C31: 1080 | D31: 0.68
B32: 12 | C32: 900 | D32: 0.59
B33: 13 | C33: 540 | D33: 0.7
B34: 14 | C34: 360 | D34: 0.71

Sheet Data_checks
B1: Data checks
B4: =Data!B4 -> Movie schedule and seating capacity by screen
B5: =Data!B5 -> Screen | C5: =Data!C5 -> Capacity | D5: =Data!D5 -> Jan | E5: =Data!E5 -> Feb | F5: =Data!F5 -> Mar | G5: =Data!G5 -> Apr | H5: =Data!H5 -> May | I5: =Data!I5 -> Jun | ... O5: =Data!O5 -> Dec
B6: =Data!B6 -> 1 | C6: =Data!C6 -> 850 | D6: =Data!D6 -> Major 1 | E6: =Data!E6 -> Major 1 | F6: =Data!F6 -> Regular 3 | G6: =Data!G6 -> Major 2 | H6: =Data!H6 -> Major 2 | I6: =Data!I6 -> Regular 6 | ... O6: =Data!O6 -> Regular 10
B7: =Data!B7 -> 2 | C7: =Data!C7 -> 450 | D7: =Data!D7 -> Major 1 | E7: =Data!E7 -> Regular 1 | F7: =Data!F7 -> Major 1 | G7: =Data!G7 -> Major 2 | H7: =Data!H7 -> Regular 5 | I7: =Data!I7 -> Major 2 | ... O7: =Data!O7 -> Major 3
B8: =Data!B8 -> 3 | C8: =Data!C8 -> 200 | D8: =Data!D8 -> Regular 1 | E8: =Data!E8 -> Regular 2 | F8: =Data!F8 -> Regular 3 | G8: =Data!G8 -> Regular 4 | H8: =Data!H8 -> Regular 4 | I8: =Data!I8 -> Regular 5 | ... O8: =Data!O8 -> Regular 10
B9: =Data!B9 -> 4 | C9: =Data!C9 -> 150 | D9: =Data!D9 -> Regular 2 | E9: =Data!E9 -> Regular 2 | F9: =Data!F9 -> Regular 1 | G9: =Data!G9 -> Regular 3 | H9: =Data!H9 -> Regular 4 | I9: =Data!I9 -> Regular 4 | ... O9: =Data!O9 -> Regular 9
B11: Checks:
C12: Equivalent number of monthly screenings
B13: Epic 1 | C13: =COUNTIF($D$6:$O$9,B13) -> 8 | E13: Commentary
B14: Major 1 | C14: =COUNTIF($D$6:$O$9,B14) -> 4 | E14: It makes sense the Epic release is shown the most times, followed by Major releases.
B15: Major 2 | C15: =COUNTIF($D$6:$O$9,B15) -> 4 | E15: Each movie is shown for two to four months over the year. No reasons to doubt the validity of the movie schedule
B16: Major 3 | C16: =COUNTIF($D$6:$O$9,B16) -> 3
B17: Regular 1 | C17: =COUNTIF($D$6:$O$9,B17) -> 3
B18: Regular 2 | C18: =COUNTIF($D$6:$O$9,B18) -> 3
B19: Regular 3 | C19: =COUNTIF($D$6:$O$9,B19) -> 3
B20: Regular 4 | C20: =COUNTIF($D$6:$O$9,B20) -> 4
B21: Regular 5 | C21: =COUNTIF($D$6:$O$9,B21) -> 2
B22: Regular 6 | C22: =COUNTIF($D$6:$O$9,B22) -> 2
B23: Regular 7 | C23: =COUNTIF($D$6:$O$9,B23) -> 2
B24: Regular 8 | C24: =COUNTIF($D$6:$O$9,B24) -> 2
B25: Regular 9 | C25: =COUNTIF($D$6:$O$9,B25) -> 4
B26: Regular 10 | C26: =COUNTIF($D$6:$O$9,B26) -> 3
B27: Total | C27: =SUM(C13:C26) -> 47 | D27: =COUNTA(D6:O9)=C27 -> FALSE
B29: =Data!B12 -> Projected utilisation rate | H29: =Data!H12 -> Commission arrangement with movie distributors (% of ticket price)
B30: Month | C30: =Data!C13 -> R | D30: =Data!D13 -> M | E30: =Data!E13 -> E | H30: Month | I30: =Data!I13 -> R | J30: =Data!J13 -> M | K30: =Data!K13 -> E
B31: 1 | C31: =Data!C14 -> 0.85 | D31: =Data!D14 -> 0.93 | E31: =Data!E14 -> 0.98 | H31: 1 | I31: =Data!I14 -> 0.45 | J31: =Data!J14 -> 0.55 | K31: =Data!K14 -> 0.65
B32: 2 | C32: =Data!C15 -> 0.65 | D32: =Data!D15 -> 0.8 | E32: =Data!E15 -> 0.85 | H32: 2 | I32: =Data!I15 -> 0.35 | J32: =Data!J15 -> 0.45 | K32: =Data!K15 -> 0.55
B33: 3 | C33: =Data!C16 -> 0.45 | D33: =Data!D16 -> 0.65 | E33: =Data!E16 -> 0.7 | H33: 3 | I33: =Data!I16 -> 0.15 | J33: =Data!J16 -> 0.3 | K33: =Data!K16 -> 0.45
B34: 4 | C34: =Data!C17 -> 0 | D34: =Data!D17 -> 0 | E34: =Data!E17 -> 0.6 | H34: 4 | I34: =Data!I17 -> 0 | J34: =Data!J17 -> 0 | K34: =Data!K17 -> 0.2
B36: Checks:
B37: By eyes only, Epic has the highest utilisation rate, followed by Major then Regular, which makes sense
B38: The utilisation rate is lower the longer a movie has been in the cinema, which seems reasonable.
B39: Commision rates follows a very similar pattern as the utilisation rate, which again makes sense.
B40: No doubt in the validity of the data provided.
B43: =Data!B20 -> A. Number of movies seen over a year | C43: =Data!C20 -> B. Unique Cinemagoers (annual) | D43: =Data!D20 -> C. Proportion buying snacks | E43: Numbers of movies seen | F43: As a proportion of number of movies seen
B44: =Data!B21 -> 1 | C44: =Data!C21 -> 185220 | D44: =Data!D21 -> 0.22257935 | E44: =C44*B44 -> 185220 | F44: =E44/$E$58 -> 0.065118339
B45: =Data!B22 -> 2 | C45: =Data!C22 -> 270000 | D45: =Data!D22 -> 0.28935316 | E45: =C45*B45 -> 540000 | F45: =E45/$E$58 -> 0.18984939
B46: =Data!B23 -> 3 | C46: =Data!C23 -> 180000 | D46: =Data!D23 -> 0.30048212 | E46: =C46*B46 -> 540000 | F46: =E46/$E$58 -> 0.18984939
B47: =Data!B24 -> 4 | C47: =Data!C24 -> 135000 | D47: =Data!D24 -> 0.39 | E47: =C47*B47 -> 540000 | F47: =E47/$E$58 -> 0.18984939
B48: =Data!B25 -> 5 | C48: =Data!C25 -> 81000 | D48: =Data!D25 -> 0.35 | E48: =C48*B48 -> 405000 | F48: =E48/$E$58 -> 0.14238704
B49: =Data!B26 -> 6 | C49: =Data!C26 -> 54000 | D49: =Data!D26 -> 0.42 | E49: =C49*B49 -> 324000 | F49: =E49/$E$58 -> 0.11390963
B50: =Data!B27 -> 7 | C50: =Data!C27 -> 27000 | D50: =Data!D27 -> 0.4 | E50: =C50*B50 -> 189000 | F50: =E50/$E$58 -> 0.066447285
B51: =Data!B28 -> 8 | C51: =Data!C28 -> 5400 | D51: =Data!D28 -> 0.5 | E51: =C51*B51 -> 43200 | F51: =E51/$E$58 -> 0.015187951
B52: =Data!B29 -> 9 | C52: =Data!C29 -> 3600 | D52: =Data!D29 -> 0.65 | E52: =C52*B52 -> 32400 | F52: =E52/$E$58 -> 0.011390963
B53: =Data!B30 -> 10 | C53: =Data!C30 -> 1080 | D53: =Data!D30 -> 0.57 | E53: =C53*B53 -> 10800 | F53: =E53/$E$58 -> 0.0037969877
B54: =Data!B31 -> 11 | C54: =Data!C31 -> 1080 | D54: =Data!D31 -> 0.68 | E54: =C54*B54 -> 11880 | F54: =E54/$E$58 -> 0.0041766865
B55: =Data!B32 -> 12 | C55: =Data!C32 -> 900 | D55: =Data!D32 -> 0.59 | E55: =C55*B55 -> 10800 | F55: =E55/$E$58 -> 0.0037969877
... B57: =Data!B34 -> 14 | C57: =Data!C34 -> 360 | D57: =Data!D34 -> 0.71 | E57: =C57*B57 -> 5040 | F57: =E57/$E$58 -> 0.0017719276
C58: =SUM(C44:C57) -> 945180 | E58: =SUM(E44:E57) -> 2844360
B60: Checks:
B61: Intuitively would expect most cinemagoers only go to the cinema a few times a year, perhaps to watch the movies they wanted to watch.
B62: There appears to be some die-hard cinema fans who would watch almost all movies in the year, which again does not seem surprising.

Sheet Parameters
B1: Parameters
C3: Original | D3: Annual pass
B4: Screenings per day | C4: 6
B5: Number of day in a month | C5: 30
B6: Ticket price ($) | C6: 13
B7: Average snack spend ($) | C7: 22
B9: Staff | C9: 32
B10: Hourly rate ($) | C10: 25
B11: Number of hours worked a day | C11: 8
B12: Monthly overheads ($) | C12: 300000
B13: Costs per average snack spend ($) | C13: 2
B15: Annual pass fee | C15: 0 | D15: 74
B16: Number of films for annual pass* (Annual pass threshold) | C16: 15 | D16: 5 | E16: *In the original scenario this is entered as 15 as annual pass is not an option and no cinemagoers will watch 15 or more films.
B17: Change in snack spending habit | C17: 0 | D17: 0.2
B18: Discount on snacks for passholders | C18: 0 | D18: 0.1

Sheet Calc_original
B1: Cinema going and profit calculations for original scenario (i.e. no annual pass)
B5: Schedule
B6: Screen | C6: Jan | D6: Feb | E6: Mar | F6: Apr | G6: May | H6: Jun | I6: Jul | J6: Aug | K6: Sep | L6: Oct | M6: Nov | N6: Dec
B7: =Data_checks!$B6 -> 1 | C7: =Data_checks!D6 -> Major 1 | D7: =Data_checks!E6 -> Major 1 | E7: =Data_checks!F6 -> Regular 3 | F7: =Data_checks!G6 -> Major 2 | G7: =Data_checks!H6 -> Major 2 | H7: =Data_checks!I6 -> Regular 6 | I7: =Data_checks!J6 -> Epic 1 | J7: =Data_checks!K6 -> Epic 1 | ... N7: =Data_checks!O6 -> Regular 10
B8: =Data_checks!$B7 -> 2 | C8: =Data_checks!D7 -> Major 1 | D8: =Data_checks!E7 -> Regular 1 | E8: =Data_checks!F7 -> Major 1 | F8: =Data_checks!G7 -> Major 2 | G8: =Data_checks!H7 -> Regular 5 | H8: =Data_checks!I7 -> Major 2 | I8: =Data_checks!J7 -> Epic 1 | J8: =Data_checks!K7 -> Epic 1 | ... N8: =Data_checks!O7 -> Major 3
B9: =Data_checks!$B8 -> 3 | C9: =Data_checks!D8 -> Regular 1 | D9: =Data_checks!E8 -> Regular 2 | E9: =Data_checks!F8 -> Regular 3 | F9: =Data_checks!G8 -> Regular 4 | G9: =Data_checks!H8 -> Regular 4 | H9: =Data_checks!I8 -> Regular 5 | I9: =Data_checks!J8 -> Epic 1 | J9: =Data_checks!K8 -> Regular 7 | ... N9: =Data_checks!O8 -> Regular 10
B10: =Data_checks!$B9 -> 4 | C10: =Data_checks!D9 -> Regular 2 | D10: =Data_checks!E9 -> Regular 2 | E10: =Data_checks!F9 -> Regular 1 | F10: =Data_checks!G9 -> Regular 3 | G10: =Data_checks!H9 -> Regular 4 | H10: =Data_checks!I9 -> Regular 4 | I10: =Data_checks!J9 -> Regular 6 | J10: =Data_checks!K9 -> Regular 8 | ... N10: =Data_checks!O9 -> Regular 9
B12: Number of months movie has been showing
B13: Screen | C13: =C6 -> Jan | D13: =D6 -> Feb | E13: =E6 -> Mar | F13: =F6 -> Apr | G13: =G6 -> May | H13: =H6 -> Jun | I13: =I6 -> Jul | J13: =J6 -> Aug | ... N13: =N6 -> Dec
B14: =B7 -> 1 | C14: 1 | D14: =IF(COUNTIF(C$7:C$10,D7)>0,1,0)+IF(COUNTIF(B$7:B$10,D7)>0,1,0)+IF(COUNTIF(A$7:A$10,D7)>0,1,0)+1 -> 2 | E14: =IF(COUNTIF(D$7:D$10,E7)>0,1,0)+IF(COUNTIF(C$7:C$10,E7)>0,1,0)+IF(COUNTIF(B$7:B$10,E7)>0,1,0)+1 -> 1 | F14: =IF(COUNTIF(E$7:E$10,F7)>0,1,0)+IF(COUNTIF(D$7:D$10,F7)>0,1,0)+IF(COUNTIF(C$7:C$10,F7)>0,1,0)+1 -> 1 | G14: =IF(COUNTIF(F$7:F$10,G7)>0,1,0)+IF(COUNTIF(E$7:E$10,G7)>0,1,0)+IF(COUNTIF(D$7:D$10,G7)>0,1,0)+1 -> 2 | H14: =IF(COUNTIF(G$7:G$10,H7)>0,1,0)+IF(COUNTIF(F$7:F$10,H7)>0,1,0)+IF(COUNTIF(E$7:E$10,H7)>0,1,0)+1 -> 1 | I14: =IF(COUNTIF(H$7:H$10,I7)>0,1,0)+IF(COUNTIF(G$7:G$10,I7)>0,1,0)+IF(COUNTIF(F$7:F$10,I7)>0,1,0)+1 -> 1 | J14: =IF(COUNTIF(I$7:I$10,J7)>0,1,0)+IF(COUNTIF(H$7:H$10,J7)>0,1,0)+IF(COUNTIF(G$7:G$10,J7)>0,1,0)+1 -> 2 | K14: =IF(COUNTIF(J$7:J$10,K7)>0,1,0)+IF(COUNTIF(I$7:I$10,K7)>0,1,0)+IF(COUNTIF(H$7:H$10,K7)>0,1,0)+1 -> 2 | ... N14: =IF(COUNTIF(M$7:M$10,N7)>0,1,0)+IF(COUNTIF(L$7:L$10,N7)>0,1,0)+IF(COUNTIF(K$7:K$10,N7)>0,1,0)+1 -> 2
B15: =B8 -> 2 | C15: 1 | D15: =IF(COUNTIF(C$7:C$10,D8)>0,1,0)+IF(COUNTIF(B$7:B$10,D8)>0,1,0)+IF(COUNTIF(A$7:A$10,D8)>0,1,0)+1 -> 2 | E15: =IF(COUNTIF(D$7:D$10,E8)>0,1,0)+IF(COUNTIF(C$7:C$10,E8)>0,1,0)+IF(COUNTIF(B$7:B$10,E8)>0,1,0)+1 -> 3 | F15: =IF(COUNTIF(E$7:E$10,F8)>0,1,0)+IF(COUNTIF(D$7:D$10,F8)>0,1,0)+IF(COUNTIF(C$7:C$10,F8)>0,1,0)+1 -> 1 | G15: =IF(COUNTIF(F$7:F$10,G8)>0,1,0)+IF(COUNTIF(E$7:E$10,G8)>0,1,0)+IF(COUNTIF(D$7:D$10,G8)>0,1,0)+1 -> 1 | H15: =IF(COUNTIF(G$7:G$10,H8)>0,1,0)+IF(COUNTIF(F$7:F$10,H8)>0,1,0)+IF(COUNTIF(E$7:E$10,H8)>0,1,0)+1 -> 3 | I15: =IF(COUNTIF(H$7:H$10,I8)>0,1,0)+IF(COUNTIF(G$7:G$10,I8)>0,1,0)+IF(COUNTIF(F$7:F$10,I8)>0,1,0)+1 -> 1 | J15: =IF(COUNTIF(I$7:I$10,J8)>0,1,0)+IF(COUNTIF(H$7:H$10,J8)>0,1,0)+IF(COUNTIF(G$7:G$10,J8)>0,1,0)+1 -> 2 | K15: =IF(COUNTIF(J$7:J$10,K8)>0,1,0)+IF(COUNTIF(I$7:I$10,K8)>0,1,0)+IF(COUNTIF(H$7:H$10,K8)>0,1,0)+1 -> 3 | ... N15: =IF(COUNTIF(M$7:M$10,N8)>0,1,0)+IF(COUNTIF(L$7:L$10,N8)>0,1,0)+IF(COUNTIF(K$7:K$10,N8)>0,1,0)+1 -> 3
B16: =B9 -> 3 | C16: 1 | D16: =IF(COUNTIF(C$7:C$10,D9)>0,1,0)+IF(COUNTIF(B$7:B$10,D9)>0,1,0)+IF(COUNTIF(A$7:A$10,D9)>0,1,0)+1 -> 2 | E16: =IF(COUNTIF(D$7:D$10,E9)>0,1,0)+IF(COUNTIF(C$7:C$10,E9)>0,1,0)+IF(COUNTIF(B$7:B$10,E9)>0,1,0)+1 -> 1 | F16: =IF(COUNTIF(E$7:E$10,F9)>0,1,0)+IF(COUNTIF(D$7:D$10,F9)>0,1,0)+IF(COUNTIF(C$7:C$10,F9)>0,1,0)+1 -> 1 | G16: =IF(COUNTIF(F$7:F$10,G9)>0,1,0)+IF(COUNTIF(E$7:E$10,G9)>0,1,0)+IF(COUNTIF(D$7:D$10,G9)>0,1,0)+1 -> 2 | H16: =IF(COUNTIF(G$7:G$10,H9)>0,1,0)+IF(COUNTIF(F$7:F$10,H9)>0,1,0)+IF(COUNTIF(E$7:E$10,H9)>0,1,0)+1 -> 2 | I16: =IF(COUNTIF(H$7:H$10,I9)>0,1,0)+IF(COUNTIF(G$7:G$10,I9)>0,1,0)+IF(COUNTIF(F$7:F$10,I9)>0,1,0)+1 -> 1 | J16: =IF(COUNTIF(I$7:I$10,J9)>0,1,0)+IF(COUNTIF(H$7:H$10,J9)>0,1,0)+IF(COUNTIF(G$7:G$10,J9)>0,1,0)+1 -> 1 | K16: =IF(COUNTIF(J$7:J$10,K9)>0,1,0)+IF(COUNTIF(I$7:I$10,K9)>0,1,0)+IF(COUNTIF(H$7:H$10,K9)>0,1,0)+1 -> 3 | ... N16: =IF(COUNTIF(M$7:M$10,N9)>0,1,0)+IF(COUNTIF(L$7:L$10,N9)>0,1,0)+IF(COUNTIF(K$7:K$10,N9)>0,1,0)+1 -> 2
B17: =B10 -> 4 | C17: 1 | D17: =IF(COUNTIF(C$7:C$10,D10)>0,1,0)+IF(COUNTIF(B$7:B$10,D10)>0,1,0)+IF(COUNTIF(A$7:A$10,D10)>0,1,0)+1 -> 2 | E17: =IF(COUNTIF(D$7:D$10,E10)>0,1,0)+IF(COUNTIF(C$7:C$10,E10)>0,1,0)+IF(COUNTIF(B$7:B$10,E10)>0,1,0)+1 -> 3 | F17: =IF(COUNTIF(E$7:E$10,F10)>0,1,0)+IF(COUNTIF(D$7:D$10,F10)>0,1,0)+IF(COUNTIF(C$7:C$10,F10)>0,1,0)+1 -> 2 | G17: =IF(COUNTIF(F$7:F$10,G10)>0,1,0)+IF(COUNTIF(E$7:E$10,G10)>0,1,0)+IF(COUNTIF(D$7:D$10,G10)>0,1,0)+1 -> 2 | H17: =IF(COUNTIF(G$7:G$10,H10)>0,1,0)+IF(COUNTIF(F$7:F$10,H10)>0,1,0)+IF(COUNTIF(E$7:E$10,H10)>0,1,0)+1 -> 3 | I17: =IF(COUNTIF(H$7:H$10,I10)>0,1,0)+IF(COUNTIF(G$7:G$10,I10)>0,1,0)+IF(COUNTIF(F$7:F$10,I10)>0,1,0)+1 -> 2 | J17: =IF(COUNTIF(I$7:I$10,J10)>0,1,0)+IF(COUNTIF(H$7:H$10,J10)>0,1,0)+IF(COUNTIF(G$7:G$10,J10)>0,1,0)+1 -> 1 | K17: =IF(COUNTIF(J$7:J$10,K10)>0,1,0)+IF(COUNTIF(I$7:I$10,K10)>0,1,0)+IF(COUNTIF(H$7:H$10,K10)>0,1,0)+1 -> 2 | ... N17: =IF(COUNTIF(M$7:M$10,N10)>0,1,0)+IF(COUNTIF(L$7:L$10,N10)>0,1,0)+IF(COUNTIF(K$7:K$10,N10)>0,1,0)+1 -> 3
B19: Projected screen usage
B20: Screen | C20: =C13 -> Jan | D20: =D13 -> Feb | E20: =E13 -> Mar | F20: =F13 -> Apr | G20: =G13 -> May | H20: =H13 -> Jun | I20: =I13 -> Jul | J20: =J13 -> Aug | ... N20: =N13 -> Dec
B21: =B14 -> 1 | C21: =INDEX(Data_checks!$C$31:$E$34,MATCH(C14,Data_checks!$B$31:$B$34,0),MATCH(LEFT(C7,1),Data_checks!$C$30:$E$30,0)) -> 0.93 | D21: =INDEX(Data_checks!$C$31:$E$34,MATCH(D14,Data_checks!$B$31:$B$34,0),MATCH(LEFT(D7,1),Data_checks!$C$30:$E$30,0)) -> 0.8 | E21: =INDEX(Data_checks!$C$31:$E$34,MATCH(E14,Data_checks!$B$31:$B$34,0),MATCH(LEFT(E7,1),Data_checks!$C$30:$E$30,0)) -> 0.85 | F21: =INDEX(Data_checks!$C$31:$E$34,MATCH(F14,Data_checks!$B$31:$B$34,0),MATCH(LEFT(F7,1),Data_checks!$C$30:$E$30,0)) -> 0.93 | G21: =INDEX(Data_checks!$C$31:$E$34,MATCH(G14,Data_checks!$B$31:$B$34,0),MATCH(LEFT(G7,1),Data_checks!$C$30:$E$30,0)) -> 0.8 | H21: =INDEX(Data_checks!$C$31:$E$34,MATCH(H14,Data_checks!$B$31:$B$34,0),MATCH(LEFT(H7,1),Data_checks!$C$30:$E$30,0)) -> 0.85 | I21: =INDEX(Data_checks!$C$31:$E$34,MATCH(I14,Data_checks!$B$31:$B$34,0),MATCH(LEFT(I7,1),Data_checks!$C$30:$E$30,0)) -> 0.98 | J21: =INDEX(Data_checks!$C$31:$E$34,MATCH(J14,Data_checks!$B$31:$B$34,0),MATCH(LEFT(J7,1),Data_checks!$C$30:$E$30,0)) -> 0.85 | ... N21: =INDEX(Data_checks!$C$31:$E$34,MATCH(N14,Data_checks!$B$31:$B$34,0),MATCH(LEFT(N7,1),Data_checks!$C$30:$E$30,0)) -> 0.65
B22: =B15 -> 2 | C22: =INDEX(Data_checks!$C$31:$E$34,MATCH(C15,Data_checks!$B$31:$B$34,0),MATCH(LEFT(C8,1),Data_checks!$C$30:$E$30,0)) -> 0.93 | D22: =INDEX(Data_checks!$C$31:$E$34,MATCH(D15,Data_checks!$B$31:$B$34,0),MATCH(LEFT(D8,1),Data_checks!$C$30:$E$30,0)) -> 0.65 | E22: =INDEX(Data_checks!$C$31:$E$34,MATCH(E15,Data_checks!$B$31:$B$34,0),MATCH(LEFT(E8,1),Data_checks!$C$30:$E$30,0)) -> 0.65 | F22: =INDEX(Data_checks!$C$31:$E$34,MATCH(F15,Data_checks!$B$31:$B$34,0),MATCH(LEFT(F8,1),Data_checks!$C$30:$E$30,0)) -> 0.93 | G22: =INDEX(Data_checks!$C$31:$E$34,MATCH(G15,Data_checks!$B$31:$B$34,0),MATCH(LEFT(G8,1),Data_checks!$C$30:$E$30,0)) -> 0.85 | H22: =INDEX(Data_checks!$C$31:$E$34,MATCH(H15,Data_checks!$B$31:$B$34,0),MATCH(LEFT(H8,1),Data_checks!$C$30:$E$30,0)) -> 0.65 | I22: =INDEX(Data_checks!$C$31:$E$34,MATCH(I15,Data_checks!$B$31:$B$34,0),MATCH(LEFT(I8,1),Data_checks!$C$30:$E$30,0)) -> 0.98 | J22: =INDEX(Data_checks!$C$31:$E$34,MATCH(J15,Data_checks!$B$31:$B$34,0),MATCH(LEFT(J8,1),Data_checks!$C$30:$E$30,0)) -> 0.85 | ... N22: =INDEX(Data_checks!$C$31:$E$34,MATCH(N15,Data_checks!$B$31:$B$34,0),MATCH(LEFT(N8,1),Data_checks!$C$30:$E$30,0)) -> 0.65
B23: =B16 -> 3 | C23: =INDEX(Data_checks!$C$31:$E$34,MATCH(C16,Data_checks!$B$31:$B$34,0),MATCH(LEFT(C9,1),Data_checks!$C$30:$E$30,0)) -> 0.85 | D23: =INDEX(Data_checks!$C$31:$E$34,MATCH(D16,Data_checks!$B$31:$B$34,0),MATCH(LEFT(D9,1),Data_checks!$C$30:$E$30,0)) -> 0.65 | E23: =INDEX(Data_checks!$C$31:$E$34,MATCH(E16,Data_checks!$B$31:$B$34,0),MATCH(LEFT(E9,1),Data_checks!$C$30:$E$30,0)) -> 0.85 | F23: =INDEX(Data_checks!$C$31:$E$34,MATCH(F16,Data_checks!$B$31:$B$34,0),MATCH(LEFT(F9,1),Data_checks!$C$30:$E$30,0)) -> 0.85 | G23: =INDEX(Data_checks!$C$31:$E$34,MATCH(G16,Data_checks!$B$31:$B$34,0),MATCH(LEFT(G9,1),Data_checks!$C$30:$E$30,0)) -> 0.65 | H23: =INDEX(Data_checks!$C$31:$E$34,MATCH(H16,Data_checks!$B$31:$B$34,0),MATCH(LEFT(H9,1),Data_checks!$C$30:$E$30,0)) -> 0.65 | I23: =INDEX(Data_checks!$C$31:$E$34,MATCH(I16,Data_checks!$B$31:$B$34,0),MATCH(LEFT(I9,1),Data_checks!$C$30:$E$30,0)) -> 0.98 | J23: =INDEX(Data_checks!$C$31:$E$34,MATCH(J16,Data_checks!$B$31:$B$34,0),MATCH(LEFT(J9,1),Data_checks!$C$30:$E$30,0)) -> 0.85 | ... N23: =INDEX(Data_checks!$C$31:$E$34,MATCH(N16,Data_checks!$B$31:$B$34,0),MATCH(LEFT(N9,1),Data_checks!$C$30:$E$30,0)) -> 0.65
B24: =B17 -> 4 | C24: =INDEX(Data_checks!$C$31:$E$34,MATCH(C17,Data_checks!$B$31:$B$34,0),MATCH(LEFT(C10,1),Data_checks!$C$30:$E$30,0)) -> 0.85 | D24: =INDEX(Data_checks!$C$31:$E$34,MATCH(D17,Data_checks!$B$31:$B$34,0),MATCH(LEFT(D10,1),Data_checks!$C$30:$E$30,0)) -> 0.65 | E24: =INDEX(Data_checks!$C$31:$E$34,MATCH(E17,Data_checks!$B$31:$B$34,0),MATCH(LEFT(E10,1),Data_checks!$C$30:$E$30,0)) -> 0.45 | F24: =INDEX(Data_checks!$C$31:$E$34,MATCH(F17,Data_checks!$B$31:$B$34,0),MATCH(LEFT(F10,1),Data_checks!$C$30:$E$30,0)) -> 0.65 | G24: =INDEX(Data_checks!$C$31:$E$34,MATCH(G17,Data_checks!$B$31:$B$34,0),MATCH(LEFT(G10,1),Data_checks!$C$30:$E$30,0)) -> 0.65 | H24: =INDEX(Data_checks!$C$31:$E$34,MATCH(H17,Data_checks!$B$31:$B$34,0),MATCH(LEFT(H10,1),Data_checks!$C$30:$E$30,0)) -> 0.45 | I24: =INDEX(Data_checks!$C$31:$E$34,MATCH(I17,Data_checks!$B$31:$B$34,0),MATCH(LEFT(I10,1),Data_checks!$C$30:$E$30,0)) -> 0.65 | J24: =INDEX(Data_checks!$C$31:$E$34,MATCH(J17,Data_checks!$B$31:$B$34,0),MATCH(LEFT(J10,1),Data_checks!$C$30:$E$30,0)) -> 0.85 | ... N24: =INDEX(Data_checks!$C$31:$E$34,MATCH(N17,Data_checks!$B$31:$B$34,0),MATCH(LEFT(N10,1),Data_checks!$C$30:$E$30,0)) -> 0.45
B26: Projected cinemagoers (split by screen for commission calculation)
B27: Screen | C27: {=C20:N20} -> Jan | D27: Feb | E27: Mar | F27: Apr | G27: May | H27: Jun | I27: Jul | J27: Aug | K27: Sep | L27: Oct | M27: Nov | N27: Dec
B28: =B21 -> 1 | C28: =VLOOKUP($B28,Data_checks!$B$6:$C$9,2,TRUE)*C21*Parameters!$C$5*Parameters!$C$4 -> 142290 | D28: =VLOOKUP($B28,Data_checks!$B$6:$C$9,2,TRUE)*D21*Parameters!$C$5*Parameters!$C$4 -> 122400 | E28: =VLOOKUP($B28,Data_checks!$B$6:$C$9,2,TRUE)*E21*Parameters!$C$5*Parameters!$C$4 -> 130050 | F28: =VLOOKUP($B28,Data_checks!$B$6:$C$9,2,TRUE)*F21*Parameters!$C$5*Parameters!$C$4 -> 142290 | G28: =VLOOKUP($B28,Data_checks!$B$6:$C$9,2,TRUE)*G21*Parameters!$C$5*Parameters!$C$4 -> 122400 | H28: =VLOOKUP($B28,Data_checks!$B$6:$C$9,2,TRUE)*H21*Parameters!$C$5*Parameters!$C$4 -> 130050 | I28: =VLOOKUP($B28,Data_checks!$B$6:$C$9,2,TRUE)*I21*Parameters!$C$5*Parameters!$C$4 -> 149940 | J28: =VLOOKUP($B28,Data_checks!$B$6:$C$9,2,TRUE)*J21*Parameters!$C$5*Parameters!$C$4 -> 130050 | ... N28: =VLOOKUP($B28,Data_checks!$B$6:$C$9,2,TRUE)*N21*Parameters!$C$5*Parameters!$C$4 -> 99450
B29: =B22 -> 2 | C29: =VLOOKUP($B29,Data_checks!$B$6:$C$9,2,TRUE)*C22*Parameters!$C$5*Parameters!$C$4 -> 75330 | D29: =VLOOKUP($B29,Data_checks!$B$6:$C$9,2,TRUE)*D22*Parameters!$C$5*Parameters!$C$4 -> 52650 | E29: =VLOOKUP($B29,Data_checks!$B$6:$C$9,2,TRUE)*E22*Parameters!$C$5*Parameters!$C$4 -> 52650 | F29: =VLOOKUP($B29,Data_checks!$B$6:$C$9,2,TRUE)*F22*Parameters!$C$5*Parameters!$C$4 -> 75330 | G29: =VLOOKUP($B29,Data_checks!$B$6:$C$9,2,TRUE)*G22*Parameters!$C$5*Parameters!$C$4 -> 68850 | H29: =VLOOKUP($B29,Data_checks!$B$6:$C$9,2,TRUE)*H22*Parameters!$C$5*Parameters!$C$4 -> 52650 | I29: =VLOOKUP($B29,Data_checks!$B$6:$C$9,2,TRUE)*I22*Parameters!$C$5*Parameters!$C$4 -> 79380 | J29: =VLOOKUP($B29,Data_checks!$B$6:$C$9,2,TRUE)*J22*Parameters!$C$5*Parameters!$C$4 -> 68850 | ... N29: =VLOOKUP($B29,Data_checks!$B$6:$C$9,2,TRUE)*N22*Parameters!$C$5*Parameters!$C$4 -> 52650
B30: =B23 -> 3 | C30: =VLOOKUP($B30,Data_checks!$B$6:$C$9,2,TRUE)*C23*Parameters!$C$5*Parameters!$C$4 -> 30600 | D30: =VLOOKUP($B30,Data_checks!$B$6:$C$9,2,TRUE)*D23*Parameters!$C$5*Parameters!$C$4 -> 23400 | E30: =VLOOKUP($B30,Data_checks!$B$6:$C$9,2,TRUE)*E23*Parameters!$C$5*Parameters!$C$4 -> 30600 | F30: =VLOOKUP($B30,Data_checks!$B$6:$C$9,2,TRUE)*F23*Parameters!$C$5*Parameters!$C$4 -> 30600 | G30: =VLOOKUP($B30,Data_checks!$B$6:$C$9,2,TRUE)*G23*Parameters!$C$5*Parameters!$C$4 -> 23400 | H30: =VLOOKUP($B30,Data_checks!$B$6:$C$9,2,TRUE)*H23*Parameters!$C$5*Parameters!$C$4 -> 23400 | I30: =VLOOKUP($B30,Data_checks!$B$6:$C$9,2,TRUE)*I23*Parameters!$C$5*Parameters!$C$4 -> 35280 | J30: =VLOOKUP($B30,Data_checks!$B$6:$C$9,2,TRUE)*J23*Parameters!$C$5*Parameters!$C$4 -> 30600 | ... N30: =VLOOKUP($B30,Data_checks!$B$6:$C$9,2,TRUE)*N23*Parameters!$C$5*Parameters!$C$4 -> 23400
B31: =B24 -> 4 | C31: =VLOOKUP($B31,Data_checks!$B$6:$C$9,2,TRUE)*C24*Parameters!$C$5*Parameters!$C$4 -> 22950 | D31: =VLOOKUP($B31,Data_checks!$B$6:$C$9,2,TRUE)*D24*Parameters!$C$5*Parameters!$C$4 -> 17550 | E31: =VLOOKUP($B31,Data_checks!$B$6:$C$9,2,TRUE)*E24*Parameters!$C$5*Parameters!$C$4 -> 12150 | F31: =VLOOKUP($B31,Data_checks!$B$6:$C$9,2,TRUE)*F24*Parameters!$C$5*Parameters!$C$4 -> 17550 | G31: =VLOOKUP($B31,Data_checks!$B$6:$C$9,2,TRUE)*G24*Parameters!$C$5*Parameters!$C$4 -> 17550 | H31: =VLOOKUP($B31,Data_checks!$B$6:$C$9,2,TRUE)*H24*Parameters!$C$5*Parameters!$C$4 -> 12150 | I31: =VLOOKUP($B31,Data_checks!$B$6:$C$9,2,TRUE)*I24*Parameters!$C$5*Parameters!$C$4 -> 17550 | J31: =VLOOKUP($B31,Data_checks!$B$6:$C$9,2,TRUE)*J24*Parameters!$C$5*Parameters!$C$4 -> 22950 | ... N31: =VLOOKUP($B31,Data_checks!$B$6:$C$9,2,TRUE)*N24*Parameters!$C$5*Parameters!$C$4 -> 12150 | P31: Check on attendance data
B32: Total cinema | C32: =SUM(C28:C31) -> 271170 | D32: =SUM(D28:D31) -> 216000 | E32: =SUM(E28:E31) -> 225450 | F32: =SUM(F28:F31) -> 265770 | G32: =SUM(G28:G31) -> 232200 | H32: =SUM(H28:H31) -> 218250 | I32: =SUM(I28:I31) -> 282150 | J32: =SUM(J28:J31) -> 252450 | ... N32: =SUM(N28:N31) -> 187650 | O32: =SUM(C32:N32) -> 2844360 | P32: =IF(O32=Data_checks!E58,"Data is internally consistent","Data is not consistent. Please check") -> Data is internally consistent
B34: Number of films seen split by unique cinemagoers (This is the number of films seen split by month and by unique cinemagoers. E.g. if you sum up row 49, i.e. the number of cinemagoers who have seen 14 movies a year, the sum would equal to that in the data check (5040))
B35: Total number of movies seen in yr | C35: =C27 -> Jan | D35: =D27 -> Feb | E35: =E27 -> Mar | F35: =F27 -> Apr | G35: =G27 -> May | H35: =H27 -> Jun | I35: =I27 -> Jul | J35: =J27 -> Aug | ... N35: =N27 -> Dec
B36: =Data!B21 -> 1 | C36: =C$32*Data_checks!$F44 -> 17658.14 | D36: =D$32*Data_checks!$F44 -> 14065.561 | E36: =E$32*Data_checks!$F44 -> 14680.93 | F36: =F$32*Data_checks!$F44 -> 17306.501 | G36: =G$32*Data_checks!$F44 -> 15120.478 | H36: =H$32*Data_checks!$F44 -> 14212.078 | I36: =I$32*Data_checks!$F44 -> 18373.139 | J36: =J$32*Data_checks!$F44 -> 16439.125 | ... N36: =N$32*Data_checks!$F44 -> 12219.456
B37: =Data!B22 -> 2 | C37: =C$32*Data_checks!$F45 -> 51481.458 | D37: =D$32*Data_checks!$F45 -> 41007.467 | E37: =E$32*Data_checks!$F45 -> 42801.544 | F37: =F$32*Data_checks!$F45 -> 50456.271 | G37: =G$32*Data_checks!$F45 -> 44083.027 | H37: =H$32*Data_checks!$F45 -> 41434.629 | I37: =I$32*Data_checks!$F45 -> 53566.004 | J37: =J$32*Data_checks!$F45 -> 47927.478 | ... N37: =N$32*Data_checks!$F45 -> 35625.237
B38: =Data!B23 -> 3 | C38: =C$32*Data_checks!$F46 -> 51481.458 | D38: =D$32*Data_checks!$F46 -> 41007.467 | E38: =E$32*Data_checks!$F46 -> 42801.544 | F38: =F$32*Data_checks!$F46 -> 50456.271 | G38: =G$32*Data_checks!$F46 -> 44083.027 | H38: =H$32*Data_checks!$F46 -> 41434.629 | I38: =I$32*Data_checks!$F46 -> 53566.004 | J38: =J$32*Data_checks!$F46 -> 47927.478 | ... N38: =N$32*Data_checks!$F46 -> 35625.237
B39: =Data!B24 -> 4 | C39: =C$32*Data_checks!$F47 -> 51481.458 | D39: =D$32*Data_checks!$F47 -> 41007.467 | E39: =E$32*Data_checks!$F47 -> 42801.544 | F39: =F$32*Data_checks!$F47 -> 50456.271 | G39: =G$32*Data_checks!$F47 -> 44083.027 | H39: =H$32*Data_checks!$F47 -> 41434.629 | I39: =I$32*Data_checks!$F47 -> 53566.004 | J39: =J$32*Data_checks!$F47 -> 47927.478 | ... N39: =N$32*Data_checks!$F47 -> 35625.237
B40: =Data!B25 -> 5 | C40: =C$32*Data_checks!$F48 -> 38611.094 | D40: =D$32*Data_checks!$F48 -> 30755.601 | E40: =E$32*Data_checks!$F48 -> 32101.158 | F40: =F$32*Data_checks!$F48 -> 37842.204 | G40: =G$32*Data_checks!$F48 -> 33062.271 | H40: =H$32*Data_checks!$F48 -> 31075.971 | I40: =I$32*Data_checks!$F48 -> 40174.503 | J40: =J$32*Data_checks!$F48 -> 35945.608 | ... N40: =N$32*Data_checks!$F48 -> 26718.928
B41: =Data!B26 -> 6 | C41: =C$32*Data_checks!$F49 -> 30888.875 | D41: =D$32*Data_checks!$F49 -> 24604.48 | E41: =E$32*Data_checks!$F49 -> 25680.926 | F41: =F$32*Data_checks!$F49 -> 30273.763 | G41: =G$32*Data_checks!$F49 -> 26449.816 | H41: =H$32*Data_checks!$F49 -> 24860.777 | I41: =I$32*Data_checks!$F49 -> 32139.603 | J41: =J$32*Data_checks!$F49 -> 28756.487 | ... N41: =N$32*Data_checks!$F49 -> 21375.142
B42: =Data!B27 -> 7 | C42: =C$32*Data_checks!$F50 -> 18018.51 | D42: =D$32*Data_checks!$F50 -> 14352.614 | E42: =E$32*Data_checks!$F50 -> 14980.54 | F42: =F$32*Data_checks!$F50 -> 17659.695 | G42: =G$32*Data_checks!$F50 -> 15429.06 | H42: =H$32*Data_checks!$F50 -> 14502.12 | I42: =I$32*Data_checks!$F50 -> 18748.102 | J42: =J$32*Data_checks!$F50 -> 16774.617 | ... N42: =N$32*Data_checks!$F50 -> 12468.833
B43: =Data!B28 -> 8 | C43: =C$32*Data_checks!$F51 -> 4118.5166 | D43: =D$32*Data_checks!$F51 -> 3280.5974 | E43: =E$32*Data_checks!$F51 -> 3424.1235 | F43: =F$32*Data_checks!$F51 -> 4036.5017 | G43: =G$32*Data_checks!$F51 -> 3526.6422 | H43: =H$32*Data_checks!$F51 -> 3314.7703 | I43: =I$32*Data_checks!$F51 -> 4285.2803 | J43: =J$32*Data_checks!$F51 -> 3834.1982 | ... N43: =N$32*Data_checks!$F51 -> 2850.019
B44: =Data!B29 -> 9 | C44: =C$32*Data_checks!$F52 -> 3088.8875 | D44: =D$32*Data_checks!$F52 -> 2460.448 | E44: =E$32*Data_checks!$F52 -> 2568.0926 | F44: =F$32*Data_checks!$F52 -> 3027.3763 | G44: =G$32*Data_checks!$F52 -> 2644.9816 | H44: =H$32*Data_checks!$F52 -> 2486.0777 | I44: =I$32*Data_checks!$F52 -> 3213.9603 | J44: =J$32*Data_checks!$F52 -> 2875.6487 | ... N44: =N$32*Data_checks!$F52 -> 2137.5142
B45: =Data!B30 -> 10 | C45: =C$32*Data_checks!$F53 -> 1029.6292 | D45: =D$32*Data_checks!$F53 -> 820.14935 | E45: =E$32*Data_checks!$F53 -> 856.03088 | F45: =F$32*Data_checks!$F53 -> 1009.1254 | G45: =G$32*Data_checks!$F53 -> 881.66055 | H45: =H$32*Data_checks!$F53 -> 828.69257 | I45: =I$32*Data_checks!$F53 -> 1071.3201 | J45: =J$32*Data_checks!$F53 -> 958.54955 | ... N45: =N$32*Data_checks!$F53 -> 712.50475
B46: =Data!B31 -> 11 | C46: =C$32*Data_checks!$F54 -> 1132.5921 | D46: =D$32*Data_checks!$F54 -> 902.16428 | E46: =E$32*Data_checks!$F54 -> 941.63397 | F46: =F$32*Data_checks!$F54 -> 1110.038 | G46: =G$32*Data_checks!$F54 -> 969.8266 | H46: =H$32*Data_checks!$F54 -> 911.56183 | I46: =I$32*Data_checks!$F54 -> 1178.4521 | J46: =J$32*Data_checks!$F54 -> 1054.4045 | ... N46: =N$32*Data_checks!$F54 -> 783.75522
B47: =Data!B32 -> 12 | C47: =C$32*Data_checks!$F55 -> 1029.6292 | D47: =D$32*Data_checks!$F55 -> 820.14935 | E47: =E$32*Data_checks!$F55 -> 856.03088 | F47: =F$32*Data_checks!$F55 -> 1009.1254 | G47: =G$32*Data_checks!$F55 -> 881.66055 | H47: =H$32*Data_checks!$F55 -> 828.69257 | I47: =I$32*Data_checks!$F55 -> 1071.3201 | J47: =J$32*Data_checks!$F55 -> 958.54955 | ... N47: =N$32*Data_checks!$F55 -> 712.50475
B48: =Data!B33 -> 13 | C48: =C$32*Data_checks!$F56 -> 669.25895 | D48: =D$32*Data_checks!$F56 -> 533.09708 | E48: =E$32*Data_checks!$F56 -> 556.42007 | F48: =F$32*Data_checks!$F56 -> 655.93153 | G48: =G$32*Data_checks!$F56 -> 573.07936 | H48: =H$32*Data_checks!$F56 -> 538.65017 | I48: =I$32*Data_checks!$F56 -> 696.35806 | J48: =J$32*Data_checks!$F56 -> 623.05721 | ... N48: =N$32*Data_checks!$F56 -> 463.12809 | P48: Check on consistency of projected attendance
B49: =Data!B34 -> 14 | C49: =C$32*Data_checks!$F57 -> 480.49361 | D49: =D$32*Data_checks!$F57 -> 382.73636 | E49: =E$32*Data_checks!$F57 -> 399.48108 | F49: =F$32*Data_checks!$F57 -> 470.9252 | G49: =G$32*Data_checks!$F57 -> 411.44159 | H49: =H$32*Data_checks!$F57 -> 386.7232 | I49: =I$32*Data_checks!$F57 -> 499.94937 | J49: =J$32*Data_checks!$F57 -> 447.32312 | ... N49: =N$32*Data_checks!$F57 -> 332.50221 | O49: =SUM(C36:N49) -> 2844360 | P49: =IF(O49=O32,"Data is internally consistent","Data is not consistent. Please check") -> Data is internally consistent
B50: Total | C50: =SUM(C36:C49) -> 271170 | D50: =SUM(D36:D49) -> 216000 | E50: =SUM(E36:E49) -> 225450 | F50: =SUM(F36:F49) -> 265770 | G50: =SUM(G36:G49) -> 232200 | H50: =SUM(H36:H49) -> 218250 | I50: =SUM(I36:I49) -> 282150 | J50: =SUM(J36:J49) -> 252450 | ... N50: =SUM(N36:N49) -> 187650
B51: Check | C51: =C50=C32 -> TRUE | D51: =D50=D32 -> TRUE | E51: =E50=E32 -> TRUE | F51: =F50=F32 -> TRUE | G51: =G50=G32 -> TRUE | H51: =H50=H32 -> TRUE | I51: =I50=I32 -> TRUE | J51: =J50=J32 -> TRUE | ... N51: =N50=N32 -> TRUE
B53: Income from movie screenings
C54: =C35 -> Jan | D54: =D35 -> Feb | E54: =E35 -> Mar | F54: =F35 -> Apr | G54: =G35 -> May | H54: =H35 -> Jun | I54: =I35 -> Jul | J54: =J35 -> Aug | ... N54: =N35 -> Dec
B55: Projected ticket sales | C55: =SUMIF($B$36:$B$49,"<"&Parameters!$C$16,C$36:C$49)*Parameters!$C$6 -> 3525210 | D55: =SUMIF($B$36:$B$49,"<"&Parameters!$C$16,D$36:D$49)*Parameters!$C$6 -> 2808000 | E55: =SUMIF($B$36:$B$49,"<"&Parameters!$C$16,E$36:E$49)*Parameters!$C$6 -> 2930850 | F55: =SUMIF($B$36:$B$49,"<"&Parameters!$C$16,F$36:F$49)*Parameters!$C$6 -> 3455010 | G55: =SUMIF($B$36:$B$49,"<"&Parameters!$C$16,G$36:G$49)*Parameters!$C$6 -> 3018600 | H55: =SUMIF($B$36:$B$49,"<"&Parameters!$C$16,H$36:H$49)*Parameters!$C$6 -> 2837250 | I55: =SUMIF($B$36:$B$49,"<"&Parameters!$C$16,I$36:I$49)*Parameters!$C$6 -> 3667950 | J55: =SUMIF($B$36:$B$49,"<"&Parameters!$C$16,J$36:J$49)*Parameters!$C$6 -> 3281850 | ... N55: =SUMIF($B$36:$B$49,"<"&Parameters!$C$16,N$36:N$49)*Parameters!$C$6 -> 2439450
B57: Annual pass income
B58: =Data!B21 -> 1 | C58: =IF($B36>=Parameters!$C$16,C36/$B36,0)*Parameters!$C$15 -> 0 | D58: =IF($B36>=Parameters!$C$16,D36/$B36,0)*Parameters!$C$15 -> 0 | E58: =IF($B36>=Parameters!$C$16,E36/$B36,0)*Parameters!$C$15 -> 0 | F58: =IF($B36>=Parameters!$C$16,F36/$B36,0)*Parameters!$C$15 -> 0 | G58: =IF($B36>=Parameters!$C$16,G36/$B36,0)*Parameters!$C$15 -> 0 | H58: =IF($B36>=Parameters!$C$16,H36/$B36,0)*Parameters!$C$15 -> 0 | I58: =IF($B36>=Parameters!$C$16,I36/$B36,0)*Parameters!$C$15 -> 0 | J58: =IF($B36>=Parameters!$C$16,J36/$B36,0)*Parameters!$C$15 -> 0 | ... N58: =IF($B36>=Parameters!$C$16,N36/$B36,0)*Parameters!$C$15 -> 0
B59: =Data!B22 -> 2 | C59: =IF($B37>=Parameters!$C$16,C37/$B37,0)*Parameters!$C$15 -> 0 | D59: =IF($B37>=Parameters!$C$16,D37/$B37,0)*Parameters!$C$15 -> 0 | E59: =IF($B37>=Parameters!$C$16,E37/$B37,0)*Parameters!$C$15 -> 0 | F59: =IF($B37>=Parameters!$C$16,F37/$B37,0)*Parameters!$C$15 -> 0 | G59: =IF($B37>=Parameters!$C$16,G37/$B37,0)*Parameters!$C$15 -> 0 | H59: =IF($B37>=Parameters!$C$16,H37/$B37,0)*Parameters!$C$15 -> 0 | I59: =IF($B37>=Parameters!$C$16,I37/$B37,0)*Parameters!$C$15 -> 0 | J59: =IF($B37>=Parameters!$C$16,J37/$B37,0)*Parameters!$C$15 -> 0 | ... N59: =IF($B37>=Parameters!$C$16,N37/$B37,0)*Parameters!$C$15 -> 0
B60: =Data!B23 -> 3 | C60: =IF($B38>=Parameters!$C$16,C38/$B38,0)*Parameters!$C$15 -> 0 | D60: =IF($B38>=Parameters!$C$16,D38/$B38,0)*Parameters!$C$15 -> 0 | E60: =IF($B38>=Parameters!$C$16,E38/$B38,0)*Parameters!$C$15 -> 0 | F60: =IF($B38>=Parameters!$C$16,F38/$B38,0)*Parameters!$C$15 -> 0 | G60: =IF($B38>=Parameters!$C$16,G38/$B38,0)*Parameters!$C$15 -> 0 | H60: =IF($B38>=Parameters!$C$16,H38/$B38,0)*Parameters!$C$15 -> 0 | I60: =IF($B38>=Parameters!$C$16,I38/$B38,0)*Parameters!$C$15 -> 0 | J60: =IF($B38>=Parameters!$C$16,J38/$B38,0)*Parameters!$C$15 -> 0 | ... N60: =IF($B38>=Parameters!$C$16,N38/$B38,0)*Parameters!$C$15 -> 0
B61: =Data!B24 -> 4 | C61: =IF($B39>=Parameters!$C$16,C39/$B39,0)*Parameters!$C$15 -> 0 | D61: =IF($B39>=Parameters!$C$16,D39/$B39,0)*Parameters!$C$15 -> 0 | E61: =IF($B39>=Parameters!$C$16,E39/$B39,0)*Parameters!$C$15 -> 0 | F61: =IF($B39>=Parameters!$C$16,F39/$B39,0)*Parameters!$C$15 -> 0 | G61: =IF($B39>=Parameters!$C$16,G39/$B39,0)*Parameters!$C$15 -> 0 | H61: =IF($B39>=Parameters!$C$16,H39/$B39,0)*Parameters!$C$15 -> 0 | I61: =IF($B39>=Parameters!$C$16,I39/$B39,0)*Parameters!$C$15 -> 0 | J61: =IF($B39>=Parameters!$C$16,J39/$B39,0)*Parameters!$C$15 -> 0 | ... N61: =IF($B39>=Parameters!$C$16,N39/$B39,0)*Parameters!$C$15 -> 0
B62: =Data!B25 -> 5 | C62: =IF($B40>=Parameters!$C$16,C40/$B40,0)*Parameters!$C$15 -> 0 | D62: =IF($B40>=Parameters!$C$16,D40/$B40,0)*Parameters!$C$15 -> 0 | E62: =IF($B40>=Parameters!$C$16,E40/$B40,0)*Parameters!$C$15 -> 0 | F62: =IF($B40>=Parameters!$C$16,F40/$B40,0)*Parameters!$C$15 -> 0 | G62: =IF($B40>=Parameters!$C$16,G40/$B40,0)*Parameters!$C$15 -> 0 | H62: =IF($B40>=Parameters!$C$16,H40/$B40,0)*Parameters!$C$15 -> 0 | I62: =IF($B40>=Parameters!$C$16,I40/$B40,0)*Parameters!$C$15 -> 0 | J62: =IF($B40>=Parameters!$C$16,J40/$B40,0)*Parameters!$C$15 -> 0 | ... N62: =IF($B40>=Parameters!$C$16,N40/$B40,0)*Parameters!$C$15 -> 0
B63: =Data!B26 -> 6 | C63: =IF($B41>=Parameters!$C$16,C41/$B41,0)*Parameters!$C$15 -> 0 | D63: =IF($B41>=Parameters!$C$16,D41/$B41,0)*Parameters!$C$15 -> 0 | E63: =IF($B41>=Parameters!$C$16,E41/$B41,0)*Parameters!$C$15 -> 0 | F63: =IF($B41>=Parameters!$C$16,F41/$B41,0)*Parameters!$C$15 -> 0 | G63: =IF($B41>=Parameters!$C$16,G41/$B41,0)*Parameters!$C$15 -> 0 | H63: =IF($B41>=Parameters!$C$16,H41/$B41,0)*Parameters!$C$15 -> 0 | I63: =IF($B41>=Parameters!$C$16,I41/$B41,0)*Parameters!$C$15 -> 0 | J63: =IF($B41>=Parameters!$C$16,J41/$B41,0)*Parameters!$C$15 -> 0 | ... N63: =IF($B41>=Parameters!$C$16,N41/$B41,0)*Parameters!$C$15 -> 0
B64: =Data!B27 -> 7 | C64: =IF($B42>=Parameters!$C$16,C42/$B42,0)*Parameters!$C$15 -> 0 | D64: =IF($B42>=Parameters!$C$16,D42/$B42,0)*Parameters!$C$15 -> 0 | E64: =IF($B42>=Parameters!$C$16,E42/$B42,0)*Parameters!$C$15 -> 0 | F64: =IF($B42>=Parameters!$C$16,F42/$B42,0)*Parameters!$C$15 -> 0 | G64: =IF($B42>=Parameters!$C$16,G42/$B42,0)*Parameters!$C$15 -> 0 | H64: =IF($B42>=Parameters!$C$16,H42/$B42,0)*Parameters!$C$15 -> 0 | I64: =IF($B42>=Parameters!$C$16,I42/$B42,0)*Parameters!$C$15 -> 0 | J64: =IF($B42>=Parameters!$C$16,J42/$B42,0)*Parameters!$C$15 -> 0 | ... N64: =IF($B42>=Parameters!$C$16,N42/$B42,0)*Parameters!$C$15 -> 0
B65: =Data!B28 -> 8 | C65: =IF($B43>=Parameters!$C$16,C43/$B43,0)*Parameters!$C$15 -> 0 | D65: =IF($B43>=Parameters!$C$16,D43/$B43,0)*Parameters!$C$15 -> 0 | E65: =IF($B43>=Parameters!$C$16,E43/$B43,0)*Parameters!$C$15 -> 0 | F65: =IF($B43>=Parameters!$C$16,F43/$B43,0)*Parameters!$C$15 -> 0 | G65: =IF($B43>=Parameters!$C$16,G43/$B43,0)*Parameters!$C$15 -> 0 | H65: =IF($B43>=Parameters!$C$16,H43/$B43,0)*Parameters!$C$15 -> 0 | I65: =IF($B43>=Parameters!$C$16,I43/$B43,0)*Parameters!$C$15 -> 0 | J65: =IF($B43>=Parameters!$C$16,J43/$B43,0)*Parameters!$C$15 -> 0 | ... N65: =IF($B43>=Parameters!$C$16,N43/$B43,0)*Parameters!$C$15 -> 0
B66: =Data!B29 -> 9 | C66: =IF($B44>=Parameters!$C$16,C44/$B44,0)*Parameters!$C$15 -> 0 | D66: =IF($B44>=Parameters!$C$16,D44/$B44,0)*Parameters!$C$15 -> 0 | E66: =IF($B44>=Parameters!$C$16,E44/$B44,0)*Parameters!$C$15 -> 0 | F66: =IF($B44>=Parameters!$C$16,F44/$B44,0)*Parameters!$C$15 -> 0 | G66: =IF($B44>=Parameters!$C$16,G44/$B44,0)*Parameters!$C$15 -> 0 | H66: =IF($B44>=Parameters!$C$16,H44/$B44,0)*Parameters!$C$15 -> 0 | I66: =IF($B44>=Parameters!$C$16,I44/$B44,0)*Parameters!$C$15 -> 0 | J66: =IF($B44>=Parameters!$C$16,J44/$B44,0)*Parameters!$C$15 -> 0 | ... N66: =IF($B44>=Parameters!$C$16,N44/$B44,0)*Parameters!$C$15 -> 0
B67: =Data!B30 -> 10 | C67: =IF($B45>=Parameters!$C$16,C45/$B45,0)*Parameters!$C$15 -> 0 | D67: =IF($B45>=Parameters!$C$16,D45/$B45,0)*Parameters!$C$15 -> 0 | E67: =IF($B45>=Parameters!$C$16,E45/$B45,0)*Parameters!$C$15 -> 0 | F67: =IF($B45>=Parameters!$C$16,F45/$B45,0)*Parameters!$C$15 -> 0 | G67: =IF($B45>=Parameters!$C$16,G45/$B45,0)*Parameters!$C$15 -> 0 | H67: =IF($B45>=Parameters!$C$16,H45/$B45,0)*Parameters!$C$15 -> 0 | I67: =IF($B45>=Parameters!$C$16,I45/$B45,0)*Parameters!$C$15 -> 0 | J67: =IF($B45>=Parameters!$C$16,J45/$B45,0)*Parameters!$C$15 -> 0 | ... N67: =IF($B45>=Parameters!$C$16,N45/$B45,0)*Parameters!$C$15 -> 0
B68: =Data!B31 -> 11 | C68: =IF($B46>=Parameters!$C$16,C46/$B46,0)*Parameters!$C$15 -> 0 | D68: =IF($B46>=Parameters!$C$16,D46/$B46,0)*Parameters!$C$15 -> 0 | E68: =IF($B46>=Parameters!$C$16,E46/$B46,0)*Parameters!$C$15 -> 0 | F68: =IF($B46>=Parameters!$C$16,F46/$B46,0)*Parameters!$C$15 -> 0 | G68: =IF($B46>=Parameters!$C$16,G46/$B46,0)*Parameters!$C$15 -> 0 | H68: =IF($B46>=Parameters!$C$16,H46/$B46,0)*Parameters!$C$15 -> 0 | I68: =IF($B46>=Parameters!$C$16,I46/$B46,0)*Parameters!$C$15 -> 0 | J68: =IF($B46>=Parameters!$C$16,J46/$B46,0)*Parameters!$C$15 -> 0 | ... N68: =IF($B46>=Parameters!$C$16,N46/$B46,0)*Parameters!$C$15 -> 0
B69: =Data!B32 -> 12 | C69: =IF($B47>=Parameters!$C$16,C47/$B47,0)*Parameters!$C$15 -> 0 | D69: =IF($B47>=Parameters!$C$16,D47/$B47,0)*Parameters!$C$15 -> 0 | E69: =IF($B47>=Parameters!$C$16,E47/$B47,0)*Parameters!$C$15 -> 0 | F69: =IF($B47>=Parameters!$C$16,F47/$B47,0)*Parameters!$C$15 -> 0 | G69: =IF($B47>=Parameters!$C$16,G47/$B47,0)*Parameters!$C$15 -> 0 | H69: =IF($B47>=Parameters!$C$16,H47/$B47,0)*Parameters!$C$15 -> 0 | I69: =IF($B47>=Parameters!$C$16,I47/$B47,0)*Parameters!$C$15 -> 0 | J69: =IF($B47>=Parameters!$C$16,J47/$B47,0)*Parameters!$C$15 -> 0 | ... N69: =IF($B47>=Parameters!$C$16,N47/$B47,0)*Parameters!$C$15 -> 0
... B71: =Data!B34 -> 14 | C71: =IF($B49>=Parameters!$C$16,C49/$B49,0)*Parameters!$C$15 -> 0 | D71: =IF($B49>=Parameters!$C$16,D49/$B49,0)*Parameters!$C$15 -> 0 | E71: =IF($B49>=Parameters!$C$16,E49/$B49,0)*Parameters!$C$15 -> 0 | F71: =IF($B49>=Parameters!$C$16,F49/$B49,0)*Parameters!$C$15 -> 0 | G71: =IF($B49>=Parameters!$C$16,G49/$B49,0)*Parameters!$C$15 -> 0 | H71: =IF($B49>=Parameters!$C$16,H49/$B49,0)*Parameters!$C$15 -> 0 | I71: =IF($B49>=Parameters!$C$16,I49/$B49,0)*Parameters!$C$15 -> 0 | J71: =IF($B49>=Parameters!$C$16,J49/$B49,0)*Parameters!$C$15 -> 0 | ... N71: =IF($B49>=Parameters!$C$16,N49/$B49,0)*Parameters!$C$15 -> 0
B72: Total | C72: =SUM(C58:C71) -> 0 | D72: =SUM(D58:D71) -> 0 | E72: =SUM(E58:E71) -> 0 | F72: =SUM(F58:F71) -> 0 | G72: =SUM(G58:G71) -> 0 | H72: =SUM(H58:H71) -> 0 | I72: =SUM(I58:I71) -> 0 | J72: =SUM(J58:J71) -> 0 | ... N72: =SUM(N58:N71) -> 0
B74: Projected revenue from snack sales (split by total number of movies seen in the year)
B75: Total number of movies seen in yr | C75: =C35 -> Jan | D75: =D35 -> Feb | E75: =E35 -> Mar | F75: =F35 -> Apr | G75: =G35 -> May | H75: =H35 -> Jun | I75: =I35 -> Jul | J75: =J35 -> Aug | ... N75: =N35 -> Dec
B76: =B36 -> 1 | C76: =C36*Data_checks!$D44*Parameters!$C$7*IF($B76<Parameters!$C$16,1,(1+Parameters!$C$17)*(1-Parameters!$C$18)) -> 86467.422 | D76: =D36*Data_checks!$D44*Parameters!$C$7*IF($B76<Parameters!$C$16,1,(1+Parameters!$C$17)*(1-Parameters!$C$18)) -> 68875.477 | E76: =E36*Data_checks!$D44*Parameters!$C$7*IF($B76<Parameters!$C$16,1,(1+Parameters!$C$17)*(1-Parameters!$C$18)) -> 71888.78 | F76: =F36*Data_checks!$D44*Parameters!$C$7*IF($B76<Parameters!$C$16,1,(1+Parameters!$C$17)*(1-Parameters!$C$18)) -> 84745.535 | G76: =G36*Data_checks!$D44*Parameters!$C$7*IF($B76<Parameters!$C$16,1,(1+Parameters!$C$17)*(1-Parameters!$C$18)) -> 74041.138 | H76: =H36*Data_checks!$D44*Parameters!$C$7*IF($B76<Parameters!$C$16,1,(1+Parameters!$C$17)*(1-Parameters!$C$18)) -> 69592.93 | I76: =I36*Data_checks!$D44*Parameters!$C$7*IF($B76<Parameters!$C$16,1,(1+Parameters!$C$17)*(1-Parameters!$C$18)) -> 89968.592 | J76: =J36*Data_checks!$D44*Parameters!$C$7*IF($B76<Parameters!$C$16,1,(1+Parameters!$C$17)*(1-Parameters!$C$18)) -> 80498.214 | ... N76: =N36*Data_checks!$D44*Parameters!$C$7*IF($B76<Parameters!$C$16,1,(1+Parameters!$C$17)*(1-Parameters!$C$18)) -> 59835.571
B77: =B37 -> 2 | C77: =C37*Data_checks!$D45*Parameters!$C$7*IF($B77<Parameters!$C$16,1,(1+Parameters!$C$17)*(1-Parameters!$C$18)) -> 327719.09 | D77: =D37*Data_checks!$D45*Parameters!$C$7*IF($B77<Parameters!$C$16,1,(1+Parameters!$C$17)*(1-Parameters!$C$18)) -> 261044.08 | E77: =E37*Data_checks!$D45*Parameters!$C$7*IF($B77<Parameters!$C$16,1,(1+Parameters!$C$17)*(1-Parameters!$C$18)) -> 272464.76 | F77: =F37*Data_checks!$D45*Parameters!$C$7*IF($B77<Parameters!$C$16,1,(1+Parameters!$C$17)*(1-Parameters!$C$18)) -> 321192.99 | G77: =G37*Data_checks!$D45*Parameters!$C$7*IF($B77<Parameters!$C$16,1,(1+Parameters!$C$17)*(1-Parameters!$C$18)) -> 280622.39 | H77: =H37*Data_checks!$D45*Parameters!$C$7*IF($B77<Parameters!$C$16,1,(1+Parameters!$C$17)*(1-Parameters!$C$18)) -> 263763.29 | I77: =I37*Data_checks!$D45*Parameters!$C$7*IF($B77<Parameters!$C$16,1,(1+Parameters!$C$17)*(1-Parameters!$C$18)) -> 340988.83 | J77: =J37*Data_checks!$D45*Parameters!$C$7*IF($B77<Parameters!$C$16,1,(1+Parameters!$C$17)*(1-Parameters!$C$18)) -> 305095.27 | ... N77: =N37*Data_checks!$D45*Parameters!$C$7*IF($B77<Parameters!$C$16,1,(1+Parameters!$C$17)*(1-Parameters!$C$18)) -> 226782.05
B78: =B38 -> 3 | C78: =C38*Data_checks!$D46*Parameters!$C$7*IF($B78<Parameters!$C$16,1,(1+Parameters!$C$17)*(1-Parameters!$C$18)) -> 340323.67 | D78: =D38*Data_checks!$D46*Parameters!$C$7*IF($B78<Parameters!$C$16,1,(1+Parameters!$C$17)*(1-Parameters!$C$18)) -> 271084.24 | E78: =E38*Data_checks!$D46*Parameters!$C$7*IF($B78<Parameters!$C$16,1,(1+Parameters!$C$17)*(1-Parameters!$C$18)) -> 282944.18 | F78: =F38*Data_checks!$D46*Parameters!$C$7*IF($B78<Parameters!$C$16,1,(1+Parameters!$C$17)*(1-Parameters!$C$18)) -> 333546.57 | G78: =G38*Data_checks!$D46*Parameters!$C$7*IF($B78<Parameters!$C$16,1,(1+Parameters!$C$17)*(1-Parameters!$C$18)) -> 291415.56 | H78: =H38*Data_checks!$D46*Parameters!$C$7*IF($B78<Parameters!$C$16,1,(1+Parameters!$C$17)*(1-Parameters!$C$18)) -> 273908.03 | I78: =I38*Data_checks!$D46*Parameters!$C$7*IF($B78<Parameters!$C$16,1,(1+Parameters!$C$17)*(1-Parameters!$C$18)) -> 354103.79 | J78: =J38*Data_checks!$D46*Parameters!$C$7*IF($B78<Parameters!$C$16,1,(1+Parameters!$C$17)*(1-Parameters!$C$18)) -> 316829.71 | ... N78: =N38*Data_checks!$D46*Parameters!$C$7*IF($B78<Parameters!$C$16,1,(1+Parameters!$C$17)*(1-Parameters!$C$18)) -> 235504.43
B79: =B39 -> 4 | C79: =C39*Data_checks!$D47*Parameters!$C$7*IF($B79<Parameters!$C$16,1,(1+Parameters!$C$17)*(1-Parameters!$C$18)) -> 441710.91 | D79: =D39*Data_checks!$D47*Parameters!$C$7*IF($B79<Parameters!$C$16,1,(1+Parameters!$C$17)*(1-Parameters!$C$18)) -> 351844.07 | E79: =E39*Data_checks!$D47*Parameters!$C$7*IF($B79<Parameters!$C$16,1,(1+Parameters!$C$17)*(1-Parameters!$C$18)) -> 367237.25 | F79: =F39*Data_checks!$D47*Parameters!$C$7*IF($B79<Parameters!$C$16,1,(1+Parameters!$C$17)*(1-Parameters!$C$18)) -> 432914.81 | G79: =G39*Data_checks!$D47*Parameters!$C$7*IF($B79<Parameters!$C$16,1,(1+Parameters!$C$17)*(1-Parameters!$C$18)) -> 378232.38 | H79: =H39*Data_checks!$D47*Parameters!$C$7*IF($B79<Parameters!$C$16,1,(1+Parameters!$C$17)*(1-Parameters!$C$18)) -> 355509.11 | I79: =I39*Data_checks!$D47*Parameters!$C$7*IF($B79<Parameters!$C$16,1,(1+Parameters!$C$17)*(1-Parameters!$C$18)) -> 459596.32 | J79: =J39*Data_checks!$D47*Parameters!$C$7*IF($B79<Parameters!$C$16,1,(1+Parameters!$C$17)*(1-Parameters!$C$18)) -> 411217.76 | ... N79: =N39*Data_checks!$D47*Parameters!$C$7*IF($B79<Parameters!$C$16,1,(1+Parameters!$C$17)*(1-Parameters!$C$18)) -> 305664.54
B80: =B40 -> 5 | C80: =C40*Data_checks!$D48*Parameters!$C$7*IF($B80<Parameters!$C$16,1,(1+Parameters!$C$17)*(1-Parameters!$C$18)) -> 297305.42 | D80: =D40*Data_checks!$D48*Parameters!$C$7*IF($B80<Parameters!$C$16,1,(1+Parameters!$C$17)*(1-Parameters!$C$18)) -> 236818.12 | E80: =E40*Data_checks!$D48*Parameters!$C$7*IF($B80<Parameters!$C$16,1,(1+Parameters!$C$17)*(1-Parameters!$C$18)) -> 247178.92 | F80: =F40*Data_checks!$D48*Parameters!$C$7*IF($B80<Parameters!$C$16,1,(1+Parameters!$C$17)*(1-Parameters!$C$18)) -> 291384.97 | G80: =G40*Data_checks!$D48*Parameters!$C$7*IF($B80<Parameters!$C$16,1,(1+Parameters!$C$17)*(1-Parameters!$C$18)) -> 254579.48 | H80: =H40*Data_checks!$D48*Parameters!$C$7*IF($B80<Parameters!$C$16,1,(1+Parameters!$C$17)*(1-Parameters!$C$18)) -> 239284.98 | I80: =I40*Data_checks!$D48*Parameters!$C$7*IF($B80<Parameters!$C$16,1,(1+Parameters!$C$17)*(1-Parameters!$C$18)) -> 309343.67 | J80: =J40*Data_checks!$D48*Parameters!$C$7*IF($B80<Parameters!$C$16,1,(1+Parameters!$C$17)*(1-Parameters!$C$18)) -> 276781.18 | ... N80: =N40*Data_checks!$D48*Parameters!$C$7*IF($B80<Parameters!$C$16,1,(1+Parameters!$C$17)*(1-Parameters!$C$18)) -> 205735.75
B81: =B41 -> 6 | C81: =C41*Data_checks!$D49*Parameters!$C$7*IF($B81<Parameters!$C$16,1,(1+Parameters!$C$17)*(1-Parameters!$C$18)) -> 285413.2 | D81: =D41*Data_checks!$D49*Parameters!$C$7*IF($B81<Parameters!$C$16,1,(1+Parameters!$C$17)*(1-Parameters!$C$18)) -> 227345.4 | E81: =E41*Data_checks!$D49*Parameters!$C$7*IF($B81<Parameters!$C$16,1,(1+Parameters!$C$17)*(1-Parameters!$C$18)) -> 237291.76 | F81: =F41*Data_checks!$D49*Parameters!$C$7*IF($B81<Parameters!$C$16,1,(1+Parameters!$C$17)*(1-Parameters!$C$18)) -> 279729.57 | G81: =G41*Data_checks!$D49*Parameters!$C$7*IF($B81<Parameters!$C$16,1,(1+Parameters!$C$17)*(1-Parameters!$C$18)) -> 244396.3 | H81: =H41*Data_checks!$D49*Parameters!$C$7*IF($B81<Parameters!$C$16,1,(1+Parameters!$C$17)*(1-Parameters!$C$18)) -> 229713.58 | I81: =I41*Data_checks!$D49*Parameters!$C$7*IF($B81<Parameters!$C$16,1,(1+Parameters!$C$17)*(1-Parameters!$C$18)) -> 296969.93 | J81: =J41*Data_checks!$D49*Parameters!$C$7*IF($B81<Parameters!$C$16,1,(1+Parameters!$C$17)*(1-Parameters!$C$18)) -> 265709.94 | ... N81: =N41*Data_checks!$D49*Parameters!$C$7*IF($B81<Parameters!$C$16,1,(1+Parameters!$C$17)*(1-Parameters!$C$18)) -> 197506.32
B82: =B42 -> 7 | C82: =C42*Data_checks!$D50*Parameters!$C$7*IF($B82<Parameters!$C$16,1,(1+Parameters!$C$17)*(1-Parameters!$C$18)) -> 158562.89 | D82: =D42*Data_checks!$D50*Parameters!$C$7*IF($B82<Parameters!$C$16,1,(1+Parameters!$C$17)*(1-Parameters!$C$18)) -> 126303 | E82: =E42*Data_checks!$D50*Parameters!$C$7*IF($B82<Parameters!$C$16,1,(1+Parameters!$C$17)*(1-Parameters!$C$18)) -> 131828.76 | F82: =F42*Data_checks!$D50*Parameters!$C$7*IF($B82<Parameters!$C$16,1,(1+Parameters!$C$17)*(1-Parameters!$C$18)) -> 155405.32 | G82: =G42*Data_checks!$D50*Parameters!$C$7*IF($B82<Parameters!$C$16,1,(1+Parameters!$C$17)*(1-Parameters!$C$18)) -> 135775.72 | H82: =H42*Data_checks!$D50*Parameters!$C$7*IF($B82<Parameters!$C$16,1,(1+Parameters!$C$17)*(1-Parameters!$C$18)) -> 127618.66 | I82: =I42*Data_checks!$D50*Parameters!$C$7*IF($B82<Parameters!$C$16,1,(1+Parameters!$C$17)*(1-Parameters!$C$18)) -> 164983.29 | J82: =J42*Data_checks!$D50*Parameters!$C$7*IF($B82<Parameters!$C$16,1,(1+Parameters!$C$17)*(1-Parameters!$C$18)) -> 147616.63 | ... N82: =N42*Data_checks!$D50*Parameters!$C$7*IF($B82<Parameters!$C$16,1,(1+Parameters!$C$17)*(1-Parameters!$C$18)) -> 109725.73
B83: =B43 -> 8 | C83: =C43*Data_checks!$D51*Parameters!$C$7*IF($B83<Parameters!$C$16,1,(1+Parameters!$C$17)*(1-Parameters!$C$18)) -> 45303.683 | D83: =D43*Data_checks!$D51*Parameters!$C$7*IF($B83<Parameters!$C$16,1,(1+Parameters!$C$17)*(1-Parameters!$C$18)) -> 36086.571 | E83: =E43*Data_checks!$D51*Parameters!$C$7*IF($B83<Parameters!$C$16,1,(1+Parameters!$C$17)*(1-Parameters!$C$18)) -> 37665.359 | F83: =F43*Data_checks!$D51*Parameters!$C$7*IF($B83<Parameters!$C$16,1,(1+Parameters!$C$17)*(1-Parameters!$C$18)) -> 44401.519 | G83: =G43*Data_checks!$D51*Parameters!$C$7*IF($B83<Parameters!$C$16,1,(1+Parameters!$C$17)*(1-Parameters!$C$18)) -> 38793.064 | H83: =H43*Data_checks!$D51*Parameters!$C$7*IF($B83<Parameters!$C$16,1,(1+Parameters!$C$17)*(1-Parameters!$C$18)) -> 36462.473 | I83: =I43*Data_checks!$D51*Parameters!$C$7*IF($B83<Parameters!$C$16,1,(1+Parameters!$C$17)*(1-Parameters!$C$18)) -> 47138.084 | J83: =J43*Data_checks!$D51*Parameters!$C$7*IF($B83<Parameters!$C$16,1,(1+Parameters!$C$17)*(1-Parameters!$C$18)) -> 42176.18 | ... N83: =N43*Data_checks!$D51*Parameters!$C$7*IF($B83<Parameters!$C$16,1,(1+Parameters!$C$17)*(1-Parameters!$C$18)) -> 31350.209
B84: =B44 -> 9 | C84: =C44*Data_checks!$D52*Parameters!$C$7*IF($B84<Parameters!$C$16,1,(1+Parameters!$C$17)*(1-Parameters!$C$18)) -> 44171.091 | D84: =D44*Data_checks!$D52*Parameters!$C$7*IF($B84<Parameters!$C$16,1,(1+Parameters!$C$17)*(1-Parameters!$C$18)) -> 35184.407 | E84: =E44*Data_checks!$D52*Parameters!$C$7*IF($B84<Parameters!$C$16,1,(1+Parameters!$C$17)*(1-Parameters!$C$18)) -> 36723.725 | F84: =F44*Data_checks!$D52*Parameters!$C$7*IF($B84<Parameters!$C$16,1,(1+Parameters!$C$17)*(1-Parameters!$C$18)) -> 43291.481 | G84: =G44*Data_checks!$D52*Parameters!$C$7*IF($B84<Parameters!$C$16,1,(1+Parameters!$C$17)*(1-Parameters!$C$18)) -> 37823.238 | H84: =H44*Data_checks!$D52*Parameters!$C$7*IF($B84<Parameters!$C$16,1,(1+Parameters!$C$17)*(1-Parameters!$C$18)) -> 35550.911 | I84: =I44*Data_checks!$D52*Parameters!$C$7*IF($B84<Parameters!$C$16,1,(1+Parameters!$C$17)*(1-Parameters!$C$18)) -> 45959.632 | J84: =J44*Data_checks!$D52*Parameters!$C$7*IF($B84<Parameters!$C$16,1,(1+Parameters!$C$17)*(1-Parameters!$C$18)) -> 41121.776 | ... N84: =N44*Data_checks!$D52*Parameters!$C$7*IF($B84<Parameters!$C$16,1,(1+Parameters!$C$17)*(1-Parameters!$C$18)) -> 30566.454
B85: =B45 -> 10 | C85: =C45*Data_checks!$D53*Parameters!$C$7*IF($B85<Parameters!$C$16,1,(1+Parameters!$C$17)*(1-Parameters!$C$18)) -> 12911.55 | D85: =D45*Data_checks!$D53*Parameters!$C$7*IF($B85<Parameters!$C$16,1,(1+Parameters!$C$17)*(1-Parameters!$C$18)) -> 10284.673 | E85: =E45*Data_checks!$D53*Parameters!$C$7*IF($B85<Parameters!$C$16,1,(1+Parameters!$C$17)*(1-Parameters!$C$18)) -> 10734.627 | F85: =F45*Data_checks!$D53*Parameters!$C$7*IF($B85<Parameters!$C$16,1,(1+Parameters!$C$17)*(1-Parameters!$C$18)) -> 12654.433 | G85: =G45*Data_checks!$D53*Parameters!$C$7*IF($B85<Parameters!$C$16,1,(1+Parameters!$C$17)*(1-Parameters!$C$18)) -> 11056.023 | H85: =H45*Data_checks!$D53*Parameters!$C$7*IF($B85<Parameters!$C$16,1,(1+Parameters!$C$17)*(1-Parameters!$C$18)) -> 10391.805 | I85: =I45*Data_checks!$D53*Parameters!$C$7*IF($B85<Parameters!$C$16,1,(1+Parameters!$C$17)*(1-Parameters!$C$18)) -> 13434.354 | J85: =J45*Data_checks!$D53*Parameters!$C$7*IF($B85<Parameters!$C$16,1,(1+Parameters!$C$17)*(1-Parameters!$C$18)) -> 12020.211 | ... N85: =N45*Data_checks!$D53*Parameters!$C$7*IF($B85<Parameters!$C$16,1,(1+Parameters!$C$17)*(1-Parameters!$C$18)) -> 8934.8095
B86: =B46 -> 11 | C86: =C46*Data_checks!$D54*Parameters!$C$7*IF($B86<Parameters!$C$16,1,(1+Parameters!$C$17)*(1-Parameters!$C$18)) -> 16943.577 | D86: =D46*Data_checks!$D54*Parameters!$C$7*IF($B86<Parameters!$C$16,1,(1+Parameters!$C$17)*(1-Parameters!$C$18)) -> 13496.378 | E86: =E46*Data_checks!$D54*Parameters!$C$7*IF($B86<Parameters!$C$16,1,(1+Parameters!$C$17)*(1-Parameters!$C$18)) -> 14086.844 | F86: =F46*Data_checks!$D54*Parameters!$C$7*IF($B86<Parameters!$C$16,1,(1+Parameters!$C$17)*(1-Parameters!$C$18)) -> 16606.168 | G86: =G46*Data_checks!$D54*Parameters!$C$7*IF($B86<Parameters!$C$16,1,(1+Parameters!$C$17)*(1-Parameters!$C$18)) -> 14508.606 | H86: =H46*Data_checks!$D54*Parameters!$C$7*IF($B86<Parameters!$C$16,1,(1+Parameters!$C$17)*(1-Parameters!$C$18)) -> 13636.965 | I86: =I46*Data_checks!$D54*Parameters!$C$7*IF($B86<Parameters!$C$16,1,(1+Parameters!$C$17)*(1-Parameters!$C$18)) -> 17629.643 | J86: =J46*Data_checks!$D54*Parameters!$C$7*IF($B86<Parameters!$C$16,1,(1+Parameters!$C$17)*(1-Parameters!$C$18)) -> 15773.891 | ... N86: =N46*Data_checks!$D54*Parameters!$C$7*IF($B86<Parameters!$C$16,1,(1+Parameters!$C$17)*(1-Parameters!$C$18)) -> 11724.978
B87: =B47 -> 12 | C87: =C47*Data_checks!$D55*Parameters!$C$7*IF($B87<Parameters!$C$16,1,(1+Parameters!$C$17)*(1-Parameters!$C$18)) -> 13364.587 | D87: =D47*Data_checks!$D55*Parameters!$C$7*IF($B87<Parameters!$C$16,1,(1+Parameters!$C$17)*(1-Parameters!$C$18)) -> 10645.539 | E87: =E47*Data_checks!$D55*Parameters!$C$7*IF($B87<Parameters!$C$16,1,(1+Parameters!$C$17)*(1-Parameters!$C$18)) -> 11111.281 | F87: =F47*Data_checks!$D55*Parameters!$C$7*IF($B87<Parameters!$C$16,1,(1+Parameters!$C$17)*(1-Parameters!$C$18)) -> 13098.448 | G87: =G47*Data_checks!$D55*Parameters!$C$7*IF($B87<Parameters!$C$16,1,(1+Parameters!$C$17)*(1-Parameters!$C$18)) -> 11443.954 | H87: =H47*Data_checks!$D55*Parameters!$C$7*IF($B87<Parameters!$C$16,1,(1+Parameters!$C$17)*(1-Parameters!$C$18)) -> 10756.43 | I87: =I47*Data_checks!$D55*Parameters!$C$7*IF($B87<Parameters!$C$16,1,(1+Parameters!$C$17)*(1-Parameters!$C$18)) -> 13905.735 | J87: =J47*Data_checks!$D55*Parameters!$C$7*IF($B87<Parameters!$C$16,1,(1+Parameters!$C$17)*(1-Parameters!$C$18)) -> 12441.973 | ... N87: =N47*Data_checks!$D55*Parameters!$C$7*IF($B87<Parameters!$C$16,1,(1+Parameters!$C$17)*(1-Parameters!$C$18)) -> 9248.3116
... B89: =B49 -> 14 | C89: =C49*Data_checks!$D57*Parameters!$C$7*IF($B89<Parameters!$C$16,1,(1+Parameters!$C$17)*(1-Parameters!$C$18)) -> 7505.3102 | D89: =D49*Data_checks!$D57*Parameters!$C$7*IF($B89<Parameters!$C$16,1,(1+Parameters!$C$17)*(1-Parameters!$C$18)) -> 5978.342 | E89: =E49*Data_checks!$D57*Parameters!$C$7*IF($B89<Parameters!$C$16,1,(1+Parameters!$C$17)*(1-Parameters!$C$18)) -> 6239.8944 | F89: =F49*Data_checks!$D57*Parameters!$C$7*IF($B89<Parameters!$C$16,1,(1+Parameters!$C$17)*(1-Parameters!$C$18)) -> 7355.8516 | G89: =G49*Data_checks!$D57*Parameters!$C$7*IF($B89<Parameters!$C$16,1,(1+Parameters!$C$17)*(1-Parameters!$C$18)) -> 6426.7176 | H89: =H49*Data_checks!$D57*Parameters!$C$7*IF($B89<Parameters!$C$16,1,(1+Parameters!$C$17)*(1-Parameters!$C$18)) -> 6040.6164 | I89: =I49*Data_checks!$D57*Parameters!$C$7*IF($B89<Parameters!$C$16,1,(1+Parameters!$C$17)*(1-Parameters!$C$18)) -> 7809.2092 | J89: =J49*Data_checks!$D57*Parameters!$C$7*IF($B89<Parameters!$C$16,1,(1+Parameters!$C$17)*(1-Parameters!$C$18)) -> 6987.1872 | ... N89: =N49*Data_checks!$D57*Parameters!$C$7*IF($B89<Parameters!$C$16,1,(1+Parameters!$C$17)*(1-Parameters!$C$18)) -> 5193.6846
B90: Total snack sales | C90: =SUM(C76:C89) -> 2088009 | D90: =SUM(D76:D89) -> 1663200 | E90: =SUM(E76:E89) -> 1735965 | F90: =SUM(F76:F89) -> 2046429 | G90: =SUM(G76:G89) -> 1787940 | H90: =SUM(H76:H89) -> 1680525 | I90: =SUM(I76:I89) -> 2172555 | J90: =SUM(J76:J89) -> 1943865 | ... N90: =SUM(N76:N89) -> 1444905
B92: Commission % for distributors
B93: Screen | C93: =C75 -> Jan | D93: =D75 -> Feb | E93: =E75 -> Mar | F93: =F75 -> Apr | G93: =G75 -> May | H93: =H75 -> Jun | I93: =I75 -> Jul | J93: =J75 -> Aug | ... N93: =N75 -> Dec
B94: =B7 -> 1 | C94: =INDEX(Data_checks!$I$31:$K$34,MATCH(C14,Data_checks!$H$31:$H$34,0),MATCH(LEFT(C7,1),Data_checks!$I$30:$K$30,0)) -> 0.55 | D94: =INDEX(Data_checks!$I$31:$K$34,MATCH(D14,Data_checks!$H$31:$H$34,0),MATCH(LEFT(D7,1),Data_checks!$I$30:$K$30,0)) -> 0.45 | E94: =INDEX(Data_checks!$I$31:$K$34,MATCH(E14,Data_checks!$H$31:$H$34,0),MATCH(LEFT(E7,1),Data_checks!$I$30:$K$30,0)) -> 0.45 | F94: =INDEX(Data_checks!$I$31:$K$34,MATCH(F14,Data_checks!$H$31:$H$34,0),MATCH(LEFT(F7,1),Data_checks!$I$30:$K$30,0)) -> 0.55 | G94: =INDEX(Data_checks!$I$31:$K$34,MATCH(G14,Data_checks!$H$31:$H$34,0),MATCH(LEFT(G7,1),Data_checks!$I$30:$K$30,0)) -> 0.45 | H94: =INDEX(Data_checks!$I$31:$K$34,MATCH(H14,Data_checks!$H$31:$H$34,0),MATCH(LEFT(H7,1),Data_checks!$I$30:$K$30,0)) -> 0.45 | I94: =INDEX(Data_checks!$I$31:$K$34,MATCH(I14,Data_checks!$H$31:$H$34,0),MATCH(LEFT(I7,1),Data_checks!$I$30:$K$30,0)) -> 0.65 | J94: =INDEX(Data_checks!$I$31:$K$34,MATCH(J14,Data_checks!$H$31:$H$34,0),MATCH(LEFT(J7,1),Data_checks!$I$30:$K$30,0)) -> 0.55 | ... N94: =INDEX(Data_checks!$I$31:$K$34,MATCH(N14,Data_checks!$H$31:$H$34,0),MATCH(LEFT(N7,1),Data_checks!$I$30:$K$30,0)) -> 0.35
B95: =B8 -> 2 | C95: =INDEX(Data_checks!$I$31:$K$34,MATCH(C15,Data_checks!$H$31:$H$34,0),MATCH(LEFT(C8,1),Data_checks!$I$30:$K$30,0)) -> 0.55 | D95: =INDEX(Data_checks!$I$31:$K$34,MATCH(D15,Data_checks!$H$31:$H$34,0),MATCH(LEFT(D8,1),Data_checks!$I$30:$K$30,0)) -> 0.35 | E95: =INDEX(Data_checks!$I$31:$K$34,MATCH(E15,Data_checks!$H$31:$H$34,0),MATCH(LEFT(E8,1),Data_checks!$I$30:$K$30,0)) -> 0.3 | F95: =INDEX(Data_checks!$I$31:$K$34,MATCH(F15,Data_checks!$H$31:$H$34,0),MATCH(LEFT(F8,1),Data_checks!$I$30:$K$30,0)) -> 0.55 | G95: =INDEX(Data_checks!$I$31:$K$34,MATCH(G15,Data_checks!$H$31:$H$34,0),MATCH(LEFT(G8,1),Data_checks!$I$30:$K$30,0)) -> 0.45 | H95: =INDEX(Data_checks!$I$31:$K$34,MATCH(H15,Data_checks!$H$31:$H$34,0),MATCH(LEFT(H8,1),Data_checks!$I$30:$K$30,0)) -> 0.3 | I95: =INDEX(Data_checks!$I$31:$K$34,MATCH(I15,Data_checks!$H$31:$H$34,0),MATCH(LEFT(I8,1),Data_checks!$I$30:$K$30,0)) -> 0.65 | J95: =INDEX(Data_checks!$I$31:$K$34,MATCH(J15,Data_checks!$H$31:$H$34,0),MATCH(LEFT(J8,1),Data_checks!$I$30:$K$30,0)) -> 0.55 | ... N95: =INDEX(Data_checks!$I$31:$K$34,MATCH(N15,Data_checks!$H$31:$H$34,0),MATCH(LEFT(N8,1),Data_checks!$I$30:$K$30,0)) -> 0.3
B96: =B9 -> 3 | C96: =INDEX(Data_checks!$I$31:$K$34,MATCH(C16,Data_checks!$H$31:$H$34,0),MATCH(LEFT(C9,1),Data_checks!$I$30:$K$30,0)) -> 0.45 | D96: =INDEX(Data_checks!$I$31:$K$34,MATCH(D16,Data_checks!$H$31:$H$34,0),MATCH(LEFT(D9,1),Data_checks!$I$30:$K$30,0)) -> 0.35 | E96: =INDEX(Data_checks!$I$31:$K$34,MATCH(E16,Data_checks!$H$31:$H$34,0),MATCH(LEFT(E9,1),Data_checks!$I$30:$K$30,0)) -> 0.45 | F96: =INDEX(Data_checks!$I$31:$K$34,MATCH(F16,Data_checks!$H$31:$H$34,0),MATCH(LEFT(F9,1),Data_checks!$I$30:$K$30,0)) -> 0.45 | G96: =INDEX(Data_checks!$I$31:$K$34,MATCH(G16,Data_checks!$H$31:$H$34,0),MATCH(LEFT(G9,1),Data_checks!$I$30:$K$30,0)) -> 0.35 | H96: =INDEX(Data_checks!$I$31:$K$34,MATCH(H16,Data_checks!$H$31:$H$34,0),MATCH(LEFT(H9,1),Data_checks!$I$30:$K$30,0)) -> 0.35 | I96: =INDEX(Data_checks!$I$31:$K$34,MATCH(I16,Data_checks!$H$31:$H$34,0),MATCH(LEFT(I9,1),Data_checks!$I$30:$K$30,0)) -> 0.65 | J96: =INDEX(Data_checks!$I$31:$K$34,MATCH(J16,Data_checks!$H$31:$H$34,0),MATCH(LEFT(J9,1),Data_checks!$I$30:$K$30,0)) -> 0.45 | ... N96: =INDEX(Data_checks!$I$31:$K$34,MATCH(N16,Data_checks!$H$31:$H$34,0),MATCH(LEFT(N9,1),Data_checks!$I$30:$K$30,0)) -> 0.35
B97: =B10 -> 4 | C97: =INDEX(Data_checks!$I$31:$K$34,MATCH(C17,Data_checks!$H$31:$H$34,0),MATCH(LEFT(C10,1),Data_checks!$I$30:$K$30,0)) -> 0.45 | D97: =INDEX(Data_checks!$I$31:$K$34,MATCH(D17,Data_checks!$H$31:$H$34,0),MATCH(LEFT(D10,1),Data_checks!$I$30:$K$30,0)) -> 0.35 | E97: =INDEX(Data_checks!$I$31:$K$34,MATCH(E17,Data_checks!$H$31:$H$34,0),MATCH(LEFT(E10,1),Data_checks!$I$30:$K$30,0)) -> 0.15 | F97: =INDEX(Data_checks!$I$31:$K$34,MATCH(F17,Data_checks!$H$31:$H$34,0),MATCH(LEFT(F10,1),Data_checks!$I$30:$K$30,0)) -> 0.35 | G97: =INDEX(Data_checks!$I$31:$K$34,MATCH(G17,Data_checks!$H$31:$H$34,0),MATCH(LEFT(G10,1),Data_checks!$I$30:$K$30,0)) -> 0.35 | H97: =INDEX(Data_checks!$I$31:$K$34,MATCH(H17,Data_checks!$H$31:$H$34,0),MATCH(LEFT(H10,1),Data_checks!$I$30:$K$30,0)) -> 0.15 | I97: =INDEX(Data_checks!$I$31:$K$34,MATCH(I17,Data_checks!$H$31:$H$34,0),MATCH(LEFT(I10,1),Data_checks!$I$30:$K$30,0)) -> 0.35 | J97: =INDEX(Data_checks!$I$31:$K$34,MATCH(J17,Data_checks!$H$31:$H$34,0),MATCH(LEFT(J10,1),Data_checks!$I$30:$K$30,0)) -> 0.45 | ... N97: =INDEX(Data_checks!$I$31:$K$34,MATCH(N17,Data_checks!$H$31:$H$34,0),MATCH(LEFT(N10,1),Data_checks!$I$30:$K$30,0)) -> 0.15
B99: Commission $ for distributors
B100: Screen | C100: =C93 -> Jan | D100: =D93 -> Feb | E100: =E93 -> Mar | F100: =F93 -> Apr | G100: =G93 -> May | H100: =H93 -> Jun | I100: =I93 -> Jul | J100: =J93 -> Aug | ... N100: =N93 -> Dec
B101: =B7 -> 1 | C101: =C94*C28*Parameters!$C$6 -> 1017373.5 | D101: =D94*D28*Parameters!$C$6 -> 716040 | E101: =E94*E28*Parameters!$C$6 -> 760792.5 | F101: =F94*F28*Parameters!$C$6 -> 1017373.5 | G101: =G94*G28*Parameters!$C$6 -> 716040 | H101: =H94*H28*Parameters!$C$6 -> 760792.5 | I101: =I94*I28*Parameters!$C$6 -> 1266993 | J101: =J94*J28*Parameters!$C$6 -> 929857.5 | ... N101: =N94*N28*Parameters!$C$6 -> 452497.5
B102: =B8 -> 2 | C102: =C95*C29*Parameters!$C$6 -> 538609.5 | D102: =D95*D29*Parameters!$C$6 -> 239557.5 | E102: =E95*E29*Parameters!$C$6 -> 205335 | F102: =F95*F29*Parameters!$C$6 -> 538609.5 | G102: =G95*G29*Parameters!$C$6 -> 402772.5 | H102: =H95*H29*Parameters!$C$6 -> 205335 | I102: =I95*I29*Parameters!$C$6 -> 670761 | J102: =J95*J29*Parameters!$C$6 -> 492277.5 | ... N102: =N95*N29*Parameters!$C$6 -> 205335
B103: =B9 -> 3 | C103: =C96*C30*Parameters!$C$6 -> 179010 | D103: =D96*D30*Parameters!$C$6 -> 106470 | E103: =E96*E30*Parameters!$C$6 -> 179010 | F103: =F96*F30*Parameters!$C$6 -> 179010 | G103: =G96*G30*Parameters!$C$6 -> 106470 | H103: =H96*H30*Parameters!$C$6 -> 106470 | I103: =I96*I30*Parameters!$C$6 -> 298116 | J103: =J96*J30*Parameters!$C$6 -> 179010 | ... N103: =N96*N30*Parameters!$C$6 -> 106470
B104: =B10 -> 4 | C104: =C97*C31*Parameters!$C$6 -> 134257.5 | D104: =D97*D31*Parameters!$C$6 -> 79852.5 | E104: =E97*E31*Parameters!$C$6 -> 23692.5 | F104: =F97*F31*Parameters!$C$6 -> 79852.5 | G104: =G97*G31*Parameters!$C$6 -> 79852.5 | H104: =H97*H31*Parameters!$C$6 -> 23692.5 | I104: =I97*I31*Parameters!$C$6 -> 79852.5 | J104: =J97*J31*Parameters!$C$6 -> 134257.5 | ... N104: =N97*N31*Parameters!$C$6 -> 23692.5
B105: Total | C105: =SUM(C101:C104) -> 1869250.5 | D105: =SUM(D101:D104) -> 1141920 | E105: =SUM(E101:E104) -> 1168830 | F105: =SUM(F101:F104) -> 1814845.5 | G105: =SUM(G101:G104) -> 1305135 | H105: =SUM(H101:H104) -> 1096290 | I105: =SUM(I101:I104) -> 2315722.5 | J105: =SUM(J101:J104) -> 1735402.5 | ... N105: =SUM(N101:N104) -> 787995
B107: Cinema profit calculations
C108: =C100 -> Jan | D108: =D100 -> Feb | E108: =E100 -> Mar | F108: =F100 -> Apr | G108: =G100 -> May | H108: =H100 -> Jun | I108: =I100 -> Jul | J108: =J100 -> Aug | ... N108: =N100 -> Dec | O108: Total
B109: Ticket revenue | C109: =C55 -> 3525210 | D109: =D55 -> 2808000 | E109: =E55 -> 2930850 | F109: =F55 -> 3455010 | G109: =G55 -> 3018600 | H109: =H55 -> 2837250 | I109: =I55 -> 3667950 | J109: =J55 -> 3281850 | ... N109: =N55 -> 2439450 | O109: =SUM(C109:N109) -> 36976680
B110: Annual pass revenue | C110: =C72 -> 0 | D110: =D72 -> 0 | E110: =E72 -> 0 | F110: =F72 -> 0 | G110: =G72 -> 0 | H110: =H72 -> 0 | I110: =I72 -> 0 | J110: =J72 -> 0 | ... N110: =N72 -> 0 | O110: =SUM(C110:N110) -> 0
B111: Snacks sales | C111: =C90 -> 2088009 | D111: =D90 -> 1663200 | E111: =E90 -> 1735965 | F111: =F90 -> 2046429 | G111: =G90 -> 1787940 | H111: =H90 -> 1680525 | I111: =I90 -> 2172555 | J111: =J90 -> 1943865 | ... N111: =N90 -> 1444905 | O111: =SUM(C111:N111) -> 21901572
B112: Commission | C112: =-C105 -> -1869250.5 | D112: =-D105 -> -1141920 | E112: =-E105 -> -1168830 | F112: =-F105 -> -1814845.5 | G112: =-G105 -> -1305135 | H112: =-H105 -> -1096290 | I112: =-I105 -> -2315722.5 | J112: =-J105 -> -1735402.5 | ... N112: =-N105 -> -787995 | O112: =SUM(C112:N112) -> -17298392
B113: Cost of snack sales | C113: =-C90/Parameters!$C$7*Parameters!$C$13 -> -189819 | D113: =-D90/Parameters!$C$7*Parameters!$C$13 -> -151200 | E113: =-E90/Parameters!$C$7*Parameters!$C$13 -> -157815 | F113: =-F90/Parameters!$C$7*Parameters!$C$13 -> -186039 | G113: =-G90/Parameters!$C$7*Parameters!$C$13 -> -162540 | H113: =-H90/Parameters!$C$7*Parameters!$C$13 -> -152775 | I113: =-I90/Parameters!$C$7*Parameters!$C$13 -> -197505 | J113: =-J90/Parameters!$C$7*Parameters!$C$13 -> -176715 | ... N113: =-N90/Parameters!$C$7*Parameters!$C$13 -> -131355 | O113: =SUM(C113:N113) -> -1991052
B114: Overheads | C114: =-Parameters!$C$12 -> -300000 | D114: =-Parameters!$C$12 -> -300000 | E114: =-Parameters!$C$12 -> -300000 | F114: =-Parameters!$C$12 -> -300000 | G114: =-Parameters!$C$12 -> -300000 | H114: =-Parameters!$C$12 -> -300000 | I114: =-Parameters!$C$12 -> -300000 | J114: =-Parameters!$C$12 -> -300000 | ... N114: =-Parameters!$C$12 -> -300000 | O114: =SUM(C114:N114) -> -3600000
B115: Staff expenses | C115: =-(Parameters!$C$9*Parameters!$C$10*Parameters!$C$5*Parameters!$C$11) -> -192000 | D115: =-(Parameters!$C$9*Parameters!$C$10*Parameters!$C$5*Parameters!$C$11) -> -192000 | E115: =-(Parameters!$C$9*Parameters!$C$10*Parameters!$C$5*Parameters!$C$11) -> -192000 | F115: =-(Parameters!$C$9*Parameters!$C$10*Parameters!$C$5*Parameters!$C$11) -> -192000 | G115: =-(Parameters!$C$9*Parameters!$C$10*Parameters!$C$5*Parameters!$C$11) -> -192000 | H115: =-(Parameters!$C$9*Parameters!$C$10*Parameters!$C$5*Parameters!$C$11) -> -192000 | I115: =-(Parameters!$C$9*Parameters!$C$10*Parameters!$C$5*Parameters!$C$11) -> -192000 | J115: =-(Parameters!$C$9*Parameters!$C$10*Parameters!$C$5*Parameters!$C$11) -> -192000 | ... N115: =-(Parameters!$C$9*Parameters!$C$10*Parameters!$C$5*Parameters!$C$11) -> -192000 | O115: =SUM(C115:N115) -> -2304000
...

Sheet Calc_annual_pass
B1: Cinema going and profit calculations for annual pass
B5: Schedule
B6: Screen | C6: Jan | D6: Feb | E6: Mar | F6: Apr | G6: May | H6: Jun | I6: Jul | J6: Aug | K6: Sep | L6: Oct | M6: Nov | N6: Dec
B7: =Data_checks!$B6 -> 1 | C7: =Data_checks!D6 -> Major 1 | D7: =Data_checks!E6 -> Major 1 | E7: =Data_checks!F6 -> Regular 3 | F7: =Data_checks!G6 -> Major 2 | G7: =Data_checks!H6 -> Major 2 | H7: =Data_checks!I6 -> Regular 6 | I7: =Data_checks!J6 -> Epic 1 | J7: =Data_checks!K6 -> Epic 1 | ... N7: =Data_checks!O6 -> Regular 10
B8: =Data_checks!$B7 -> 2 | C8: =Data_checks!D7 -> Major 1 | D8: =Data_checks!E7 -> Regular 1 | E8: =Data_checks!F7 -> Major 1 | F8: =Data_checks!G7 -> Major 2 | G8: =Data_checks!H7 -> Regular 5 | H8: =Data_checks!I7 -> Major 2 | I8: =Data_checks!J7 -> Epic 1 | J8: =Data_checks!K7 -> Epic 1 | ... N8: =Data_checks!O7 -> Major 3
B9: =Data_checks!$B8 -> 3 | C9: =Data_checks!D8 -> Regular 1 | D9: =Data_checks!E8 -> Regular 2 | E9: =Data_checks!F8 -> Regular 3 | F9: =Data_checks!G8 -> Regular 4 | G9: =Data_checks!H8 -> Regular 4 | H9: =Data_checks!I8 -> Regular 5 | I9: =Data_checks!J8 -> Epic 1 | J9: =Data_checks!K8 -> Regular 7 | ... N9: =Data_checks!O8 -> Regular 10
B10: =Data_checks!$B9 -> 4 | C10: =Data_checks!D9 -> Regular 2 | D10: =Data_checks!E9 -> Regular 2 | E10: =Data_checks!F9 -> Regular 1 | F10: =Data_checks!G9 -> Regular 3 | G10: =Data_checks!H9 -> Regular 4 | H10: =Data_checks!I9 -> Regular 4 | I10: =Data_checks!J9 -> Regular 6 | J10: =Data_checks!K9 -> Regular 8 | ... N10: =Data_checks!O9 -> Regular 9
B12: Number of months movie has been showing
B13: Screen | C13: =C6 -> Jan | D13: =D6 -> Feb | E13: =E6 -> Mar | F13: =F6 -> Apr | G13: =G6 -> May | H13: =H6 -> Jun | I13: =I6 -> Jul | J13: =J6 -> Aug | ... N13: =N6 -> Dec
B14: =B7 -> 1 | C14: 1 | D14: =IF(COUNTIF(C$7:C$10,D7)>0,1,0)+IF(COUNTIF(B$7:B$10,D7)>0,1,0)+IF(COUNTIF(A$7:A$10,D7)>0,1,0)+1 -> 2 | E14: =IF(COUNTIF(D$7:D$10,E7)>0,1,0)+IF(COUNTIF(C$7:C$10,E7)>0,1,0)+IF(COUNTIF(B$7:B$10,E7)>0,1,0)+1 -> 1 | F14: =IF(COUNTIF(E$7:E$10,F7)>0,1,0)+IF(COUNTIF(D$7:D$10,F7)>0,1,0)+IF(COUNTIF(C$7:C$10,F7)>0,1,0)+1 -> 1 | G14: =IF(COUNTIF(F$7:F$10,G7)>0,1,0)+IF(COUNTIF(E$7:E$10,G7)>0,1,0)+IF(COUNTIF(D$7:D$10,G7)>0,1,0)+1 -> 2 | H14: =IF(COUNTIF(G$7:G$10,H7)>0,1,0)+IF(COUNTIF(F$7:F$10,H7)>0,1,0)+IF(COUNTIF(E$7:E$10,H7)>0,1,0)+1 -> 1 | I14: =IF(COUNTIF(H$7:H$10,I7)>0,1,0)+IF(COUNTIF(G$7:G$10,I7)>0,1,0)+IF(COUNTIF(F$7:F$10,I7)>0,1,0)+1 -> 1 | J14: =IF(COUNTIF(I$7:I$10,J7)>0,1,0)+IF(COUNTIF(H$7:H$10,J7)>0,1,0)+IF(COUNTIF(G$7:G$10,J7)>0,1,0)+1 -> 2 | K14: =IF(COUNTIF(J$7:J$10,K7)>0,1,0)+IF(COUNTIF(I$7:I$10,K7)>0,1,0)+IF(COUNTIF(H$7:H$10,K7)>0,1,0)+1 -> 2 | ... N14: =IF(COUNTIF(M$7:M$10,N7)>0,1,0)+IF(COUNTIF(L$7:L$10,N7)>0,1,0)+IF(COUNTIF(K$7:K$10,N7)>0,1,0)+1 -> 2
B15: =B8 -> 2 | C15: 1 | D15: =IF(COUNTIF(C$7:C$10,D8)>0,1,0)+IF(COUNTIF(B$7:B$10,D8)>0,1,0)+IF(COUNTIF(A$7:A$10,D8)>0,1,0)+1 -> 2 | E15: =IF(COUNTIF(D$7:D$10,E8)>0,1,0)+IF(COUNTIF(C$7:C$10,E8)>0,1,0)+IF(COUNTIF(B$7:B$10,E8)>0,1,0)+1 -> 3 | F15: =IF(COUNTIF(E$7:E$10,F8)>0,1,0)+IF(COUNTIF(D$7:D$10,F8)>0,1,0)+IF(COUNTIF(C$7:C$10,F8)>0,1,0)+1 -> 1 | G15: =IF(COUNTIF(F$7:F$10,G8)>0,1,0)+IF(COUNTIF(E$7:E$10,G8)>0,1,0)+IF(COUNTIF(D$7:D$10,G8)>0,1,0)+1 -> 1 | H15: =IF(COUNTIF(G$7:G$10,H8)>0,1,0)+IF(COUNTIF(F$7:F$10,H8)>0,1,0)+IF(COUNTIF(E$7:E$10,H8)>0,1,0)+1 -> 3 | I15: =IF(COUNTIF(H$7:H$10,I8)>0,1,0)+IF(COUNTIF(G$7:G$10,I8)>0,1,0)+IF(COUNTIF(F$7:F$10,I8)>0,1,0)+1 -> 1 | J15: =IF(COUNTIF(I$7:I$10,J8)>0,1,0)+IF(COUNTIF(H$7:H$10,J8)>0,1,0)+IF(COUNTIF(G$7:G$10,J8)>0,1,0)+1 -> 2 | K15: =IF(COUNTIF(J$7:J$10,K8)>0,1,0)+IF(COUNTIF(I$7:I$10,K8)>0,1,0)+IF(COUNTIF(H$7:H$10,K8)>0,1,0)+1 -> 3 | ... N15: =IF(COUNTIF(M$7:M$10,N8)>0,1,0)+IF(COUNTIF(L$7:L$10,N8)>0,1,0)+IF(COUNTIF(K$7:K$10,N8)>0,1,0)+1 -> 3
B16: =B9 -> 3 | C16: 1 | D16: =IF(COUNTIF(C$7:C$10,D9)>0,1,0)+IF(COUNTIF(B$7:B$10,D9)>0,1,0)+IF(COUNTIF(A$7:A$10,D9)>0,1,0)+1 -> 2 | E16: =IF(COUNTIF(D$7:D$10,E9)>0,1,0)+IF(COUNTIF(C$7:C$10,E9)>0,1,0)+IF(COUNTIF(B$7:B$10,E9)>0,1,0)+1 -> 1 | F16: =IF(COUNTIF(E$7:E$10,F9)>0,1,0)+IF(COUNTIF(D$7:D$10,F9)>0,1,0)+IF(COUNTIF(C$7:C$10,F9)>0,1,0)+1 -> 1 | G16: =IF(COUNTIF(F$7:F$10,G9)>0,1,0)+IF(COUNTIF(E$7:E$10,G9)>0,1,0)+IF(COUNTIF(D$7:D$10,G9)>0,1,0)+1 -> 2 | H16: =IF(COUNTIF(G$7:G$10,H9)>0,1,0)+IF(COUNTIF(F$7:F$10,H9)>0,1,0)+IF(COUNTIF(E$7:E$10,H9)>0,1,0)+1 -> 2 | I16: =IF(COUNTIF(H$7:H$10,I9)>0,1,0)+IF(COUNTIF(G$7:G$10,I9)>0,1,0)+IF(COUNTIF(F$7:F$10,I9)>0,1,0)+1 -> 1 | J16: =IF(COUNTIF(I$7:I$10,J9)>0,1,0)+IF(COUNTIF(H$7:H$10,J9)>0,1,0)+IF(COUNTIF(G$7:G$10,J9)>0,1,0)+1 -> 1 | K16: =IF(COUNTIF(J$7:J$10,K9)>0,1,0)+IF(COUNTIF(I$7:I$10,K9)>0,1,0)+IF(COUNTIF(H$7:H$10,K9)>0,1,0)+1 -> 3 | ... N16: =IF(COUNTIF(M$7:M$10,N9)>0,1,0)+IF(COUNTIF(L$7:L$10,N9)>0,1,0)+IF(COUNTIF(K$7:K$10,N9)>0,1,0)+1 -> 2
B17: =B10 -> 4 | C17: 1 | D17: =IF(COUNTIF(C$7:C$10,D10)>0,1,0)+IF(COUNTIF(B$7:B$10,D10)>0,1,0)+IF(COUNTIF(A$7:A$10,D10)>0,1,0)+1 -> 2 | E17: =IF(COUNTIF(D$7:D$10,E10)>0,1,0)+IF(COUNTIF(C$7:C$10,E10)>0,1,0)+IF(COUNTIF(B$7:B$10,E10)>0,1,0)+1 -> 3 | F17: =IF(COUNTIF(E$7:E$10,F10)>0,1,0)+IF(COUNTIF(D$7:D$10,F10)>0,1,0)+IF(COUNTIF(C$7:C$10,F10)>0,1,0)+1 -> 2 | G17: =IF(COUNTIF(F$7:F$10,G10)>0,1,0)+IF(COUNTIF(E$7:E$10,G10)>0,1,0)+IF(COUNTIF(D$7:D$10,G10)>0,1,0)+1 -> 2 | H17: =IF(COUNTIF(G$7:G$10,H10)>0,1,0)+IF(COUNTIF(F$7:F$10,H10)>0,1,0)+IF(COUNTIF(E$7:E$10,H10)>0,1,0)+1 -> 3 | I17: =IF(COUNTIF(H$7:H$10,I10)>0,1,0)+IF(COUNTIF(G$7:G$10,I10)>0,1,0)+IF(COUNTIF(F$7:F$10,I10)>0,1,0)+1 -> 2 | J17: =IF(COUNTIF(I$7:I$10,J10)>0,1,0)+IF(COUNTIF(H$7:H$10,J10)>0,1,0)+IF(COUNTIF(G$7:G$10,J10)>0,1,0)+1 -> 1 | K17: =IF(COUNTIF(J$7:J$10,K10)>0,1,0)+IF(COUNTIF(I$7:I$10,K10)>0,1,0)+IF(COUNTIF(H$7:H$10,K10)>0,1,0)+1 -> 2 | ... N17: =IF(COUNTIF(M$7:M$10,N10)>0,1,0)+IF(COUNTIF(L$7:L$10,N10)>0,1,0)+IF(COUNTIF(K$7:K$10,N10)>0,1,0)+1 -> 3
B19: Projected screen usage
B20: Screen | C20: =C13 -> Jan | D20: =D13 -> Feb | E20: =E13 -> Mar | F20: =F13 -> Apr | G20: =G13 -> May | H20: =H13 -> Jun | I20: =I13 -> Jul | J20: =J13 -> Aug | ... N20: =N13 -> Dec
B21: =B14 -> 1 | C21: =INDEX(Data_checks!$C$31:$E$34,MATCH(C14,Data_checks!$B$31:$B$34,0),MATCH(LEFT(C7,1),Data_checks!$C$30:$E$30,0)) -> 0.93 | D21: =INDEX(Data_checks!$C$31:$E$34,MATCH(D14,Data_checks!$B$31:$B$34,0),MATCH(LEFT(D7,1),Data_checks!$C$30:$E$30,0)) -> 0.8 | E21: =INDEX(Data_checks!$C$31:$E$34,MATCH(E14,Data_checks!$B$31:$B$34,0),MATCH(LEFT(E7,1),Data_checks!$C$30:$E$30,0)) -> 0.85 | F21: =INDEX(Data_checks!$C$31:$E$34,MATCH(F14,Data_checks!$B$31:$B$34,0),MATCH(LEFT(F7,1),Data_checks!$C$30:$E$30,0)) -> 0.93 | G21: =INDEX(Data_checks!$C$31:$E$34,MATCH(G14,Data_checks!$B$31:$B$34,0),MATCH(LEFT(G7,1),Data_checks!$C$30:$E$30,0)) -> 0.8 | H21: =INDEX(Data_checks!$C$31:$E$34,MATCH(H14,Data_checks!$B$31:$B$34,0),MATCH(LEFT(H7,1),Data_checks!$C$30:$E$30,0)) -> 0.85 | I21: =INDEX(Data_checks!$C$31:$E$34,MATCH(I14,Data_checks!$B$31:$B$34,0),MATCH(LEFT(I7,1),Data_checks!$C$30:$E$30,0)) -> 0.98 | J21: =INDEX(Data_checks!$C$31:$E$34,MATCH(J14,Data_checks!$B$31:$B$34,0),MATCH(LEFT(J7,1),Data_checks!$C$30:$E$30,0)) -> 0.85 | ... N21: =INDEX(Data_checks!$C$31:$E$34,MATCH(N14,Data_checks!$B$31:$B$34,0),MATCH(LEFT(N7,1),Data_checks!$C$30:$E$30,0)) -> 0.65
B22: =B15 -> 2 | C22: =INDEX(Data_checks!$C$31:$E$34,MATCH(C15,Data_checks!$B$31:$B$34,0),MATCH(LEFT(C8,1),Data_checks!$C$30:$E$30,0)) -> 0.93 | D22: =INDEX(Data_checks!$C$31:$E$34,MATCH(D15,Data_checks!$B$31:$B$34,0),MATCH(LEFT(D8,1),Data_checks!$C$30:$E$30,0)) -> 0.65 | E22: =INDEX(Data_checks!$C$31:$E$34,MATCH(E15,Data_checks!$B$31:$B$34,0),MATCH(LEFT(E8,1),Data_checks!$C$30:$E$30,0)) -> 0.65 | F22: =INDEX(Data_checks!$C$31:$E$34,MATCH(F15,Data_checks!$B$31:$B$34,0),MATCH(LEFT(F8,1),Data_checks!$C$30:$E$30,0)) -> 0.93 | G22: =INDEX(Data_checks!$C$31:$E$34,MATCH(G15,Data_checks!$B$31:$B$34,0),MATCH(LEFT(G8,1),Data_checks!$C$30:$E$30,0)) -> 0.85 | H22: =INDEX(Data_checks!$C$31:$E$34,MATCH(H15,Data_checks!$B$31:$B$34,0),MATCH(LEFT(H8,1),Data_checks!$C$30:$E$30,0)) -> 0.65 | I22: =INDEX(Data_checks!$C$31:$E$34,MATCH(I15,Data_checks!$B$31:$B$34,0),MATCH(LEFT(I8,1),Data_checks!$C$30:$E$30,0)) -> 0.98 | J22: =INDEX(Data_checks!$C$31:$E$34,MATCH(J15,Data_checks!$B$31:$B$34,0),MATCH(LEFT(J8,1),Data_checks!$C$30:$E$30,0)) -> 0.85 | ... N22: =INDEX(Data_checks!$C$31:$E$34,MATCH(N15,Data_checks!$B$31:$B$34,0),MATCH(LEFT(N8,1),Data_checks!$C$30:$E$30,0)) -> 0.65
B23: =B16 -> 3 | C23: =INDEX(Data_checks!$C$31:$E$34,MATCH(C16,Data_checks!$B$31:$B$34,0),MATCH(LEFT(C9,1),Data_checks!$C$30:$E$30,0)) -> 0.85 | D23: =INDEX(Data_checks!$C$31:$E$34,MATCH(D16,Data_checks!$B$31:$B$34,0),MATCH(LEFT(D9,1),Data_checks!$C$30:$E$30,0)) -> 0.65 | E23: =INDEX(Data_checks!$C$31:$E$34,MATCH(E16,Data_checks!$B$31:$B$34,0),MATCH(LEFT(E9,1),Data_checks!$C$30:$E$30,0)) -> 0.85 | F23: =INDEX(Data_checks!$C$31:$E$34,MATCH(F16,Data_checks!$B$31:$B$34,0),MATCH(LEFT(F9,1),Data_checks!$C$30:$E$30,0)) -> 0.85 | G23: =INDEX(Data_checks!$C$31:$E$34,MATCH(G16,Data_checks!$B$31:$B$34,0),MATCH(LEFT(G9,1),Data_checks!$C$30:$E$30,0)) -> 0.65 | H23: =INDEX(Data_checks!$C$31:$E$34,MATCH(H16,Data_checks!$B$31:$B$34,0),MATCH(LEFT(H9,1),Data_checks!$C$30:$E$30,0)) -> 0.65 | I23: =INDEX(Data_checks!$C$31:$E$34,MATCH(I16,Data_checks!$B$31:$B$34,0),MATCH(LEFT(I9,1),Data_checks!$C$30:$E$30,0)) -> 0.98 | J23: =INDEX(Data_checks!$C$31:$E$34,MATCH(J16,Data_checks!$B$31:$B$34,0),MATCH(LEFT(J9,1),Data_checks!$C$30:$E$30,0)) -> 0.85 | ... N23: =INDEX(Data_checks!$C$31:$E$34,MATCH(N16,Data_checks!$B$31:$B$34,0),MATCH(LEFT(N9,1),Data_checks!$C$30:$E$30,0)) -> 0.65
B24: =B17 -> 4 | C24: =INDEX(Data_checks!$C$31:$E$34,MATCH(C17,Data_checks!$B$31:$B$34,0),MATCH(LEFT(C10,1),Data_checks!$C$30:$E$30,0)) -> 0.85 | D24: =INDEX(Data_checks!$C$31:$E$34,MATCH(D17,Data_checks!$B$31:$B$34,0),MATCH(LEFT(D10,1),Data_checks!$C$30:$E$30,0)) -> 0.65 | E24: =INDEX(Data_checks!$C$31:$E$34,MATCH(E17,Data_checks!$B$31:$B$34,0),MATCH(LEFT(E10,1),Data_checks!$C$30:$E$30,0)) -> 0.45 | F24: =INDEX(Data_checks!$C$31:$E$34,MATCH(F17,Data_checks!$B$31:$B$34,0),MATCH(LEFT(F10,1),Data_checks!$C$30:$E$30,0)) -> 0.65 | G24: =INDEX(Data_checks!$C$31:$E$34,MATCH(G17,Data_checks!$B$31:$B$34,0),MATCH(LEFT(G10,1),Data_checks!$C$30:$E$30,0)) -> 0.65 | H24: =INDEX(Data_checks!$C$31:$E$34,MATCH(H17,Data_checks!$B$31:$B$34,0),MATCH(LEFT(H10,1),Data_checks!$C$30:$E$30,0)) -> 0.45 | I24: =INDEX(Data_checks!$C$31:$E$34,MATCH(I17,Data_checks!$B$31:$B$34,0),MATCH(LEFT(I10,1),Data_checks!$C$30:$E$30,0)) -> 0.65 | J24: =INDEX(Data_checks!$C$31:$E$34,MATCH(J17,Data_checks!$B$31:$B$34,0),MATCH(LEFT(J10,1),Data_checks!$C$30:$E$30,0)) -> 0.85 | ... N24: =INDEX(Data_checks!$C$31:$E$34,MATCH(N17,Data_checks!$B$31:$B$34,0),MATCH(LEFT(N10,1),Data_checks!$C$30:$E$30,0)) -> 0.45
B26: Projected cinemagoers (split by screen for commission calculation)
B27: Screen | C27: {=C20:N20} -> Jan | D27: Feb | E27: Mar | F27: Apr | G27: May | H27: Jun | I27: Jul | J27: Aug | K27: Sep | L27: Oct | M27: Nov | N27: Dec
B28: =B21 -> 1 | C28: =VLOOKUP($B28,Data_checks!$B$6:$C$9,2,TRUE)*C21*Parameters!$C$5*Parameters!$C$4 -> 142290 | D28: =VLOOKUP($B28,Data_checks!$B$6:$C$9,2,TRUE)*D21*Parameters!$C$5*Parameters!$C$4 -> 122400 | E28: =VLOOKUP($B28,Data_checks!$B$6:$C$9,2,TRUE)*E21*Parameters!$C$5*Parameters!$C$4 -> 130050 | F28: =VLOOKUP($B28,Data_checks!$B$6:$C$9,2,TRUE)*F21*Parameters!$C$5*Parameters!$C$4 -> 142290 | G28: =VLOOKUP($B28,Data_checks!$B$6:$C$9,2,TRUE)*G21*Parameters!$C$5*Parameters!$C$4 -> 122400 | H28: =VLOOKUP($B28,Data_checks!$B$6:$C$9,2,TRUE)*H21*Parameters!$C$5*Parameters!$C$4 -> 130050 | I28: =VLOOKUP($B28,Data_checks!$B$6:$C$9,2,TRUE)*I21*Parameters!$C$5*Parameters!$C$4 -> 149940 | J28: =VLOOKUP($B28,Data_checks!$B$6:$C$9,2,TRUE)*J21*Parameters!$C$5*Parameters!$C$4 -> 130050 | ... N28: =VLOOKUP($B28,Data_checks!$B$6:$C$9,2,TRUE)*N21*Parameters!$C$5*Parameters!$C$4 -> 99450
B29: =B22 -> 2 | C29: =VLOOKUP($B29,Data_checks!$B$6:$C$9,2,TRUE)*C22*Parameters!$C$5*Parameters!$C$4 -> 75330 | D29: =VLOOKUP($B29,Data_checks!$B$6:$C$9,2,TRUE)*D22*Parameters!$C$5*Parameters!$C$4 -> 52650 | E29: =VLOOKUP($B29,Data_checks!$B$6:$C$9,2,TRUE)*E22*Parameters!$C$5*Parameters!$C$4 -> 52650 | F29: =VLOOKUP($B29,Data_checks!$B$6:$C$9,2,TRUE)*F22*Parameters!$C$5*Parameters!$C$4 -> 75330 | G29: =VLOOKUP($B29,Data_checks!$B$6:$C$9,2,TRUE)*G22*Parameters!$C$5*Parameters!$C$4 -> 68850 | H29: =VLOOKUP($B29,Data_checks!$B$6:$C$9,2,TRUE)*H22*Parameters!$C$5*Parameters!$C$4 -> 52650 | I29: =VLOOKUP($B29,Data_checks!$B$6:$C$9,2,TRUE)*I22*Parameters!$C$5*Parameters!$C$4 -> 79380 | J29: =VLOOKUP($B29,Data_checks!$B$6:$C$9,2,TRUE)*J22*Parameters!$C$5*Parameters!$C$4 -> 68850 | ... N29: =VLOOKUP($B29,Data_checks!$B$6:$C$9,2,TRUE)*N22*Parameters!$C$5*Parameters!$C$4 -> 52650
B30: =B23 -> 3 | C30: =VLOOKUP($B30,Data_checks!$B$6:$C$9,2,TRUE)*C23*Parameters!$C$5*Parameters!$C$4 -> 30600 | D30: =VLOOKUP($B30,Data_checks!$B$6:$C$9,2,TRUE)*D23*Parameters!$C$5*Parameters!$C$4 -> 23400 | E30: =VLOOKUP($B30,Data_checks!$B$6:$C$9,2,TRUE)*E23*Parameters!$C$5*Parameters!$C$4 -> 30600 | F30: =VLOOKUP($B30,Data_checks!$B$6:$C$9,2,TRUE)*F23*Parameters!$C$5*Parameters!$C$4 -> 30600 | G30: =VLOOKUP($B30,Data_checks!$B$6:$C$9,2,TRUE)*G23*Parameters!$C$5*Parameters!$C$4 -> 23400 | H30: =VLOOKUP($B30,Data_checks!$B$6:$C$9,2,TRUE)*H23*Parameters!$C$5*Parameters!$C$4 -> 23400 | I30: =VLOOKUP($B30,Data_checks!$B$6:$C$9,2,TRUE)*I23*Parameters!$C$5*Parameters!$C$4 -> 35280 | J30: =VLOOKUP($B30,Data_checks!$B$6:$C$9,2,TRUE)*J23*Parameters!$C$5*Parameters!$C$4 -> 30600 | ... N30: =VLOOKUP($B30,Data_checks!$B$6:$C$9,2,TRUE)*N23*Parameters!$C$5*Parameters!$C$4 -> 23400
B31: =B24 -> 4 | C31: =VLOOKUP($B31,Data_checks!$B$6:$C$9,2,TRUE)*C24*Parameters!$C$5*Parameters!$C$4 -> 22950 | D31: =VLOOKUP($B31,Data_checks!$B$6:$C$9,2,TRUE)*D24*Parameters!$C$5*Parameters!$C$4 -> 17550 | E31: =VLOOKUP($B31,Data_checks!$B$6:$C$9,2,TRUE)*E24*Parameters!$C$5*Parameters!$C$4 -> 12150 | F31: =VLOOKUP($B31,Data_checks!$B$6:$C$9,2,TRUE)*F24*Parameters!$C$5*Parameters!$C$4 -> 17550 | G31: =VLOOKUP($B31,Data_checks!$B$6:$C$9,2,TRUE)*G24*Parameters!$C$5*Parameters!$C$4 -> 17550 | H31: =VLOOKUP($B31,Data_checks!$B$6:$C$9,2,TRUE)*H24*Parameters!$C$5*Parameters!$C$4 -> 12150 | I31: =VLOOKUP($B31,Data_checks!$B$6:$C$9,2,TRUE)*I24*Parameters!$C$5*Parameters!$C$4 -> 17550 | J31: =VLOOKUP($B31,Data_checks!$B$6:$C$9,2,TRUE)*J24*Parameters!$C$5*Parameters!$C$4 -> 22950 | ... N31: =VLOOKUP($B31,Data_checks!$B$6:$C$9,2,TRUE)*N24*Parameters!$C$5*Parameters!$C$4 -> 12150 | P31: Check on attendance data
B32: Total cinema | C32: =SUM(C28:C31) -> 271170 | D32: =SUM(D28:D31) -> 216000 | E32: =SUM(E28:E31) -> 225450 | F32: =SUM(F28:F31) -> 265770 | G32: =SUM(G28:G31) -> 232200 | H32: =SUM(H28:H31) -> 218250 | I32: =SUM(I28:I31) -> 282150 | J32: =SUM(J28:J31) -> 252450 | ... N32: =SUM(N28:N31) -> 187650 | O32: =SUM(C32:N32) -> 2844360 | P32: =IF(O32=Data_checks!E58,"Data is internally consistent","Data is not consistent. Please check") -> Data is internally consistent
B34: Number of films seen split by unique cinemagoers (This is the number of films seen split by month and by unique cinemagoers. E.g. if you sum up row 49, i.e. the number of cinemagoers who have seen 14 movies a year, the sum would equal to that in the data check (5040))
B35: Total number of movies seen in yr | C35: =C27 -> Jan | D35: =D27 -> Feb | E35: =E27 -> Mar | F35: =F27 -> Apr | G35: =G27 -> May | H35: =H27 -> Jun | I35: =I27 -> Jul | J35: =J27 -> Aug | ... N35: =N27 -> Dec
B36: =Data!B21 -> 1 | C36: =C$32*Data_checks!$F44 -> 17658.14 | D36: =D$32*Data_checks!$F44 -> 14065.561 | E36: =E$32*Data_checks!$F44 -> 14680.93 | F36: =F$32*Data_checks!$F44 -> 17306.501 | G36: =G$32*Data_checks!$F44 -> 15120.478 | H36: =H$32*Data_checks!$F44 -> 14212.078 | I36: =I$32*Data_checks!$F44 -> 18373.139 | J36: =J$32*Data_checks!$F44 -> 16439.125 | ... N36: =N$32*Data_checks!$F44 -> 12219.456
B37: =Data!B22 -> 2 | C37: =C$32*Data_checks!$F45 -> 51481.458 | D37: =D$32*Data_checks!$F45 -> 41007.467 | E37: =E$32*Data_checks!$F45 -> 42801.544 | F37: =F$32*Data_checks!$F45 -> 50456.271 | G37: =G$32*Data_checks!$F45 -> 44083.027 | H37: =H$32*Data_checks!$F45 -> 41434.629 | I37: =I$32*Data_checks!$F45 -> 53566.004 | J37: =J$32*Data_checks!$F45 -> 47927.478 | ... N37: =N$32*Data_checks!$F45 -> 35625.237
B38: =Data!B23 -> 3 | C38: =C$32*Data_checks!$F46 -> 51481.458 | D38: =D$32*Data_checks!$F46 -> 41007.467 | E38: =E$32*Data_checks!$F46 -> 42801.544 | F38: =F$32*Data_checks!$F46 -> 50456.271 | G38: =G$32*Data_checks!$F46 -> 44083.027 | H38: =H$32*Data_checks!$F46 -> 41434.629 | I38: =I$32*Data_checks!$F46 -> 53566.004 | J38: =J$32*Data_checks!$F46 -> 47927.478 | ... N38: =N$32*Data_checks!$F46 -> 35625.237
B39: =Data!B24 -> 4 | C39: =C$32*Data_checks!$F47 -> 51481.458 | D39: =D$32*Data_checks!$F47 -> 41007.467 | E39: =E$32*Data_checks!$F47 -> 42801.544 | F39: =F$32*Data_checks!$F47 -> 50456.271 | G39: =G$32*Data_checks!$F47 -> 44083.027 | H39: =H$32*Data_checks!$F47 -> 41434.629 | I39: =I$32*Data_checks!$F47 -> 53566.004 | J39: =J$32*Data_checks!$F47 -> 47927.478 | ... N39: =N$32*Data_checks!$F47 -> 35625.237
B40: =Data!B25 -> 5 | C40: =C$32*Data_checks!$F48 -> 38611.094 | D40: =D$32*Data_checks!$F48 -> 30755.601 | E40: =E$32*Data_checks!$F48 -> 32101.158 | F40: =F$32*Data_checks!$F48 -> 37842.204 | G40: =G$32*Data_checks!$F48 -> 33062.271 | H40: =H$32*Data_checks!$F48 -> 31075.971 | I40: =I$32*Data_checks!$F48 -> 40174.503 | J40: =J$32*Data_checks!$F48 -> 35945.608 | ... N40: =N$32*Data_checks!$F48 -> 26718.928
B41: =Data!B26 -> 6 | C41: =C$32*Data_checks!$F49 -> 30888.875 | D41: =D$32*Data_checks!$F49 -> 24604.48 | E41: =E$32*Data_checks!$F49 -> 25680.926 | F41: =F$32*Data_checks!$F49 -> 30273.763 | G41: =G$32*Data_checks!$F49 -> 26449.816 | H41: =H$32*Data_checks!$F49 -> 24860.777 | I41: =I$32*Data_checks!$F49 -> 32139.603 | J41: =J$32*Data_checks!$F49 -> 28756.487 | ... N41: =N$32*Data_checks!$F49 -> 21375.142
B42: =Data!B27 -> 7 | C42: =C$32*Data_checks!$F50 -> 18018.51 | D42: =D$32*Data_checks!$F50 -> 14352.614 | E42: =E$32*Data_checks!$F50 -> 14980.54 | F42: =F$32*Data_checks!$F50 -> 17659.695 | G42: =G$32*Data_checks!$F50 -> 15429.06 | H42: =H$32*Data_checks!$F50 -> 14502.12 | I42: =I$32*Data_checks!$F50 -> 18748.102 | J42: =J$32*Data_checks!$F50 -> 16774.617 | ... N42: =N$32*Data_checks!$F50 -> 12468.833
B43: =Data!B28 -> 8 | C43: =C$32*Data_checks!$F51 -> 4118.5166 | D43: =D$32*Data_checks!$F51 -> 3280.5974 | E43: =E$32*Data_checks!$F51 -> 3424.1235 | F43: =F$32*Data_checks!$F51 -> 4036.5017 | G43: =G$32*Data_checks!$F51 -> 3526.6422 | H43: =H$32*Data_checks!$F51 -> 3314.7703 | I43: =I$32*Data_checks!$F51 -> 4285.2803 | J43: =J$32*Data_checks!$F51 -> 3834.1982 | ... N43: =N$32*Data_checks!$F51 -> 2850.019
B44: =Data!B29 -> 9 | C44: =C$32*Data_checks!$F52 -> 3088.8875 | D44: =D$32*Data_checks!$F52 -> 2460.448 | E44: =E$32*Data_checks!$F52 -> 2568.0926 | F44: =F$32*Data_checks!$F52 -> 3027.3763 | G44: =G$32*Data_checks!$F52 -> 2644.9816 | H44: =H$32*Data_checks!$F52 -> 2486.0777 | I44: =I$32*Data_checks!$F52 -> 3213.9603 | J44: =J$32*Data_checks!$F52 -> 2875.6487 | ... N44: =N$32*Data_checks!$F52 -> 2137.5142
B45: =Data!B30 -> 10 | C45: =C$32*Data_checks!$F53 -> 1029.6292 | D45: =D$32*Data_checks!$F53 -> 820.14935 | E45: =E$32*Data_checks!$F53 -> 856.03088 | F45: =F$32*Data_checks!$F53 -> 1009.1254 | G45: =G$32*Data_checks!$F53 -> 881.66055 | H45: =H$32*Data_checks!$F53 -> 828.69257 | I45: =I$32*Data_checks!$F53 -> 1071.3201 | J45: =J$32*Data_checks!$F53 -> 958.54955 | ... N45: =N$32*Data_checks!$F53 -> 712.50475
B46: =Data!B31 -> 11 | C46: =C$32*Data_checks!$F54 -> 1132.5921 | D46: =D$32*Data_checks!$F54 -> 902.16428 | E46: =E$32*Data_checks!$F54 -> 941.63397 | F46: =F$32*Data_checks!$F54 -> 1110.038 | G46: =G$32*Data_checks!$F54 -> 969.8266 | H46: =H$32*Data_checks!$F54 -> 911.56183 | I46: =I$32*Data_checks!$F54 -> 1178.4521 | J46: =J$32*Data_checks!$F54 -> 1054.4045 | ... N46: =N$32*Data_checks!$F54 -> 783.75522
B47: =Data!B32 -> 12 | C47: =C$32*Data_checks!$F55 -> 1029.6292 | D47: =D$32*Data_checks!$F55 -> 820.14935 | E47: =E$32*Data_checks!$F55 -> 856.03088 | F47: =F$32*Data_checks!$F55 -> 1009.1254 | G47: =G$32*Data_checks!$F55 -> 881.66055 | H47: =H$32*Data_checks!$F55 -> 828.69257 | I47: =I$32*Data_checks!$F55 -> 1071.3201 | J47: =J$32*Data_checks!$F55 -> 958.54955 | ... N47: =N$32*Data_checks!$F55 -> 712.50475
B48: =Data!B33 -> 13 | C48: =C$32*Data_checks!$F56 -> 669.25895 | D48: =D$32*Data_checks!$F56 -> 533.09708 | E48: =E$32*Data_checks!$F56 -> 556.42007 | F48: =F$32*Data_checks!$F56 -> 655.93153 | G48: =G$32*Data_checks!$F56 -> 573.07936 | H48: =H$32*Data_checks!$F56 -> 538.65017 | I48: =I$32*Data_checks!$F56 -> 696.35806 | J48: =J$32*Data_checks!$F56 -> 623.05721 | ... N48: =N$32*Data_checks!$F56 -> 463.12809 | P48: Check on consistency of projected attendance
B49: =Data!B34 -> 14 | C49: =C$32*Data_checks!$F57 -> 480.49361 | D49: =D$32*Data_checks!$F57 -> 382.73636 | E49: =E$32*Data_checks!$F57 -> 399.48108 | F49: =F$32*Data_checks!$F57 -> 470.9252 | G49: =G$32*Data_checks!$F57 -> 411.44159 | H49: =H$32*Data_checks!$F57 -> 386.7232 | I49: =I$32*Data_checks!$F57 -> 499.94937 | J49: =J$32*Data_checks!$F57 -> 447.32312 | ... N49: =N$32*Data_checks!$F57 -> 332.50221 | O49: =SUM(C36:N49) -> 2844360 | P49: =IF(O49=O32,"Data is internally consistent","Data is not consistent. Please check") -> Data is internally consistent
B50: Total | C50: =SUM(C36:C49) -> 271170 | D50: =SUM(D36:D49) -> 216000 | E50: =SUM(E36:E49) -> 225450 | F50: =SUM(F36:F49) -> 265770 | G50: =SUM(G36:G49) -> 232200 | H50: =SUM(H36:H49) -> 218250 | I50: =SUM(I36:I49) -> 282150 | J50: =SUM(J36:J49) -> 252450 | ... N50: =SUM(N36:N49) -> 187650
B51: Check | C51: =C50=C32 -> TRUE | D51: =D50=D32 -> TRUE | E51: =E50=E32 -> TRUE | F51: =F50=F32 -> TRUE | G51: =G50=G32 -> TRUE | H51: =H50=H32 -> TRUE | I51: =I50=I32 -> TRUE | J51: =J50=J32 -> TRUE | ... N51: =N50=N32 -> TRUE
B53: Income from movie screenings
C54: =C35 -> Jan | D54: =D35 -> Feb | E54: =E35 -> Mar | F54: =F35 -> Apr | G54: =G35 -> May | H54: =H35 -> Jun | I54: =I35 -> Jul | J54: =J35 -> Aug | ... N54: =N35 -> Dec
B55: Projected ticket sales | C55: =SUMIF($B$36:$B$49,"<"&Parameters!$D$16,C$36:C$49)*Parameters!$C$6 -> 2237332.7 | D55: =SUMIF($B$36:$B$49,"<"&Parameters!$D$16,D$36:D$49)*Parameters!$C$6 -> 1782143.5 | E55: =SUMIF($B$36:$B$49,"<"&Parameters!$D$16,E$36:E$49)*Parameters!$C$6 -> 1860112.3 | F55: =SUMIF($B$36:$B$49,"<"&Parameters!$D$16,F$36:F$49)*Parameters!$C$6 -> 2192779.1 | G55: =SUMIF($B$36:$B$49,"<"&Parameters!$D$16,G$36:G$49)*Parameters!$C$6 -> 1915804.3 | H55: =SUMIF($B$36:$B$49,"<"&Parameters!$D$16,H$36:H$49)*Parameters!$C$6 -> 1800707.5 | I55: =SUMIF($B$36:$B$49,"<"&Parameters!$D$16,I$36:I$49)*Parameters!$C$6 -> 2327925 | J55: =SUMIF($B$36:$B$49,"<"&Parameters!$D$16,J$36:J$49)*Parameters!$C$6 -> 2082880.2 | ... N55: =SUMIF($B$36:$B$49,"<"&Parameters!$D$16,N$36:N$49)*Parameters!$C$6 -> 1548237.2
B57: Annual pass income
B58: =Data!B21 -> 1 | C58: =IF($B36>=Parameters!$D$16,C36/$B36,0)*Parameters!$D$15 -> 0 | D58: =IF($B36>=Parameters!$D$16,D36/$B36,0)*Parameters!$D$15 -> 0 | E58: =IF($B36>=Parameters!$D$16,E36/$B36,0)*Parameters!$D$15 -> 0 | F58: =IF($B36>=Parameters!$D$16,F36/$B36,0)*Parameters!$D$15 -> 0 | G58: =IF($B36>=Parameters!$D$16,G36/$B36,0)*Parameters!$D$15 -> 0 | H58: =IF($B36>=Parameters!$D$16,H36/$B36,0)*Parameters!$D$15 -> 0 | I58: =IF($B36>=Parameters!$D$16,I36/$B36,0)*Parameters!$D$15 -> 0 | J58: =IF($B36>=Parameters!$D$16,J36/$B36,0)*Parameters!$D$15 -> 0 | ... N58: =IF($B36>=Parameters!$D$16,N36/$B36,0)*Parameters!$D$15 -> 0
B59: =Data!B22 -> 2 | C59: =IF($B37>=Parameters!$D$16,C37/$B37,0)*Parameters!$D$15 -> 0 | D59: =IF($B37>=Parameters!$D$16,D37/$B37,0)*Parameters!$D$15 -> 0 | E59: =IF($B37>=Parameters!$D$16,E37/$B37,0)*Parameters!$D$15 -> 0 | F59: =IF($B37>=Parameters!$D$16,F37/$B37,0)*Parameters!$D$15 -> 0 | G59: =IF($B37>=Parameters!$D$16,G37/$B37,0)*Parameters!$D$15 -> 0 | H59: =IF($B37>=Parameters!$D$16,H37/$B37,0)*Parameters!$D$15 -> 0 | I59: =IF($B37>=Parameters!$D$16,I37/$B37,0)*Parameters!$D$15 -> 0 | J59: =IF($B37>=Parameters!$D$16,J37/$B37,0)*Parameters!$D$15 -> 0 | ... N59: =IF($B37>=Parameters!$D$16,N37/$B37,0)*Parameters!$D$15 -> 0
B60: =Data!B23 -> 3 | C60: =IF($B38>=Parameters!$D$16,C38/$B38,0)*Parameters!$D$15 -> 0 | D60: =IF($B38>=Parameters!$D$16,D38/$B38,0)*Parameters!$D$15 -> 0 | E60: =IF($B38>=Parameters!$D$16,E38/$B38,0)*Parameters!$D$15 -> 0 | F60: =IF($B38>=Parameters!$D$16,F38/$B38,0)*Parameters!$D$15 -> 0 | G60: =IF($B38>=Parameters!$D$16,G38/$B38,0)*Parameters!$D$15 -> 0 | H60: =IF($B38>=Parameters!$D$16,H38/$B38,0)*Parameters!$D$15 -> 0 | I60: =IF($B38>=Parameters!$D$16,I38/$B38,0)*Parameters!$D$15 -> 0 | J60: =IF($B38>=Parameters!$D$16,J38/$B38,0)*Parameters!$D$15 -> 0 | ... N60: =IF($B38>=Parameters!$D$16,N38/$B38,0)*Parameters!$D$15 -> 0
B61: =Data!B24 -> 4 | C61: =IF($B39>=Parameters!$D$16,C39/$B39,0)*Parameters!$D$15 -> 0 | D61: =IF($B39>=Parameters!$D$16,D39/$B39,0)*Parameters!$D$15 -> 0 | E61: =IF($B39>=Parameters!$D$16,E39/$B39,0)*Parameters!$D$15 -> 0 | F61: =IF($B39>=Parameters!$D$16,F39/$B39,0)*Parameters!$D$15 -> 0 | G61: =IF($B39>=Parameters!$D$16,G39/$B39,0)*Parameters!$D$15 -> 0 | H61: =IF($B39>=Parameters!$D$16,H39/$B39,0)*Parameters!$D$15 -> 0 | I61: =IF($B39>=Parameters!$D$16,I39/$B39,0)*Parameters!$D$15 -> 0 | J61: =IF($B39>=Parameters!$D$16,J39/$B39,0)*Parameters!$D$15 -> 0 | ... N61: =IF($B39>=Parameters!$D$16,N39/$B39,0)*Parameters!$D$15 -> 0
B62: =Data!B25 -> 5 | C62: =IF($B40>=Parameters!$D$16,C40/$B40,0)*Parameters!$D$15 -> 571444.18 | D62: =IF($B40>=Parameters!$D$16,D40/$B40,0)*Parameters!$D$15 -> 455182.89 | E62: =IF($B40>=Parameters!$D$16,E40/$B40,0)*Parameters!$D$15 -> 475097.14 | F62: =IF($B40>=Parameters!$D$16,F40/$B40,0)*Parameters!$D$15 -> 560064.61 | G62: =IF($B40>=Parameters!$D$16,G40/$B40,0)*Parameters!$D$15 -> 489321.6 | H62: =IF($B40>=Parameters!$D$16,H40/$B40,0)*Parameters!$D$15 -> 459924.38 | I62: =IF($B40>=Parameters!$D$16,I40/$B40,0)*Parameters!$D$15 -> 594582.65 | J62: =IF($B40>=Parameters!$D$16,J40/$B40,0)*Parameters!$D$15 -> 531995 | ... N62: =IF($B40>=Parameters!$D$16,N40/$B40,0)*Parameters!$D$15 -> 395440.13
B63: =Data!B26 -> 6 | C63: =IF($B41>=Parameters!$D$16,C41/$B41,0)*Parameters!$D$15 -> 380962.79 | D63: =IF($B41>=Parameters!$D$16,D41/$B41,0)*Parameters!$D$15 -> 303455.26 | E63: =IF($B41>=Parameters!$D$16,E41/$B41,0)*Parameters!$D$15 -> 316731.43 | F63: =IF($B41>=Parameters!$D$16,F41/$B41,0)*Parameters!$D$15 -> 373376.41 | G63: =IF($B41>=Parameters!$D$16,G41/$B41,0)*Parameters!$D$15 -> 326214.4 | H63: =IF($B41>=Parameters!$D$16,H41/$B41,0)*Parameters!$D$15 -> 306616.25 | I63: =IF($B41>=Parameters!$D$16,I41/$B41,0)*Parameters!$D$15 -> 396388.43 | J63: =IF($B41>=Parameters!$D$16,J41/$B41,0)*Parameters!$D$15 -> 354663.33 | ... N63: =IF($B41>=Parameters!$D$16,N41/$B41,0)*Parameters!$D$15 -> 263626.76
B64: =Data!B27 -> 7 | C64: =IF($B42>=Parameters!$D$16,C42/$B42,0)*Parameters!$D$15 -> 190481.39 | D64: =IF($B42>=Parameters!$D$16,D42/$B42,0)*Parameters!$D$15 -> 151727.63 | E64: =IF($B42>=Parameters!$D$16,E42/$B42,0)*Parameters!$D$15 -> 158365.71 | F64: =IF($B42>=Parameters!$D$16,F42/$B42,0)*Parameters!$D$15 -> 186688.2 | G64: =IF($B42>=Parameters!$D$16,G42/$B42,0)*Parameters!$D$15 -> 163107.2 | H64: =IF($B42>=Parameters!$D$16,H42/$B42,0)*Parameters!$D$15 -> 153308.13 | I64: =IF($B42>=Parameters!$D$16,I42/$B42,0)*Parameters!$D$15 -> 198194.22 | J64: =IF($B42>=Parameters!$D$16,J42/$B42,0)*Parameters!$D$15 -> 177331.67 | ... N64: =IF($B42>=Parameters!$D$16,N42/$B42,0)*Parameters!$D$15 -> 131813.38
B65: =Data!B28 -> 8 | C65: =IF($B43>=Parameters!$D$16,C43/$B43,0)*Parameters!$D$15 -> 38096.279 | D65: =IF($B43>=Parameters!$D$16,D43/$B43,0)*Parameters!$D$15 -> 30345.526 | E65: =IF($B43>=Parameters!$D$16,E43/$B43,0)*Parameters!$D$15 -> 31673.143 | F65: =IF($B43>=Parameters!$D$16,F43/$B43,0)*Parameters!$D$15 -> 37337.641 | G65: =IF($B43>=Parameters!$D$16,G43/$B43,0)*Parameters!$D$15 -> 32621.44 | H65: =IF($B43>=Parameters!$D$16,H43/$B43,0)*Parameters!$D$15 -> 30661.625 | I65: =IF($B43>=Parameters!$D$16,I43/$B43,0)*Parameters!$D$15 -> 39638.843 | J65: =IF($B43>=Parameters!$D$16,J43/$B43,0)*Parameters!$D$15 -> 35466.333 | ... N65: =IF($B43>=Parameters!$D$16,N43/$B43,0)*Parameters!$D$15 -> 26362.676
B66: =Data!B29 -> 9 | C66: =IF($B44>=Parameters!$D$16,C44/$B44,0)*Parameters!$D$15 -> 25397.519 | D66: =IF($B44>=Parameters!$D$16,D44/$B44,0)*Parameters!$D$15 -> 20230.351 | E66: =IF($B44>=Parameters!$D$16,E44/$B44,0)*Parameters!$D$15 -> 21115.428 | F66: =IF($B44>=Parameters!$D$16,F44/$B44,0)*Parameters!$D$15 -> 24891.761 | G66: =IF($B44>=Parameters!$D$16,G44/$B44,0)*Parameters!$D$15 -> 21747.627 | H66: =IF($B44>=Parameters!$D$16,H44/$B44,0)*Parameters!$D$15 -> 20441.083 | I66: =IF($B44>=Parameters!$D$16,I44/$B44,0)*Parameters!$D$15 -> 26425.895 | J66: =IF($B44>=Parameters!$D$16,J44/$B44,0)*Parameters!$D$15 -> 23644.222 | ... N66: =IF($B44>=Parameters!$D$16,N44/$B44,0)*Parameters!$D$15 -> 17575.117
B67: =Data!B30 -> 10 | C67: =IF($B45>=Parameters!$D$16,C45/$B45,0)*Parameters!$D$15 -> 7619.2558 | D67: =IF($B45>=Parameters!$D$16,D45/$B45,0)*Parameters!$D$15 -> 6069.1052 | E67: =IF($B45>=Parameters!$D$16,E45/$B45,0)*Parameters!$D$15 -> 6334.6285 | F67: =IF($B45>=Parameters!$D$16,F45/$B45,0)*Parameters!$D$15 -> 7467.5282 | G67: =IF($B45>=Parameters!$D$16,G45/$B45,0)*Parameters!$D$15 -> 6524.2881 | H67: =IF($B45>=Parameters!$D$16,H45/$B45,0)*Parameters!$D$15 -> 6132.325 | I67: =IF($B45>=Parameters!$D$16,I45/$B45,0)*Parameters!$D$15 -> 7927.7686 | J67: =IF($B45>=Parameters!$D$16,J45/$B45,0)*Parameters!$D$15 -> 7093.2667 | ... N67: =IF($B45>=Parameters!$D$16,N45/$B45,0)*Parameters!$D$15 -> 5272.5351
B68: =Data!B31 -> 11 | C68: =IF($B46>=Parameters!$D$16,C46/$B46,0)*Parameters!$D$15 -> 7619.2558 | D68: =IF($B46>=Parameters!$D$16,D46/$B46,0)*Parameters!$D$15 -> 6069.1052 | E68: =IF($B46>=Parameters!$D$16,E46/$B46,0)*Parameters!$D$15 -> 6334.6285 | F68: =IF($B46>=Parameters!$D$16,F46/$B46,0)*Parameters!$D$15 -> 7467.5282 | G68: =IF($B46>=Parameters!$D$16,G46/$B46,0)*Parameters!$D$15 -> 6524.2881 | H68: =IF($B46>=Parameters!$D$16,H46/$B46,0)*Parameters!$D$15 -> 6132.325 | I68: =IF($B46>=Parameters!$D$16,I46/$B46,0)*Parameters!$D$15 -> 7927.7686 | J68: =IF($B46>=Parameters!$D$16,J46/$B46,0)*Parameters!$D$15 -> 7093.2667 | ... N68: =IF($B46>=Parameters!$D$16,N46/$B46,0)*Parameters!$D$15 -> 5272.5351
B69: =Data!B32 -> 12 | C69: =IF($B47>=Parameters!$D$16,C47/$B47,0)*Parameters!$D$15 -> 6349.3798 | D69: =IF($B47>=Parameters!$D$16,D47/$B47,0)*Parameters!$D$15 -> 5057.5876 | E69: =IF($B47>=Parameters!$D$16,E47/$B47,0)*Parameters!$D$15 -> 5278.8571 | F69: =IF($B47>=Parameters!$D$16,F47/$B47,0)*Parameters!$D$15 -> 6222.9401 | G69: =IF($B47>=Parameters!$D$16,G47/$B47,0)*Parameters!$D$15 -> 5436.9067 | H69: =IF($B47>=Parameters!$D$16,H47/$B47,0)*Parameters!$D$15 -> 5110.2709 | I69: =IF($B47>=Parameters!$D$16,I47/$B47,0)*Parameters!$D$15 -> 6606.4739 | J69: =IF($B47>=Parameters!$D$16,J47/$B47,0)*Parameters!$D$15 -> 5911.0556 | ... N69: =IF($B47>=Parameters!$D$16,N47/$B47,0)*Parameters!$D$15 -> 4393.7793
... B71: =Data!B34 -> 14 | C71: =IF($B49>=Parameters!$D$16,C49/$B49,0)*Parameters!$D$15 -> 2539.7519 | D71: =IF($B49>=Parameters!$D$16,D49/$B49,0)*Parameters!$D$15 -> 2023.0351 | E71: =IF($B49>=Parameters!$D$16,E49/$B49,0)*Parameters!$D$15 -> 2111.5428 | F71: =IF($B49>=Parameters!$D$16,F49/$B49,0)*Parameters!$D$15 -> 2489.1761 | G71: =IF($B49>=Parameters!$D$16,G49/$B49,0)*Parameters!$D$15 -> 2174.7627 | H71: =IF($B49>=Parameters!$D$16,H49/$B49,0)*Parameters!$D$15 -> 2044.1083 | I71: =IF($B49>=Parameters!$D$16,I49/$B49,0)*Parameters!$D$15 -> 2642.5895 | J71: =IF($B49>=Parameters!$D$16,J49/$B49,0)*Parameters!$D$15 -> 2364.4222 | ... N71: =IF($B49>=Parameters!$D$16,N49/$B49,0)*Parameters!$D$15 -> 1757.5117
B72: Total | C72: =SUM(C58:C71) -> 1234319.4 | D72: =SUM(D58:D71) -> 983195.04 | E72: =SUM(E58:E71) -> 1026209.8 | F72: =SUM(F58:F71) -> 1209739.6 | G72: =SUM(G58:G71) -> 1056934.7 | H72: =SUM(H58:H71) -> 993436.65 | I72: =SUM(I58:I71) -> 1284298.5 | J72: =SUM(J58:J71) -> 1149109.2 | ... N72: =SUM(N58:N71) -> 854150.69
B74: Projected revenue from snack sales (split by total number of movies seen in the year)
B75: Total number of movies seen in yr | C75: =C54 -> Jan | D75: =D54 -> Feb | E75: =E54 -> Mar | F75: =F54 -> Apr | G75: =G54 -> May | H75: =H54 -> Jun | I75: =I54 -> Jul | J75: =J54 -> Aug | ... N75: =N54 -> Dec
B76: =B36 -> 1 | C76: =C36*Data_checks!$D44*Parameters!$C$7*IF($B76<Parameters!$D$16,1,(1+Parameters!$D$17)*(1-Parameters!$D$18)) -> 86467.422 | D76: =D36*Data_checks!$D44*Parameters!$C$7*IF($B76<Parameters!$D$16,1,(1+Parameters!$D$17)*(1-Parameters!$D$18)) -> 68875.477 | E76: =E36*Data_checks!$D44*Parameters!$C$7*IF($B76<Parameters!$D$16,1,(1+Parameters!$D$17)*(1-Parameters!$D$18)) -> 71888.78 | F76: =F36*Data_checks!$D44*Parameters!$C$7*IF($B76<Parameters!$D$16,1,(1+Parameters!$D$17)*(1-Parameters!$D$18)) -> 84745.535 | G76: =G36*Data_checks!$D44*Parameters!$C$7*IF($B76<Parameters!$D$16,1,(1+Parameters!$D$17)*(1-Parameters!$D$18)) -> 74041.138 | H76: =H36*Data_checks!$D44*Parameters!$C$7*IF($B76<Parameters!$D$16,1,(1+Parameters!$D$17)*(1-Parameters!$D$18)) -> 69592.93 | I76: =I36*Data_checks!$D44*Parameters!$C$7*IF($B76<Parameters!$D$16,1,(1+Parameters!$D$17)*(1-Parameters!$D$18)) -> 89968.592 | J76: =J36*Data_checks!$D44*Parameters!$C$7*IF($B76<Parameters!$D$16,1,(1+Parameters!$D$17)*(1-Parameters!$D$18)) -> 80498.214 | ... N76: =N36*Data_checks!$D44*Parameters!$C$7*IF($B76<Parameters!$D$16,1,(1+Parameters!$D$17)*(1-Parameters!$D$18)) -> 59835.571
B77: =B37 -> 2 | C77: =C37*Data_checks!$D45*Parameters!$C$7*IF($B77<Parameters!$D$16,1,(1+Parameters!$D$17)*(1-Parameters!$D$18)) -> 327719.09 | D77: =D37*Data_checks!$D45*Parameters!$C$7*IF($B77<Parameters!$D$16,1,(1+Parameters!$D$17)*(1-Parameters!$D$18)) -> 261044.08 | E77: =E37*Data_checks!$D45*Parameters!$C$7*IF($B77<Parameters!$D$16,1,(1+Parameters!$D$17)*(1-Parameters!$D$18)) -> 272464.76 | F77: =F37*Data_checks!$D45*Parameters!$C$7*IF($B77<Parameters!$D$16,1,(1+Parameters!$D$17)*(1-Parameters!$D$18)) -> 321192.99 | G77: =G37*Data_checks!$D45*Parameters!$C$7*IF($B77<Parameters!$D$16,1,(1+Parameters!$D$17)*(1-Parameters!$D$18)) -> 280622.39 | H77: =H37*Data_checks!$D45*Parameters!$C$7*IF($B77<Parameters!$D$16,1,(1+Parameters!$D$17)*(1-Parameters!$D$18)) -> 263763.29 | I77: =I37*Data_checks!$D45*Parameters!$C$7*IF($B77<Parameters!$D$16,1,(1+Parameters!$D$17)*(1-Parameters!$D$18)) -> 340988.83 | J77: =J37*Data_checks!$D45*Parameters!$C$7*IF($B77<Parameters!$D$16,1,(1+Parameters!$D$17)*(1-Parameters!$D$18)) -> 305095.27 | ... N77: =N37*Data_checks!$D45*Parameters!$C$7*IF($B77<Parameters!$D$16,1,(1+Parameters!$D$17)*(1-Parameters!$D$18)) -> 226782.05
B78: =B38 -> 3 | C78: =C38*Data_checks!$D46*Parameters!$C$7*IF($B78<Parameters!$D$16,1,(1+Parameters!$D$17)*(1-Parameters!$D$18)) -> 340323.67 | D78: =D38*Data_checks!$D46*Parameters!$C$7*IF($B78<Parameters!$D$16,1,(1+Parameters!$D$17)*(1-Parameters!$D$18)) -> 271084.24 | E78: =E38*Data_checks!$D46*Parameters!$C$7*IF($B78<Parameters!$D$16,1,(1+Parameters!$D$17)*(1-Parameters!$D$18)) -> 282944.18 | F78: =F38*Data_checks!$D46*Parameters!$C$7*IF($B78<Parameters!$D$16,1,(1+Parameters!$D$17)*(1-Parameters!$D$18)) -> 333546.57 | G78: =G38*Data_checks!$D46*Parameters!$C$7*IF($B78<Parameters!$D$16,1,(1+Parameters!$D$17)*(1-Parameters!$D$18)) -> 291415.56 | H78: =H38*Data_checks!$D46*Parameters!$C$7*IF($B78<Parameters!$D$16,1,(1+Parameters!$D$17)*(1-Parameters!$D$18)) -> 273908.03 | I78: =I38*Data_checks!$D46*Parameters!$C$7*IF($B78<Parameters!$D$16,1,(1+Parameters!$D$17)*(1-Parameters!$D$18)) -> 354103.79 | J78: =J38*Data_checks!$D46*Parameters!$C$7*IF($B78<Parameters!$D$16,1,(1+Parameters!$D$17)*(1-Parameters!$D$18)) -> 316829.71 | ... N78: =N38*Data_checks!$D46*Parameters!$C$7*IF($B78<Parameters!$D$16,1,(1+Parameters!$D$17)*(1-Parameters!$D$18)) -> 235504.43
B79: =B39 -> 4 | C79: =C39*Data_checks!$D47*Parameters!$C$7*IF($B79<Parameters!$D$16,1,(1+Parameters!$D$17)*(1-Parameters!$D$18)) -> 441710.91 | D79: =D39*Data_checks!$D47*Parameters!$C$7*IF($B79<Parameters!$D$16,1,(1+Parameters!$D$17)*(1-Parameters!$D$18)) -> 351844.07 | E79: =E39*Data_checks!$D47*Parameters!$C$7*IF($B79<Parameters!$D$16,1,(1+Parameters!$D$17)*(1-Parameters!$D$18)) -> 367237.25 | F79: =F39*Data_checks!$D47*Parameters!$C$7*IF($B79<Parameters!$D$16,1,(1+Parameters!$D$17)*(1-Parameters!$D$18)) -> 432914.81 | G79: =G39*Data_checks!$D47*Parameters!$C$7*IF($B79<Parameters!$D$16,1,(1+Parameters!$D$17)*(1-Parameters!$D$18)) -> 378232.38 | H79: =H39*Data_checks!$D47*Parameters!$C$7*IF($B79<Parameters!$D$16,1,(1+Parameters!$D$17)*(1-Parameters!$D$18)) -> 355509.11 | I79: =I39*Data_checks!$D47*Parameters!$C$7*IF($B79<Parameters!$D$16,1,(1+Parameters!$D$17)*(1-Parameters!$D$18)) -> 459596.32 | J79: =J39*Data_checks!$D47*Parameters!$C$7*IF($B79<Parameters!$D$16,1,(1+Parameters!$D$17)*(1-Parameters!$D$18)) -> 411217.76 | ... N79: =N39*Data_checks!$D47*Parameters!$C$7*IF($B79<Parameters!$D$16,1,(1+Parameters!$D$17)*(1-Parameters!$D$18)) -> 305664.54
B80: =B40 -> 5 | C80: =C40*Data_checks!$D48*Parameters!$C$7*IF($B80<Parameters!$D$16,1,(1+Parameters!$D$17)*(1-Parameters!$D$18)) -> 321089.85 | D80: =D40*Data_checks!$D48*Parameters!$C$7*IF($B80<Parameters!$D$16,1,(1+Parameters!$D$17)*(1-Parameters!$D$18)) -> 255763.57 | E80: =E40*Data_checks!$D48*Parameters!$C$7*IF($B80<Parameters!$D$16,1,(1+Parameters!$D$17)*(1-Parameters!$D$18)) -> 266953.23 | F80: =F40*Data_checks!$D48*Parameters!$C$7*IF($B80<Parameters!$D$16,1,(1+Parameters!$D$17)*(1-Parameters!$D$18)) -> 314695.76 | G80: =G40*Data_checks!$D48*Parameters!$C$7*IF($B80<Parameters!$D$16,1,(1+Parameters!$D$17)*(1-Parameters!$D$18)) -> 274945.84 | H80: =H40*Data_checks!$D48*Parameters!$C$7*IF($B80<Parameters!$D$16,1,(1+Parameters!$D$17)*(1-Parameters!$D$18)) -> 258427.78 | I80: =I40*Data_checks!$D48*Parameters!$C$7*IF($B80<Parameters!$D$16,1,(1+Parameters!$D$17)*(1-Parameters!$D$18)) -> 334091.17 | J80: =J40*Data_checks!$D48*Parameters!$C$7*IF($B80<Parameters!$D$16,1,(1+Parameters!$D$17)*(1-Parameters!$D$18)) -> 298923.68 | ... N80: =N40*Data_checks!$D48*Parameters!$C$7*IF($B80<Parameters!$D$16,1,(1+Parameters!$D$17)*(1-Parameters!$D$18)) -> 222194.61
B81: =B41 -> 6 | C81: =C41*Data_checks!$D49*Parameters!$C$7*IF($B81<Parameters!$D$16,1,(1+Parameters!$D$17)*(1-Parameters!$D$18)) -> 308246.26 | D81: =D41*Data_checks!$D49*Parameters!$C$7*IF($B81<Parameters!$D$16,1,(1+Parameters!$D$17)*(1-Parameters!$D$18)) -> 245533.03 | E81: =E41*Data_checks!$D49*Parameters!$C$7*IF($B81<Parameters!$D$16,1,(1+Parameters!$D$17)*(1-Parameters!$D$18)) -> 256275.1 | F81: =F41*Data_checks!$D49*Parameters!$C$7*IF($B81<Parameters!$D$16,1,(1+Parameters!$D$17)*(1-Parameters!$D$18)) -> 302107.93 | G81: =G41*Data_checks!$D49*Parameters!$C$7*IF($B81<Parameters!$D$16,1,(1+Parameters!$D$17)*(1-Parameters!$D$18)) -> 263948.01 | H81: =H41*Data_checks!$D49*Parameters!$C$7*IF($B81<Parameters!$D$16,1,(1+Parameters!$D$17)*(1-Parameters!$D$18)) -> 248090.67 | I81: =I41*Data_checks!$D49*Parameters!$C$7*IF($B81<Parameters!$D$16,1,(1+Parameters!$D$17)*(1-Parameters!$D$18)) -> 320727.52 | J81: =J41*Data_checks!$D49*Parameters!$C$7*IF($B81<Parameters!$D$16,1,(1+Parameters!$D$17)*(1-Parameters!$D$18)) -> 286966.73 | ... N81: =N41*Data_checks!$D49*Parameters!$C$7*IF($B81<Parameters!$D$16,1,(1+Parameters!$D$17)*(1-Parameters!$D$18)) -> 213306.82
B82: =B42 -> 7 | C82: =C42*Data_checks!$D50*Parameters!$C$7*IF($B82<Parameters!$D$16,1,(1+Parameters!$D$17)*(1-Parameters!$D$18)) -> 171247.92 | D82: =D42*Data_checks!$D50*Parameters!$C$7*IF($B82<Parameters!$D$16,1,(1+Parameters!$D$17)*(1-Parameters!$D$18)) -> 136407.24 | E82: =E42*Data_checks!$D50*Parameters!$C$7*IF($B82<Parameters!$D$16,1,(1+Parameters!$D$17)*(1-Parameters!$D$18)) -> 142375.06 | F82: =F42*Data_checks!$D50*Parameters!$C$7*IF($B82<Parameters!$D$16,1,(1+Parameters!$D$17)*(1-Parameters!$D$18)) -> 167837.74 | G82: =G42*Data_checks!$D50*Parameters!$C$7*IF($B82<Parameters!$D$16,1,(1+Parameters!$D$17)*(1-Parameters!$D$18)) -> 146637.78 | H82: =H42*Data_checks!$D50*Parameters!$C$7*IF($B82<Parameters!$D$16,1,(1+Parameters!$D$17)*(1-Parameters!$D$18)) -> 137828.15 | I82: =I42*Data_checks!$D50*Parameters!$C$7*IF($B82<Parameters!$D$16,1,(1+Parameters!$D$17)*(1-Parameters!$D$18)) -> 178181.96 | J82: =J42*Data_checks!$D50*Parameters!$C$7*IF($B82<Parameters!$D$16,1,(1+Parameters!$D$17)*(1-Parameters!$D$18)) -> 159425.96 | ... N82: =N42*Data_checks!$D50*Parameters!$C$7*IF($B82<Parameters!$D$16,1,(1+Parameters!$D$17)*(1-Parameters!$D$18)) -> 118503.79
B83: =B43 -> 8 | C83: =C43*Data_checks!$D51*Parameters!$C$7*IF($B83<Parameters!$D$16,1,(1+Parameters!$D$17)*(1-Parameters!$D$18)) -> 48927.978 | D83: =D43*Data_checks!$D51*Parameters!$C$7*IF($B83<Parameters!$D$16,1,(1+Parameters!$D$17)*(1-Parameters!$D$18)) -> 38973.497 | E83: =E43*Data_checks!$D51*Parameters!$C$7*IF($B83<Parameters!$D$16,1,(1+Parameters!$D$17)*(1-Parameters!$D$18)) -> 40678.588 | F83: =F43*Data_checks!$D51*Parameters!$C$7*IF($B83<Parameters!$D$16,1,(1+Parameters!$D$17)*(1-Parameters!$D$18)) -> 47953.64 | G83: =G43*Data_checks!$D51*Parameters!$C$7*IF($B83<Parameters!$D$16,1,(1+Parameters!$D$17)*(1-Parameters!$D$18)) -> 41896.509 | H83: =H43*Data_checks!$D51*Parameters!$C$7*IF($B83<Parameters!$D$16,1,(1+Parameters!$D$17)*(1-Parameters!$D$18)) -> 39379.471 | I83: =I43*Data_checks!$D51*Parameters!$C$7*IF($B83<Parameters!$D$16,1,(1+Parameters!$D$17)*(1-Parameters!$D$18)) -> 50909.13 | J83: =J43*Data_checks!$D51*Parameters!$C$7*IF($B83<Parameters!$D$16,1,(1+Parameters!$D$17)*(1-Parameters!$D$18)) -> 45550.275 | ... N83: =N43*Data_checks!$D51*Parameters!$C$7*IF($B83<Parameters!$D$16,1,(1+Parameters!$D$17)*(1-Parameters!$D$18)) -> 33858.226
B84: =B44 -> 9 | C84: =C44*Data_checks!$D52*Parameters!$C$7*IF($B84<Parameters!$D$16,1,(1+Parameters!$D$17)*(1-Parameters!$D$18)) -> 47704.778 | D84: =D44*Data_checks!$D52*Parameters!$C$7*IF($B84<Parameters!$D$16,1,(1+Parameters!$D$17)*(1-Parameters!$D$18)) -> 37999.16 | E84: =E44*Data_checks!$D52*Parameters!$C$7*IF($B84<Parameters!$D$16,1,(1+Parameters!$D$17)*(1-Parameters!$D$18)) -> 39661.623 | F84: =F44*Data_checks!$D52*Parameters!$C$7*IF($B84<Parameters!$D$16,1,(1+Parameters!$D$17)*(1-Parameters!$D$18)) -> 46754.799 | G84: =G44*Data_checks!$D52*Parameters!$C$7*IF($B84<Parameters!$D$16,1,(1+Parameters!$D$17)*(1-Parameters!$D$18)) -> 40849.097 | H84: =H44*Data_checks!$D52*Parameters!$C$7*IF($B84<Parameters!$D$16,1,(1+Parameters!$D$17)*(1-Parameters!$D$18)) -> 38394.984 | I84: =I44*Data_checks!$D52*Parameters!$C$7*IF($B84<Parameters!$D$16,1,(1+Parameters!$D$17)*(1-Parameters!$D$18)) -> 49636.402 | J84: =J44*Data_checks!$D52*Parameters!$C$7*IF($B84<Parameters!$D$16,1,(1+Parameters!$D$17)*(1-Parameters!$D$18)) -> 44411.518 | ... N84: =N44*Data_checks!$D52*Parameters!$C$7*IF($B84<Parameters!$D$16,1,(1+Parameters!$D$17)*(1-Parameters!$D$18)) -> 33011.77
B85: =B45 -> 10 | C85: =C45*Data_checks!$D53*Parameters!$C$7*IF($B85<Parameters!$D$16,1,(1+Parameters!$D$17)*(1-Parameters!$D$18)) -> 13944.474 | D85: =D45*Data_checks!$D53*Parameters!$C$7*IF($B85<Parameters!$D$16,1,(1+Parameters!$D$17)*(1-Parameters!$D$18)) -> 11107.447 | E85: =E45*Data_checks!$D53*Parameters!$C$7*IF($B85<Parameters!$D$16,1,(1+Parameters!$D$17)*(1-Parameters!$D$18)) -> 11593.397 | F85: =F45*Data_checks!$D53*Parameters!$C$7*IF($B85<Parameters!$D$16,1,(1+Parameters!$D$17)*(1-Parameters!$D$18)) -> 13666.787 | G85: =G45*Data_checks!$D53*Parameters!$C$7*IF($B85<Parameters!$D$16,1,(1+Parameters!$D$17)*(1-Parameters!$D$18)) -> 11940.505 | H85: =H45*Data_checks!$D53*Parameters!$C$7*IF($B85<Parameters!$D$16,1,(1+Parameters!$D$17)*(1-Parameters!$D$18)) -> 11223.149 | I85: =I45*Data_checks!$D53*Parameters!$C$7*IF($B85<Parameters!$D$16,1,(1+Parameters!$D$17)*(1-Parameters!$D$18)) -> 14509.102 | J85: =J45*Data_checks!$D53*Parameters!$C$7*IF($B85<Parameters!$D$16,1,(1+Parameters!$D$17)*(1-Parameters!$D$18)) -> 12981.828 | ... N85: =N45*Data_checks!$D53*Parameters!$C$7*IF($B85<Parameters!$D$16,1,(1+Parameters!$D$17)*(1-Parameters!$D$18)) -> 9649.5943
B86: =B46 -> 11 | C86: =C46*Data_checks!$D54*Parameters!$C$7*IF($B86<Parameters!$D$16,1,(1+Parameters!$D$17)*(1-Parameters!$D$18)) -> 18299.064 | D86: =D46*Data_checks!$D54*Parameters!$C$7*IF($B86<Parameters!$D$16,1,(1+Parameters!$D$17)*(1-Parameters!$D$18)) -> 14576.088 | E86: =E46*Data_checks!$D54*Parameters!$C$7*IF($B86<Parameters!$D$16,1,(1+Parameters!$D$17)*(1-Parameters!$D$18)) -> 15213.792 | F86: =F46*Data_checks!$D54*Parameters!$C$7*IF($B86<Parameters!$D$16,1,(1+Parameters!$D$17)*(1-Parameters!$D$18)) -> 17934.661 | G86: =G46*Data_checks!$D54*Parameters!$C$7*IF($B86<Parameters!$D$16,1,(1+Parameters!$D$17)*(1-Parameters!$D$18)) -> 15669.294 | H86: =H46*Data_checks!$D54*Parameters!$C$7*IF($B86<Parameters!$D$16,1,(1+Parameters!$D$17)*(1-Parameters!$D$18)) -> 14727.922 | I86: =I46*Data_checks!$D54*Parameters!$C$7*IF($B86<Parameters!$D$16,1,(1+Parameters!$D$17)*(1-Parameters!$D$18)) -> 19040.015 | J86: =J46*Data_checks!$D54*Parameters!$C$7*IF($B86<Parameters!$D$16,1,(1+Parameters!$D$17)*(1-Parameters!$D$18)) -> 17035.803 | ... N86: =N46*Data_checks!$D54*Parameters!$C$7*IF($B86<Parameters!$D$16,1,(1+Parameters!$D$17)*(1-Parameters!$D$18)) -> 12662.976
B87: =B47 -> 12 | C87: =C47*Data_checks!$D55*Parameters!$C$7*IF($B87<Parameters!$D$16,1,(1+Parameters!$D$17)*(1-Parameters!$D$18)) -> 14433.753 | D87: =D47*Data_checks!$D55*Parameters!$C$7*IF($B87<Parameters!$D$16,1,(1+Parameters!$D$17)*(1-Parameters!$D$18)) -> 11497.182 | E87: =E47*Data_checks!$D55*Parameters!$C$7*IF($B87<Parameters!$D$16,1,(1+Parameters!$D$17)*(1-Parameters!$D$18)) -> 12000.183 | F87: =F47*Data_checks!$D55*Parameters!$C$7*IF($B87<Parameters!$D$16,1,(1+Parameters!$D$17)*(1-Parameters!$D$18)) -> 14146.324 | G87: =G47*Data_checks!$D55*Parameters!$C$7*IF($B87<Parameters!$D$16,1,(1+Parameters!$D$17)*(1-Parameters!$D$18)) -> 12359.47 | H87: =H47*Data_checks!$D55*Parameters!$C$7*IF($B87<Parameters!$D$16,1,(1+Parameters!$D$17)*(1-Parameters!$D$18)) -> 11616.944 | I87: =I47*Data_checks!$D55*Parameters!$C$7*IF($B87<Parameters!$D$16,1,(1+Parameters!$D$17)*(1-Parameters!$D$18)) -> 15018.193 | J87: =J47*Data_checks!$D55*Parameters!$C$7*IF($B87<Parameters!$D$16,1,(1+Parameters!$D$17)*(1-Parameters!$D$18)) -> 13437.331 | ... N87: =N47*Data_checks!$D55*Parameters!$C$7*IF($B87<Parameters!$D$16,1,(1+Parameters!$D$17)*(1-Parameters!$D$18)) -> 9988.1765
... B89: =B49 -> 14 | C89: =C49*Data_checks!$D57*Parameters!$C$7*IF($B89<Parameters!$D$16,1,(1+Parameters!$D$17)*(1-Parameters!$D$18)) -> 8105.735 | D89: =D49*Data_checks!$D57*Parameters!$C$7*IF($B89<Parameters!$D$16,1,(1+Parameters!$D$17)*(1-Parameters!$D$18)) -> 6456.6093 | E89: =E49*Data_checks!$D57*Parameters!$C$7*IF($B89<Parameters!$D$16,1,(1+Parameters!$D$17)*(1-Parameters!$D$18)) -> 6739.086 | F89: =F49*Data_checks!$D57*Parameters!$C$7*IF($B89<Parameters!$D$16,1,(1+Parameters!$D$17)*(1-Parameters!$D$18)) -> 7944.3197 | G89: =G49*Data_checks!$D57*Parameters!$C$7*IF($B89<Parameters!$D$16,1,(1+Parameters!$D$17)*(1-Parameters!$D$18)) -> 6940.855 | H89: =H49*Data_checks!$D57*Parameters!$C$7*IF($B89<Parameters!$D$16,1,(1+Parameters!$D$17)*(1-Parameters!$D$18)) -> 6523.8657 | I89: =I49*Data_checks!$D57*Parameters!$C$7*IF($B89<Parameters!$D$16,1,(1+Parameters!$D$17)*(1-Parameters!$D$18)) -> 8433.946 | J89: =J49*Data_checks!$D57*Parameters!$C$7*IF($B89<Parameters!$D$16,1,(1+Parameters!$D$17)*(1-Parameters!$D$18)) -> 7546.1622 | ... N89: =N49*Data_checks!$D57*Parameters!$C$7*IF($B89<Parameters!$D$16,1,(1+Parameters!$D$17)*(1-Parameters!$D$18)) -> 5609.1794
B90: Total snack sales | C90: =SUM(C76:C89) -> 2159352 | D90: =SUM(D76:D89) -> 1720028.2 | E90: =SUM(E76:E89) -> 1795279.4 | F90: =SUM(F76:F89) -> 2116351.3 | G90: =SUM(G76:G89) -> 1849030.3 | H90: =SUM(H76:H89) -> 1737945.1 | I90: =SUM(I76:I89) -> 2246786.8 | J90: =SUM(J76:J89) -> 2010282.9 | ... N90: =SUM(N76:N89) -> 1494274.5
B92: Commission % for distributors
B93: Screen | C93: =C75 -> Jan | D93: =D75 -> Feb | E93: =E75 -> Mar | F93: =F75 -> Apr | G93: =G75 -> May | H93: =H75 -> Jun | I93: =I75 -> Jul | J93: =J75 -> Aug | ... N93: =N75 -> Dec
B94: =B7 -> 1 | C94: =INDEX(Data_checks!$I$31:$K$34,MATCH(C14,Data_checks!$H$31:$H$34,0),MATCH(LEFT(C7,1),Data_checks!$I$30:$K$30,0)) -> 0.55 | D94: =INDEX(Data_checks!$I$31:$K$34,MATCH(D14,Data_checks!$H$31:$H$34,0),MATCH(LEFT(D7,1),Data_checks!$I$30:$K$30,0)) -> 0.45 | E94: =INDEX(Data_checks!$I$31:$K$34,MATCH(E14,Data_checks!$H$31:$H$34,0),MATCH(LEFT(E7,1),Data_checks!$I$30:$K$30,0)) -> 0.45 | F94: =INDEX(Data_checks!$I$31:$K$34,MATCH(F14,Data_checks!$H$31:$H$34,0),MATCH(LEFT(F7,1),Data_checks!$I$30:$K$30,0)) -> 0.55 | G94: =INDEX(Data_checks!$I$31:$K$34,MATCH(G14,Data_checks!$H$31:$H$34,0),MATCH(LEFT(G7,1),Data_checks!$I$30:$K$30,0)) -> 0.45 | H94: =INDEX(Data_checks!$I$31:$K$34,MATCH(H14,Data_checks!$H$31:$H$34,0),MATCH(LEFT(H7,1),Data_checks!$I$30:$K$30,0)) -> 0.45 | I94: =INDEX(Data_checks!$I$31:$K$34,MATCH(I14,Data_checks!$H$31:$H$34,0),MATCH(LEFT(I7,1),Data_checks!$I$30:$K$30,0)) -> 0.65 | J94: =INDEX(Data_checks!$I$31:$K$34,MATCH(J14,Data_checks!$H$31:$H$34,0),MATCH(LEFT(J7,1),Data_checks!$I$30:$K$30,0)) -> 0.55 | ... N94: =INDEX(Data_checks!$I$31:$K$34,MATCH(N14,Data_checks!$H$31:$H$34,0),MATCH(LEFT(N7,1),Data_checks!$I$30:$K$30,0)) -> 0.35
B95: =B8 -> 2 | C95: =INDEX(Data_checks!$I$31:$K$34,MATCH(C15,Data_checks!$H$31:$H$34,0),MATCH(LEFT(C8,1),Data_checks!$I$30:$K$30,0)) -> 0.55 | D95: =INDEX(Data_checks!$I$31:$K$34,MATCH(D15,Data_checks!$H$31:$H$34,0),MATCH(LEFT(D8,1),Data_checks!$I$30:$K$30,0)) -> 0.35 | E95: =INDEX(Data_checks!$I$31:$K$34,MATCH(E15,Data_checks!$H$31:$H$34,0),MATCH(LEFT(E8,1),Data_checks!$I$30:$K$30,0)) -> 0.3 | F95: =INDEX(Data_checks!$I$31:$K$34,MATCH(F15,Data_checks!$H$31:$H$34,0),MATCH(LEFT(F8,1),Data_checks!$I$30:$K$30,0)) -> 0.55 | G95: =INDEX(Data_checks!$I$31:$K$34,MATCH(G15,Data_checks!$H$31:$H$34,0),MATCH(LEFT(G8,1),Data_checks!$I$30:$K$30,0)) -> 0.45 | H95: =INDEX(Data_checks!$I$31:$K$34,MATCH(H15,Data_checks!$H$31:$H$34,0),MATCH(LEFT(H8,1),Data_checks!$I$30:$K$30,0)) -> 0.3 | I95: =INDEX(Data_checks!$I$31:$K$34,MATCH(I15,Data_checks!$H$31:$H$34,0),MATCH(LEFT(I8,1),Data_checks!$I$30:$K$30,0)) -> 0.65 | J95: =INDEX(Data_checks!$I$31:$K$34,MATCH(J15,Data_checks!$H$31:$H$34,0),MATCH(LEFT(J8,1),Data_checks!$I$30:$K$30,0)) -> 0.55 | ... N95: =INDEX(Data_checks!$I$31:$K$34,MATCH(N15,Data_checks!$H$31:$H$34,0),MATCH(LEFT(N8,1),Data_checks!$I$30:$K$30,0)) -> 0.3
B96: =B9 -> 3 | C96: =INDEX(Data_checks!$I$31:$K$34,MATCH(C16,Data_checks!$H$31:$H$34,0),MATCH(LEFT(C9,1),Data_checks!$I$30:$K$30,0)) -> 0.45 | D96: =INDEX(Data_checks!$I$31:$K$34,MATCH(D16,Data_checks!$H$31:$H$34,0),MATCH(LEFT(D9,1),Data_checks!$I$30:$K$30,0)) -> 0.35 | E96: =INDEX(Data_checks!$I$31:$K$34,MATCH(E16,Data_checks!$H$31:$H$34,0),MATCH(LEFT(E9,1),Data_checks!$I$30:$K$30,0)) -> 0.45 | F96: =INDEX(Data_checks!$I$31:$K$34,MATCH(F16,Data_checks!$H$31:$H$34,0),MATCH(LEFT(F9,1),Data_checks!$I$30:$K$30,0)) -> 0.45 | G96: =INDEX(Data_checks!$I$31:$K$34,MATCH(G16,Data_checks!$H$31:$H$34,0),MATCH(LEFT(G9,1),Data_checks!$I$30:$K$30,0)) -> 0.35 | H96: =INDEX(Data_checks!$I$31:$K$34,MATCH(H16,Data_checks!$H$31:$H$34,0),MATCH(LEFT(H9,1),Data_checks!$I$30:$K$30,0)) -> 0.35 | I96: =INDEX(Data_checks!$I$31:$K$34,MATCH(I16,Data_checks!$H$31:$H$34,0),MATCH(LEFT(I9,1),Data_checks!$I$30:$K$30,0)) -> 0.65 | J96: =INDEX(Data_checks!$I$31:$K$34,MATCH(J16,Data_checks!$H$31:$H$34,0),MATCH(LEFT(J9,1),Data_checks!$I$30:$K$30,0)) -> 0.45 | ... N96: =INDEX(Data_checks!$I$31:$K$34,MATCH(N16,Data_checks!$H$31:$H$34,0),MATCH(LEFT(N9,1),Data_checks!$I$30:$K$30,0)) -> 0.35
B97: =B10 -> 4 | C97: =INDEX(Data_checks!$I$31:$K$34,MATCH(C17,Data_checks!$H$31:$H$34,0),MATCH(LEFT(C10,1),Data_checks!$I$30:$K$30,0)) -> 0.45 | D97: =INDEX(Data_checks!$I$31:$K$34,MATCH(D17,Data_checks!$H$31:$H$34,0),MATCH(LEFT(D10,1),Data_checks!$I$30:$K$30,0)) -> 0.35 | E97: =INDEX(Data_checks!$I$31:$K$34,MATCH(E17,Data_checks!$H$31:$H$34,0),MATCH(LEFT(E10,1),Data_checks!$I$30:$K$30,0)) -> 0.15 | F97: =INDEX(Data_checks!$I$31:$K$34,MATCH(F17,Data_checks!$H$31:$H$34,0),MATCH(LEFT(F10,1),Data_checks!$I$30:$K$30,0)) -> 0.35 | G97: =INDEX(Data_checks!$I$31:$K$34,MATCH(G17,Data_checks!$H$31:$H$34,0),MATCH(LEFT(G10,1),Data_checks!$I$30:$K$30,0)) -> 0.35 | H97: =INDEX(Data_checks!$I$31:$K$34,MATCH(H17,Data_checks!$H$31:$H$34,0),MATCH(LEFT(H10,1),Data_checks!$I$30:$K$30,0)) -> 0.15 | I97: =INDEX(Data_checks!$I$31:$K$34,MATCH(I17,Data_checks!$H$31:$H$34,0),MATCH(LEFT(I10,1),Data_checks!$I$30:$K$30,0)) -> 0.35 | J97: =INDEX(Data_checks!$I$31:$K$34,MATCH(J17,Data_checks!$H$31:$H$34,0),MATCH(LEFT(J10,1),Data_checks!$I$30:$K$30,0)) -> 0.45 | ... N97: =INDEX(Data_checks!$I$31:$K$34,MATCH(N17,Data_checks!$H$31:$H$34,0),MATCH(LEFT(N10,1),Data_checks!$I$30:$K$30,0)) -> 0.15
B99: Commission $ for distributors
B100: Screen | C100: =C93 -> Jan | D100: =D93 -> Feb | E100: =E93 -> Mar | F100: =F93 -> Apr | G100: =G93 -> May | H100: =H93 -> Jun | I100: =I93 -> Jul | J100: =J93 -> Aug | ... N100: =N93 -> Dec
B101: =B7 -> 1 | C101: =C94*C28*Parameters!$C$6 -> 1017373.5 | D101: =D94*D28*Parameters!$C$6 -> 716040 | E101: =E94*E28*Parameters!$C$6 -> 760792.5 | F101: =F94*F28*Parameters!$C$6 -> 1017373.5 | G101: =G94*G28*Parameters!$C$6 -> 716040 | H101: =H94*H28*Parameters!$C$6 -> 760792.5 | I101: =I94*I28*Parameters!$C$6 -> 1266993 | J101: =J94*J28*Parameters!$C$6 -> 929857.5 | ... N101: =N94*N28*Parameters!$C$6 -> 452497.5
B102: =B8 -> 2 | C102: =C95*C29*Parameters!$C$6 -> 538609.5 | D102: =D95*D29*Parameters!$C$6 -> 239557.5 | E102: =E95*E29*Parameters!$C$6 -> 205335 | F102: =F95*F29*Parameters!$C$6 -> 538609.5 | G102: =G95*G29*Parameters!$C$6 -> 402772.5 | H102: =H95*H29*Parameters!$C$6 -> 205335 | I102: =I95*I29*Parameters!$C$6 -> 670761 | J102: =J95*J29*Parameters!$C$6 -> 492277.5 | ... N102: =N95*N29*Parameters!$C$6 -> 205335
B103: =B9 -> 3 | C103: =C96*C30*Parameters!$C$6 -> 179010 | D103: =D96*D30*Parameters!$C$6 -> 106470 | E103: =E96*E30*Parameters!$C$6 -> 179010 | F103: =F96*F30*Parameters!$C$6 -> 179010 | G103: =G96*G30*Parameters!$C$6 -> 106470 | H103: =H96*H30*Parameters!$C$6 -> 106470 | I103: =I96*I30*Parameters!$C$6 -> 298116 | J103: =J96*J30*Parameters!$C$6 -> 179010 | ... N103: =N96*N30*Parameters!$C$6 -> 106470
B104: =B10 -> 4 | C104: =C97*C31*Parameters!$C$6 -> 134257.5 | D104: =D97*D31*Parameters!$C$6 -> 79852.5 | E104: =E97*E31*Parameters!$C$6 -> 23692.5 | F104: =F97*F31*Parameters!$C$6 -> 79852.5 | G104: =G97*G31*Parameters!$C$6 -> 79852.5 | H104: =H97*H31*Parameters!$C$6 -> 23692.5 | I104: =I97*I31*Parameters!$C$6 -> 79852.5 | J104: =J97*J31*Parameters!$C$6 -> 134257.5 | ... N104: =N97*N31*Parameters!$C$6 -> 23692.5
B105: Total | C105: =SUM(C101:C104) -> 1869250.5 | D105: =SUM(D101:D104) -> 1141920 | E105: =SUM(E101:E104) -> 1168830 | F105: =SUM(F101:F104) -> 1814845.5 | G105: =SUM(G101:G104) -> 1305135 | H105: =SUM(H101:H104) -> 1096290 | I105: =SUM(I101:I104) -> 2315722.5 | J105: =SUM(J101:J104) -> 1735402.5 | ... N105: =SUM(N101:N104) -> 787995
B107: Cinema profit calculations
C108: =C100 -> Jan | D108: =D100 -> Feb | E108: =E100 -> Mar | F108: =F100 -> Apr | G108: =G100 -> May | H108: =H100 -> Jun | I108: =I100 -> Jul | J108: =J100 -> Aug | ... N108: =N100 -> Dec | O108: Total
B109: Ticket revenue | C109: =C55 -> 2237332.7 | D109: =D55 -> 1782143.5 | E109: =E55 -> 1860112.3 | F109: =F55 -> 2192779.1 | G109: =G55 -> 1915804.3 | H109: =H55 -> 1800707.5 | I109: =I55 -> 2327925 | J109: =J55 -> 2082880.2 | ... N109: =N55 -> 1548237.2 | O109: =SUM(C109:N109) -> 23467860
B110: Annual pass revenue | C110: =C72 -> 1234319.4 | D110: =D72 -> 983195.04 | E110: =E72 -> 1026209.8 | F110: =F72 -> 1209739.6 | G110: =G72 -> 1056934.7 | H110: =H72 -> 993436.65 | I110: =I72 -> 1284298.5 | J110: =J72 -> 1149109.2 | ... N110: =N72 -> 854150.69 | O110: =SUM(C110:N110) -> 12947040
B111: Snacks sales | C111: =C90 -> 2159352 | D111: =D90 -> 1720028.2 | E111: =E90 -> 1795279.4 | F111: =F90 -> 2116351.3 | G111: =G90 -> 1849030.3 | H111: =H90 -> 1737945.1 | I111: =I90 -> 2246786.8 | J111: =J90 -> 2010282.9 | ... N111: =N90 -> 1494274.5 | O111: =SUM(C111:N111) -> 22649904
B112: Commission | C112: =-C105 -> -1869250.5 | D112: =-D105 -> -1141920 | E112: =-E105 -> -1168830 | F112: =-F105 -> -1814845.5 | G112: =-G105 -> -1305135 | H112: =-H105 -> -1096290 | I112: =-I105 -> -2315722.5 | J112: =-J105 -> -1735402.5 | ... N112: =-N105 -> -787995 | O112: =SUM(C112:N112) -> -17298392
B113: Cost of snacks sale | C113: =-C90/Parameters!$C$7*Parameters!$C$13 -> -196304.73 | D113: =-D90/Parameters!$C$7*Parameters!$C$13 -> -156366.2 | E113: =-E90/Parameters!$C$7*Parameters!$C$13 -> -163207.22 | F113: =-F90/Parameters!$C$7*Parameters!$C$13 -> -192395.58 | G113: =-G90/Parameters!$C$7*Parameters!$C$13 -> -168093.66 | H113: =-H90/Parameters!$C$7*Parameters!$C$13 -> -157995.01 | I113: =-I90/Parameters!$C$7*Parameters!$C$13 -> -204253.35 | J113: =-J90/Parameters!$C$7*Parameters!$C$13 -> -182752.99 | ... N113: =-N90/Parameters!$C$7*Parameters!$C$13 -> -135843.13 | O113: =SUM(C113:N113) -> -2059082.2
B114: Overheads | C114: =-Parameters!$C$12 -> -300000 | D114: =-Parameters!$C$12 -> -300000 | E114: =-Parameters!$C$12 -> -300000 | F114: =-Parameters!$C$12 -> -300000 | G114: =-Parameters!$C$12 -> -300000 | H114: =-Parameters!$C$12 -> -300000 | I114: =-Parameters!$C$12 -> -300000 | J114: =-Parameters!$C$12 -> -300000 | ... N114: =-Parameters!$C$12 -> -300000 | O114: =SUM(C114:N114) -> -3600000
B115: Staff expenses | C115: =-(Parameters!$C$9*Parameters!$C$10*Parameters!$C$5*Parameters!$C$11) -> -192000 | D115: =-(Parameters!$C$9*Parameters!$C$10*Parameters!$C$5*Parameters!$C$11) -> -192000 | E115: =-(Parameters!$C$9*Parameters!$C$10*Parameters!$C$5*Parameters!$C$11) -> -192000 | F115: =-(Parameters!$C$9*Parameters!$C$10*Parameters!$C$5*Parameters!$C$11) -> -192000 | G115: =-(Parameters!$C$9*Parameters!$C$10*Parameters!$C$5*Parameters!$C$11) -> -192000 | H115: =-(Parameters!$C$9*Parameters!$C$10*Parameters!$C$5*Parameters!$C$11) -> -192000 | I115: =-(Parameters!$C$9*Parameters!$C$10*Parameters!$C$5*Parameters!$C$11) -> -192000 | J115: =-(Parameters!$C$9*Parameters!$C$10*Parameters!$C$5*Parameters!$C$11) -> -192000 | ... N115: =-(Parameters!$C$9*Parameters!$C$10*Parameters!$C$5*Parameters!$C$11) -> -192000 | O115: =SUM(C115:N115) -> -2304000
...
